Workbook
Name \: #REF!
Name \0: #REF!
Name \A: #REF!
Name \B: #REF!
Name \E: #REF!
Name \G: #REF!
Name \L: #REF!
Name \q: #REF!
Name \S: #REF!
Name \T: #REF!
Name \U: #REF!
Name ________DAT7: #REF!
Name ________DAT8: #REF!
Name ________DAT9: #REF!
Name _______DAT13: #REF!
Name _______DAT2: #REF!
Name _______DAT3: #REF!
Name _______DAT4: #REF!
Name _______DAT5: #REF!
Name _______DAT6: #REF!
Name _______DAT7: #REF!
Name _______DAT8: #REF!
Name _______DAT9: #REF!
Name _______New1: #REF!
Name ______DAT13: #REF!
Name ______DAT2: #REF!
Name ______DAT3: #REF!
Name ______DAT4: #REF!
Name ______DAT5: #REF!
Name ______DAT6: #REF!
Name ______DAT7: #REF!
Name ______DAT8: #REF!
Name ______DAT9: #REF!
Name ______New1: #REF!
Name _____DAT1: #REF!
Name _____DAT13: #REF!
Name _____DAT2: #REF!
Name _____DAT3: #REF!
Name _____DAT4: #REF!
Name _____DAT5: #REF!
Name _____DAT6: #REF!
Name _____DAT7: #REF!
Name _____DAT8: #REF!
Name _____DAT9: #REF!
Name _____New1: #REF!
Name ____DAT1: #REF!
Name ____DAT13: #REF!
Name ____DAT2: #REF!
Name ____DAT3: #REF!
Name ____DAT4: #REF!
Name ____DAT5: #REF!
Name ____DAT6: #REF!
Name ____DAT7: #REF!
Name ____DAT8: #REF!
Name ____DAT9: #REF!
Name ____New1: #REF!
Name ___col1: #REF!
Name ___col10: #REF!
Name ___col11: #REF!
Name ___col12: #REF!

Sheet Sheet1
H2: Total Days | I2: 23 | J2: 21 | K2: 21 | L2: 22 | M2: 23 | N2: 20 | O2: 23 | P2: 22 | Q2: 21 | R2: 23 | S2: 21 | T2: 22
H3: Holidays | I3: 3 | J3: 0 | K3: 0 | L3: 0 | M3: 2 | N3: 1 | O3: 4 | P3: 1 | Q3: 1 | R3: 2 | S3: 2 | T3: 1
H4: Working Days | I4: =I2-I3 -> 20 | J4: =J2-J3 -> 21 | K4: =K2-K3 -> 21 | L4: =L2-L3 -> 22 | M4: =M2-M3 -> 21 | N4: =N2-N3 -> 19 | O4: =O2-O3 -> 19 | P4: =P2-P3 -> 21 | ... T4: =T2-T3 -> 21
A5: Project | B5: Active/Inactive | C5: Scope | D5: EHR system | E5: Norms | F5: Billing Type | G5: Pricing | H5: Daily volume | I5: Jan | J5: Feb | K5: Mar | L5: Apr | M5: May | N5: Jun | O5: Jul | P5: Aug | Q5: Sep | R5: Oct | S5: Nov | T5: Dec
A6: D'Souza | B6: Active | C6: Demographics - Established patient | D6: Intergy | E6: 300 | F6: Transcation | G6: 0.27 | H6: 355 | I6: 7100 | J6: 7455 | K6: 7455 | L6: 7810 | M6: 7455 | N6: 6745 | O6: 6745 | P6: 7455 | Q6: 7100 | R6: 7455 | S6: 6745 | T6: 7455
B7: Active | C7: Demographics - New Patient | D7: Intergy | E7: 300 | F7: Transcation | G7: 0.55 | H7: 55 | I7: 1100 | J7: 1155 | K7: 1155 | L7: 1210 | M7: 1155 | N7: 1045 | O7: 1045 | P7: 1155 | Q7: 1100 | R7: 1155 | S7: 1045 | T7: 1155
B8: Active | C8: Insurance Update - Established Patient | D8: Intergy | E8: 150 | F8: Transcation | G8: 0.54 | H8: =7300/20 -> 365 | I8: =H8*I4 -> 7300 | J8: =H8*J4 -> 7665 | K8: =H8*K4 -> 7665 | L8: =H8*L4 -> 8030 | M8: =H8*M4 -> 7665 | N8: =H8*N4 -> 6935 | O8: =H8*O4 -> 6935 | P8: =H8*P4 -> 7665 | Q8: =H8*Q4 -> 7300 | R8: =H8*R4 -> 7665 | S8: =H8*S4 -> 6935 | T8: =H8*T4 -> 7665
B9: Active | C9: Insurance Update - New Patient | D9: Intergy | E9: 150 | F9: Transcation | G9: 0.25 | H9: =1200/20 -> 60 | I9: =H9*I4 -> 1200 | J9: =H9*J4 -> 1260 | K9: =H9*K4 -> 1260 | L9: =H9*L4 -> 1320 | M9: =H9*M4 -> 1260 | N9: =H9*N4 -> 1140 | O9: =H9*O4 -> 1140 | P9: =H9*P4 -> 1260 | Q9: =H9*Q4 -> 1200 | R9: =H9*R4 -> 1260 | S9: =H9*S4 -> 1140 | T9: =H9*T4 -> 1260
B10: Active | C10: Charge entry | D10: Intergy | E10: 380 | F10: Transcation | G10: 0.14 | H10: =23000/20 -> 1150 | I10: =H10*I4 -> 23000 | J10: =H10*J4 -> 24150 | K10: =H10*K4 -> 24150 | L10: =H10*L4 -> 25300 | M10: =H10*M4 -> 24150 | N10: =H10*N4 -> 21850 | O10: =H10*O4 -> 21850 | P10: =H10*P4 -> 24150 | Q10: =H10*Q4 -> 23000 | R10: =H10*R4 -> 24150 | S10: =H10*S4 -> 21850 | T10: =H10*T4 -> 24150
B11: Active | C11: Payment posting - Manual | D11: Intergy | E11: 450 | F11: Transcation | G11: 0.16 | H11: =11000/20 -> 550 | I11: =H11*I4 -> 11000 | J11: =H11*J4 -> 11550 | K11: =H11*K4 -> 11550 | L11: =H11*L4 -> 12100 | M11: =H11*M4 -> 11550 | N11: =H11*N4 -> 10450 | O11: =H11*O4 -> 10450 | P11: =H11*P4 -> 11550 | Q11: =H11*Q4 -> 11000 | R11: =H11*R4 -> 11550 | S11: =H11*S4 -> 10450 | T11: =H11*T4 -> 11550
B12: Active | C12: Payment posting ERA | D12: Intergy | E12: 2000 | F12: Transcation | G12: 0.026 | H12: =34538/20 -> 1726.9 | I12: =H12*I4 -> 34538 | J12: =H12*J4 -> 36264.9 | K12: =H12*K4 -> 36264.9 | L12: =H12*L4 -> 37991.8 | M12: =H12*M4 -> 36264.9 | N12: =H12*N4 -> 32811.1 | O12: =H12*O4 -> 32811.1 | P12: =H12*P4 -> 36264.9 | Q12: =H12*Q4 -> 34538 | R12: =H12*R4 -> 36264.9 | S12: =H12*S4 -> 32811.1 | T12: =H12*T4 -> 36264.9
B13: Active | C13: Medicare Calling | D13: Intergy | E13: 200 | F13: Transcation | G13: 0.3 | H13: =369/20 -> 18.45 | I13: =H13*I4 -> 369 | J13: =H13*J4 -> 387.45 | K13: =H13*K4 -> 387.45 | L13: =H13*L4 -> 405.9 | M13: =H13*M4 -> 387.45 | N13: =H13*N4 -> 350.55 | O13: =H13*O4 -> 350.55 | P13: =H13*P4 -> 387.45 | Q13: =H13*Q4 -> 369 | R13: =H13*R4 -> 387.45 | S13: =H13*S4 -> 350.55 | T13: =H13*T4 -> 387.45
B14: Active | C14: AR Non - Calling | D14: Intergy | E14: 64 | F14: Transcation | G14: 1.35 | H14: =11500/20 -> 575 | I14: =H14*I4 -> 11500 | J14: =H14*J4 -> 12075 | K14: =H14*K4 -> 12075 | L14: =H14*L4 -> 12650 | M14: =H14*M4 -> 12075 | N14: =H14*N4 -> 10925 | O14: =H14*O4 -> 10925 | P14: =H14*P4 -> 12075 | Q14: =H14*Q4 -> 11500 | R14: =H14*R4 -> 12075 | S14: =H14*S4 -> 10925 | T14: =H14*T4 -> 12075
B15: Active | C15: AR Calling | D15: Intergy | E15: 40 | F15: Transcation | G15: 1.35 | H15: =1500/20 -> 75 | I15: =H15*I4 -> 1500 | J15: =H15*J4 -> 1575 | K15: =H15*K4 -> 1575 | L15: =H15*L4 -> 1650 | M15: =H15*M4 -> 1575 | N15: =H15*N4 -> 1425 | O15: =H15*O4 -> 1425 | P15: =H15*P4 -> 1575 | Q15: =H15*Q4 -> 1500 | R15: =H15*R4 -> 1575 | S15: =H15*S4 -> 1425 | T15: =H15*T4 -> 1575
A16: Biotek | B16: In-Active | C16: AR | D16: CPR + | E16: 20 | F16: Collection | G16: 0.015
A17: Biotek | B17: In-Active | C17: Eligibility Verification | D17: CPR + | F17: FTE | G17: 1400
A18: Biotek | B18: In-Active | C18: Payment Posting | D18: CPR + | F18: FTE | G18: 1300
A19: UGBZ | B19: Active | C19: AR | D19: Next Gen | E19: 40 | F19: Collection | G19: 0.03 | H19: =250000/20 -> 12500 | I19: =H19*I4 -> 250000 | J19: =H19*J4 -> 262500 | K19: =H19*K4 -> 262500 | L19: =H19*L4 -> 275000 | M19: =H19*M4 -> 262500 | N19: =H19*N4 -> 237500 | O19: =H19*O4 -> 237500 | P19: =H19*P4 -> 262500 | Q19: =H19*Q4 -> 250000 | R19: =H19*R4 -> 262500 | S19: =H19*S4 -> 237500 | T19: =H19*T4 -> 262500
B20: In-Active | C20: Auth | D20: Next Gen | E20: 20 | F20: Collection | K20: =H20*K9 -> 0 | L20: =I20*L9 -> 0 | M20: =J20*M9 -> 0 | N20: =K20*N9 -> 0 | O20: =L20*O9 -> 0 | P20: =M20*P9 -> 0 | Q20: =N20*Q9 -> 0 | R20: =O20*R9 -> 0 | ... T20: =Q20*T9 -> 0
B21: Active | C21: Payment posting Manual | D21: Next Gen | E21: 350 | F21: Collection | K21: =H21*K10 -> 0 | L21: =I21*L10 -> 0 | M21: =J21*M10 -> 0 | N21: =K21*N10 -> 0 | O21: =L21*O10 -> 0 | P21: =M21*P10 -> 0 | Q21: =N21*Q10 -> 0 | R21: =O21*R10 -> 0 | ... T21: =Q21*T10 -> 0
B22: Active | C22: Payment posting ERA | D22: Next Gen | E22: 2000 | F22: Collection | K22: =H22*K11 -> 0 | L22: =I22*L11 -> 0 | M22: =J22*M11 -> 0 | N22: =K22*N11 -> 0 | O22: =L22*O11 -> 0 | P22: =M22*P11 -> 0 | Q22: =N22*Q11 -> 0 | R22: =O22*R11 -> 0 | ... T22: =Q22*T11 -> 0
B23: Active | C23: Eligibility Benefits and Auth verification | D23: Next Gen | F23: FTE | G23: 1400
A24: HCA | B24: In-Active | C24: Adjustment | D24: Primesuite | E24: 250 | F24: FTE | G24: 1200
B25: Active | C25: AR Follow up | D25: Primesuite | E25: 40 | F25: FTE | G25: 1300 | H25: 4 | I25: 5200 | J25: 5200 | K25: 5200 | L25: 5200 | M25: 5200 | N25: 5200 | O25: 5200 | P25: 5200 | Q25: 5200 | R25: 5200 | S25: 5200 | T25: 5200
A26: BMMSA | B26: In-Active | C26: AR | D26: Intergy | E26: 20 | F26: FTE | G26: 1200
A27: Nova GI | B27: In-Active | C27: Charge entry | D27: Gastro Med | E27: 150 | F27: Collection | G27: 0.025 | M27: Price change from 3% to 2.5% effective from. July 2023
B28: In-Active | C28: Payment posting - Manual | D28: Gastro Med | E28: 180 | F28: Collection
B29: In-Active | C29: Payment posting ERA | D29: Gastro Med | E29: 300 | F29: Collection
B30: In-Active | C30: AR calling | D30: Gastro Med | E30: 40 | F30: Collection
B31: In-Active | C31: Patient Collection | D31: Gastro Med | E31: 64 | G31: 0.005
A32: CMS | B32: Active | C32: AR | D32: Intergy / Advanced MD / eCw | E32: 40 | F32: Transaction | G32: 2.1 | H32: =1500/20 -> 75 | I32: =H32*I4 -> 1500 | J32: =H32*J4 -> 1575 | K32: =H32*K4 -> 1575 | L32: =H32*L4 -> 1650 | M32: =H32*M4 -> 1575 | N32: =H32*N4 -> 1425 | O32: =H32*O4 -> 1425 | P32: =H32*P4 -> 1575 | Q32: =H32*Q4 -> 1500 | R32: =H32*R4 -> 1575 | S32: =H32*S4 -> 1425 | T32: =H32*T4 -> 1575
B33: Active | C33: Demographics | D33: Intergy / Advanced MD / eCw | E33: 100 | F33: Transaction | G33: 0.55 | H33: =150/20 -> 7.5 | I33: =H33*I4 -> 150 | J33: =H33*J4 -> 157.5 | K33: =H33*K4 -> 157.5 | L33: =H33*L4 -> 165 | M33: =H33*M4 -> 157.5 | N33: =H33*N4 -> 142.5 | O33: =H33*O4 -> 142.5 | P33: =H33*P4 -> 157.5 | Q33: =H33*Q4 -> 150 | R33: =H33*R4 -> 157.5 | S33: =H33*S4 -> 142.5 | T33: =H33*T4 -> 157.5
B34: Active | C34: Charge entry | D34: Intergy / Advanced MD / eCw | E34: 150 | F34: Transaction | G34: 0.3 | H34: =150/20 -> 7.5 | I34: =H34*I4 -> 150 | J34: =H34*J4 -> 157.5 | K34: =H34*K4 -> 157.5 | L34: =H34*L4 -> 165 | M34: =H34*M4 -> 157.5 | N34: =H34*N4 -> 142.5 | O34: =H34*O4 -> 142.5 | P34: =H34*P4 -> 157.5 | Q34: =H34*Q4 -> 150 | R34: =H34*R4 -> 157.5 | S34: =H34*S4 -> 142.5 | T34: =H34*T4 -> 157.5
B35: Active | C35: Payment posting - Manual | D35: Intergy / Advanced MD / eCw | E35: 450 | F35: Transaction | G35: 0.27 | H35: =700/20 -> 35 | I35: =H35*I4 -> 700 | J35: =H35*J4 -> 735 | K35: =H35*K4 -> 735 | L35: =H35*L4 -> 770 | M35: =H35*M4 -> 735 | N35: =H35*N4 -> 665 | O35: =H35*O4 -> 665 | P35: =H35*P4 -> 735 | Q35: =H35*Q4 -> 700 | R35: =H35*R4 -> 735 | S35: =H35*S4 -> 665 | T35: =H35*T4 -> 735
B36: Active | C36: Payment posting ERA | D36: Intergy / Advanced MD / eCw | E36: 450 | F36: Transaction | G36: 0.03 | H36: =4000/20 -> 200 | I36: =H36*I4 -> 4000 | J36: =H36*J4 -> 4200 | K36: =H36*K4 -> 4200 | L36: =H36*L4 -> 4400 | M36: =H36*M4 -> 4200 | N36: =H36*N4 -> 3800 | O36: =H36*O4 -> 3800 | P36: =H36*P4 -> 4200 | Q36: =H36*Q4 -> 4000 | R36: =H36*R4 -> 4200 | S36: =H36*S4 -> 3800 | T36: =H36*T4 -> 4200
A37: Open dental | B37: Active | C37: Payment posting | D37: Open Dental | E37: 80 | F37: FTE | G37: 1280 | I37: =1280+1280 -> 2560 | J37: =1280+1280 -> 2560 | K37: =1280+1280 -> 2560 | L37: =1280+1280 -> 2560 | M37: =1280+1280 -> 2560 | N37: =1280+1280 -> 2560 | O37: =1280+1280 -> 2560 | P37: =1280+1280 -> 2560 | ... T37: =1280+1280 -> 2560
A38: DDR | B38: Active | C38: Payment posting - Manual | D38: Gastro Med | E38: 180 | F38: FTE | G38: 1250 | I38: 5000 | J38: 5000 | K38: 5000 | L38: 5000 | M38: 5000 | N38: 5000 | O38: 5000 | P38: 5000 | Q38: 5000 | R38: 5000 | S38: 5000 | T38: 5000
B39: Active | C39: Payment posting ERA | D39: Gastro Med | E39: 300 | F39: FTE
B40: In-Active | C40: Eligibility Benefits and Auth verification | D40: Gastro Med | E40: 30 | F40: FTE | G40: 1350
A41: Encore | B41: In-Active | C41: Charge entry | D41: Raintree | E41: 800 | F41: Collection | G41: 0.065 | U41: Price change from 4% to 6.5% effective from. October 2023
B42: In-Active | C42: Payment posting - Manual | D42: Raintree | E42: 300 | F42: Collection
B43: In-Active | C43: Payment posting ERA | D43: Raintree | E43: 800 | F43: Collection
B44: Active | C44: AR | D44: Raintree | E44: 40 | F44: Collection
B45: In-Active | C45: EV | D45: Raintree | E45: 20 | F45: Collection
B46: Active | C46: Credentialling | D46: CredSimplify | E46: 50 | F46: FTE | G46: 1300
B47: In-Active | C47: Eligibility & Benefit Verification | D47: Raintree | E47: 30 | F47: FTE | G47: 1500
A48: Hillmed | B48: In-Active | C48: AR | D48: Intergy | E48: 35 | F48: FTE | G48: 1280
B49: In-Active | C49: Charge entry | D49: Intergy | E49: 380 | F49: FTE | G49: 1120
A50: MISS & Dr. Tay | B50: In-Active | C50: AR | D50: Intergy | E50: 35 | F50: FTE | G50: 1280
B51: In-Active | C51: Charge entry | D51: Intergy | E51: 380 | F51: FTE | G51: 1120
A52: ARMG | B52: Active | C52: Charge entry | D52: eCw | E52: 90 | F52: Collection | G52: IVF Collection 0.43% | I52: 12000 | J52: 12000 | K52: 12000 | L52: 12000 | M52: 12000 | N52: 12000 | O52: 12000 | P52: 12000 | Q52: 12000 | R52: 12000 | S52: 12000 | T52: 12000
B53: Active | C53: Payment posting - Manual | D53: eCw | E53: 120 | F53: Collection | G53: Non-IVF Collection 2.55%
B54: Active | C54: Payment posting ERA | D54: eCw | E54: 175 | F54: Collection | G54: Patient Collection 0.64%
B55: Active | C55: Print HCFA | D55: eCw | E55: 100 | F55: Collection
B56: Active | C56: Patient statement | D56: eCw | E56: 100 | F56: Collection
B57: Active | C57: AR Non calling | D57: eCw | E57: 64 | F57: Collection
B58: Active | C58: AR Calling | D58: eCw | E58: 40 | F58: Collection
A59: Billpro | B59: Active | C59: Demo Verify | D59: Billpro | E59: 300 | F59: FTE | G59: 1440 | I59: 1800 | J59: 4320 | K59: 7200 | L59: 7200 | M59: 7200 | N59: 7200 | O59: 7200 | P59: 7200 | Q59: 7200 | R59: 7200 | S59: 7200 | T59: 7200
B60: Active | C60: Demo Entry | D60: Billpro | E60: 300 | F60: FTE
B61: Active | C61: Charges | D61: Billpro | E61: 350 | F61: FTE
B62: Active | C62: AR Calling | D62: Billpro | E62: 30 | F62: FTE
A63: Von Marie | B63: Active | C63: AR | D63: Intergy | E63: 30 | F63: FTE | G63: 1600 | I63: 2400 | J63: 2400 | K63: 2400 | L63: 2400 | M63: 2400 | N63: 2400 | O63: 2400 | P63: 2400 | Q63: 2400 | R63: 2400 | S63: 2400 | T63: 2400
A64: SSP | B64: Active | C64: Payment posting ERA | D64: eCw | E64: 180 | F64: FTE | G64: 1250
B65: Active | C65: Payment posting Manual | D65: eCw | E65: 120 | F65: FTE | G65: 1250
A66: Comprehensive Sleep Care Center | B66: Active | C66: Comprehensive Sleep Care Center | E66: 30 | F66: FTE | G66: 1450 | I66: 13050 | J66: 13050 | K66: 13050 | L66: 13050 | M66: 7250 | N66: 7250 | O66: 7250 | P66: 7250 | Q66: 7250 | R66: 7250 | S66: 7250 | T66: 7250
A67: Dr Scott | B67: Active | C67: End to End | F67: Collection | G67: 0.06 | I67: 100000 | J67: 100000 | K67: 100000 | L67: 100000 | M67: 100000 | N67: 100000 | O67: 100000 | P67: 100000 | Q67: 100000 | R67: 100000 | S67: 100000 | T67: 100000
A68: Sasan PTSMC | B68: Active | C68: End to End | F68: Collection | G68: 0.035 | J68: 250000 | K68: 250000 | L68: 250000 | M68: 250000 | N68: 250000 | O68: 250000 | P68: 250000 | Q68: 250000 | R68: 250000 | S68: 250000 | T68: 250000
A69: Visco Supplements | B69: In-Active | C69: Visco Supplements | E69: 30 | F69: FTE | G69: 1500
A70: HIS Special Project | B70: Active | C70: Payment Posing one time | E70: 200 | F70: FTE | G70: 2100
A71: HIS OSIS | B71: In-Active | C71: Old AR Follow-up | E71: 30 | F71: Collection | G71: 0.14
A72: RCS7 IOSSM | B72: In-Active | C72: AR Follow-up | E72: 30 | F72: FTE | G72: 1350
A73: IQMS | B73: In-Active | C73: Old AR Follow-up | E73: 30 | F73: FTE | G73: 1450
A74: Dr Debbas | B74: In-Active | C74: End to End | F74: Collection | G74: 0.07
A75: Falcon Er Urgent Care | B75: Active | C75: Credentialing | F75: Per Application | G75: 100
A76: Primepulmonarysleep Dr Bansal | B76: In-Active | C76: AR Follow-up | E76: 30 | F76: FTE | G76: 1440
A77: Dr Henry | B77: In-Active | C77: End to End | F77: Collection | G77: 300
A78: Aloha Vein | B78: In-Active | C78: Payment Posting | F78: Transaction | G78: 7
A79: eCare | B79: In-Active | C79: Patient Payment | F79: Transaction | G79: 7
A80: eCare | B80: In-Active | C80: Insurance Payment | F80: Transaction | G80: 7
A81: eCare | B81: In-Active | C81: Patient Statement | F81: Transaction | G81: 7
A82: eCare | B82: In-Active | C82: AR Follow-up | F82: Transaction | G82: 8
A83: eCare | B83: In-Active | C83: Collection Patients e-Message | F83: Transaction | G83: 7

Sheet Sheet 3
D1: AR | H1: 2024 Expected Volume | AX1: Base | AY1: =SUM(AJ6:AJ15) -> 20.263613 | BA1: Deployment
D2: Date Entry | I2: Total Days | J2: 23 | K2: 21 | L2: 21 | M2: 22 | N2: 23 | O2: 20 | P2: 23 | Q2: 22 | R2: 21 | S2: 23 | T2: 21 | U2: 22 | AX2: Absenteeism | AY2: 0.1 | AZ2: =100%-AY2-AY3 -> 0.85 | BA2: =AY1/AZ2 -> 23.839545 | BB2: =BA2*AZ2 -> 20.263613
D3: Coding | I3: Holidays | J3: 3 | K3: 0 | L3: 0 | M3: 0 | N3: 2 | O3: 1 | P3: 4 | Q3: 1 | R3: 1 | S3: 2 | T3: 2 | U3: 1 | AJ3: Base FTEs | AX3: Attrition | AY3: 0.05
I4: Working Days | J4: =J2-J3 -> 20 | K4: =K2-K3 -> 21 | L4: =L2-L3 -> 21 | M4: =M2-M3 -> 22 | N4: =N2-N3 -> 21 | O4: =O2-O3 -> 19 | P4: =P2-P3 -> 19 | Q4: =Q2-Q3 -> 21 | ... U4: =U2-U3 -> 21 | W4: Revenue in $
A5: Project | B5: Active/Inactive | C5: Scope | D5: Manpower Type | E5: EHR system | F5: Norms | G5: Billing Type | H5: Pricing | I5: Daily volume | J5: Jan | K5: Feb | L5: Mar | M5: Apr | N5: May | O5: Jun | P5: Jul | Q5: Aug | R5: Sep | S5: Oct | T5: Nov | U5: Dec | W5: Jan | X5: Feb | Y5: Mar | Z5: Apr | AA5: May | AB5: Jun | AC5: Jul | AD5: Aug | AE5: Sep | AF5: Oct | AG5: Nov | AH5: Dec | AJ5: Jan | AK5: Feb | AL5: Mar | AM5: Apr | AN5: May | AO5: Jun | AP5: Jul | AQ5: Aug | AR5: Sep | AS5: Oct | AT5: Nov | AU5: Dec
A6: D'Souza | B6: Active | C6: Demographics - Established patient | D6: Date Entry | E6: Intergy | F6: 300 | G6: Transcation | H6: 0.27 | I6: 355 | J6: 7100 | K6: 7455 | L6: 7455 | M6: 7810 | N6: 7455 | O6: 6745 | P6: 6745 | Q6: 7455 | R6: 7100 | S6: 7455 | T6: 6745 | U6: 7455 | W6: =$H6*J6 -> 1917 | X6: =$H6*K6 -> 2012.85 | Y6: =$H6*L6 -> 2012.85 | Z6: =$H6*M6 -> 2108.7 | AA6: =$H6*N6 -> 2012.85 | AB6: =$H6*O6 -> 1821.15 | AC6: =$H6*P6 -> 1821.15 | AD6: =$H6*Q6 -> 2012.85 | ... AH6: =$H6*U6 -> 2012.85 | AJ6: =(J6/J$4)/$F6 -> 1.1833333 | AK6: =(K6/K$4)/$F6 -> 1.1833333 | AL6: =(L6/L$4)/$F6 -> 1.1833333 | AM6: =(M6/M$4)/$F6 -> 1.1833333 | AN6: =(N6/N$4)/$F6 -> 1.1833333 | AO6: =(O6/O$4)/$F6 -> 1.1833333 | AP6: =(P6/P$4)/$F6 -> 1.1833333 | AQ6: =(Q6/Q$4)/$F6 -> 1.1833333 | ... AU6: =(U6/U$4)/$F6 -> 1.1833333 | AY6: Client Name
A7: =A6 -> D'Souza | B7: Active | C7: Demographics - New Patient | D7: Date Entry | E7: Intergy | F7: 300 | G7: Transcation | H7: 0.55 | I7: 55 | J7: 1100 | K7: 1155 | L7: 1155 | M7: 1210 | N7: 1155 | O7: 1045 | P7: 1045 | Q7: 1155 | R7: 1100 | S7: 1155 | T7: 1045 | U7: 1155 | W7: =$H7*J7 -> 605 | X7: =$H7*K7 -> 635.25 | Y7: =$H7*L7 -> 635.25 | Z7: =$H7*M7 -> 665.5 | AA7: =$H7*N7 -> 635.25 | AB7: =$H7*O7 -> 574.75 | AC7: =$H7*P7 -> 574.75 | AD7: =$H7*Q7 -> 635.25 | ... AH7: =$H7*U7 -> 635.25 | AJ7: =(J7/J$4)/$F7 -> 0.18333333 | AK7: =(K7/K$4)/$F7 -> 0.18333333 | AL7: =(L7/L$4)/$F7 -> 0.18333333 | AM7: =(M7/M$4)/$F7 -> 0.18333333 | AN7: =(N7/N$4)/$F7 -> 0.18333333 | AO7: =(O7/O$4)/$F7 -> 0.18333333 | AP7: =(P7/P$4)/$F7 -> 0.18333333 | AQ7: =(Q7/Q$4)/$F7 -> 0.18333333 | ... AU7: =(U7/U$4)/$F7 -> 0.18333333 | AY7: Type of Manpower
A8: =A7 -> D'Souza | B8: Active | C8: Insurance Update - Established Patient | D8: Date Entry | E8: Intergy | F8: 150 | G8: Transcation | H8: 0.54 | I8: =7300/20 -> 365 | J8: =I8*J4 -> 7300 | K8: =I8*K4 -> 7665 | L8: =I8*L4 -> 7665 | M8: =I8*M4 -> 8030 | N8: =I8*N4 -> 7665 | O8: =I8*O4 -> 6935 | P8: =I8*P4 -> 6935 | Q8: =I8*Q4 -> 7665 | R8: =I8*R4 -> 7300 | S8: =I8*S4 -> 7665 | T8: =I8*T4 -> 6935 | U8: =I8*U4 -> 7665 | W8: =$H8*J8 -> 3942 | X8: =$H8*K8 -> 4139.1 | Y8: =$H8*L8 -> 4139.1 | Z8: =$H8*M8 -> 4336.2 | AA8: =$H8*N8 -> 4139.1 | AB8: =$H8*O8 -> 3744.9 | AC8: =$H8*P8 -> 3744.9 | AD8: =$H8*Q8 -> 4139.1 | ... AH8: =$H8*U8 -> 4139.1 | AJ8: =(J8/J$4)/$F8 -> 2.4333333 | AK8: =(K8/K$4)/$F8 -> 2.4333333 | AL8: =(L8/L$4)/$F8 -> 2.4333333 | AM8: =(M8/M$4)/$F8 -> 2.4333333 | AN8: =(N8/N$4)/$F8 -> 2.4333333 | AO8: =(O8/O$4)/$F8 -> 2.4333333 | AP8: =(P8/P$4)/$F8 -> 2.4333333 | AQ8: =(Q8/Q$4)/$F8 -> 2.4333333 | ... AU8: =(U8/U$4)/$F8 -> 2.4333333 | AY8: Required Headcount
A9: =A8 -> D'Souza | B9: Active | C9: Insurance Update - New Patient | D9: Date Entry | E9: Intergy | F9: 150 | G9: Transcation | H9: 0.25 | I9: =1200/20 -> 60 | J9: =I9*J4 -> 1200 | K9: =I9*K4 -> 1260 | L9: =I9*L4 -> 1260 | M9: =I9*M4 -> 1320 | N9: =I9*N4 -> 1260 | O9: =I9*O4 -> 1140 | P9: =I9*P4 -> 1140 | Q9: =I9*Q4 -> 1260 | R9: =I9*R4 -> 1200 | S9: =I9*S4 -> 1260 | T9: =I9*T4 -> 1140 | U9: =I9*U4 -> 1260 | W9: =$H9*J9 -> 300 | X9: =$H9*K9 -> 315 | Y9: =$H9*L9 -> 315 | Z9: =$H9*M9 -> 330 | AA9: =$H9*N9 -> 315 | AB9: =$H9*O9 -> 285 | AC9: =$H9*P9 -> 285 | AD9: =$H9*Q9 -> 315 | ... AH9: =$H9*U9 -> 315 | AJ9: =(J9/J$4)/$F9 -> 0.4 | AK9: =(K9/K$4)/$F9 -> 0.4 | AL9: =(L9/L$4)/$F9 -> 0.4 | AM9: =(M9/M$4)/$F9 -> 0.4 | AN9: =(N9/N$4)/$F9 -> 0.4 | AO9: =(O9/O$4)/$F9 -> 0.4 | AP9: =(P9/P$4)/$F9 -> 0.4 | AQ9: =(Q9/Q$4)/$F9 -> 0.4 | ... AU9: =(U9/U$4)/$F9 -> 0.4
A10: =A9 -> D'Souza | B10: Active | C10: Charge entry | D10: Date Entry | E10: Intergy | F10: 380 | G10: Transcation | H10: 0.14 | I10: =23000/20 -> 1150 | J10: =I10*J4 -> 23000 | K10: =I10*K4 -> 24150 | L10: =I10*L4 -> 24150 | M10: =I10*M4 -> 25300 | N10: =I10*N4 -> 24150 | O10: =I10*O4 -> 21850 | P10: =I10*P4 -> 21850 | Q10: =I10*Q4 -> 24150 | R10: =I10*R4 -> 23000 | S10: =I10*S4 -> 24150 | T10: =I10*T4 -> 21850 | U10: =I10*U4 -> 24150 | W10: =$H10*J10 -> 3220 | X10: =$H10*K10 -> 3381 | Y10: =$H10*L10 -> 3381 | Z10: =$H10*M10 -> 3542 | AA10: =$H10*N10 -> 3381 | AB10: =$H10*O10 -> 3059 | AC10: =$H10*P10 -> 3059 | AD10: =$H10*Q10 -> 3381 | ... AH10: =$H10*U10 -> 3381 | AJ10: =(J10/J$4)/$F10 -> 3.0263158 | AK10: =(K10/K$4)/$F10 -> 3.0263158 | AL10: =(L10/L$4)/$F10 -> 3.0263158 | AM10: =(M10/M$4)/$F10 -> 3.0263158 | AN10: =(N10/N$4)/$F10 -> 3.0263158 | AO10: =(O10/O$4)/$F10 -> 3.0263158 | AP10: =(P10/P$4)/$F10 -> 3.0263158 | AQ10: =(Q10/Q$4)/$F10 -> 3.0263158 | ... AU10: =(U10/U$4)/$F10 -> 3.0263158
A11: =A10 -> D'Souza | B11: Active | C11: Payment posting - Manual | D11: Date Entry | E11: Intergy | F11: 450 | G11: Transcation | H11: 0.16 | I11: =11000/20 -> 550 | J11: =I11*J4 -> 11000 | K11: =I11*K4 -> 11550 | L11: =I11*L4 -> 11550 | M11: =I11*M4 -> 12100 | N11: =I11*N4 -> 11550 | O11: =I11*O4 -> 10450 | P11: =I11*P4 -> 10450 | Q11: =I11*Q4 -> 11550 | R11: =I11*R4 -> 11000 | S11: =I11*S4 -> 11550 | T11: =I11*T4 -> 10450 | U11: =I11*U4 -> 11550 | W11: =$H11*J11 -> 1760 | X11: =$H11*K11 -> 1848 | Y11: =$H11*L11 -> 1848 | Z11: =$H11*M11 -> 1936 | AA11: =$H11*N11 -> 1848 | AB11: =$H11*O11 -> 1672 | AC11: =$H11*P11 -> 1672 | AD11: =$H11*Q11 -> 1848 | ... AH11: =$H11*U11 -> 1848 | AJ11: =(J11/J$4)/$F11 -> 1.2222222 | AK11: =(K11/K$4)/$F11 -> 1.2222222 | AL11: =(L11/L$4)/$F11 -> 1.2222222 | AM11: =(M11/M$4)/$F11 -> 1.2222222 | AN11: =(N11/N$4)/$F11 -> 1.2222222 | AO11: =(O11/O$4)/$F11 -> 1.2222222 | AP11: =(P11/P$4)/$F11 -> 1.2222222 | AQ11: =(Q11/Q$4)/$F11 -> 1.2222222 | ... AU11: =(U11/U$4)/$F11 -> 1.2222222
A12: =A11 -> D'Souza | B12: Active | C12: Payment posting ERA | D12: Date Entry | E12: Intergy | F12: 2000 | G12: Transcation | H12: 0.026 | I12: =34538/20 -> 1726.9 | J12: =I12*J4 -> 34538 | K12: =I12*K4 -> 36264.9 | L12: =I12*L4 -> 36264.9 | M12: =I12*M4 -> 37991.8 | N12: =I12*N4 -> 36264.9 | O12: =I12*O4 -> 32811.1 | P12: =I12*P4 -> 32811.1 | Q12: =I12*Q4 -> 36264.9 | R12: =I12*R4 -> 34538 | S12: =I12*S4 -> 36264.9 | T12: =I12*T4 -> 32811.1 | U12: =I12*U4 -> 36264.9 | W12: =$H12*J12 -> 897.988 | X12: =$H12*K12 -> 942.8874 | Y12: =$H12*L12 -> 942.8874 | Z12: =$H12*M12 -> 987.7868 | AA12: =$H12*N12 -> 942.8874 | AB12: =$H12*O12 -> 853.0886 | AC12: =$H12*P12 -> 853.0886 | AD12: =$H12*Q12 -> 942.8874 | ... AH12: =$H12*U12 -> 942.8874 | AJ12: =(J12/J$4)/$F12 -> 0.86345 | AK12: =(K12/K$4)/$F12 -> 0.86345 | AL12: =(L12/L$4)/$F12 -> 0.86345 | AM12: =(M12/M$4)/$F12 -> 0.86345 | AN12: =(N12/N$4)/$F12 -> 0.86345 | AO12: =(O12/O$4)/$F12 -> 0.86345 | AP12: =(P12/P$4)/$F12 -> 0.86345 | AQ12: =(Q12/Q$4)/$F12 -> 0.86345 | ... AU12: =(U12/U$4)/$F12 -> 0.86345
A13: =A12 -> D'Souza | B13: Active | C13: Medicare Calling | D13: AR | E13: Intergy | F13: 200 | G13: Transcation | H13: 0.3 | I13: =369/20 -> 18.45 | J13: =I13*J4 -> 369 | K13: =I13*K4 -> 387.45 | L13: =I13*L4 -> 387.45 | M13: =I13*M4 -> 405.9 | N13: =I13*N4 -> 387.45 | O13: =I13*O4 -> 350.55 | P13: =I13*P4 -> 350.55 | Q13: =I13*Q4 -> 387.45 | R13: =I13*R4 -> 369 | S13: =I13*S4 -> 387.45 | T13: =I13*T4 -> 350.55 | U13: =I13*U4 -> 387.45 | W13: =$H13*J13 -> 110.7 | X13: =$H13*K13 -> 116.235 | Y13: =$H13*L13 -> 116.235 | Z13: =$H13*M13 -> 121.77 | AA13: =$H13*N13 -> 116.235 | AB13: =$H13*O13 -> 105.165 | AC13: =$H13*P13 -> 105.165 | AD13: =$H13*Q13 -> 116.235 | ... AH13: =$H13*U13 -> 116.235 | AJ13: =(J13/J$4)/$F13 -> 0.09225 | AK13: =(K13/K$4)/$F13 -> 0.09225 | AL13: =(L13/L$4)/$F13 -> 0.09225 | AM13: =(M13/M$4)/$F13 -> 0.09225 | AN13: =(N13/N$4)/$F13 -> 0.09225 | AO13: =(O13/O$4)/$F13 -> 0.09225 | AP13: =(P13/P$4)/$F13 -> 0.09225 | AQ13: =(Q13/Q$4)/$F13 -> 0.09225 | ... AU13: =(U13/U$4)/$F13 -> 0.09225
A14: =A13 -> D'Souza | B14: Active | C14: AR Non - Calling | D14: AR | E14: Intergy | F14: 64 | G14: Transcation | H14: 1.35 | I14: =11500/20 -> 575 | J14: =I14*J4 -> 11500 | K14: =I14*K4 -> 12075 | L14: =I14*L4 -> 12075 | M14: =I14*M4 -> 12650 | N14: =I14*N4 -> 12075 | O14: =I14*O4 -> 10925 | P14: =I14*P4 -> 10925 | Q14: =I14*Q4 -> 12075 | R14: =I14*R4 -> 11500 | S14: =I14*S4 -> 12075 | T14: =I14*T4 -> 10925 | U14: =I14*U4 -> 12075 | W14: =$H14*J14 -> 15525 | X14: =$H14*K14 -> 16301.25 | Y14: =$H14*L14 -> 16301.25 | Z14: =$H14*M14 -> 17077.5 | AA14: =$H14*N14 -> 16301.25 | AB14: =$H14*O14 -> 14748.75 | AC14: =$H14*P14 -> 14748.75 | AD14: =$H14*Q14 -> 16301.25 | ... AH14: =$H14*U14 -> 16301.25 | AJ14: =(J14/J$4)/$F14 -> 8.984375 | AK14: =(K14/K$4)/$F14 -> 8.984375 | AL14: =(L14/L$4)/$F14 -> 8.984375 | AM14: =(M14/M$4)/$F14 -> 8.984375 | AN14: =(N14/N$4)/$F14 -> 8.984375 | AO14: =(O14/O$4)/$F14 -> 8.984375 | AP14: =(P14/P$4)/$F14 -> 8.984375 | AQ14: =(Q14/Q$4)/$F14 -> 8.984375 | ... AU14: =(U14/U$4)/$F14 -> 8.984375
A15: =A14 -> D'Souza | B15: Active | C15: AR Calling | D15: AR | E15: Intergy | F15: 40 | G15: Transcation | H15: 1.35 | I15: =1500/20 -> 75 | J15: =I15*J4 -> 1500 | K15: =I15*K4 -> 1575 | L15: =I15*L4 -> 1575 | M15: =I15*M4 -> 1650 | N15: =I15*N4 -> 1575 | O15: =I15*O4 -> 1425 | P15: =I15*P4 -> 1425 | Q15: =I15*Q4 -> 1575 | R15: =I15*R4 -> 1500 | S15: =I15*S4 -> 1575 | T15: =I15*T4 -> 1425 | U15: =I15*U4 -> 1575 | W15: =$H15*J15 -> 2025 | X15: =$H15*K15 -> 2126.25 | Y15: =$H15*L15 -> 2126.25 | Z15: =$H15*M15 -> 2227.5 | AA15: =$H15*N15 -> 2126.25 | AB15: =$H15*O15 -> 1923.75 | AC15: =$H15*P15 -> 1923.75 | AD15: =$H15*Q15 -> 2126.25 | ... AH15: =$H15*U15 -> 2126.25 | AJ15: =(J15/J$4)/$F15 -> 1.875 | AK15: =(K15/K$4)/$F15 -> 1.875 | AL15: =(L15/L$4)/$F15 -> 1.875 | AM15: =(M15/M$4)/$F15 -> 1.875 | AN15: =(N15/N$4)/$F15 -> 1.875 | AO15: =(O15/O$4)/$F15 -> 1.875 | AP15: =(P15/P$4)/$F15 -> 1.875 | AQ15: =(Q15/Q$4)/$F15 -> 1.875 | ... AU15: =(U15/U$4)/$F15 -> 1.875
A16: UGBZ | B16: Active | C16: AR | D16: AR | E16: Next Gen | F16: 40 | G16: Collection | H16: 0.03 | I16: =250000/20 -> 12500 | J16: =I16*J4 -> 250000 | K16: =I16*K4 -> 262500 | L16: =I16*L4 -> 262500 | M16: =I16*M4 -> 275000 | N16: =I16*N4 -> 262500 | O16: =I16*O4 -> 237500 | P16: =I16*P4 -> 237500 | Q16: =I16*Q4 -> 262500 | R16: =I16*R4 -> 250000 | S16: =I16*S4 -> 262500 | T16: =I16*T4 -> 237500 | U16: =I16*U4 -> 262500 | W16: =$H16*J16 -> 7500 | X16: =$H16*K16 -> 7875 | Y16: =$H16*L16 -> 7875 | Z16: =$H16*M16 -> 8250 | AA16: =$H16*N16 -> 7875 | AB16: =$H16*O16 -> 7125 | AC16: =$H16*P16 -> 7125 | AD16: =$H16*Q16 -> 7875 | ... AH16: =$H16*U16 -> 7875 | AJ16: =AI16*AY1 -> 0
A17: =A16 -> UGBZ | B17: In-Active | C17: Auth | D17: Date Entry | E17: Next Gen | F17: 20 | G17: Collection | L17: =I17*L9 -> 0 | M17: =J17*M9 -> 0 | N17: =K17*N9 -> 0 | O17: =L17*O9 -> 0 | P17: =M17*P9 -> 0 | Q17: =N17*Q9 -> 0 | R17: =O17*R9 -> 0 | S17: =P17*S9 -> 0 | ... U17: =R17*U9 -> 0 | W17: =$H17*J17 -> 0 | X17: =$H17*K17 -> 0 | Y17: =$H17*L17 -> 0 | Z17: =$H17*M17 -> 0 | AA17: =$H17*N17 -> 0 | AB17: =$H17*O17 -> 0 | AC17: =$H17*P17 -> 0 | AD17: =$H17*Q17 -> 0 | ... AH17: =$H17*U17 -> 0
A18: =A17 -> UGBZ | B18: Active | C18: Payment posting Manual | D18: Date Entry | E18: Next Gen | F18: 350 | G18: Collection | L18: =I18*L10 -> 0 | M18: =J18*M10 -> 0 | N18: =K18*N10 -> 0 | O18: =L18*O10 -> 0 | P18: =M18*P10 -> 0 | Q18: =N18*Q10 -> 0 | R18: =O18*R10 -> 0 | S18: =P18*S10 -> 0 | ... U18: =R18*U10 -> 0 | W18: =$H18*J18 -> 0 | X18: =$H18*K18 -> 0 | Y18: =$H18*L18 -> 0 | Z18: =$H18*M18 -> 0 | AA18: =$H18*N18 -> 0 | AB18: =$H18*O18 -> 0 | AC18: =$H18*P18 -> 0 | AD18: =$H18*Q18 -> 0 | ... AH18: =$H18*U18 -> 0
A19: =A18 -> UGBZ | B19: Active | C19: Payment posting ERA | D19: Date Entry | E19: Next Gen | F19: 2000 | G19: Collection | L19: =I19*L11 -> 0 | M19: =J19*M11 -> 0 | N19: =K19*N11 -> 0 | O19: =L19*O11 -> 0 | P19: =M19*P11 -> 0 | Q19: =N19*Q11 -> 0 | R19: =O19*R11 -> 0 | S19: =P19*S11 -> 0 | ... U19: =R19*U11 -> 0 | W19: =$H19*J19 -> 0 | X19: =$H19*K19 -> 0 | Y19: =$H19*L19 -> 0 | Z19: =$H19*M19 -> 0 | AA19: =$H19*N19 -> 0 | AB19: =$H19*O19 -> 0 | AC19: =$H19*P19 -> 0 | AD19: =$H19*Q19 -> 0 | ... AH19: =$H19*U19 -> 0
A20: =A19 -> UGBZ | B20: Active | C20: Eligibility Benefits and Auth verification | D20: Date Entry | E20: Next Gen | G20: FTE | H20: 1400
A21: HCA | B21: In-Active | C21: Adjustment | D21: Date Entry | E21: Primesuite | F21: 250 | G21: FTE | H21: 1200
A22: =A21 -> HCA | B22: Active | C22: AR Follow up | D22: AR | E22: Primesuite | F22: 40 | G22: FTE | H22: 1300 | I22: 4 | J22: 4 | K22: 4 | L22: 4 | M22: 4 | N22: 4 | O22: 4 | P22: 4 | Q22: 4 | R22: 4 | S22: 4 | T22: 4 | U22: 4 | W22: =$H22*J22 -> 5200 | X22: =$H22*K22 -> 5200 | Y22: =$H22*L22 -> 5200 | Z22: =$H22*M22 -> 5200 | AA22: =$H22*N22 -> 5200 | AB22: =$H22*O22 -> 5200 | AC22: =$H22*P22 -> 5200 | AD22: =$H22*Q22 -> 5200 | ... AH22: =$H22*U22 -> 5200 | AJ22: =J22 -> 4 | AK22: =K22 -> 4 | AL22: =L22 -> 4 | AM22: =M22 -> 4 | AN22: =N22 -> 4 | AO22: =O22 -> 4 | AP22: =P22 -> 4 | AQ22: =Q22 -> 4 | ... AU22: =U22 -> 4
A23: BMMSA | B23: In-Active | C23: AR | D23: AR | E23: Intergy | F23: 20 | G23: FTE | H23: 1200
A24: CMS | B24: Active | C24: AR | D24: AR | E24: Intergy / Advanced MD / eCw | F24: 40 | G24: Transaction | H24: 2.1 | I24: =1500/20 -> 75 | J24: =I24*J4 -> 1500 | K24: =I24*K4 -> 1575 | L24: =I24*L4 -> 1575 | M24: =I24*M4 -> 1650 | N24: =I24*N4 -> 1575 | O24: =I24*O4 -> 1425 | P24: =I24*P4 -> 1425 | Q24: =I24*Q4 -> 1575 | R24: =I24*R4 -> 1500 | S24: =I24*S4 -> 1575 | T24: =I24*T4 -> 1425 | U24: =I24*U4 -> 1575 | W24: =$H24*J24 -> 3150 | X24: =$H24*K24 -> 3307.5 | Y24: =$H24*L24 -> 3307.5 | Z24: =$H24*M24 -> 3465 | AA24: =$H24*N24 -> 3307.5 | AB24: =$H24*O24 -> 2992.5 | AC24: =$H24*P24 -> 2992.5 | AD24: =$H24*Q24 -> 3307.5 | ... AH24: =$H24*U24 -> 3307.5 | AJ24: =(J24/J$4)/$F24 -> 1.875 | AK24: =(K24/K$4)/$F24 -> 1.875 | AL24: =(L24/L$4)/$F24 -> 1.875 | AM24: =(M24/M$4)/$F24 -> 1.875 | AN24: =(N24/N$4)/$F24 -> 1.875 | AO24: =(O24/O$4)/$F24 -> 1.875 | AP24: =(P24/P$4)/$F24 -> 1.875 | AQ24: =(Q24/Q$4)/$F24 -> 1.875 | ... AU24: =(U24/U$4)/$F24 -> 1.875
A25: =A24 -> CMS | B25: Active | C25: Demographics | D25: Date Entry | E25: Intergy / Advanced MD / eCw | F25: 100 | G25: Transaction | H25: 0.55 | I25: =150/20 -> 7.5 | J25: =I25*J4 -> 150 | K25: =I25*K4 -> 157.5 | L25: =I25*L4 -> 157.5 | M25: =I25*M4 -> 165 | N25: =I25*N4 -> 157.5 | O25: =I25*O4 -> 142.5 | P25: =I25*P4 -> 142.5 | Q25: =I25*Q4 -> 157.5 | R25: =I25*R4 -> 150 | S25: =I25*S4 -> 157.5 | T25: =I25*T4 -> 142.5 | U25: =I25*U4 -> 157.5 | W25: =$H25*J25 -> 82.5 | X25: =$H25*K25 -> 86.625 | Y25: =$H25*L25 -> 86.625 | Z25: =$H25*M25 -> 90.75 | AA25: =$H25*N25 -> 86.625 | AB25: =$H25*O25 -> 78.375 | AC25: =$H25*P25 -> 78.375 | AD25: =$H25*Q25 -> 86.625 | ... AH25: =$H25*U25 -> 86.625 | AJ25: =(J25/J$4)/$F25 -> 0.075 | AK25: =(K25/K$4)/$F25 -> 0.075 | AL25: =(L25/L$4)/$F25 -> 0.075 | AM25: =(M25/M$4)/$F25 -> 0.075 | AN25: =(N25/N$4)/$F25 -> 0.075 | AO25: =(O25/O$4)/$F25 -> 0.075 | AP25: =(P25/P$4)/$F25 -> 0.075 | AQ25: =(Q25/Q$4)/$F25 -> 0.075 | ... AU25: =(U25/U$4)/$F25 -> 0.075
A26: =A25 -> CMS | B26: Active | C26: Charge entry | D26: Date Entry | E26: Intergy / Advanced MD / eCw | F26: 150 | G26: Transaction | H26: 0.3 | I26: =150/20 -> 7.5 | J26: =I26*J4 -> 150 | K26: =I26*K4 -> 157.5 | L26: =I26*L4 -> 157.5 | M26: =I26*M4 -> 165 | N26: =I26*N4 -> 157.5 | O26: =I26*O4 -> 142.5 | P26: =I26*P4 -> 142.5 | Q26: =I26*Q4 -> 157.5 | R26: =I26*R4 -> 150 | S26: =I26*S4 -> 157.5 | T26: =I26*T4 -> 142.5 | U26: =I26*U4 -> 157.5 | W26: =$H26*J26 -> 45 | X26: =$H26*K26 -> 47.25 | Y26: =$H26*L26 -> 47.25 | Z26: =$H26*M26 -> 49.5 | AA26: =$H26*N26 -> 47.25 | AB26: =$H26*O26 -> 42.75 | AC26: =$H26*P26 -> 42.75 | AD26: =$H26*Q26 -> 47.25 | ... AH26: =$H26*U26 -> 47.25 | AJ26: =(J26/J$4)/$F26 -> 0.05 | AK26: =(K26/K$4)/$F26 -> 0.05 | AL26: =(L26/L$4)/$F26 -> 0.05 | AM26: =(M26/M$4)/$F26 -> 0.05 | AN26: =(N26/N$4)/$F26 -> 0.05 | AO26: =(O26/O$4)/$F26 -> 0.05 | AP26: =(P26/P$4)/$F26 -> 0.05 | AQ26: =(Q26/Q$4)/$F26 -> 0.05 | ... AU26: =(U26/U$4)/$F26 -> 0.05
A27: =A26 -> CMS | B27: Active | C27: Payment posting - Manual | D27: Date Entry | E27: Intergy / Advanced MD / eCw | F27: 450 | G27: Transaction | H27: 0.27 | I27: =700/20 -> 35 | J27: =I27*J4 -> 700 | K27: =I27*K4 -> 735 | L27: =I27*L4 -> 735 | M27: =I27*M4 -> 770 | N27: =I27*N4 -> 735 | O27: =I27*O4 -> 665 | P27: =I27*P4 -> 665 | Q27: =I27*Q4 -> 735 | R27: =I27*R4 -> 700 | S27: =I27*S4 -> 735 | T27: =I27*T4 -> 665 | U27: =I27*U4 -> 735 | W27: =$H27*J27 -> 189 | X27: =$H27*K27 -> 198.45 | Y27: =$H27*L27 -> 198.45 | Z27: =$H27*M27 -> 207.9 | AA27: =$H27*N27 -> 198.45 | AB27: =$H27*O27 -> 179.55 | AC27: =$H27*P27 -> 179.55 | AD27: =$H27*Q27 -> 198.45 | ... AH27: =$H27*U27 -> 198.45 | AJ27: =(J27/J$4)/$F27 -> 0.077777778 | AK27: =(K27/K$4)/$F27 -> 0.077777778 | AL27: =(L27/L$4)/$F27 -> 0.077777778 | AM27: =(M27/M$4)/$F27 -> 0.077777778 | AN27: =(N27/N$4)/$F27 -> 0.077777778 | AO27: =(O27/O$4)/$F27 -> 0.077777778 | AP27: =(P27/P$4)/$F27 -> 0.077777778 | AQ27: =(Q27/Q$4)/$F27 -> 0.077777778 | ... AU27: =(U27/U$4)/$F27 -> 0.077777778
A28: =A27 -> CMS | B28: Active | C28: Payment posting ERA | D28: Date Entry | E28: Intergy / Advanced MD / eCw | F28: 450 | G28: Transaction | H28: 0.03 | I28: =4000/20 -> 200 | J28: =I28*J4 -> 4000 | K28: =I28*K4 -> 4200 | L28: =I28*L4 -> 4200 | M28: =I28*M4 -> 4400 | N28: =I28*N4 -> 4200 | O28: =I28*O4 -> 3800 | P28: =I28*P4 -> 3800 | Q28: =I28*Q4 -> 4200 | R28: =I28*R4 -> 4000 | S28: =I28*S4 -> 4200 | T28: =I28*T4 -> 3800 | U28: =I28*U4 -> 4200 | W28: =$H28*J28 -> 120 | X28: =$H28*K28 -> 126 | Y28: =$H28*L28 -> 126 | Z28: =$H28*M28 -> 132 | AA28: =$H28*N28 -> 126 | AB28: =$H28*O28 -> 114 | AC28: =$H28*P28 -> 114 | AD28: =$H28*Q28 -> 126 | ... AH28: =$H28*U28 -> 126 | AJ28: =(J28/J$4)/$F28 -> 0.44444444 | AK28: =(K28/K$4)/$F28 -> 0.44444444 | AL28: =(L28/L$4)/$F28 -> 0.44444444 | AM28: =(M28/M$4)/$F28 -> 0.44444444 | AN28: =(N28/N$4)/$F28 -> 0.44444444 | AO28: =(O28/O$4)/$F28 -> 0.44444444 | AP28: =(P28/P$4)/$F28 -> 0.44444444 | AQ28: =(Q28/Q$4)/$F28 -> 0.44444444 | ... AU28: =(U28/U$4)/$F28 -> 0.44444444
A29: Open dental | B29: Active | C29: Payment posting | D29: Date Entry | E29: Open Dental | F29: 80 | G29: FTE | H29: 1280 | J29: 2 | K29: 2 | L29: 2 | M29: 2 | N29: 2 | O29: 2 | P29: 2 | Q29: 2 | R29: 2 | S29: 2 | T29: 2 | U29: 2 | W29: =$H29*J29 -> 2560 | X29: =$H29*K29 -> 2560 | Y29: =$H29*L29 -> 2560 | Z29: =$H29*M29 -> 2560 | AA29: =$H29*N29 -> 2560 | AB29: =$H29*O29 -> 2560 | AC29: =$H29*P29 -> 2560 | AD29: =$H29*Q29 -> 2560 | ... AH29: =$H29*U29 -> 2560 | AJ29: =J29 -> 2 | AK29: =K29 -> 2 | AL29: =L29 -> 2 | AM29: =M29 -> 2 | AN29: =N29 -> 2 | AO29: =O29 -> 2 | AP29: =P29 -> 2 | AQ29: =Q29 -> 2 | ... AU29: =U29 -> 2
A30: DDR | B30: Active | C30: Payment posting - Manual | D30: Date Entry | E30: Gastro Med | F30: 180 | G30: FTE | H30: 1250 | J30: 4 | K30: 4 | L30: 4 | M30: 4 | N30: 4 | O30: 4 | P30: 4 | Q30: 4 | R30: 4 | S30: 4 | T30: 4 | U30: 4 | W30: =$H30*J30 -> 5000 | X30: =$H30*K30 -> 5000 | Y30: =$H30*L30 -> 5000 | Z30: =$H30*M30 -> 5000 | AA30: =$H30*N30 -> 5000 | AB30: =$H30*O30 -> 5000 | AC30: =$H30*P30 -> 5000 | AD30: =$H30*Q30 -> 5000 | ... AH30: =$H30*U30 -> 5000 | AJ30: =J30 -> 4 | AK30: =K30 -> 4 | AL30: =L30 -> 4 | AM30: =M30 -> 4 | AN30: =N30 -> 4 | AO30: =O30 -> 4 | AP30: =P30 -> 4 | AQ30: =Q30 -> 4 | ... AU30: =U30 -> 4
A31: =A30 -> DDR | B31: Active | C31: Payment posting ERA | D31: Date Entry | E31: Gastro Med | F31: 300 | G31: FTE | W31: =$H31*J31 -> 0 | X31: =$H31*K31 -> 0 | Y31: =$H31*L31 -> 0 | Z31: =$H31*M31 -> 0 | AA31: =$H31*N31 -> 0 | AB31: =$H31*O31 -> 0 | AC31: =$H31*P31 -> 0 | AD31: =$H31*Q31 -> 0 | ... AH31: =$H31*U31 -> 0 | AJ31: =J31 -> 0 | AK31: =K31 -> 0 | AL31: =L31 -> 0 | AM31: =M31 -> 0 | AN31: =N31 -> 0 | AO31: =O31 -> 0 | AP31: =P31 -> 0 | AQ31: =Q31 -> 0 | ... AU31: =U31 -> 0
A32: =A31 -> DDR | B32: In-Active | C32: Eligibility Benefits and Auth verification | D32: Date Entry | E32: Gastro Med | F32: 30 | G32: FTE | H32: 1350
A33: Encore | B33: In-Active | C33: Charge entry | E33: Raintree | F33: 800 | G33: Collection | H33: 0.065 | V33: Price change from 4% to 6.5% effective from. October 2023
A34: =A33 -> Encore | B34: In-Active | C34: Payment posting - Manual | E34: Raintree | F34: 300 | G34: Collection
A35: =A34 -> Encore | B35: In-Active | C35: Payment posting ERA | E35: Raintree | F35: 800 | G35: Collection
A36: =A35 -> Encore | B36: Active | C36: AR | D36: AR | E36: Raintree | F36: 40 | G36: Collection
A37: =A36 -> Encore | B37: In-Active | C37: EV | E37: Raintree | F37: 20 | G37: Collection
A38: =A37 -> Encore | B38: Active | C38: Credentialling | E38: CredSimplify | F38: 50 | G38: FTE | H38: 1300
A39: =A38 -> Encore | B39: In-Active | C39: Eligibility & Benefit Verification | E39: Raintree | F39: 30 | G39: FTE | H39: 1500
A40: Hillmed | B40: In-Active | C40: AR | E40: Intergy | F40: 35 | G40: FTE | H40: 1280
A41: =A40 -> Hillmed | B41: In-Active | C41: Charge entry | E41: Intergy | F41: 380 | G41: FTE | H41: 1120
A42: MISS & Dr. Tay | B42: In-Active | C42: AR | E42: Intergy | F42: 35 | G42: FTE | H42: 1280
A43: =A42 -> MISS & Dr. Tay | B43: In-Active | C43: Charge entry | E43: Intergy | F43: 380 | G43: FTE | H43: 1120
A44: ARMG | B44: Active | C44: Charge entry | E44: eCw | F44: 90 | G44: Collection | H44: IVF Collection 0.43% | J44: 12000 | K44: 12000 | L44: 12000 | M44: 12000 | N44: 12000 | O44: 12000 | P44: 12000 | Q44: 12000 | R44: 12000 | S44: 12000 | T44: 12000 | U44: 12000 | W44: 12000 | X44: 12000 | Y44: 12000 | Z44: 12000 | AA44: 12000 | AB44: 12000 | AC44: 12000 | AD44: 12000 | AE44: 12000 | AF44: 12000 | AG44: 12000 | AH44: 12000
A45: =A44 -> ARMG | B45: Active | C45: Payment posting - Manual | E45: eCw | F45: 120 | G45: Collection | H45: Non-IVF Collection 2.55%
A46: =A45 -> ARMG | B46: Active | C46: Payment posting ERA | E46: eCw | F46: 175 | G46: Collection | H46: Patient Collection 0.64%
A47: =A46 -> ARMG | B47: Active | C47: Print HCFA | E47: eCw | F47: 100 | G47: Collection
A48: =A47 -> ARMG | B48: Active | C48: Patient statement | E48: eCw | F48: 100 | G48: Collection
A49: =A48 -> ARMG | B49: Active | C49: AR Non calling | E49: eCw | F49: 64 | G49: Collection
A50: =A49 -> ARMG | B50: Active | C50: AR Calling | E50: eCw | F50: 40 | G50: Collection | J50: =J51/H51 -> 0.00086805556 | K50: =K51/H51 -> 0.0020833333
A51: Billpro | B51: Active | C51: Demo Verify | E51: Billpro | F51: 300 | G51: FTE | H51: 1440 | J51: 1.25 | K51: 3 | L51: 5 | M51: 5 | N51: 5 | O51: 5 | P51: 5 | Q51: 5 | R51: 5 | S51: 5 | T51: 5 | U51: 5 | W51: =$H51*J51 -> 1800 | X51: =$H51*K51 -> 4320 | Y51: =$H51*L51 -> 7200 | Z51: =$H51*M51 -> 7200 | AA51: =$H51*N51 -> 7200 | AB51: =$H51*O51 -> 7200 | AC51: =$H51*P51 -> 7200 | AD51: =$H51*Q51 -> 7200 | ... AH51: =$H51*U51 -> 7200 | AJ51: =J51 -> 1.25 | AK51: =K51 -> 3 | AL51: =L51 -> 5 | AM51: =M51 -> 5 | AN51: =N51 -> 5 | AO51: =O51 -> 5 | AP51: =P51 -> 5 | AQ51: =Q51 -> 5 | ... AU51: =U51 -> 5
A52: =A51 -> Billpro | B52: Active | C52: Demo Entry | E52: Billpro | F52: 300 | G52: FTE | W52: =$H52*J52 -> 0 | X52: =$H52*K52 -> 0 | Y52: =$H52*L52 -> 0 | Z52: =$H52*M52 -> 0 | AA52: =$H52*N52 -> 0 | AB52: =$H52*O52 -> 0 | AC52: =$H52*P52 -> 0 | AD52: =$H52*Q52 -> 0 | ... AH52: =$H52*U52 -> 0
A53: =A52 -> Billpro | B53: Active | C53: Charges | E53: Billpro | F53: 350 | G53: FTE | W53: =$H53*J53 -> 0 | X53: =$H53*K53 -> 0 | Y53: =$H53*L53 -> 0 | Z53: =$H53*M53 -> 0 | AA53: =$H53*N53 -> 0 | AB53: =$H53*O53 -> 0 | AC53: =$H53*P53 -> 0 | AD53: =$H53*Q53 -> 0 | ... AH53: =$H53*U53 -> 0
A54: =A53 -> Billpro | B54: Active | C54: AR Calling | E54: Billpro | F54: 30 | G54: FTE | W54: =$H54*J54 -> 0 | X54: =$H54*K54 -> 0 | Y54: =$H54*L54 -> 0 | Z54: =$H54*M54 -> 0 | AA54: =$H54*N54 -> 0 | AB54: =$H54*O54 -> 0 | AC54: =$H54*P54 -> 0 | AD54: =$H54*Q54 -> 0 | ... AH54: =$H54*U54 -> 0
A55: Von Marie | B55: Active | C55: AR | E55: Intergy | F55: 30 | G55: FTE | H55: 1600 | J55: 1.5 | K55: 1.5 | L55: 1.5 | M55: 1.5 | N55: 1.5 | O55: 1.5 | P55: 1.5 | Q55: 1.5 | R55: 1.5 | S55: 1.5 | T55: 1.5 | U55: 1.5 | W55: 2400 | X55: 2400 | Y55: 2400 | Z55: 2400 | AA55: 2400 | AB55: 2400 | AC55: 2400 | AD55: 2400 | AE55: 2400 | AF55: 2400 | AG55: 2400 | AH55: 2400 | AJ55: =J55 -> 1.5 | AK55: =K55 -> 1.5 | AL55: =L55 -> 1.5 | AM55: =M55 -> 1.5 | AN55: =N55 -> 1.5 | AO55: =O55 -> 1.5 | AP55: =P55 -> 1.5 | AQ55: =Q55 -> 1.5 | ... AU55: =U55 -> 1.5
A56: SSP | B56: Active | C56: Payment posting ERA | E56: eCw | F56: 180 | G56: FTE | H56: 1250
A57: =A56 -> SSP | B57: Active | C57: Payment posting Manual | E57: eCw | F57: 120 | G57: FTE | H57: 1250
A58: Comprehensive Sleep Care Center | B58: Active | C58: Comprehensive Sleep Care Center | F58: 30 | G58: FTE | H58: 1450 | J58: 9 | K58: 9 | L58: 9 | M58: 9 | N58: 5 | O58: 5 | P58: 5 | Q58: 5 | R58: 5 | S58: 5 | T58: 5 | U58: 5 | W58: =$H58*J58 -> 13050 | X58: =$H58*K58 -> 13050 | Y58: =$H58*L58 -> 13050 | Z58: =$H58*M58 -> 13050 | AA58: =$H58*N58 -> 7250 | AB58: =$H58*O58 -> 7250 | AC58: =$H58*P58 -> 7250 | AD58: =$H58*Q58 -> 7250 | ... AH58: =$H58*U58 -> 7250 | AJ58: =J58 -> 9 | AK58: =K58 -> 9 | AL58: =L58 -> 9 | AM58: =M58 -> 9 | AN58: =N58 -> 5 | AO58: =O58 -> 5 | AP58: =P58 -> 5 | AQ58: =Q58 -> 5 | ... AU58: =U58 -> 5
A59: Dr Scott | B59: Active | C59: End to End | G59: Collection | H59: 0.06 | J59: 100000 | K59: 100000 | L59: 100000 | M59: 100000 | N59: 100000 | O59: 100000 | P59: 100000 | Q59: 100000 | R59: 100000 | S59: 100000 | T59: 100000 | U59: 100000 | W59: =$H59*J59 -> 6000 | X59: =$H59*K59 -> 6000 | Y59: =$H59*L59 -> 6000 | Z59: =$H59*M59 -> 6000 | AA59: =$H59*N59 -> 6000 | AB59: =$H59*O59 -> 6000 | AC59: =$H59*P59 -> 6000 | AD59: =$H59*Q59 -> 6000 | ... AH59: =$H59*U59 -> 6000
A60: Sasan PTSMC | B60: Active | C60: End to End | G60: Collection | H60: 0.035 | K60: 250000 | L60: 250000 | M60: 250000 | N60: 250000 | O60: 250000 | P60: 250000 | Q60: 250000 | R60: 250000 | S60: 250000 | T60: 250000 | U60: 250000 | W60: =$H60*J60 -> 0 | X60: =$H60*K60 -> 8750 | Y60: =$H60*L60 -> 8750 | Z60: =$H60*M60 -> 8750 | AA60: =$H60*N60 -> 8750 | AB60: =$H60*O60 -> 8750 | AC60: =$H60*P60 -> 8750 | AD60: =$H60*Q60 -> 8750 | ... AH60: =$H60*U60 -> 8750
A61: Visco Supplements | B61: In-Active | C61: Visco Supplements | F61: 30 | G61: FTE | H61: 1500
A62: HIS Special Project | B62: Active | C62: Payment Posing one time | F62: 200 | G62: FTE | H62: 2100
A63: HIS OSIS | B63: In-Active | C63: Old AR Follow-up | F63: 30 | G63: Collection | H63: 0.14
A64: RCS7 IOSSM | B64: In-Active | C64: AR Follow-up | F64: 30 | G64: FTE | H64: 1350
A65: IQMS | B65: In-Active | C65: Old AR Follow-up | F65: 30 | G65: FTE | H65: 1450
A66: Dr Debbas | B66: In-Active | C66: End to End | G66: Collection | H66: 0.07
A67: Falcon Er Urgent Care | B67: Active | C67: Credentialing | G67: Per Application | H67: 100
A68: Primepulmonarysleep Dr Bansal | B68: In-Active | C68: AR Follow-up | F68: 30 | G68: FTE | H68: 1440
A69: Dr Henry | B69: In-Active | C69: End to End | G69: Collection | H69: 300
A70: Aloha Vein | B70: In-Active | C70: Payment Posting | G70: Transaction | H70: 7
A71: eCare | B71: In-Active | C71: Patient Payment | G71: Transaction | H71: 7
A72: eCare | B72: In-Active | C72: Insurance Payment | G72: Transaction | H72: 7
A73: eCare | B73: In-Active | C73: Patient Statement | G73: Transaction | H73: 7
A74: eCare | B74: In-Active | C74: AR Follow-up | G74: Transaction | H74: 8
A75: eCare | B75: In-Active | C75: Collection Patients e-Message | G75: Transaction | H75: 7
T77: Base Revenue | W77: =SUM(W6:W75) -> 89399.188 | X77: =SUM(X6:X75) -> 102738.65 | Y77: =SUM(Y6:Y75) -> 105618.65 | Z77: =SUM(Z6:Z75) -> 107688.11 | AA77: =SUM(AA6:AA75) -> 99818.647 | AB77: =SUM(AB6:AB75) -> 95679.729 | AC77: =SUM(AC6:AC75) -> 95679.729 | AD77: =SUM(AD6:AD75) -> 99818.647 | ... AH77: =SUM(AH6:AH75) -> 99818.647 | AJ77: =SUM(AJ6:AJ75) -> 44.535835 | AK77: =SUM(AK6:AK75) -> 46.285835 | AL77: =SUM(AL6:AL75) -> 48.285835 | AM77: =SUM(AM6:AM75) -> 48.285835 | AN77: =SUM(AN6:AN75) -> 44.285835 | AO77: =SUM(AO6:AO75) -> 44.285835 | AP77: =SUM(AP6:AP75) -> 44.285835 | AQ77: =SUM(AQ6:AQ75) -> 44.285835 | ... AU77: =SUM(AU6:AU75) -> 44.285835
T78: Price per FTE | W78: =W77/AJ77 -> 2007.354 | X78: =X77/AK77 -> 2219.6563 | Y78: =Y77/AL77 -> 2187.363 | Z78: =Z77/AM77 -> 2230.2215 | AA78: =AA77/AN77 -> 2253.9633 | AB78: =AB77/AO77 -> 2160.5041 | AC78: =AC77/AP77 -> 2160.5041 | AD78: =AD77/AQ77 -> 2253.9633 | ... AH78: =AH77/AU77 -> 2253.9633
T79: Base FTE | W79: =AJ77 -> 44.535835 | X79: =AK77 -> 46.285835 | Y79: =AL77 -> 48.285835 | Z79: =AM77 -> 48.285835 | AA79: =AN77 -> 44.285835 | AB79: =AO77 -> 44.285835 | AC79: =AP77 -> 44.285835 | AD79: =AQ77 -> 44.285835 | ... AH79: =AU77 -> 44.285835
T82: New Revenue | W82: 25000 | X82: =W82+25000 -> 50000 | Y82: =X82+25000 -> 75000 | Z82: =Y82+25000 -> 100000 | AA82: =Z82+25000 -> 125000 | AB82: =AA82+25000 -> 150000 | AC82: =AB82+25000 -> 175000 | AD82: =AC82+25000 -> 200000 | AE82: =AD82+25000 -> 225000 | ... AH82: =AG82+25000 -> 300000
T83: Price per FTE | W83: 1800 | X83: 1800 | Y83: 1800 | Z83: 1800 | AA83: 1800 | AB83: 1800 | AC83: 1800 | AD83: 1800 | AE83: 1800 | AF83: 1800 | AG83: 1800 | AH83: 1800
T84: Base FTE | W84: =W82/W83 -> 13.888889 | X84: =X82/X83 -> 27.777778 | Y84: =Y82/Y83 -> 41.666667 | Z84: =Z82/Z83 -> 55.555556 | AA84: =AA82/AA83 -> 69.444444 | AB84: =AB82/AB83 -> 83.333333 | AC84: =AC82/AC83 -> 97.222222 | AD84: =AD82/AD83 -> 111.11111 | ... AH84: =AH82/AH83 -> 166.66667
T86: Total Base FTE | W86: =W84+W79 -> 58.424724 | X86: =X84+X79 -> 74.063613 | Y86: =Y84+Y79 -> 89.952502 | Z86: =Z84+Z79 -> 103.84139 | AA86: =AA84+AA79 -> 113.73028 | AB86: =AB84+AB79 -> 127.61917 | AC86: =AC84+AC79 -> 141.50806 | AD86: =AD84+AD79 -> 155.39695 | ... AH86: =AH84+AH79 -> 210.9525
T87: DE
T88: AR
T91: Utilisation | W91: 0.65 | X91: =W91+5% -> 0.7 | Y91: =X91+5% -> 0.75 | Z91: =Y91+5% -> 0.8 | AA91: =Z91+5% -> 0.85 | AB91: =AA91 -> 0.85 | AC91: =AB91 -> 0.85 | AD91: =AC91 -> 0.85 | AE91: =AD91 -> 0.85 | AF91: =AE91 -> 0.85 | AG91: =AF91 -> 0.85 | AH91: =AG91 -> 0.85
V92: Current HC
T93: Deployed FTEs | W93: =W86/W91 -> 89.884191 | X93: =X86/X91 -> 105.80516 | Y93: =Y86/Y91 -> 119.93667 | Z93: =Z86/Z91 -> 129.80174 | AA93: =AA86/AA91 -> 133.80033 | AB93: =AB86/AB91 -> 150.1402 | AC93: =AC86/AC91 -> 166.48007 | AD93: =AD86/AD91 -> 182.81994 | ... AH93: =AH86/AH91 -> 248.17941
T94: DE
T95: AR
T97: TL | U97: 20 | W97: =W$93/$U97 -> 4.4942095 | X97: =X$93/$U97 -> 5.2902581 | Y97: =Y$93/$U97 -> 5.9968335 | Z97: =Z$93/$U97 -> 6.4900869 | AA97: =AA$93/$U97 -> 6.6900165 | AB97: =AB$93/$U97 -> 7.5070099 | AC97: =AC$93/$U97 -> 8.3240034 | AD97: =AD$93/$U97 -> 9.1409968 | ... AH97: =AH$93/$U97 -> 12.408971
T98: AM | U98: 50 | W98: =W$93/$U98 -> 1.7976838 | X98: =X$93/$U98 -> 2.1161032 | Y98: =Y$93/$U98 -> 2.3987334 | Z98: =Z$93/$U98 -> 2.5960348 | AA98: =AA$93/$U98 -> 2.6760066 | AB98: =AB$93/$U98 -> 3.002804 | AC98: =AC$93/$U98 -> 3.3296014 | AD98: =AD$93/$U98 -> 3.6563987 | ... AH98: =AH$93/$U98 -> 4.9635883
T99: Manager | U99: 100 | W99: =W$93/$U99 -> 0.89884191 | X99: =X$93/$U99 -> 1.0580516 | Y99: =Y$93/$U99 -> 1.1993667 | Z99: =Z$93/$U99 -> 1.2980174 | AA99: =AA$93/$U99 -> 1.3380033 | AB99: =AB$93/$U99 -> 1.501402 | AC99: =AC$93/$U99 -> 1.6648007 | AD99: =AD$93/$U99 -> 1.8281994 | ... AH99: =AH$93/$U99 -> 2.4817941
T101: QA | U101: 50 | W101: =W$93/$U101 -> 1.7976838 | X101: =X$93/$U101 -> 2.1161032 | Y101: =Y$93/$U101 -> 2.3987334 | Z101: =Z$93/$U101 -> 2.5960348 | AA101: =AA$93/$U101 -> 2.6760066 | AB101: =AB$93/$U101 -> 3.002804 | AC101: =AC$93/$U101 -> 3.3296014 | AD101: =AD$93/$U101 -> 3.6563987 | ... AH101: =AH$93/$U101 -> 4.9635883
T102: Training | U102: 25 | W102: =W$93/$U102 -> 3.5953676 | X102: =X$93/$U102 -> 4.2322065 | Y102: =Y$93/$U102 -> 4.7974668 | Z102: =Z$93/$U102 -> 5.1920695 | AA102: =AA$93/$U102 -> 5.3520132 | AB102: =AB$93/$U102 -> 6.0056079 | AC102: =AC$93/$U102 -> 6.6592027 | AD102: =AD$93/$U102 -> 7.3127975 | ... AH102: =AH$93/$U102 -> 9.9271766
T105: Total Headcount - Operations | W105: =SUM(W93:W104) -> 102.46798 | X105: =SUM(X93:X104) -> 120.61788 | Y105: =SUM(Y93:Y104) -> 136.7278 | Z105: =SUM(Z93:Z104) -> 147.97398 | AA105: =SUM(AA93:AA104) -> 152.53238 | AB105: =SUM(AB93:AB104) -> 171.15983 | AC105: =SUM(AC93:AC104) -> 189.78728 | AD105: =SUM(AD93:AD104) -> 208.41473 | ... AH105: =SUM(AH93:AH104) -> 282.92453
C108: Operational Expenses
C109: Salaries-Operations & Support
C110: Facilities
C111: Telcom/Data & others
C112: Transportation charges
...

Sheet 1. Revenue Buildup 2026
A1: Imagnum India Private Limited
A2: Revenue Buildup
B4: Revenue Summary - 2026 (Budgeted)
B5: Particulars | C5: Total | D5: 46023 | E5: 46054 | F5: 46082 | G5: 46113 | H5: 46143 | I5: 46174 | J5: 46204 | K5: 46235 | L5: 46266 | M5: 46296 | N5: 46327 | O5: 46357
A6: 1 | B6: Base Revenue + New confirmed | C6: =SUM(D6:O6) -> 2490257.2 | D6: ='Base Revenue Details'!J59 -> 225414.12 | E6: ='Base Revenue Details'!L59 -> 238765.5 | F6: ='Base Revenue Details'!N59 -> 239597.86 | G6: ='Base Revenue Details'!P59 -> 203603.86 | H6: ='Base Revenue Details'!S59 -> 199015.5 | I6: ='Base Revenue Details'!U59 -> 198603.86 | J6: ='Base Revenue Details'!W59 -> 198603.86 | K6: ='Base Revenue Details'!Y59 -> 196937.7 | L6: ='Base Revenue Details'!AA59 -> 196937.7 | M6: ='Base Revenue Details'!AC59 -> 198603.86 | N6: ='Base Revenue Details'!AE59 -> 195569.5 | O6: ='Base Revenue Details'!AG59 -> 198603.86
B7: Price per FTE | D7: =D6/'Base Revenue'!X61 -> 1751.4515 | E7: =E6/'Base Revenue'!Y61 -> 1806.075 | F7: =F6/'Base Revenue'!Z61 -> 1960.2002 | G7: =G6/'Base Revenue'!AA61 -> 1665.7258 | H7: =H6/'Base Revenue'!AB61 -> 1628.1875 | I7: =I6/'Base Revenue'!AC61 -> 1624.8198 | J7: =J6/'Base Revenue'!AD61 -> 1624.8198 | K7: =K6/'Base Revenue'!AE61 -> 1611.1885 | ... O7: =O6/'Base Revenue'!AI61 -> 1624.8198
B8: Base FTE | D8: ='Base Revenue'!X61 -> 128.70132 | E8: ='Base Revenue'!Y61 -> 132.20132 | F8: ='Base Revenue'!Z61 -> 122.23132 | G8: ='Base Revenue'!AA61 -> 122.23132 | H8: ='Base Revenue'!AB61 -> 122.23132 | I8: ='Base Revenue'!AC61 -> 122.23132 | J8: ='Base Revenue'!AD61 -> 122.23132 | K8: ='Base Revenue'!AE61 -> 122.23132 | ... O8: ='Base Revenue'!AI61 -> 122.23132
A9: 2 | B9: New Revenue | C9: =SUM(D9:O9) -> 319500 | H9: =H55 -> 13800 | I9: =I55 -> 16800 | J9: =J55 -> 17150 | K9: =K55 -> 49550 | L9: =L55 -> 53550 | M9: =M55 -> 53550 | N9: =N55 -> 57550 | O9: =O55 -> 57550
B10: Price per FTE | D10: 1400 | E10: 1400 | F10: 1400 | G10: 1400 | H10: 1400 | I10: 1400 | J10: 1400 | K10: 1400 | L10: 1400 | M10: 1400 | N10: 1400 | O10: 1400
B11: Additional FTE | D11: =IFERROR(D9/D10,0) -> 0 | E11: =IFERROR(E9/E10,0) -> 0 | F11: =IFERROR(F9/F10,0) -> 0 | G11: =IFERROR(G9/G10,0) -> 0 | H11: =H66 -> 7 | I11: =I66 -> 7 | J11: =J66 -> 12 | K11: =K66 -> 40 | L11: =L66 -> 45 | M11: =M66 -> 50 | N11: =N66 -> 55 | O11: =O66 -> 60
B13: Total Revenue | D13: =D9+D6 -> 225414.12 | E13: =E9+E6 -> 238765.5 | F13: =F9+F6 -> 239597.86 | G13: =G9+G6 -> 203603.86 | H13: =H9+H6 -> 212815.5 | I13: =I9+I6 -> 215403.86 | J13: =J9+J6 -> 215753.86 | K13: =K9+K6 -> 246487.7 | ... O13: =O9+O6 -> 256153.86
B14: Utilisation | D14: 0.85 | E14: 0.85 | F14: 0.85 | G14: 0.85 | H14: 0.85 | I14: 0.85 | J14: 0.85 | K14: 0.85 | L14: 0.85 | M14: 0.85 | N14: 0.85 | O14: 0.85
B15: Deployed FTEs for Total Revenue | D15: =D8+D11 -> 128.70132 | E15: =E8+E11 -> 132.20132 | F15: =F8+F11 -> 122.23132 | G15: =G8+G11 -> 122.23132 | H15: =H8+H11 -> 129.23132 | I15: =I8+I11 -> 129.23132 | J15: =J8+J11 -> 134.23132 | K15: =K8+K11 -> 162.23132 | ... O15: =O8+O11 -> 182.23132 | P15: =SUM(D15:O15) -> 1759.2158
B16: Deployed FTEs @ 85% Utilization | D16: =D15/D14 -> 151.41332 | E16: =E15/E14 -> 155.53096 | F16: =F15/F14 -> 143.80155 | G16: =G15/G14 -> 143.80155 | H16: =H15/H14 -> 152.03684 | I16: =I15/I14 -> 152.03684 | J16: =J15/J14 -> 157.9192 | K16: =K15/K14 -> 190.86037 | ... O16: =O15/O14 -> 214.38979 | P16: =SUM(D16:O16) -> 2069.6657
B17: Current Deployed FTEs | D17: ='India Expenses - Detailed'!E13+19 -> 185 | E17: ='India Expenses - Detailed'!F13+19 -> 185 | F17: ='India Expenses - Detailed'!G13+19 -> 176 | G17: ='India Expenses - Detailed'!H13 -> 157 | H17: ='India Expenses - Detailed'!I13 -> 164 | I17: ='India Expenses - Detailed'!J13 -> 164 | J17: ='India Expenses - Detailed'!K13 -> 169 | K17: ='India Expenses - Detailed'!L13 -> 197 | L17: ='India Expenses - Detailed'!M13 -> 202 | M17: ='India Expenses - Detailed'!N13 -> 207 | N17: ='India Expenses - Detailed'!O13 -> 212 | O17: ='India Expenses - Detailed'!P13 -> 217 | P17: =SUM(D17:O17) -> 2235
B19: Rev/FTE | D19: =D13/D15 -> 1751.4515 | E19: =E13/E15 -> 1806.075 | F19: =F13/F15 -> 1960.2002 | G19: =G13/G15 -> 1665.7258 | H19: =H13/H15 -> 1646.7796 | I19: =I13/I15 -> 1666.8085 | J19: =J13/J15 -> 1607.3288 | K19: =K13/K15 -> 1519.3595 | ... O19: =O13/O15 -> 1405.6522
B20: Rev/FTE @ 85% Utilization | D20: =D13/D16 -> 1488.7338 | E20: =E13/E16 -> 1535.1638 | F20: =F13/F16 -> 1666.1702 | G20: =G13/G16 -> 1415.8669 | H20: =H13/H16 -> 1399.7627 | I20: =I13/I16 -> 1416.7872 | J20: =J13/J16 -> 1366.2295 | K20: =K13/K16 -> 1291.4556 | ... O20: =O13/O16 -> 1194.8044
B21: Rev/FTE @ Current headcount | D21: =D13/D17 -> 1218.4547 | E21: =E13/E17 -> 1290.6243 | F21: =F13/F17 -> 1361.3515 | G21: =G13/G17 -> 1296.8399 | H21: =H13/H17 -> 1297.6555 | I21: =I13/I17 -> 1313.4382 | J21: =J13/J17 -> 1276.6501 | K21: =K13/K17 -> 1251.2066 | ... O21: =O13/O17 -> 1180.4325
B23: % growth | E23: =(E13-D13)/D13 -> 0.059230451 | F23: =(F13-E13)/E13 -> 0.0034860983 | G23: =(G13-F13)/F13 -> -0.15022672 | H23: =(H13-G13)/G13 -> 0.045242954 | I23: =(I13-H13)/H13 -> 0.01216246 | J23: =(J13-I13)/I13 -> 0.0016248548 | K23: =(K13-J13)/J13 -> 0.14244862 | L23: =(L13-K13)/K13 -> 0.01622799 | ... O23: =(O13-N13)/N13 -> 0.011987856
B25: Actual Scenario for CY 2025 for comparison
B26: Particulars | C26: Total | D26: 45658 | E26: 45689 | F26: 45717 | G26: 45748 | H26: 45778 | I26: 45809 | J26: 45839 | K26: 45870 | L26: 45901 | M26: 45931 | N26: 45962 | O26: 45992
B27: Base Revenue | C27: =SUM(D27:O27) -> 2793856.9 | D27: 190587.61 | E27: 238264.71 | F27: 206236 | G27: 220307.54 | H27: 241763 | I27: 255826 | J27: 269055.27 | K27: 245075.07 | L27: 241343.74 | M27: 236462 | N27: 224468 | O27: 224468
B28: Price per FTE
B29: Base FTE
B31: Directs | C31: =SUM(D31:O31) -> 2181 | D31: 148 | E31: 154 | F31: 163 | G31: 170 | H31: 170 | I31: 173 | J31: 187 | K31: 205 | L31: 200 | M31: 205 | N31: 203 | O31: =N31 -> 203
B32: FTE generated | C32: =SUM(D32:O32) -> 1399.2135 | D32: 118 | E32: 87 | F32: 95 | G32: 102 | H32: 103 | I32: 110 | J32: 116 | K32: 139.75092 | L32: 137.62317 | M32: 134.83942 | N32: 128 | O32: 128
B33: Actual Utilisation | C33: =C32/C31 -> 0.64154677 | D33: =D32/D31 -> 0.7972973 | E33: =E32/E31 -> 0.56493506 | F33: =F32/F31 -> 0.58282209 | G33: =G32/G31 -> 0.6 | H33: =H32/H31 -> 0.60588235 | I33: =I32/I31 -> 0.63583815 | J33: =J32/J31 -> 0.62032086 | ... O33: =O32/O31 -> 0.63054187
B35: Utilisation | D35: 0.85 | E35: 0.85 | F35: 0.85 | G35: 0.85 | H35: 0.85 | I35: 0.85 | J35: 0.85 | K35: 0.85 | L35: 0.85 | M35: 0.85 | N35: 0.85 | O35: 0.85
B36: Rev/ FTE (Operational HC) | C36: =C27/C31 -> 1280.9981 | D36: =D27/D31 -> 1287.7541 | E36: =E27/E31 -> 1547.1734 | F36: =F27/F31 -> 1265.2515 | G36: =G27/G31 -> 1295.9267 | H36: =H27/H31 -> 1422.1353 | I36: =I27/I31 -> 1478.763 | J36: =J27/J31 -> 1438.7982 | ... O36: =O27/O31 -> 1105.7537
B37: Price/ FTE (based on budgeted utilisation for FTE generated) | D37: =D27/(D32/85%) -> 1372.8769 | E37: =E27/(E32/85%) -> 2327.8736 | F37: =F27/(F32/85%) -> 1845.2695 | G37: =G27/(G32/85%) -> 1835.8962 | H37: =H27/(H32/85%) -> 1995.1316 | I37: =I27/(I32/85%) -> 1976.8373 | J37: =J27/(J32/85%) -> 1971.5257 | K37: =K27/(K32/85%) -> 1490.6078 | ... O37: =O27/(O32/85%) -> 1490.6078
B38: Cost/FTE | D38: 739.17474 | E38: 682.37081 | F38: 810 | G38: 719 | H38: 744 | I38: 746 | J38: 777 | K38: 860 | L38: 793 | M38: 840 | N38: 842 | O38: 842
B48: New Revenue Calculations Breakdown
B49: New Revenue Workings( 7FTE * 1450) starting in May | H49: =7*1450 -> 10150 | I49: =7*1450 -> 10150 | J49: =7*1450 -> 10150 | K49: =7*1450 -> 10150 | L49: =7*1450 -> 10150 | M49: =7*1450 -> 10150 | N49: =7*1450 -> 10150 | O49: =7*1450 -> 10150
B50: 2650 Rev for 2months only - No headcount increase | H50: 2650 | I50: 2650
B51: 1000 Rev for 2months only - No headcount increase | H51: 1000 | I51: 1000
B52: 32400 Rev per month from August | K52: 32400 | L52: 32400 | M52: 32400 | N52: 32400 | O52: 32400
B53: 200000 collections @ 2% from July till Dec and increase in Sep and Nov | J53: =200000*2% -> 4000 | K53: =200000*2% -> 4000 | L53: =200000*2%+200000*2% -> 8000 | M53: =200000*2%+200000*2% -> 8000 | N53: =200000*2%+200000*2%+200000*2% -> 12000 | O53: =200000*2%+200000*2%+200000*2% -> 12000
B54: 3000 Rev from June till Dec | I54: 3000 | J54: 3000 | K54: 3000 | L54: 3000 | M54: 3000 | N54: 3000 | O54: 3000
H55: =SUM(H49:H54) -> 13800 | I55: =SUM(I49:I54) -> 16800 | J55: =SUM(J49:J54) -> 17150 | K55: =SUM(K49:K54) -> 49550 | L55: =SUM(L49:L54) -> 53550 | M55: =SUM(M49:M54) -> 53550 | N55: =SUM(N49:N54) -> 57550 | O55: =SUM(O49:O54) -> 57550
B57: FTE Required for the increased Rev
B58: 1450*7 FTEs | H58: 7 | I58: 7 | J58: 7 | K58: 7 | L58: 7 | M58: 7 | N58: 7 | O58: 7
B59: Added 5 FTEs every month from July till Dec | J59: 5 | K59: 5 | L59: 5 | M59: 5 | N59: 5 | O59: 5
B60: Added 5 FTEs every month from July till Dec | K60: 5 | L60: 5 | M60: 5 | N60: 5 | O60: 5
B61: Added 5 FTEs every month from July till Dec | L61: 5 | M61: 5 | N61: 5 | O61: 5
B62: Added 5 FTEs every month from July till Dec | M62: 5 | N62: 5 | O62: 5
B63: Added 5 FTEs every month from July till Dec | N63: 5 | O63: 5
B64: Added 5 FTEs every month from July till Dec | O64: 5
B65: FTEs for 32.4K Rev | K65: =ROUND(K52/1400,0) -> 23 | L65: =ROUND(L52/1400,0) -> 23 | M65: =ROUND(M52/1400,0) -> 23 | N65: =ROUND(N52/1400,0) -> 23 | O65: =ROUND(O52/1400,0) -> 23
H66: =SUM(H58:H65) -> 7 | I66: =SUM(I58:I65) -> 7 | J66: =SUM(J58:J65) -> 12 | K66: =SUM(K58:K65) -> 40 | L66: =SUM(L58:L65) -> 45 | M66: =SUM(M58:M65) -> 50 | N66: =SUM(N58:N65) -> 55 | O66: =SUM(O58:O65) -> 60
J67: =J66*360 -> 4320
J68: =J67*12% -> 518.4

Sheet Base Revenue
A1: I Magnum | BK1: Base | BL1: =SUM(AJ6:AJ60) -> 1483.2158 | BN1: Deployment
A2: Base Revenue | BK2: Absenteeism | BL2: 0.1 | BM2: =100%-BL2-BL3 -> 0.85 | BN2: =BL1/BM2 -> 1744.9598 | BO2: =BN2*BM2 -> 1483.2158
X3: Base FTEs | AL3: Base FTEs @85% Utlization | BK3: Attrition | BL3: 0.05
AL4: 0.8
A5: Client Code | B5: Status2 | C5: Client | D5: Active/Inactive | E5: Scope | F5: Billing Type | G5: Norm | H5: Pricing | I5: Total Volume | J5: Jan | K5: Feb | L5: Mar | M5: Apr | N5: May | O5: Jun | P5: Jul | Q5: Aug | R5: Sep | S5: Oct | T5: Nov | U5: Dec | V5: Total | X5: Jan | Y5: Feb | Z5: Mar | AA5: Apr | AB5: May | AC5: Jun | AD5: Jul | AE5: Aug | AF5: Sep | AG5: Oct | AH5: Nov | AI5: Dec | AJ5: Total | AL5: Jan | AM5: Feb | AN5: Mar | AO5: Apr | AP5: May | AQ5: Jun | AR5: Jul | AS5: Aug | AT5: Sep | AU5: Oct | AV5: Nov | AW5: Dec | AX5: Total | AY5: Monthly Avg | BA5: AM & MT | BB5: DM | BC5: Manager | BD5: Training | BE5: SWAT | BF5: MIS | BG5: Development | BH5: Ops Support | BK5: Overall | BL5: Rev | BM5: Base FTE | BN5: Rev/FTE
B6: Base | C6: eC3 LLC | E6: IVF Collection | F6: Collection | G6: 150 | H6: 0.0043 | J6: 2365 | K6: 2365 | L6: 2451 | M6: 2580 | N6: 2365 | O6: 2580 | P6: 2580 | Q6: 2580 | R6: 2580 | S6: 2580 | T6: 2580 | U6: 2580 | V6: =SUM(J6:U6) -> 30186 | X6: ='Base FTE'!$I36 -> 2.2857143 | Y6: ='Base FTE'!$I36 -> 2.2857143 | Z6: ='Base FTE'!$I36 -> 2.2857143 | AA6: ='Base FTE'!$I36 -> 2.2857143 | AB6: ='Base FTE'!$I36 -> 2.2857143 | AC6: ='Base FTE'!$I36 -> 2.2857143 | AD6: ='Base FTE'!$I36 -> 2.2857143 | AE6: ='Base FTE'!$I36 -> 2.2857143 | ... AI6: ='Base FTE'!$I36 -> 2.2857143 | AJ6: =SUM(X6:AI6) -> 27.428571 | AL6: =X6/$AL$4 -> 2.8571429 | AM6: =Y6/$AL$4 -> 2.8571429 | AN6: =Z6/$AL$4 -> 2.8571429 | AO6: =AA6/$AL$4 -> 2.8571429 | AP6: =AB6/$AL$4 -> 2.8571429 | AQ6: =AC6/$AL$4 -> 2.8571429 | AR6: =AD6/$AL$4 -> 2.8571429 | AS6: =AE6/$AL$4 -> 2.8571429 | ... AW6: =AI6/$AL$4 -> 2.8571429 | AX6: =SUM(AL6:AW6) -> 34.285714 | AY6: =AX6/12 -> 2.8571429 | BA6: =AY6/'2. Headcount Buildup'!$D$36 -> 0.19047619 | BB6: =AY6/'2. Headcount Buildup'!$D$37 -> 0.057142857 | BC6: =AY6/'2. Headcount Buildup'!$D$38 -> 0.028571429 | BD6: =AY6/'2. Headcount Buildup'!$D$43 -> 0.028571429 | BE6: =(SUM('2. Headcount Buildup'!$F$44:$Q$44)/12)*('Base Revenue'!$AY6/'Base Revenue'!$AY$61) -> 0.05547791 | BF6: =(SUM('2. Headcount Buildup'!$F$45:$Q$45)/12)*('Base Revenue'!$AY6/'Base Revenue'!$AY$61) -> 0.092463184 | BG6: =(SUM('2. Headcount Buildup'!$F$46:$Q$46)/12)*('Base Revenue'!$AY6/'Base Revenue'!$AY$61) -> 0.14794109 | BH6: =SUM(BA6:BG6) -> 0.60064409 | BK6: eC3 LLC | BL6: =IFERROR(SUMIF($C$6:$C$60,BK6,$V$6:$V$60),0) -> 136567 | BM6: =IFERROR(SUMIF($C$5:$C$60,BK6,$AJ$5:$AJ$60),0) -> 27.428571 | BN6: =IFERROR(BL6/BM6,0) -> 4979.0052
B7: Base | C7: eC3 LLC | E7: Non-IVF Collection | F7: Collection | G7: 150 | H7: 0.0255 | J7: 7650 | K7: 7650 | L7: 8415 | M7: 8925 | N7: 7650 | O7: 8925 | P7: 8925 | Q7: 8925 | R7: 8925 | S7: 8925 | T7: 8925 | U7: 8925 | V7: =SUM(J7:U7) -> 102765 | AJ7: =SUM(X7:AI7) -> 0 | AX7: =SUM(AL7:AW7) -> 0 | AY7: =AX7/12 -> 0 | BA7: =AY7/'2. Headcount Buildup'!$D$36 -> 0 | BB7: =AY7/'2. Headcount Buildup'!$D$37 -> 0 | BC7: =AY7/'2. Headcount Buildup'!$D$38 -> 0 | BD7: =AY7/'2. Headcount Buildup'!$D$43 -> 0 | BE7: =(SUM('2. Headcount Buildup'!$F$44:$Q$44)/12)*('Base Revenue'!$AY7/'Base Revenue'!$AY$61) -> 0 | BF7: =(SUM('2. Headcount Buildup'!$F$45:$Q$45)/12)*('Base Revenue'!$AY7/'Base Revenue'!$AY$61) -> 0 | BG7: =(SUM('2. Headcount Buildup'!$F$46:$Q$46)/12)*('Base Revenue'!$AY7/'Base Revenue'!$AY$61) -> 0 | BH7: =SUM(BA7:BG7) -> 0 | BK7: D'Souza & Associates, Inc | BL7: =IFERROR(SUMIF($C$6:$C$60,BK7,$V$6:$V$60),0) -> 365662.68 | BM7: =IFERROR(SUMIF($C$5:$C$60,BK7,$AJ$5:$AJ$60),0) -> 341.41311 | BN7: =IFERROR(BL7/BM7,0) -> 1071.0271
B8: Base | C8: eC3 LLC | E8: Patient Collection | F8: Collection | G8: 150 | H8: 0.0064 | J8: 256 | K8: 256 | L8: 288 | M8: 320 | N8: 256 | O8: 320 | P8: 320 | Q8: 320 | R8: 320 | S8: 320 | T8: 320 | U8: 320 | V8: =SUM(J8:U8) -> 3616 | AJ8: =SUM(X8:AI8) -> 0 | AX8: =SUM(AL8:AW8) -> 0 | AY8: =AX8/12 -> 0 | BA8: =AY8/'2. Headcount Buildup'!$D$36 -> 0 | BB8: =AY8/'2. Headcount Buildup'!$D$37 -> 0 | BC8: =AY8/'2. Headcount Buildup'!$D$38 -> 0 | BD8: =AY8/'2. Headcount Buildup'!$D$43 -> 0 | BE8: =(SUM('2. Headcount Buildup'!$F$44:$Q$44)/12)*('Base Revenue'!$AY8/'Base Revenue'!$AY$61) -> 0 | BF8: =(SUM('2. Headcount Buildup'!$F$45:$Q$45)/12)*('Base Revenue'!$AY8/'Base Revenue'!$AY$61) -> 0 | BG8: =(SUM('2. Headcount Buildup'!$F$46:$Q$46)/12)*('Base Revenue'!$AY8/'Base Revenue'!$AY$61) -> 0 | BH8: =SUM(BA8:BG8) -> 0 | BK8: Univ. Of Delaware | BL8: =IFERROR(SUMIF($C$6:$C$60,BK8,$V$6:$V$60),0) -> 104400 | BM8: =IFERROR(SUMIF($C$5:$C$60,BK8,$AJ$5:$AJ$60),0) -> 87.770327 | BN8: =IFERROR(BL8/BM8,0) -> 1189.4681
B9: Base | C9: D'Souza & Associates, Inc | E9: Demo Entry | F9: Transaction | G9: 300 | H9: 0.55 | I9: 840 | J9: 462 | K9: 462 | L9: 462 | M9: 462 | N9: 462 | O9: 462 | P9: 462 | Q9: 462 | R9: 462 | S9: 462 | T9: 462 | U9: 462 | V9: =SUM(J9:U9) -> 5544 | X9: =$I9/$G9/21 -> 0.13333333 | Y9: =$I9/$G9/21 -> 0.13333333 | Z9: =$I9/$G9/21 -> 0.13333333 | AA9: =$I9/$G9/21 -> 0.13333333 | AB9: =$I9/$G9/21 -> 0.13333333 | AC9: =$I9/$G9/21 -> 0.13333333 | AD9: =$I9/$G9/21 -> 0.13333333 | AE9: =$I9/$G9/21 -> 0.13333333 | ... AI9: =$I9/$G9/21 -> 0.13333333 | AJ9: =SUM(X9:AI9) -> 1.6 | AL9: =X9/$AL$4 -> 0.16666667 | AM9: =Y9/$AL$4 -> 0.16666667 | AN9: =Z9/$AL$4 -> 0.16666667 | AO9: =AA9/$AL$4 -> 0.16666667 | AP9: =AB9/$AL$4 -> 0.16666667 | AQ9: =AC9/$AL$4 -> 0.16666667 | AR9: =AD9/$AL$4 -> 0.16666667 | AS9: =AE9/$AL$4 -> 0.16666667 | ... AW9: =AI9/$AL$4 -> 0.16666667 | AX9: =SUM(AL9:AW9) -> 2 | AY9: =AX9/12 -> 0.16666667 | BA9: =AY9/'2. Headcount Buildup'!$D$36 -> 0.011111111 | BB9: =AY9/'2. Headcount Buildup'!$D$37 -> 0.0033333333 | BC9: =AY9/'2. Headcount Buildup'!$D$38 -> 0.0016666667 | BD9: =AY9/'2. Headcount Buildup'!$D$43 -> 0.0016666667 | BE9: =(SUM('2. Headcount Buildup'!$F$44:$Q$44)/12)*('Base Revenue'!$AY9/'Base Revenue'!$AY$61) -> 0.0032362114 | BF9: =(SUM('2. Headcount Buildup'!$F$45:$Q$45)/12)*('Base Revenue'!$AY9/'Base Revenue'!$AY$61) -> 0.0053936857 | BG9: =(SUM('2. Headcount Buildup'!$F$46:$Q$46)/12)*('Base Revenue'!$AY9/'Base Revenue'!$AY$61) -> 0.0086298972 | BH9: =SUM(BA9:BG9) -> 0.035037572 | BK9: Staff a Dental LLC | BL9: =IFERROR(SUMIF($C$6:$C$60,BK9,$V$6:$V$60),0) -> 30720 | BM9: =IFERROR(SUMIF($C$5:$C$60,BK9,$AJ$5:$AJ$60),0) -> 24 | BN9: =IFERROR(BL9/BM9,0) -> 1280
B10: Base | C10: D'Souza & Associates, Inc | E10: Demo Verify | F10: Transaction | G10: 300 | H10: 0.27 | I10: 6143.5 | J10: 1620 | K10: 1593 | L10: 1710.99 | M10: 1710.99 | N10: 1593 | O10: 1710.99 | P10: 1710.99 | Q10: 1620 | R10: 1620 | S10: 1710.99 | T10: 1593 | U10: 1710.99 | V10: =SUM(J10:U10) -> 19904.94 | X10: =$I10/$G10/21 -> 0.97515873 | Y10: =$I10/$G10/21 -> 0.97515873 | Z10: =$I10/$G10/21 -> 0.97515873 | AA10: =$I10/$G10/21 -> 0.97515873 | AB10: =$I10/$G10/21 -> 0.97515873 | AC10: =$I10/$G10/21 -> 0.97515873 | AD10: =$I10/$G10/21 -> 0.97515873 | AE10: =$I10/$G10/21 -> 0.97515873 | ... AI10: =$I10/$G10/21 -> 0.97515873 | AJ10: =SUM(X10:AI10) -> 11.701905 | AL10: =X10/$AL$4 -> 1.2189484 | AM10: =Y10/$AL$4 -> 1.2189484 | AN10: =Z10/$AL$4 -> 1.2189484 | AO10: =AA10/$AL$4 -> 1.2189484 | AP10: =AB10/$AL$4 -> 1.2189484 | AQ10: =AC10/$AL$4 -> 1.2189484 | AR10: =AD10/$AL$4 -> 1.2189484 | AS10: =AE10/$AL$4 -> 1.2189484 | ... AW10: =AI10/$AL$4 -> 1.2189484 | AX10: =SUM(AL10:AW10) -> 14.627381 | AY10: =AX10/12 -> 1.2189484 | BA10: =AY10/'2. Headcount Buildup'!$D$36 -> 0.081263228 | BB10: =AY10/'2. Headcount Buildup'!$D$37 -> 0.024378968 | BC10: =AY10/'2. Headcount Buildup'!$D$38 -> 0.012189484 | BD10: =AY10/'2. Headcount Buildup'!$D$43 -> 0.012189484 | BE10: =(SUM('2. Headcount Buildup'!$F$44:$Q$44)/12)*('Base Revenue'!$AY10/'Base Revenue'!$AY$61) -> 0.023668649 | BF10: =(SUM('2. Headcount Buildup'!$F$45:$Q$45)/12)*('Base Revenue'!$AY10/'Base Revenue'!$AY$61) -> 0.039447748 | BG10: =(SUM('2. Headcount Buildup'!$F$46:$Q$46)/12)*('Base Revenue'!$AY10/'Base Revenue'!$AY$61) -> 0.063116397 | BH10: =SUM(BA10:BG10) -> 0.25625396 | BK10: Source It Dental | BL10: =IFERROR(SUMIF($C$6:$C$60,BK10,$V$6:$V$60),0) -> 34560 | BM10: =IFERROR(SUMIF($C$5:$C$60,BK10,$AJ$5:$AJ$60),0) -> 24 | BN10: =IFERROR(BL10/BM10,0) -> 1440
B11: Base | C11: D'Souza & Associates, Inc | E11: IV Entry | F11: Transaction | G11: 150 | H11: 0.54 | I11: 813 | J11: 447.12 | K11: 432 | L11: 447.12 | M11: 447.12 | N11: 432 | O11: 447.12 | P11: 447.12 | Q11: 421.2 | R11: 421.2 | S11: 447.12 | T11: 432 | U11: 447.12 | V11: =SUM(J11:U11) -> 5268.24 | X11: =$I11/$G11/21 -> 0.25809524 | Y11: =$I11/$G11/21 -> 0.25809524 | Z11: =$I11/$G11/21 -> 0.25809524 | AA11: =$I11/$G11/21 -> 0.25809524 | AB11: =$I11/$G11/21 -> 0.25809524 | AC11: =$I11/$G11/21 -> 0.25809524 | AD11: =$I11/$G11/21 -> 0.25809524 | AE11: =$I11/$G11/21 -> 0.25809524 | ... AI11: =$I11/$G11/21 -> 0.25809524 | AJ11: =SUM(X11:AI11) -> 3.0971429 | AL11: =X11/$AL$4 -> 0.32261905 | AM11: =Y11/$AL$4 -> 0.32261905 | AN11: =Z11/$AL$4 -> 0.32261905 | AO11: =AA11/$AL$4 -> 0.32261905 | AP11: =AB11/$AL$4 -> 0.32261905 | AQ11: =AC11/$AL$4 -> 0.32261905 | AR11: =AD11/$AL$4 -> 0.32261905 | AS11: =AE11/$AL$4 -> 0.32261905 | ... AW11: =AI11/$AL$4 -> 0.32261905 | AX11: =SUM(AL11:AW11) -> 3.8714286 | AY11: =AX11/12 -> 0.32261905 | BA11: =AY11/'2. Headcount Buildup'!$D$36 -> 0.021507937 | BB11: =AY11/'2. Headcount Buildup'!$D$37 -> 0.006452381 | BC11: =AY11/'2. Headcount Buildup'!$D$38 -> 0.0032261905 | BD11: =AY11/'2. Headcount Buildup'!$D$43 -> 0.0032261905 | BE11: =(SUM('2. Headcount Buildup'!$F$44:$Q$44)/12)*('Base Revenue'!$AY11/'Base Revenue'!$AY$61) -> 0.0062643807 | BF11: =(SUM('2. Headcount Buildup'!$F$45:$Q$45)/12)*('Base Revenue'!$AY11/'Base Revenue'!$AY$61) -> 0.010440635 | BG11: =(SUM('2. Headcount Buildup'!$F$46:$Q$46)/12)*('Base Revenue'!$AY11/'Base Revenue'!$AY$61) -> 0.016705015 | BH11: =SUM(BA11:BG11) -> 0.067822729 | BK11: Physical Therapy & Sports Medicine Center | BL11: =IFERROR(SUMIF($C$6:$C$60,BK11,$V$6:$V$60),0) -> 0 | BM11: =IFERROR(SUMIF($C$5:$C$60,BK11,$AJ$5:$AJ$60),0) -> 0 | BN11: =IFERROR(BL11/BM11,0) -> 0
B12: Base | C12: D'Souza & Associates, Inc | E12: IV Verify | F12: Transaction | G12: 150 | H12: 0.25 | I12: 6114.5 | J12: 1500 | K12: 1500 | L12: 1557.25 | M12: 1557.25 | N12: 1500 | O12: 1557.25 | P12: 1557.25 | Q12: 1500 | R12: 1500 | S12: 1557.25 | T12: 1500 | U12: 1557.25 | V12: =SUM(J12:U12) -> 18343.5 | X12: =$I12/$G12/21 -> 1.9411111 | Y12: =$I12/$G12/21 -> 1.9411111 | Z12: =$I12/$G12/21 -> 1.9411111 | AA12: =$I12/$G12/21 -> 1.9411111 | AB12: =$I12/$G12/21 -> 1.9411111 | AC12: =$I12/$G12/21 -> 1.9411111 | AD12: =$I12/$G12/21 -> 1.9411111 | AE12: =$I12/$G12/21 -> 1.9411111 | ... AI12: =$I12/$G12/21 -> 1.9411111 | AJ12: =SUM(X12:AI12) -> 23.293333 | AL12: =X12/$AL$4 -> 2.4263889 | AM12: =Y12/$AL$4 -> 2.4263889 | AN12: =Z12/$AL$4 -> 2.4263889 | AO12: =AA12/$AL$4 -> 2.4263889 | AP12: =AB12/$AL$4 -> 2.4263889 | AQ12: =AC12/$AL$4 -> 2.4263889 | AR12: =AD12/$AL$4 -> 2.4263889 | AS12: =AE12/$AL$4 -> 2.4263889 | ... AW12: =AI12/$AL$4 -> 2.4263889 | AX12: =SUM(AL12:AW12) -> 29.116667 | AY12: =AX12/12 -> 2.4263889 | BA12: =AY12/'2. Headcount Buildup'!$D$36 -> 0.16175926 | BB12: =AY12/'2. Headcount Buildup'!$D$37 -> 0.048527778 | BC12: =AY12/'2. Headcount Buildup'!$D$38 -> 0.024263889 | BD12: =AY12/'2. Headcount Buildup'!$D$43 -> 0.024263889 | BE12: =(SUM('2. Headcount Buildup'!$F$44:$Q$44)/12)*('Base Revenue'!$AY12/'Base Revenue'!$AY$61) -> 0.047113845 | BF12: =(SUM('2. Headcount Buildup'!$F$45:$Q$45)/12)*('Base Revenue'!$AY12/'Base Revenue'!$AY$61) -> 0.078523075 | BG12: =(SUM('2. Headcount Buildup'!$F$46:$Q$46)/12)*('Base Revenue'!$AY12/'Base Revenue'!$AY$61) -> 0.12563692 | BH12: =SUM(BA12:BG12) -> 0.51008865 | BK12: Primetime Physical Therapy | BL12: =IFERROR(SUMIF($C$6:$C$60,BK12,$V$6:$V$60),0) -> 86400 | BM12: =IFERROR(SUMIF($C$5:$C$60,BK12,$AJ$5:$AJ$60),0) -> 24.212381 | BN12: =IFERROR(BL12/BM12,0) -> 3568.4223
B13: Base | C13: D'Souza & Associates, Inc | E13: AR Follow-up | F13: Transaction | G13: 40 | H13: 1 | I13: 9250 | J13: 9000 | K13: 8000 | L13: 10000 | M13: 10000 | N13: 8000 | O13: 10000 | P13: 10000 | Q13: 9000 | R13: 9000 | S13: 10000 | T13: 8000 | U13: 10000 | V13: =SUM(J13:U13) -> 111000 | X13: =$I13/$G13/21 -> 11.011905 | Y13: =$I13/$G13/21 -> 11.011905 | Z13: =$I13/$G13/21 -> 11.011905 | AA13: =$I13/$G13/21 -> 11.011905 | AB13: =$I13/$G13/21 -> 11.011905 | AC13: =$I13/$G13/21 -> 11.011905 | AD13: =$I13/$G13/21 -> 11.011905 | AE13: =$I13/$G13/21 -> 11.011905 | ... AI13: =$I13/$G13/21 -> 11.011905 | AJ13: =SUM(X13:AI13) -> 132.14286 | AL13: =X13/$AL$4 -> 13.764881 | AM13: =Y13/$AL$4 -> 13.764881 | AN13: =Z13/$AL$4 -> 13.764881 | AO13: =AA13/$AL$4 -> 13.764881 | AP13: =AB13/$AL$4 -> 13.764881 | AQ13: =AC13/$AL$4 -> 13.764881 | AR13: =AD13/$AL$4 -> 13.764881 | AS13: =AE13/$AL$4 -> 13.764881 | ... AW13: =AI13/$AL$4 -> 13.764881 | AX13: =SUM(AL13:AW13) -> 165.17857 | AY13: =AX13/12 -> 13.764881 | BA13: =AY13/'2. Headcount Buildup'!$D$36 -> 0.91765873 | BB13: =AY13/'2. Headcount Buildup'!$D$37 -> 0.27529762 | BC13: =AY13/'2. Headcount Buildup'!$D$38 -> 0.13764881 | BD13: =AY13/'2. Headcount Buildup'!$D$43 -> 0.13764881 | BE13: =(SUM('2. Headcount Buildup'!$F$44:$Q$44)/12)*('Base Revenue'!$AY13/'Base Revenue'!$AY$61) -> 0.26727639 | BF13: =(SUM('2. Headcount Buildup'!$F$45:$Q$45)/12)*('Base Revenue'!$AY13/'Base Revenue'!$AY$61) -> 0.44546065 | BG13: =(SUM('2. Headcount Buildup'!$F$46:$Q$46)/12)*('Base Revenue'!$AY13/'Base Revenue'!$AY$61) -> 0.71273704 | BH13: =SUM(BA13:BG13) -> 2.8937281 | BK13: Comprehensive Sleep Care Center | BL13: =IFERROR(SUMIF($C$6:$C$60,BK13,$V$6:$V$60),0) -> 784400 | BM13: =IFERROR(SUMIF($C$5:$C$60,BK13,$AJ$5:$AJ$60),0) -> 551 | BN13: =IFERROR(BL13/BM13,0) -> 1423.5935
B14: Base | C14: D'Souza & Associates, Inc | E14: HCA & Intergy Charge Entry | F14: Transaction | G14: 380 | H14: 0.14 | I14: 41750 | J14: 5740 | K14: 5600 | L14: 6020 | M14: 6020 | N14: 5600 | O14: 6020 | P14: 6020 | Q14: 5740 | R14: 5740 | S14: 6020 | T14: 5600 | U14: 6020 | V14: =SUM(J14:U14) -> 70140 | X14: =$I14/$G14/21 -> 5.2318296 | Y14: =$I14/$G14/21 -> 5.2318296 | Z14: =$I14/$G14/21 -> 5.2318296 | AA14: =$I14/$G14/21 -> 5.2318296 | AB14: =$I14/$G14/21 -> 5.2318296 | AC14: =$I14/$G14/21 -> 5.2318296 | AD14: =$I14/$G14/21 -> 5.2318296 | AE14: =$I14/$G14/21 -> 5.2318296 | ... AI14: =$I14/$G14/21 -> 5.2318296 | AJ14: =SUM(X14:AI14) -> 62.781955 | AL14: =X14/$AL$4 -> 6.539787 | AM14: =Y14/$AL$4 -> 6.539787 | AN14: =Z14/$AL$4 -> 6.539787 | AO14: =AA14/$AL$4 -> 6.539787 | AP14: =AB14/$AL$4 -> 6.539787 | AQ14: =AC14/$AL$4 -> 6.539787 | AR14: =AD14/$AL$4 -> 6.539787 | AS14: =AE14/$AL$4 -> 6.539787 | ... AW14: =AI14/$AL$4 -> 6.539787 | AX14: =SUM(AL14:AW14) -> 78.477444 | AY14: =AX14/12 -> 6.539787 | BA14: =AY14/'2. Headcount Buildup'!$D$36 -> 0.4359858 | BB14: =AY14/'2. Headcount Buildup'!$D$37 -> 0.13079574 | BC14: =AY14/'2. Headcount Buildup'!$D$38 -> 0.06539787 | BD14: =AY14/'2. Headcount Buildup'!$D$43 -> 0.06539787 | BE14: =(SUM('2. Headcount Buildup'!$F$44:$Q$44)/12)*('Base Revenue'!$AY14/'Base Revenue'!$AY$61) -> 0.1269848 | BF14: =(SUM('2. Headcount Buildup'!$F$45:$Q$45)/12)*('Base Revenue'!$AY14/'Base Revenue'!$AY$61) -> 0.21164133 | BG14: =(SUM('2. Headcount Buildup'!$F$46:$Q$46)/12)*('Base Revenue'!$AY14/'Base Revenue'!$AY$61) -> 0.33862613 | BH14: =SUM(BA14:BG14) -> 1.3748295 | BK14: Your Docs In | BL14: =IFERROR(SUMIF($C$6:$C$60,BK14,$V$6:$V$60),0) -> 130315 | BM14: =IFERROR(SUMIF($C$5:$C$60,BK14,$AJ$5:$AJ$60),0) -> 36.94 | BN14: =IFERROR(BL14/BM14,0) -> 3527.7477
B15: Base | C15: D'Souza & Associates, Inc | E15: Payment Posting - ERA | F15: Transaction | G15: 2000 | H15: 0.026 | I15: 38500 | J15: 988 | K15: 936 | L15: 1040 | M15: 1040 | N15: 936 | O15: 1040 | P15: 1040 | Q15: 988 | R15: 988 | S15: 1040 | T15: 936 | U15: 1040 | V15: =SUM(J15:U15) -> 12012 | X15: =$I15/$G15/21 -> 0.91666667 | Y15: =$I15/$G15/21 -> 0.91666667 | Z15: =$I15/$G15/21 -> 0.91666667 | AA15: =$I15/$G15/21 -> 0.91666667 | AB15: =$I15/$G15/21 -> 0.91666667 | AC15: =$I15/$G15/21 -> 0.91666667 | AD15: =$I15/$G15/21 -> 0.91666667 | AE15: =$I15/$G15/21 -> 0.91666667 | ... AI15: =$I15/$G15/21 -> 0.91666667 | AJ15: =SUM(X15:AI15) -> 11 | AL15: =X15/$AL$4 -> 1.1458333 | AM15: =Y15/$AL$4 -> 1.1458333 | AN15: =Z15/$AL$4 -> 1.1458333 | AO15: =AA15/$AL$4 -> 1.1458333 | AP15: =AB15/$AL$4 -> 1.1458333 | AQ15: =AC15/$AL$4 -> 1.1458333 | AR15: =AD15/$AL$4 -> 1.1458333 | AS15: =AE15/$AL$4 -> 1.1458333 | ... AW15: =AI15/$AL$4 -> 1.1458333 | AX15: =SUM(AL15:AW15) -> 13.75 | AY15: =AX15/12 -> 1.1458333 | BA15: =AY15/'2. Headcount Buildup'!$D$36 -> 0.076388889 | BB15: =AY15/'2. Headcount Buildup'!$D$37 -> 0.022916667 | BC15: =AY15/'2. Headcount Buildup'!$D$38 -> 0.011458333 | BD15: =AY15/'2. Headcount Buildup'!$D$43 -> 0.011458333 | BE15: =(SUM('2. Headcount Buildup'!$F$44:$Q$44)/12)*('Base Revenue'!$AY15/'Base Revenue'!$AY$61) -> 0.022248954 | BF15: =(SUM('2. Headcount Buildup'!$F$45:$Q$45)/12)*('Base Revenue'!$AY15/'Base Revenue'!$AY$61) -> 0.037081589 | BG15: =(SUM('2. Headcount Buildup'!$F$46:$Q$46)/12)*('Base Revenue'!$AY15/'Base Revenue'!$AY$61) -> 0.059330543 | BH15: =SUM(BA15:BG15) -> 0.24088331 | BK15: The Physical Therapy Institute | BL15: =IFERROR(SUMIF($C$6:$C$60,BK15,$V$6:$V$60),0) -> 31875 | BM15: =IFERROR(SUMIF($C$5:$C$60,BK15,$AJ$5:$AJ$60),0) -> 31.857143 | BN15: =IFERROR(BL15/BM15,0) -> 1000.5605
B16: Base | C16: D'Souza & Associates, Inc | E16: Payment Posting - Manual | F16: Transaction | G16: 350 | H16: 0.16 | I16: 18250 | J16: 2880 | K16: 2720 | L16: 3040 | M16: 3040 | N16: 2720 | O16: 3040 | P16: 3040 | Q16: 2880 | R16: 2880 | S16: 3040 | T16: 2720 | U16: 3040 | V16: =SUM(J16:U16) -> 35040 | X16: =$I16/$G16/21 -> 2.4829932 | Y16: =$I16/$G16/21 -> 2.4829932 | Z16: =$I16/$G16/21 -> 2.4829932 | AA16: =$I16/$G16/21 -> 2.4829932 | AB16: =$I16/$G16/21 -> 2.4829932 | AC16: =$I16/$G16/21 -> 2.4829932 | AD16: =$I16/$G16/21 -> 2.4829932 | AE16: =$I16/$G16/21 -> 2.4829932 | ... AI16: =$I16/$G16/21 -> 2.4829932 | AJ16: =SUM(X16:AI16) -> 29.795918 | AL16: =X16/$AL$4 -> 3.1037415 | AM16: =Y16/$AL$4 -> 3.1037415 | AN16: =Z16/$AL$4 -> 3.1037415 | AO16: =AA16/$AL$4 -> 3.1037415 | AP16: =AB16/$AL$4 -> 3.1037415 | AQ16: =AC16/$AL$4 -> 3.1037415 | AR16: =AD16/$AL$4 -> 3.1037415 | AS16: =AE16/$AL$4 -> 3.1037415 | ... AW16: =AI16/$AL$4 -> 3.1037415 | AX16: =SUM(AL16:AW16) -> 37.244898 | AY16: =AX16/12 -> 3.1037415 | BA16: =AY16/'2. Headcount Buildup'!$D$36 -> 0.2069161 | BB16: =AY16/'2. Headcount Buildup'!$D$37 -> 0.06207483 | BC16: =AY16/'2. Headcount Buildup'!$D$38 -> 0.031037415 | BD16: =AY16/'2. Headcount Buildup'!$D$43 -> 0.031037415 | BE16: =(SUM('2. Headcount Buildup'!$F$44:$Q$44)/12)*('Base Revenue'!$AY16/'Base Revenue'!$AY$61) -> 0.060266182 | BF16: =(SUM('2. Headcount Buildup'!$F$45:$Q$45)/12)*('Base Revenue'!$AY16/'Base Revenue'!$AY$61) -> 0.10044364 | BG16: =(SUM('2. Headcount Buildup'!$F$46:$Q$46)/12)*('Base Revenue'!$AY16/'Base Revenue'!$AY$61) -> 0.16070982 | BH16: =SUM(BA16:BG16) -> 0.6524854 | BK16: Procle Healthworks | BL16: =IFERROR(SUMIF($C$6:$C$60,BK16,$V$6:$V$60),0) -> 14400 | BM16: =IFERROR(SUMIF($C$5:$C$60,BK16,$AJ$5:$AJ$60),0) -> 15.214286 | BN16: =IFERROR(BL16/BM16,0) -> 946.47887
B17: Base | C17: D'Souza & Associates, Inc | E17: Medicare Calling | F17: Transaction | G17: 200 | H17: 0.3 | I17: 350 | J17: 105 | K17: 105 | L17: 105 | M17: 105 | N17: 105 | O17: 105 | P17: 105 | Q17: 105 | R17: 105 | S17: 105 | T17: 105 | U17: 105 | V17: =SUM(J17:U17) -> 1260 | X17: =$I17/$G17/21 -> 0.083333333 | Y17: =$I17/$G17/21 -> 0.083333333 | Z17: =$I17/$G17/21 -> 0.083333333 | AA17: =$I17/$G17/21 -> 0.083333333 | AB17: =$I17/$G17/21 -> 0.083333333 | AC17: =$I17/$G17/21 -> 0.083333333 | AD17: =$I17/$G17/21 -> 0.083333333 | AE17: =$I17/$G17/21 -> 0.083333333 | ... AI17: =$I17/$G17/21 -> 0.083333333 | AJ17: =SUM(X17:AI17) -> 1 | AL17: =X17/$AL$4 -> 0.10416667 | AM17: =Y17/$AL$4 -> 0.10416667 | AN17: =Z17/$AL$4 -> 0.10416667 | AO17: =AA17/$AL$4 -> 0.10416667 | AP17: =AB17/$AL$4 -> 0.10416667 | AQ17: =AC17/$AL$4 -> 0.10416667 | AR17: =AD17/$AL$4 -> 0.10416667 | AS17: =AE17/$AL$4 -> 0.10416667 | ... AW17: =AI17/$AL$4 -> 0.10416667 | AX17: =SUM(AL17:AW17) -> 1.25 | AY17: =AX17/12 -> 0.10416667 | BA17: =AY17/'2. Headcount Buildup'!$D$36 -> 0.0069444444 | BB17: =AY17/'2. Headcount Buildup'!$D$37 -> 0.0020833333 | BC17: =AY17/'2. Headcount Buildup'!$D$38 -> 0.0010416667 | BD17: =AY17/'2. Headcount Buildup'!$D$43 -> 0.0010416667 | BE17: =(SUM('2. Headcount Buildup'!$F$44:$Q$44)/12)*('Base Revenue'!$AY17/'Base Revenue'!$AY$61) -> 0.0020226321 | BF17: =(SUM('2. Headcount Buildup'!$F$45:$Q$45)/12)*('Base Revenue'!$AY17/'Base Revenue'!$AY$61) -> 0.0033710536 | BG17: =(SUM('2. Headcount Buildup'!$F$46:$Q$46)/12)*('Base Revenue'!$AY17/'Base Revenue'!$AY$61) -> 0.0053936857 | BH17: =SUM(BA17:BG17) -> 0.021898483 | BK17: BayLife | BL17: =IFERROR(SUMIF($C$6:$C$60,BK17,$V$6:$V$60),0) -> 63000 | BM17: =IFERROR(SUMIF($C$5:$C$60,BK17,$AJ$5:$AJ$60),0) -> 37.428571 | BN17: =IFERROR(BL17/BM17,0) -> 1683.2061
B18: Base | C18: D'Souza & Associates, Inc | E18: HCA AR Follow-up | F18: FTE | G18: 40 | H18: 1300 | I18: 1 | J18: 1300 | K18: 1300 | L18: 1300 | M18: 1300 | N18: 1300 | O18: 1300 | P18: 1300 | Q18: 1300 | R18: 1300 | S18: 1300 | T18: 1300 | U18: 1300 | V18: =SUM(J18:U18) -> 15600 | X18: =$I18 -> 1 | Y18: =$I18 -> 1 | Z18: =$I18 -> 1 | AA18: =$I18 -> 1 | AB18: =$I18 -> 1 | AC18: =$I18 -> 1 | AD18: =$I18 -> 1 | AE18: =$I18 -> 1 | ... AI18: =$I18 -> 1 | AJ18: =SUM(X18:AI18) -> 12 | AL18: =X18/$AL$4 -> 1.25 | AM18: =Y18/$AL$4 -> 1.25 | AN18: =Z18/$AL$4 -> 1.25 | AO18: =AA18/$AL$4 -> 1.25 | AP18: =AB18/$AL$4 -> 1.25 | AQ18: =AC18/$AL$4 -> 1.25 | AR18: =AD18/$AL$4 -> 1.25 | AS18: =AE18/$AL$4 -> 1.25 | ... AW18: =AI18/$AL$4 -> 1.25 | AX18: =SUM(AL18:AW18) -> 15 | AY18: =AX18/12 -> 1.25 | BA18: =AY18/'2. Headcount Buildup'!$D$36 -> 0.083333333 | BB18: =AY18/'2. Headcount Buildup'!$D$37 -> 0.025 | BC18: =AY18/'2. Headcount Buildup'!$D$38 -> 0.0125 | BD18: =AY18/'2. Headcount Buildup'!$D$43 -> 0.0125 | BE18: =(SUM('2. Headcount Buildup'!$F$44:$Q$44)/12)*('Base Revenue'!$AY18/'Base Revenue'!$AY$61) -> 0.024271586 | BF18: =(SUM('2. Headcount Buildup'!$F$45:$Q$45)/12)*('Base Revenue'!$AY18/'Base Revenue'!$AY$61) -> 0.040452643 | BG18: =(SUM('2. Headcount Buildup'!$F$46:$Q$46)/12)*('Base Revenue'!$AY18/'Base Revenue'!$AY$61) -> 0.064724229 | BH18: =SUM(BA18:BG18) -> 0.26278179 | BK18: Premier Sleep Center | BL18: =IFERROR(SUMIF($C$6:$C$60,BK18,$V$6:$V$60),0) -> 81000 | BM18: =IFERROR(SUMIF($C$5:$C$60,BK18,$AJ$5:$AJ$60),0) -> 16.468571 | BN18: =IFERROR(BL18/BM18,0) -> 4918.4594
B19: New Addition | C19: D'Souza & Associates, Inc | E19: HCA | F19: FTE | H19: 1350 | K19: 2025 | L19: 2700 | M19: 2700 | N19: 2700 | O19: 2700 | P19: 2700 | Q19: 2700 | R19: 2700 | S19: 2700 | T19: 2700 | U19: 2700 | V19: =SUM(J19:U19) -> 29025 | Y19: 1.5 | Z19: 2 | AA19: 2 | AB19: 2 | AC19: 2 | AD19: 2 | AE19: 2 | AF19: 2 | AG19: 2 | AH19: 2 | AI19: 2 | AJ19: =SUM(X19:AI19) -> 21.5 | AL19: =X19/$AL$4 -> 0 | AM19: =Y19/$AL$4 -> 1.875 | AN19: =Z19/$AL$4 -> 2.5 | AO19: =AA19/$AL$4 -> 2.5 | AP19: =AB19/$AL$4 -> 2.5 | AQ19: =AC19/$AL$4 -> 2.5 | AR19: =AD19/$AL$4 -> 2.5 | AS19: =AE19/$AL$4 -> 2.5 | ... AW19: =AI19/$AL$4 -> 2.5 | AX19: =SUM(AL19:AW19) -> 26.875 | AY19: =AX19/12 -> 2.2395833 | BA19: =AY19/'2. Headcount Buildup'!$D$36 -> 0.14930556 | BB19: =AY19/'2. Headcount Buildup'!$D$37 -> 0.044791667 | BC19: =AY19/'2. Headcount Buildup'!$D$38 -> 0.022395833 | BD19: =AY19/'2. Headcount Buildup'!$D$43 -> 0.022395833 | BE19: =(SUM('2. Headcount Buildup'!$F$44:$Q$44)/12)*('Base Revenue'!$AY19/'Base Revenue'!$AY$61) -> 0.043486591 | BF19: =(SUM('2. Headcount Buildup'!$F$45:$Q$45)/12)*('Base Revenue'!$AY19/'Base Revenue'!$AY$61) -> 0.072477652 | BG19: =(SUM('2. Headcount Buildup'!$F$46:$Q$46)/12)*('Base Revenue'!$AY19/'Base Revenue'!$AY$61) -> 0.11596424 | BH19: =SUM(BA19:BG19) -> 0.47081738
B20: New Addition | C20: D'Souza & Associates, Inc | E20: Athena | F20: FTE | H20: 1350 | K20: 2025 | L20: 4050 | M20: 4050 | N20: 4050 | O20: 4050 | P20: 4050 | Q20: 4050 | R20: 4050 | S20: 4050 | T20: 4050 | U20: 4050 | V20: =SUM(J20:U20) -> 42525 | Y20: 1.5 | Z20: 3 | AA20: 3 | AB20: 3 | AC20: 3 | AD20: 3 | AE20: 3 | AF20: 3 | AG20: 3 | AH20: 3 | AI20: 3 | AJ20: =SUM(X20:AI20) -> 31.5 | AL20: =X20/$AL$4 -> 0 | AM20: =Y20/$AL$4 -> 1.875 | AN20: =Z20/$AL$4 -> 3.75 | AO20: =AA20/$AL$4 -> 3.75 | AP20: =AB20/$AL$4 -> 3.75 | AQ20: =AC20/$AL$4 -> 3.75 | AR20: =AD20/$AL$4 -> 3.75 | AS20: =AE20/$AL$4 -> 3.75 | ... AW20: =AI20/$AL$4 -> 3.75 | AX20: =SUM(AL20:AW20) -> 39.375 | AY20: =AX20/12 -> 3.28125 | BA20: =AY20/'2. Headcount Buildup'!$D$36 -> 0.21875 | BB20: =AY20/'2. Headcount Buildup'!$D$37 -> 0.065625 | BC20: =AY20/'2. Headcount Buildup'!$D$38 -> 0.0328125 | BD20: =AY20/'2. Headcount Buildup'!$D$43 -> 0.0328125 | BE20: =(SUM('2. Headcount Buildup'!$F$44:$Q$44)/12)*('Base Revenue'!$AY20/'Base Revenue'!$AY$61) -> 0.063712913 | BF20: =(SUM('2. Headcount Buildup'!$F$45:$Q$45)/12)*('Base Revenue'!$AY20/'Base Revenue'!$AY$61) -> 0.10618819 | BG20: =(SUM('2. Headcount Buildup'!$F$46:$Q$46)/12)*('Base Revenue'!$AY20/'Base Revenue'!$AY$61) -> 0.1699011 | BH20: =SUM(BA20:BG20) -> 0.6898022
B21: Base | C21: Univ. Of Delaware | E21: End to End | F21: Collection | H21: 0.03 | I21: 290000 | J21: 8700 | K21: 8700 | L21: 8700 | M21: 8700 | N21: 8700 | O21: 8700 | P21: 8700 | Q21: 8700 | R21: 8700 | S21: 8700 | T21: 8700 | U21: 8700 | V21: =SUM(J21:U21) -> 104400 | X21: ='Base FTE'!$I55 -> 7.3141939 | Y21: ='Base FTE'!$I55 -> 7.3141939 | Z21: ='Base FTE'!$I55 -> 7.3141939 | AA21: ='Base FTE'!$I55 -> 7.3141939 | AB21: ='Base FTE'!$I55 -> 7.3141939 | AC21: ='Base FTE'!$I55 -> 7.3141939 | AD21: ='Base FTE'!$I55 -> 7.3141939 | AE21: ='Base FTE'!$I55 -> 7.3141939 | ... AI21: ='Base FTE'!$I55 -> 7.3141939 | AJ21: =SUM(X21:AI21) -> 87.770327 | AL21: =X21/$AL$4 -> 9.1427423 | AM21: =Y21/$AL$4 -> 9.1427423 | AN21: =Z21/$AL$4 -> 9.1427423 | AO21: =AA21/$AL$4 -> 9.1427423 | AP21: =AB21/$AL$4 -> 9.1427423 | AQ21: =AC21/$AL$4 -> 9.1427423 | AR21: =AD21/$AL$4 -> 9.1427423 | AS21: =AE21/$AL$4 -> 9.1427423 | ... AW21: =AI21/$AL$4 -> 9.1427423 | AX21: =SUM(AL21:AW21) -> 109.71291 | AY21: =AX21/12 -> 9.1427423 | BA21: =AY21/'2. Headcount Buildup'!$D$36 -> 0.60951616 | BB21: =AY21/'2. Headcount Buildup'!$D$37 -> 0.18285485 | BC21: =AY21/'2. Headcount Buildup'!$D$38 -> 0.091427423 | BD21: =AY21/'2. Headcount Buildup'!$D$43 -> 0.091427423 | BE21: =(SUM('2. Headcount Buildup'!$F$44:$Q$44)/12)*('Base Revenue'!$AY21/'Base Revenue'!$AY$61) -> 0.17752708 | BF21: =(SUM('2. Headcount Buildup'!$F$45:$Q$45)/12)*('Base Revenue'!$AY21/'Base Revenue'!$AY$61) -> 0.29587847 | BG21: =(SUM('2. Headcount Buildup'!$F$46:$Q$46)/12)*('Base Revenue'!$AY21/'Base Revenue'!$AY$61) -> 0.47340556 | BH21: =SUM(BA21:BG21) -> 1.922037 | BK21: Emergence Health Holdings | BL21: =IFERROR(SUMIF($C$6:$C$60,BK21,$V$6:$V$60),0) -> 252500 | BM21: =IFERROR(SUMIF($C$5:$C$60,BK21,$AJ$5:$AJ$60),0) -> 120 | BN21: =IFERROR(BL21/BM21,0) -> 2104.1667
B22: Base | C22: Staff a Dental LLC | E22: Payment Posting | F22: FTE | G22: 80 | H22: 1280 | I22: 2 | J22: 2560 | K22: 2560 | L22: 2560 | M22: 2560 | N22: 2560 | O22: 2560 | P22: 2560 | Q22: 2560 | R22: 2560 | S22: 2560 | T22: 2560 | U22: 2560 | V22: =SUM(J22:U22) -> 30720 | X22: ='Base FTE'!$I47 -> 2 | Y22: ='Base FTE'!$I47 -> 2 | Z22: ='Base FTE'!$I47 -> 2 | AA22: ='Base FTE'!$I47 -> 2 | AB22: ='Base FTE'!$I47 -> 2 | AC22: ='Base FTE'!$I47 -> 2 | AD22: ='Base FTE'!$I47 -> 2 | AE22: ='Base FTE'!$I47 -> 2 | ... AI22: ='Base FTE'!$I47 -> 2 | AJ22: =SUM(X22:AI22) -> 24 | AL22: =X22/$AL$4 -> 2.5 | AM22: =Y22/$AL$4 -> 2.5 | AN22: =Z22/$AL$4 -> 2.5 | AO22: =AA22/$AL$4 -> 2.5 | AP22: =AB22/$AL$4 -> 2.5 | AQ22: =AC22/$AL$4 -> 2.5 | AR22: =AD22/$AL$4 -> 2.5 | AS22: =AE22/$AL$4 -> 2.5 | ... AW22: =AI22/$AL$4 -> 2.5 | AX22: =SUM(AL22:AW22) -> 30 | AY22: =AX22/12 -> 2.5 | BA22: =AY22/'2. Headcount Buildup'!$D$36 -> 0.16666667 | BB22: =AY22/'2. Headcount Buildup'!$D$37 -> 0.05 | BC22: =AY22/'2. Headcount Buildup'!$D$38 -> 0.025 | BD22: =AY22/'2. Headcount Buildup'!$D$43 -> 0.025 | BE22: =(SUM('2. Headcount Buildup'!$F$44:$Q$44)/12)*('Base Revenue'!$AY22/'Base Revenue'!$AY$61) -> 0.048543172 | BF22: =(SUM('2. Headcount Buildup'!$F$45:$Q$45)/12)*('Base Revenue'!$AY22/'Base Revenue'!$AY$61) -> 0.080905286 | BG22: =(SUM('2. Headcount Buildup'!$F$46:$Q$46)/12)*('Base Revenue'!$AY22/'Base Revenue'!$AY$61) -> 0.12944846 | BH22: =SUM(BA22:BG22) -> 0.52556358 | BK22: Nova Physician Wellness | BL22: =IFERROR(SUMIF($C$6:$C$60,BK22,$V$6:$V$60),0) -> 17400 | BM22: =IFERROR(SUMIF($C$5:$C$60,BK22,$AJ$5:$AJ$60),0) -> 12 | BN22: =IFERROR(BL22/BM22,0) -> 1450
B23: Base | C23: Source It Dental | E23: AR Follow-up | F23: FTE | H23: 1440 | I23: 2 | J23: 2880 | K23: 2880 | L23: 2880 | M23: 2880 | N23: 2880 | O23: 2880 | P23: 2880 | Q23: 2880 | R23: 2880 | S23: 2880 | T23: 2880 | U23: 2880 | V23: =SUM(J23:U23) -> 34560 | X23: ='Base FTE'!$I2 -> 2 | Y23: ='Base FTE'!$I2 -> 2 | Z23: ='Base FTE'!$I2 -> 2 | AA23: ='Base FTE'!$I2 -> 2 | AB23: ='Base FTE'!$I2 -> 2 | AC23: ='Base FTE'!$I2 -> 2 | AD23: ='Base FTE'!$I2 -> 2 | AE23: ='Base FTE'!$I2 -> 2 | ... AI23: ='Base FTE'!$I2 -> 2 | AJ23: =SUM(X23:AI23) -> 24 | AL23: =X23/$AL$4 -> 2.5 | AM23: =Y23/$AL$4 -> 2.5 | AN23: =Z23/$AL$4 -> 2.5 | AO23: =AA23/$AL$4 -> 2.5 | AP23: =AB23/$AL$4 -> 2.5 | AQ23: =AC23/$AL$4 -> 2.5 | AR23: =AD23/$AL$4 -> 2.5 | AS23: =AE23/$AL$4 -> 2.5 | ... AW23: =AI23/$AL$4 -> 2.5 | AX23: =SUM(AL23:AW23) -> 30 | AY23: =AX23/12 -> 2.5 | BA23: =AY23/'2. Headcount Buildup'!$D$36 -> 0.16666667 | BB23: =AY23/'2. Headcount Buildup'!$D$37 -> 0.05 | BC23: =AY23/'2. Headcount Buildup'!$D$38 -> 0.025 | BD23: =AY23/'2. Headcount Buildup'!$D$43 -> 0.025 | BE23: =(SUM('2. Headcount Buildup'!$F$44:$Q$44)/12)*('Base Revenue'!$AY23/'Base Revenue'!$AY$61) -> 0.048543172 | BF23: =(SUM('2. Headcount Buildup'!$F$45:$Q$45)/12)*('Base Revenue'!$AY23/'Base Revenue'!$AY$61) -> 0.080905286 | BG23: =(SUM('2. Headcount Buildup'!$F$46:$Q$46)/12)*('Base Revenue'!$AY23/'Base Revenue'!$AY$61) -> 0.12944846 | BH23: =SUM(BA23:BG23) -> 0.52556358 | BK23: Medrina Document Retrival | BL23: =IFERROR(SUMIF($C$6:$C$60,BK23,$V$6:$V$60),0) -> 76032 | BM23: =IFERROR(SUMIF($C$5:$C$60,BK23,$AJ$5:$AJ$60),0) -> 0.41142857 | BN23: =IFERROR(BL23/BM23,0) -> 184800
B24: Base | C24: Primetime Physical Therapy | E24: Collections | F24: Collection | G24: 900 | H24: 0.06 | I24: 120000 | J24: 7200 | K24: 7200 | L24: 7200 | M24: 7200 | N24: 7200 | O24: 7200 | P24: 7200 | Q24: 7200 | R24: 7200 | S24: 7200 | T24: 7200 | U24: 7200 | V24: =SUM(J24:U24) -> 86400 | X24: ='Base FTE'!$I45 -> 2.0176984 | Y24: ='Base FTE'!$I45 -> 2.0176984 | Z24: ='Base FTE'!$I45 -> 2.0176984 | AA24: ='Base FTE'!$I45 -> 2.0176984 | AB24: ='Base FTE'!$I45 -> 2.0176984 | AC24: ='Base FTE'!$I45 -> 2.0176984 | AD24: ='Base FTE'!$I45 -> 2.0176984 | AE24: ='Base FTE'!$I45 -> 2.0176984 | ... AI24: ='Base FTE'!$I45 -> 2.0176984 | AJ24: =SUM(X24:AI24) -> 24.212381 | AL24: =X24/$AL$4 -> 2.522123 | AM24: =Y24/$AL$4 -> 2.522123 | AN24: =Z24/$AL$4 -> 2.522123 | AO24: =AA24/$AL$4 -> 2.522123 | AP24: =AB24/$AL$4 -> 2.522123 | AQ24: =AC24/$AL$4 -> 2.522123 | AR24: =AD24/$AL$4 -> 2.522123 | AS24: =AE24/$AL$4 -> 2.522123 | ... AW24: =AI24/$AL$4 -> 2.522123 | AX24: =SUM(AL24:AW24) -> 30.265476 | AY24: =AX24/12 -> 2.522123 | BA24: =AY24/'2. Headcount Buildup'!$D$36 -> 0.16814153 | BB24: =AY24/'2. Headcount Buildup'!$D$37 -> 0.05044246 | BC24: =AY24/'2. Headcount Buildup'!$D$38 -> 0.02522123 | BD24: =AY24/'2. Headcount Buildup'!$D$43 -> 0.02522123 | BE24: =(SUM('2. Headcount Buildup'!$F$44:$Q$44)/12)*('Base Revenue'!$AY24/'Base Revenue'!$AY$61) -> 0.04897274 | BF24: =(SUM('2. Headcount Buildup'!$F$45:$Q$45)/12)*('Base Revenue'!$AY24/'Base Revenue'!$AY$61) -> 0.081621234 | BG24: =(SUM('2. Headcount Buildup'!$F$46:$Q$46)/12)*('Base Revenue'!$AY24/'Base Revenue'!$AY$61) -> 0.13059397 | BH24: =SUM(BA24:BG24) -> 0.5302144 | BK24: Medrina Coding | BL24: =IFERROR(SUMIF($C$6:$C$60,BK24,$V$6:$V$60),0) -> 56700 | BM24: =IFERROR(SUMIF($C$5:$C$60,BK24,$AJ$5:$AJ$60),0) -> 28.571429 | BN24: =IFERROR(BL24/BM24,0) -> 1984.5
B25: Base | C25: Comprehensive Sleep Care Center | E25: Eligibility & Benefit Verification | F25: FTE | G25: 60 | H25: 1300 | I25: 10 | J25: 13000 | K25: 13000 | L25: 13000 | M25: 13000 | N25: 13000 | O25: 13000 | P25: 13000 | Q25: 13000 | R25: 13000 | S25: 13000 | T25: 13000 | U25: 13000 | V25: =SUM(J25:U25) -> 156000 | X25: 10 | Y25: 10 | Z25: 10 | AA25: 10 | AB25: 10 | AC25: 10 | AD25: 10 | AE25: 10 | AF25: 10 | AG25: 10 | AH25: 10 | AI25: 10 | AJ25: =SUM(X25:AI25) -> 120 | AL25: =X25/$AL$4 -> 12.5 | AM25: =Y25/$AL$4 -> 12.5 | AN25: =Z25/$AL$4 -> 12.5 | AO25: =AA25/$AL$4 -> 12.5 | AP25: =AB25/$AL$4 -> 12.5 | AQ25: =AC25/$AL$4 -> 12.5 | AR25: =AD25/$AL$4 -> 12.5 | AS25: =AE25/$AL$4 -> 12.5 | ... AW25: =AI25/$AL$4 -> 12.5 | AX25: =SUM(AL25:AW25) -> 150 | AY25: =AX25/12 -> 12.5 | BA25: =AY25/'2. Headcount Buildup'!$D$36 -> 0.83333333 | BB25: =AY25/'2. Headcount Buildup'!$D$37 -> 0.25 | BC25: =AY25/'2. Headcount Buildup'!$D$38 -> 0.125 | BD25: =AY25/'2. Headcount Buildup'!$D$43 -> 0.125 | BE25: =(SUM('2. Headcount Buildup'!$F$44:$Q$44)/12)*('Base Revenue'!$AY25/'Base Revenue'!$AY$61) -> 0.24271586 | BF25: =(SUM('2. Headcount Buildup'!$F$45:$Q$45)/12)*('Base Revenue'!$AY25/'Base Revenue'!$AY$61) -> 0.40452643 | BG25: =(SUM('2. Headcount Buildup'!$F$46:$Q$46)/12)*('Base Revenue'!$AY25/'Base Revenue'!$AY$61) -> 0.64724229 | BH25: =SUM(BA25:BG25) -> 2.6278179 | BK25: MBMS | BL25: =IFERROR(SUMIF($C$6:$C$60,BK25,$V$6:$V$60),0) -> 160471 | BM25: =IFERROR(SUMIF($C$5:$C$60,BK25,$AJ$5:$AJ$60),0) -> 61 | BN25: =IFERROR(BL25/BM25,0) -> 2630.6721
B26: Base | C26: Comprehensive Sleep Care Center | E26: Patient Calling(Call Centre) | F26: FTE | G26: 40 | H26: 1400 | I26: 9 | J26: 12600 | K26: 12600 | L26: 12600 | M26: 12600 | N26: 12600 | O26: 12600 | P26: 12600 | Q26: 12600 | R26: 12600 | S26: 12600 | T26: 12600 | U26: 12600 | V26: =SUM(J26:U26) -> 151200 | X26: 9 | Y26: 9 | Z26: 9 | AA26: 9 | AB26: 9 | AC26: 9 | AD26: 9 | AE26: 9 | AF26: 9 | AG26: 9 | AH26: 9 | AI26: 9 | AJ26: =SUM(X26:AI26) -> 108 | AL26: =X26/$AL$4 -> 11.25 | AM26: =Y26/$AL$4 -> 11.25 | AN26: =Z26/$AL$4 -> 11.25 | AO26: =AA26/$AL$4 -> 11.25 | AP26: =AB26/$AL$4 -> 11.25 | AQ26: =AC26/$AL$4 -> 11.25 | AR26: =AD26/$AL$4 -> 11.25 | AS26: =AE26/$AL$4 -> 11.25 | ... AW26: =AI26/$AL$4 -> 11.25 | AX26: =SUM(AL26:AW26) -> 135 | AY26: =AX26/12 -> 11.25 | BA26: =AY26/'2. Headcount Buildup'!$D$36 -> 0.75 | BB26: =AY26/'2. Headcount Buildup'!$D$37 -> 0.225 | BC26: =AY26/'2. Headcount Buildup'!$D$38 -> 0.1125 | BD26: =AY26/'2. Headcount Buildup'!$D$43 -> 0.1125 | BE26: =(SUM('2. Headcount Buildup'!$F$44:$Q$44)/12)*('Base Revenue'!$AY26/'Base Revenue'!$AY$61) -> 0.21844427 | BF26: =(SUM('2. Headcount Buildup'!$F$45:$Q$45)/12)*('Base Revenue'!$AY26/'Base Revenue'!$AY$61) -> 0.36407379 | BG26: =(SUM('2. Headcount Buildup'!$F$46:$Q$46)/12)*('Base Revenue'!$AY26/'Base Revenue'!$AY$61) -> 0.58251806 | BH26: =SUM(BA26:BG26) -> 2.3650361 | BK26: All Medical Revenue Solutions | BL26: =IFERROR(SUMIF($C$6:$C$60,BK26,$V$6:$V$60),0) -> 43200 | BM26: =IFERROR(SUMIF($C$5:$C$60,BK26,$AJ$5:$AJ$60),0) -> 33 | BN26: =IFERROR(BL26/BM26,0) -> 1309.0909
B27: Base | C27: Comprehensive Sleep Care Center | E27: Patient Calling(Provider Scheduling) | F27: FTE | G27: 70 | H27: 1400 | I27: 6 | J27: 8400 | K27: 8400 | L27: 8400 | M27: 8400 | N27: 8400 | O27: 8400 | P27: 8400 | Q27: 8400 | R27: 8400 | S27: 8400 | T27: 8400 | U27: 8400 | V27: =SUM(J27:U27) -> 100800 | X27: 6 | Y27: 6 | Z27: 6 | AA27: 6 | AB27: 6 | AC27: 6 | AD27: 6 | AE27: 6 | AF27: 6 | AG27: 6 | AH27: 6 | AI27: 6 | AJ27: =SUM(X27:AI27) -> 72 | AL27: =X27/$AL$4 -> 7.5 | AM27: =Y27/$AL$4 -> 7.5 | AN27: =Z27/$AL$4 -> 7.5 | AO27: =AA27/$AL$4 -> 7.5 | AP27: =AB27/$AL$4 -> 7.5 | AQ27: =AC27/$AL$4 -> 7.5 | AR27: =AD27/$AL$4 -> 7.5 | AS27: =AE27/$AL$4 -> 7.5 | ... AW27: =AI27/$AL$4 -> 7.5 | AX27: =SUM(AL27:AW27) -> 90 | AY27: =AX27/12 -> 7.5 | BA27: =AY27/'2. Headcount Buildup'!$D$36 -> 0.5 | BB27: =AY27/'2. Headcount Buildup'!$D$37 -> 0.15 | BC27: =AY27/'2. Headcount Buildup'!$D$38 -> 0.075 | BD27: =AY27/'2. Headcount Buildup'!$D$43 -> 0.075 | BE27: =(SUM('2. Headcount Buildup'!$F$44:$Q$44)/12)*('Base Revenue'!$AY27/'Base Revenue'!$AY$61) -> 0.14562951 | BF27: =(SUM('2. Headcount Buildup'!$F$45:$Q$45)/12)*('Base Revenue'!$AY27/'Base Revenue'!$AY$61) -> 0.24271586 | BG27: =(SUM('2. Headcount Buildup'!$F$46:$Q$46)/12)*('Base Revenue'!$AY27/'Base Revenue'!$AY$61) -> 0.38834537 | BH27: =SUM(BA27:BG27) -> 1.5766907 | BK27: Serenity Bay Hospice | BL27: =IFERROR(SUMIF($C$6:$C$60,BK27,$V$6:$V$60),0) -> 0 | BM27: =IFERROR(SUMIF($C$5:$C$60,BK27,$AJ$5:$AJ$60),0) -> 0 | BN27: =IFERROR(BL27/BM27,0) -> 0
B28: Base | C28: Comprehensive Sleep Care Center | E28: Patient Soft Collections | F28: FTE | G28: 70 | H28: 1400 | I28: 6 | J28: 8400 | K28: 8400 | L28: 8400 | M28: 8400 | N28: 8400 | O28: 8400 | P28: 8400 | Q28: 8400 | R28: 8400 | S28: 8400 | T28: 8400 | U28: 8400 | V28: =SUM(J28:U28) -> 100800 | X28: 6 | Y28: 6 | Z28: 6 | AA28: 6 | AB28: 6 | AC28: 6 | AD28: 6 | AE28: 6 | AF28: 6 | AG28: 6 | AH28: 6 | AI28: 6 | AJ28: =SUM(X28:AI28) -> 72 | AL28: =X28/$AL$4 -> 7.5 | AM28: =Y28/$AL$4 -> 7.5 | AN28: =Z28/$AL$4 -> 7.5 | AO28: =AA28/$AL$4 -> 7.5 | AP28: =AB28/$AL$4 -> 7.5 | AQ28: =AC28/$AL$4 -> 7.5 | AR28: =AD28/$AL$4 -> 7.5 | AS28: =AE28/$AL$4 -> 7.5 | ... AW28: =AI28/$AL$4 -> 7.5 | AX28: =SUM(AL28:AW28) -> 90 | AY28: =AX28/12 -> 7.5 | BA28: =AY28/'2. Headcount Buildup'!$D$36 -> 0.5 | BB28: =AY28/'2. Headcount Buildup'!$D$37 -> 0.15 | BC28: =AY28/'2. Headcount Buildup'!$D$38 -> 0.075 | BD28: =AY28/'2. Headcount Buildup'!$D$43 -> 0.075 | BE28: =(SUM('2. Headcount Buildup'!$F$44:$Q$44)/12)*('Base Revenue'!$AY28/'Base Revenue'!$AY$61) -> 0.14562951 | BF28: =(SUM('2. Headcount Buildup'!$F$45:$Q$45)/12)*('Base Revenue'!$AY28/'Base Revenue'!$AY$61) -> 0.24271586 | BG28: =(SUM('2. Headcount Buildup'!$F$46:$Q$46)/12)*('Base Revenue'!$AY28/'Base Revenue'!$AY$61) -> 0.38834537 | BH28: =SUM(BA28:BG28) -> 1.5766907 | BK28: Total | BL28: =SUM(BL6:BL27) -> 2469602.7 | BM28: =SUM(BM6:BM27) -> 1472.7158 | BN28: =BL28/BM28 -> 1676.9038
B29: Base | C29: Comprehensive Sleep Care Center | E29: Medical Records | F29: FTE | G29: 55 | H29: 1400 | I29: 1 | J29: 1400 | K29: 1400 | L29: 1400 | M29: 1400 | N29: 1400 | O29: 1400 | P29: 1400 | Q29: 1400 | R29: 1400 | S29: 1400 | T29: 1400 | U29: 1400 | V29: =SUM(J29:U29) -> 16800 | X29: 1 | Y29: 1 | Z29: 1 | AA29: 1 | AB29: 1 | AC29: 1 | AD29: 1 | AE29: 1 | AF29: 1 | AG29: 1 | AH29: 1 | AI29: 1 | AJ29: =SUM(X29:AI29) -> 12 | AL29: =X29/$AL$4 -> 1.25 | AM29: =Y29/$AL$4 -> 1.25 | AN29: =Z29/$AL$4 -> 1.25 | AO29: =AA29/$AL$4 -> 1.25 | AP29: =AB29/$AL$4 -> 1.25 | AQ29: =AC29/$AL$4 -> 1.25 | AR29: =AD29/$AL$4 -> 1.25 | AS29: =AE29/$AL$4 -> 1.25 | ... AW29: =AI29/$AL$4 -> 1.25 | AX29: =SUM(AL29:AW29) -> 15 | AY29: =AX29/12 -> 1.25 | BA29: =AY29/'2. Headcount Buildup'!$D$36 -> 0.083333333 | BB29: =AY29/'2. Headcount Buildup'!$D$37 -> 0.025 | BC29: =AY29/'2. Headcount Buildup'!$D$38 -> 0.0125 | BD29: =AY29/'2. Headcount Buildup'!$D$43 -> 0.0125 | BE29: =(SUM('2. Headcount Buildup'!$F$44:$Q$44)/12)*('Base Revenue'!$AY29/'Base Revenue'!$AY$61) -> 0.024271586 | BF29: =(SUM('2. Headcount Buildup'!$F$45:$Q$45)/12)*('Base Revenue'!$AY29/'Base Revenue'!$AY$61) -> 0.040452643 | BG29: =(SUM('2. Headcount Buildup'!$F$46:$Q$46)/12)*('Base Revenue'!$AY29/'Base Revenue'!$AY$61) -> 0.064724229 | BH29: =SUM(BA29:BG29) -> 0.26278179
B30: Base | C30: Comprehensive Sleep Care Center | E30: AASM | F30: FTE | G30: 40 | H30: 1300 | I30: 1 | J30: 1300 | K30: 1300 | L30: 1300 | M30: 1300 | N30: 1300 | O30: 1300 | P30: 1300 | Q30: 1300 | R30: 1300 | S30: 1300 | T30: 1300 | U30: 1300 | V30: =SUM(J30:U30) -> 15600 | X30: 1 | Y30: 1 | Z30: 1 | AA30: 1 | AB30: 1 | AC30: 1 | AD30: 1 | AE30: 1 | AF30: 1 | AG30: 1 | AH30: 1 | AI30: 1 | AJ30: =SUM(X30:AI30) -> 12 | AL30: =X30/$AL$4 -> 1.25 | AM30: =Y30/$AL$4 -> 1.25 | AN30: =Z30/$AL$4 -> 1.25 | AO30: =AA30/$AL$4 -> 1.25 | AP30: =AB30/$AL$4 -> 1.25 | AQ30: =AC30/$AL$4 -> 1.25 | AR30: =AD30/$AL$4 -> 1.25 | AS30: =AE30/$AL$4 -> 1.25 | ... AW30: =AI30/$AL$4 -> 1.25 | AX30: =SUM(AL30:AW30) -> 15 | AY30: =AX30/12 -> 1.25 | BA30: =AY30/'2. Headcount Buildup'!$D$36 -> 0.083333333 | BB30: =AY30/'2. Headcount Buildup'!$D$37 -> 0.025 | BC30: =AY30/'2. Headcount Buildup'!$D$38 -> 0.0125 | BD30: =AY30/'2. Headcount Buildup'!$D$43 -> 0.0125 | BE30: =(SUM('2. Headcount Buildup'!$F$44:$Q$44)/12)*('Base Revenue'!$AY30/'Base Revenue'!$AY$61) -> 0.024271586 | BF30: =(SUM('2. Headcount Buildup'!$F$45:$Q$45)/12)*('Base Revenue'!$AY30/'Base Revenue'!$AY$61) -> 0.040452643 | BG30: =(SUM('2. Headcount Buildup'!$F$46:$Q$46)/12)*('Base Revenue'!$AY30/'Base Revenue'!$AY$61) -> 0.064724229 | BH30: =SUM(BA30:BG30) -> 0.26278179 | BK30: Data Entry | BL30: Rev | BM30: Base FTE | BN30: Pricing
B31: Base | C31: Comprehensive Sleep Care Center | E31: DME Admin | F31: FTE | G31: 40 | H31: 1400 | I31: 1 | J31: 1400 | K31: 1400 | L31: 1400 | M31: 1400 | N31: 1400 | O31: 1400 | P31: 1400 | Q31: 1400 | R31: 1400 | S31: 1400 | T31: 1400 | U31: 1400 | V31: =SUM(J31:U31) -> 16800 | X31: 1 | Y31: 1 | Z31: 1 | AA31: 1 | AB31: 1 | AC31: 1 | AD31: 1 | AE31: 1 | AF31: 1 | AG31: 1 | AH31: 1 | AI31: 1 | AJ31: =SUM(X31:AI31) -> 12 | AL31: =X31/$AL$4 -> 1.25 | AM31: =Y31/$AL$4 -> 1.25 | AN31: =Z31/$AL$4 -> 1.25 | AO31: =AA31/$AL$4 -> 1.25 | AP31: =AB31/$AL$4 -> 1.25 | AQ31: =AC31/$AL$4 -> 1.25 | AR31: =AD31/$AL$4 -> 1.25 | AS31: =AE31/$AL$4 -> 1.25 | ... AW31: =AI31/$AL$4 -> 1.25 | AX31: =SUM(AL31:AW31) -> 15 | AY31: =AX31/12 -> 1.25 | BA31: =AY31/'2. Headcount Buildup'!$D$36 -> 0.083333333 | BB31: =AY31/'2. Headcount Buildup'!$D$37 -> 0.025 | BC31: =AY31/'2. Headcount Buildup'!$D$38 -> 0.0125 | BD31: =AY31/'2. Headcount Buildup'!$D$43 -> 0.0125 | BE31: =(SUM('2. Headcount Buildup'!$F$44:$Q$44)/12)*('Base Revenue'!$AY31/'Base Revenue'!$AY$61) -> 0.024271586 | BF31: =(SUM('2. Headcount Buildup'!$F$45:$Q$45)/12)*('Base Revenue'!$AY31/'Base Revenue'!$AY$61) -> 0.040452643 | BG31: =(SUM('2. Headcount Buildup'!$F$46:$Q$46)/12)*('Base Revenue'!$AY31/'Base Revenue'!$AY$61) -> 0.064724229 | BH31: =SUM(BA31:BG31) -> 0.26278179 | BK31: eC3 LLC | BN31: =IFERROR(BL31/BM31,0) -> 0
B32: Base | C32: Comprehensive Sleep Care Center | E32: SS Coordinatior | F32: FTE | G32: 40 | H32: 1400 | I32: 2 | J32: 2800 | K32: 2800 | L32: 2800 | M32: 2800 | N32: 2800 | O32: 2800 | P32: 2800 | Q32: 2800 | R32: 2800 | S32: 2800 | T32: 2800 | U32: 2800 | V32: =SUM(J32:U32) -> 33600 | X32: 2 | Y32: 2 | Z32: 2 | AA32: 2 | AB32: 2 | AC32: 2 | AD32: 2 | AE32: 2 | AF32: 2 | AG32: 2 | AH32: 2 | AI32: 2 | AJ32: =SUM(X32:AI32) -> 24 | AL32: =X32/$AL$4 -> 2.5 | AM32: =Y32/$AL$4 -> 2.5 | AN32: =Z32/$AL$4 -> 2.5 | AO32: =AA32/$AL$4 -> 2.5 | AP32: =AB32/$AL$4 -> 2.5 | AQ32: =AC32/$AL$4 -> 2.5 | AR32: =AD32/$AL$4 -> 2.5 | AS32: =AE32/$AL$4 -> 2.5 | ... AW32: =AI32/$AL$4 -> 2.5 | AX32: =SUM(AL32:AW32) -> 30 | AY32: =AX32/12 -> 2.5 | BA32: =AY32/'2. Headcount Buildup'!$D$36 -> 0.16666667 | BB32: =AY32/'2. Headcount Buildup'!$D$37 -> 0.05 | BC32: =AY32/'2. Headcount Buildup'!$D$38 -> 0.025 | BD32: =AY32/'2. Headcount Buildup'!$D$43 -> 0.025 | BE32: =(SUM('2. Headcount Buildup'!$F$44:$Q$44)/12)*('Base Revenue'!$AY32/'Base Revenue'!$AY$61) -> 0.048543172 | BF32: =(SUM('2. Headcount Buildup'!$F$45:$Q$45)/12)*('Base Revenue'!$AY32/'Base Revenue'!$AY$61) -> 0.080905286 | BG32: =(SUM('2. Headcount Buildup'!$F$46:$Q$46)/12)*('Base Revenue'!$AY32/'Base Revenue'!$AY$61) -> 0.12944846 | BH32: =SUM(BA32:BG32) -> 0.52556358 | BK32: D'Souza & Associates, Inc | BN32: =IFERROR(BL32/BM32,0) -> 0
B33: Base | C33: Comprehensive Sleep Care Center | E33: Referral Coordinator | F33: FTE | G33: 50 | H33: 1400 | I33: 2 | J33: 2800 | K33: 2800 | L33: 2800 | M33: 2800 | N33: 2800 | O33: 2800 | P33: 2800 | Q33: 2800 | R33: 2800 | S33: 2800 | T33: 2800 | U33: 2800 | V33: =SUM(J33:U33) -> 33600 | X33: 2 | Y33: 2 | Z33: 2 | AA33: 2 | AB33: 2 | AC33: 2 | AD33: 2 | AE33: 2 | AF33: 2 | AG33: 2 | AH33: 2 | AI33: 2 | AJ33: =SUM(X33:AI33) -> 24 | AL33: =X33/$AL$4 -> 2.5 | AM33: =Y33/$AL$4 -> 2.5 | AN33: =Z33/$AL$4 -> 2.5 | AO33: =AA33/$AL$4 -> 2.5 | AP33: =AB33/$AL$4 -> 2.5 | AQ33: =AC33/$AL$4 -> 2.5 | AR33: =AD33/$AL$4 -> 2.5 | AS33: =AE33/$AL$4 -> 2.5 | ... AW33: =AI33/$AL$4 -> 2.5 | AX33: =SUM(AL33:AW33) -> 30 | AY33: =AX33/12 -> 2.5 | BA33: =AY33/'2. Headcount Buildup'!$D$36 -> 0.16666667 | BB33: =AY33/'2. Headcount Buildup'!$D$37 -> 0.05 | BC33: =AY33/'2. Headcount Buildup'!$D$38 -> 0.025 | BD33: =AY33/'2. Headcount Buildup'!$D$43 -> 0.025 | BE33: =(SUM('2. Headcount Buildup'!$F$44:$Q$44)/12)*('Base Revenue'!$AY33/'Base Revenue'!$AY$61) -> 0.048543172 | BF33: =(SUM('2. Headcount Buildup'!$F$45:$Q$45)/12)*('Base Revenue'!$AY33/'Base Revenue'!$AY$61) -> 0.080905286 | BG33: =(SUM('2. Headcount Buildup'!$F$46:$Q$46)/12)*('Base Revenue'!$AY33/'Base Revenue'!$AY$61) -> 0.12944846 | BH33: =SUM(BA33:BG33) -> 0.52556358 | BK33: Univ. Of Delaware | BN33: =IFERROR(BL33/BM33,0) -> 0
B34: Base | C34: Comprehensive Sleep Care Center | E34: OA Auth | F34: FTE | G34: 40 | H34: 1400 | I34: 1 | J34: 1400 | K34: 1400 | L34: 1400 | M34: 1400 | N34: 1400 | O34: 1400 | P34: 1400 | Q34: 1400 | R34: 1400 | S34: 1400 | T34: 1400 | U34: 1400 | V34: =SUM(J34:U34) -> 16800 | X34: 1 | Y34: 1 | Z34: 1 | AA34: 1 | AB34: 1 | AC34: 1 | AD34: 1 | AE34: 1 | AF34: 1 | AG34: 1 | AH34: 1 | AI34: 1 | AJ34: =SUM(X34:AI34) -> 12 | AL34: =X34/$AL$4 -> 1.25 | AM34: =Y34/$AL$4 -> 1.25 | AN34: =Z34/$AL$4 -> 1.25 | AO34: =AA34/$AL$4 -> 1.25 | AP34: =AB34/$AL$4 -> 1.25 | AQ34: =AC34/$AL$4 -> 1.25 | AR34: =AD34/$AL$4 -> 1.25 | AS34: =AE34/$AL$4 -> 1.25 | ... AW34: =AI34/$AL$4 -> 1.25 | AX34: =SUM(AL34:AW34) -> 15 | AY34: =AX34/12 -> 1.25 | BA34: =AY34/'2. Headcount Buildup'!$D$36 -> 0.083333333 | BB34: =AY34/'2. Headcount Buildup'!$D$37 -> 0.025 | BC34: =AY34/'2. Headcount Buildup'!$D$38 -> 0.0125 | BD34: =AY34/'2. Headcount Buildup'!$D$43 -> 0.0125 | BE34: =(SUM('2. Headcount Buildup'!$F$44:$Q$44)/12)*('Base Revenue'!$AY34/'Base Revenue'!$AY$61) -> 0.024271586 | BF34: =(SUM('2. Headcount Buildup'!$F$45:$Q$45)/12)*('Base Revenue'!$AY34/'Base Revenue'!$AY$61) -> 0.040452643 | BG34: =(SUM('2. Headcount Buildup'!$F$46:$Q$46)/12)*('Base Revenue'!$AY34/'Base Revenue'!$AY$61) -> 0.064724229 | BH34: =SUM(BA34:BG34) -> 0.26278179 | BK34: Staff a Dental LLC | BN34: =IFERROR(BL34/BM34,0) -> 0
B35: Base | C35: Comprehensive Sleep Care Center | E35: DME OOPC | F35: FTE | G35: 60 | H35: 1400 | I35: 1 | J35: 1400 | K35: 1400 | L35: 1400 | M35: 1400 | N35: 1400 | O35: 1400 | P35: 1400 | Q35: 1400 | R35: 1400 | S35: 1400 | T35: 1400 | U35: 1400 | V35: =SUM(J35:U35) -> 16800 | X35: 1 | Y35: 1 | Z35: 1 | AA35: 1 | AB35: 1 | AC35: 1 | AD35: 1 | AE35: 1 | AF35: 1 | AG35: 1 | AH35: 1 | AI35: 1 | AJ35: =SUM(X35:AI35) -> 12 | AL35: =X35/$AL$4 -> 1.25 | AM35: =Y35/$AL$4 -> 1.25 | AN35: =Z35/$AL$4 -> 1.25 | AO35: =AA35/$AL$4 -> 1.25 | AP35: =AB35/$AL$4 -> 1.25 | AQ35: =AC35/$AL$4 -> 1.25 | AR35: =AD35/$AL$4 -> 1.25 | AS35: =AE35/$AL$4 -> 1.25 | ... AW35: =AI35/$AL$4 -> 1.25 | AX35: =SUM(AL35:AW35) -> 15 | AY35: =AX35/12 -> 1.25 | BA35: =AY35/'2. Headcount Buildup'!$D$36 -> 0.083333333 | BB35: =AY35/'2. Headcount Buildup'!$D$37 -> 0.025 | BC35: =AY35/'2. Headcount Buildup'!$D$38 -> 0.0125 | BD35: =AY35/'2. Headcount Buildup'!$D$43 -> 0.0125 | BE35: =(SUM('2. Headcount Buildup'!$F$44:$Q$44)/12)*('Base Revenue'!$AY35/'Base Revenue'!$AY$61) -> 0.024271586 | BF35: =(SUM('2. Headcount Buildup'!$F$45:$Q$45)/12)*('Base Revenue'!$AY35/'Base Revenue'!$AY$61) -> 0.040452643 | BG35: =(SUM('2. Headcount Buildup'!$F$46:$Q$46)/12)*('Base Revenue'!$AY35/'Base Revenue'!$AY$61) -> 0.064724229 | BH35: =SUM(BA35:BG35) -> 0.26278179 | BK35: Source It Dental | BN35: =IFERROR(BL35/BM35,0) -> 0
B36: New Addition | C36: Comprehensive Sleep Care Center | E36: Patient Calling | F36: FTE | H36: 1350 | L36: =$H36*8 -> 10800 | M36: =$H36*8 -> 10800 | N36: =$H36*8 -> 10800 | O36: =$H36*8 -> 10800 | P36: =$H36*8 -> 10800 | Q36: =$H36*8 -> 10800 | R36: =$H36*8 -> 10800 | S36: =$H36*8 -> 10800 | ... U36: =$H36*8 -> 10800 | V36: =SUM(J36:U36) -> 108000 | Z36: 6 | AA36: 6 | AB36: 6 | AC36: 6 | AD36: 6 | AE36: 6 | AF36: 6 | AG36: 6 | AH36: 6 | AI36: 6 | AJ36: =SUM(X36:AI36) -> 60 | AL36: =X36/$AL$4 -> 0 | AM36: =Y36/$AL$4 -> 0 | AN36: =Z36/$AL$4 -> 7.5 | AO36: =AA36/$AL$4 -> 7.5 | AP36: =AB36/$AL$4 -> 7.5 | AQ36: =AC36/$AL$4 -> 7.5 | AR36: =AD36/$AL$4 -> 7.5 | AS36: =AE36/$AL$4 -> 7.5 | ... AX36: =AJ36/$AL$4 -> 75 | AY36: =AX36/12 -> 6.25 | BA36: =AY36/'2. Headcount Buildup'!$D$36 -> 0.41666667 | BB36: =AY36/'2. Headcount Buildup'!$D$37 -> 0.125 | BC36: =AY36/'2. Headcount Buildup'!$D$38 -> 0.0625 | BD36: =AY36/'2. Headcount Buildup'!$D$43 -> 0.0625 | BE36: =(SUM('2. Headcount Buildup'!$F$44:$Q$44)/12)*('Base Revenue'!$AY36/'Base Revenue'!$AY$61) -> 0.12135793 | BF36: =(SUM('2. Headcount Buildup'!$F$45:$Q$45)/12)*('Base Revenue'!$AY36/'Base Revenue'!$AY$61) -> 0.20226321 | BG36: =(SUM('2. Headcount Buildup'!$F$46:$Q$46)/12)*('Base Revenue'!$AY36/'Base Revenue'!$AY$61) -> 0.32362114 | BH36: =SUM(BA36:BG36) -> 1.313909
B37: New Addition | C37: Comprehensive Sleep Care Center | E37: Account Manager | F37: FTE | H37: 1600 | K37: 1600 | L37: 1600 | M37: 1600 | N37: 1600 | O37: 1600 | P37: 1600 | Q37: 1600 | R37: 1600 | S37: 1600 | T37: 1600 | U37: 1600 | V37: =SUM(J37:U37) -> 17600 | Y37: 1 | Z37: 1 | AA37: 1 | AB37: 1 | AC37: 1 | AD37: 1 | AE37: 1 | AF37: 1 | AG37: 1 | AH37: 1 | AI37: 1 | AJ37: =SUM(X37:AI37) -> 11 | AL37: =X37/$AL$4 -> 0 | AM37: =Y37/$AL$4 -> 1.25 | AN37: =Z37/$AL$4 -> 1.25 | AO37: =AA37/$AL$4 -> 1.25 | AP37: =AB37/$AL$4 -> 1.25 | AQ37: =AC37/$AL$4 -> 1.25 | AR37: =AD37/$AL$4 -> 1.25 | AS37: =AE37/$AL$4 -> 1.25 | ... AX37: =AJ37/$AL$4 -> 13.75 | AY37: =AX37/12 -> 1.1458333 | BA37: =AY37/'2. Headcount Buildup'!$D$36 -> 0.076388889 | BB37: =AY37/'2. Headcount Buildup'!$D$37 -> 0.022916667 | BC37: =AY37/'2. Headcount Buildup'!$D$38 -> 0.011458333 | BD37: =AY37/'2. Headcount Buildup'!$D$43 -> 0.011458333 | BE37: =(SUM('2. Headcount Buildup'!$F$44:$Q$44)/12)*('Base Revenue'!$AY37/'Base Revenue'!$AY$61) -> 0.022248954 | BF37: =(SUM('2. Headcount Buildup'!$F$45:$Q$45)/12)*('Base Revenue'!$AY37/'Base Revenue'!$AY$61) -> 0.037081589 | BG37: =(SUM('2. Headcount Buildup'!$F$46:$Q$46)/12)*('Base Revenue'!$AY37/'Base Revenue'!$AY$61) -> 0.059330543 | BH37: =SUM(BA37:BG37) -> 0.24088331
B38: New Addition | C38: Cair Health | E38: Biller | F38: FTE | H38: 1350 | K38: 675 | L38: 1350 | M38: 1350 | N38: 1350 | O38: 1350 | P38: 1350 | Q38: 1350 | R38: 1350 | S38: 1350 | T38: 1350 | U38: 1350 | V38: =SUM(J38:U38) -> 14175 | Y38: 0.5 | Z38: 1 | AA38: 1 | AB38: 1 | AC38: 1 | AD38: 1 | AE38: 1 | AF38: 1 | AG38: 1 | AH38: 1 | AI38: 1 | AJ38: =SUM(X38:AI38) -> 10.5 | AL38: =X38/$AL$4 -> 0 | AM38: =Y38/$AL$4 -> 0.625 | AN38: =Z38/$AL$4 -> 1.25 | AO38: =AA38/$AL$4 -> 1.25 | AP38: =AB38/$AL$4 -> 1.25 | AQ38: =AC38/$AL$4 -> 1.25 | AR38: =AD38/$AL$4 -> 1.25 | AS38: =AE38/$AL$4 -> 1.25 | ... AX38: =AJ38/$AL$4 -> 13.125 | AY38: =AX38/12 -> 1.09375 | BA38: =AY38/'2. Headcount Buildup'!$D$36 -> 0.072916667 | BB38: =AY38/'2. Headcount Buildup'!$D$37 -> 0.021875 | BC38: =AY38/'2. Headcount Buildup'!$D$38 -> 0.0109375 | BD38: =AY38/'2. Headcount Buildup'!$D$43 -> 0.0109375 | BE38: =(SUM('2. Headcount Buildup'!$F$44:$Q$44)/12)*('Base Revenue'!$AY38/'Base Revenue'!$AY$61) -> 0.021237638 | BF38: =(SUM('2. Headcount Buildup'!$F$45:$Q$45)/12)*('Base Revenue'!$AY38/'Base Revenue'!$AY$61) -> 0.035396063 | BG38: =(SUM('2. Headcount Buildup'!$F$46:$Q$46)/12)*('Base Revenue'!$AY38/'Base Revenue'!$AY$61) -> 0.0566337 | BH38: =SUM(BA38:BG38) -> 0.22993407
B39: Base | C39: Your Docs In | E39: End to End | F39: Collection | H39: $0.06 | I39: 820000 | J39: 45100 | K39: 45100 | L39: 30415 | V39: =SUM(J39:U39) -> 120615 | X39: 15.47 | Y39: 15.47 | AJ39: =SUM(X39:AI39) -> 30.94 | AL39: =X39/$AL$4 -> 19.3375 | AM39: =Y39/$AL$4 -> 19.3375 | AN39: =Z39/$AL$4 -> 0 | AO39: =AA39/$AL$4 -> 0 | AP39: =AB39/$AL$4 -> 0 | AQ39: =AC39/$AL$4 -> 0 | AR39: =AD39/$AL$4 -> 0 | AS39: =AE39/$AL$4 -> 0 | ... AW39: =AI39/$AL$4 -> 0 | AX39: =SUM(AL39:AW39) -> 38.675 | AY39: =AX39/12 -> 3.2229167 | BA39: =AY39/'2. Headcount Buildup'!$D$36 -> 0.21486111 | BB39: =AY39/'2. Headcount Buildup'!$D$37 -> 0.064458333 | BC39: =AY39/'2. Headcount Buildup'!$D$38 -> 0.032229167 | BD39: =AY39/'2. Headcount Buildup'!$D$43 -> 0.032229167 | BE39: =(SUM('2. Headcount Buildup'!$F$44:$Q$44)/12)*('Base Revenue'!$AY39/'Base Revenue'!$AY$61) -> 0.062580239 | BF39: =(SUM('2. Headcount Buildup'!$F$45:$Q$45)/12)*('Base Revenue'!$AY39/'Base Revenue'!$AY$61) -> 0.1043004 | BG39: =(SUM('2. Headcount Buildup'!$F$46:$Q$46)/12)*('Base Revenue'!$AY39/'Base Revenue'!$AY$61) -> 0.16688064 | BH39: =SUM(BA39:BG39) -> 0.67753905 | BK39: Physical Therapy & Sports Medicine Center | BN39: =IFERROR(BL39/BM39,0) -> 0
B40: Base | C40: Your Docs In | E40: Patient AR Caller | F40: FTE | G40: 80 | H40: $1,750.00 | I40: 2 | J40: 3500 | K40: 3500 | V40: =SUM(J40:U40) -> 7000 | X40: 2 | Y40: 2 | AJ40: =SUM(X40:AI40) -> 4 | AL40: =X40/$AL$4 -> 2.5 | AM40: =Y40/$AL$4 -> 2.5 | AN40: =Z40/$AL$4 -> 0 | AO40: =AA40/$AL$4 -> 0 | AP40: =AB40/$AL$4 -> 0 | AQ40: =AC40/$AL$4 -> 0 | AR40: =AD40/$AL$4 -> 0 | AS40: =AE40/$AL$4 -> 0 | ... AW40: =AI40/$AL$4 -> 0 | AX40: =SUM(AL40:AW40) -> 5 | AY40: =AX40/12 -> 0.41666667 | BA40: =AY40/'2. Headcount Buildup'!$D$36 -> 0.027777778 | BB40: =AY40/'2. Headcount Buildup'!$D$37 -> 0.0083333333 | BC40: =AY40/'2. Headcount Buildup'!$D$38 -> 0.0041666667 | BD40: =AY40/'2. Headcount Buildup'!$D$43 -> 0.0041666667 | BE40: =(SUM('2. Headcount Buildup'!$F$44:$Q$44)/12)*('Base Revenue'!$AY40/'Base Revenue'!$AY$61) -> 0.0080905286 | BF40: =(SUM('2. Headcount Buildup'!$F$45:$Q$45)/12)*('Base Revenue'!$AY40/'Base Revenue'!$AY$61) -> 0.013484214 | BG40: =(SUM('2. Headcount Buildup'!$F$46:$Q$46)/12)*('Base Revenue'!$AY40/'Base Revenue'!$AY$61) -> 0.021574743 | BH40: =SUM(BA40:BG40) -> 0.08759393 | BK40: Primetime Physical Therapy | BN40: =IFERROR(BL40/BM40,0) -> 0
B41: Base | C41: Your Docs In | E41: AMD Pay Feature | F41: FTE | H41: $1,350.00 | I41: 1 | J41: 1350 | K41: 1350 | V41: =SUM(J41:U41) -> 2700 | X41: 1 | Y41: 1 | AJ41: =SUM(X41:AI41) -> 2 | AL41: =X41/$AL$4 -> 1.25 | AM41: =Y41/$AL$4 -> 1.25 | AN41: =Z41/$AL$4 -> 0 | AO41: =AA41/$AL$4 -> 0 | AP41: =AB41/$AL$4 -> 0 | AQ41: =AC41/$AL$4 -> 0 | AR41: =AD41/$AL$4 -> 0 | AS41: =AE41/$AL$4 -> 0 | ... AW41: =AI41/$AL$4 -> 0 | AX41: =SUM(AL41:AW41) -> 2.5 | AY41: =AX41/12 -> 0.20833333 | BA41: =AY41/'2. Headcount Buildup'!$D$36 -> 0.013888889 | BB41: =AY41/'2. Headcount Buildup'!$D$37 -> 0.0041666667 | BC41: =AY41/'2. Headcount Buildup'!$D$38 -> 0.0020833333 | BD41: =AY41/'2. Headcount Buildup'!$D$43 -> 0.0020833333 | BE41: =(SUM('2. Headcount Buildup'!$F$44:$Q$44)/12)*('Base Revenue'!$AY41/'Base Revenue'!$AY$61) -> 0.0040452643 | BF41: =(SUM('2. Headcount Buildup'!$F$45:$Q$45)/12)*('Base Revenue'!$AY41/'Base Revenue'!$AY$61) -> 0.0067421072 | BG41: =(SUM('2. Headcount Buildup'!$F$46:$Q$46)/12)*('Base Revenue'!$AY41/'Base Revenue'!$AY$61) -> 0.010787371 | BH41: =SUM(BA41:BG41) -> 0.043796965 | BK41: Comprehensive Sleep Care Center | BN41: =IFERROR(BL41/BM41,0) -> 0
B42: Base | C42: The Physical Therapy Institute | E42: Auth | F42: Transaction | G42: 40 | J42: 2475 | K42: 2475 | L42: 2475 | M42: 2475 | N42: 2475 | O42: 2475 | P42: 2475 | Q42: 2475 | R42: 2475 | S42: 2475 | T42: 2475 | U42: 2475 | V42: =SUM(J42:U42) -> 29700 | X42: ='Base FTE'!$I48 -> 0.6547619 | Y42: ='Base FTE'!$I48 -> 0.6547619 | Z42: ='Base FTE'!$I48 -> 0.6547619 | AA42: ='Base FTE'!$I48 -> 0.6547619 | AB42: ='Base FTE'!$I48 -> 0.6547619 | AC42: ='Base FTE'!$I48 -> 0.6547619 | AD42: ='Base FTE'!$I48 -> 0.6547619 | AE42: ='Base FTE'!$I48 -> 0.6547619 | ... AI42: ='Base FTE'!$I48 -> 0.6547619 | AJ42: =SUM(X42:AI42) -> 7.8571429 | AL42: =X42/$AL$4 -> 0.81845238 | AM42: =Y42/$AL$4 -> 0.81845238 | AN42: =Z42/$AL$4 -> 0.81845238 | AO42: =AA42/$AL$4 -> 0.81845238 | AP42: =AB42/$AL$4 -> 0.81845238 | AQ42: =AC42/$AL$4 -> 0.81845238 | AR42: =AD42/$AL$4 -> 0.81845238 | AS42: =AE42/$AL$4 -> 0.81845238 | ... AW42: =AI42/$AL$4 -> 0.81845238 | AX42: =SUM(AL42:AW42) -> 9.8214286 | AY42: =AX42/12 -> 0.81845238 | BA42: =AY42/'2. Headcount Buildup'!$D$36 -> 0.054563492 | BB42: =AY42/'2. Headcount Buildup'!$D$37 -> 0.016369048 | BC42: =AY42/'2. Headcount Buildup'!$D$38 -> 0.0081845238 | BD42: =AY42/'2. Headcount Buildup'!$D$43 -> 0.0081845238 | BE42: =(SUM('2. Headcount Buildup'!$F$44:$Q$44)/12)*('Base Revenue'!$AY42/'Base Revenue'!$AY$61) -> 0.01589211 | BF42: =(SUM('2. Headcount Buildup'!$F$45:$Q$45)/12)*('Base Revenue'!$AY42/'Base Revenue'!$AY$61) -> 0.02648685 | BG42: =(SUM('2. Headcount Buildup'!$F$46:$Q$46)/12)*('Base Revenue'!$AY42/'Base Revenue'!$AY$61) -> 0.042378959 | BH42: =SUM(BA42:BG42) -> 0.17205951 | BK42: Your Docs In | BN42: =IFERROR(BL42/BM42,0) -> 0
B43: Base | C43: Procle Healthworks | E43: End to End | F43: Collection | G43: 120 | H43: 0.03 | I43: 40000 | J43: 1200 | K43: 1200 | L43: 1200 | M43: 1200 | N43: 1200 | O43: 1200 | P43: 1200 | Q43: 1200 | R43: 1200 | S43: 1200 | T43: 1200 | U43: 1200 | V43: =SUM(J43:U43) -> 14400 | X43: ='Base FTE'!$I75 -> 1.2678571 | Y43: ='Base FTE'!$I75 -> 1.2678571 | Z43: ='Base FTE'!$I75 -> 1.2678571 | AA43: ='Base FTE'!$I75 -> 1.2678571 | AB43: ='Base FTE'!$I75 -> 1.2678571 | AC43: ='Base FTE'!$I75 -> 1.2678571 | AD43: ='Base FTE'!$I75 -> 1.2678571 | AE43: ='Base FTE'!$I75 -> 1.2678571 | ... AI43: ='Base FTE'!$I75 -> 1.2678571 | AJ43: =SUM(X43:AI43) -> 15.214286 | AL43: =X43/$AL$4 -> 1.5848214 | AM43: =Y43/$AL$4 -> 1.5848214 | AN43: =Z43/$AL$4 -> 1.5848214 | AO43: =AA43/$AL$4 -> 1.5848214 | AP43: =AB43/$AL$4 -> 1.5848214 | AQ43: =AC43/$AL$4 -> 1.5848214 | AR43: =AD43/$AL$4 -> 1.5848214 | AS43: =AE43/$AL$4 -> 1.5848214 | ... AW43: =AI43/$AL$4 -> 1.5848214 | AX43: =SUM(AL43:AW43) -> 19.017857 | AY43: =AX43/12 -> 1.5848214 | BA43: =AY43/'2. Headcount Buildup'!$D$36 -> 0.10565476 | BB43: =AY43/'2. Headcount Buildup'!$D$37 -> 0.031696429 | BC43: =AY43/'2. Headcount Buildup'!$D$38 -> 0.015848214 | BD43: =AY43/'2. Headcount Buildup'!$D$43 -> 0.015848214 | BE43: =(SUM('2. Headcount Buildup'!$F$44:$Q$44)/12)*('Base Revenue'!$AY43/'Base Revenue'!$AY$61) -> 0.030772903 | BF43: =(SUM('2. Headcount Buildup'!$F$45:$Q$45)/12)*('Base Revenue'!$AY43/'Base Revenue'!$AY$61) -> 0.051288172 | BG43: =(SUM('2. Headcount Buildup'!$F$46:$Q$46)/12)*('Base Revenue'!$AY43/'Base Revenue'!$AY$61) -> 0.082061076 | BH43: =SUM(BA43:BG43) -> 0.33316977 | BK43: The Physical Therapy Institute | BN43: =IFERROR(BL43/BM43,0) -> 0
B44: Base | C44: BayLife | E44: AR Follow-up | F44: FTE | H44: 1600 | I44: 3 | J44: 4800 | K44: 4800 | L44: 4800 | M44: 4800 | N44: 4800 | O44: 4800 | P44: 4800 | Q44: 4800 | R44: 4800 | S44: 4800 | T44: 4800 | U44: 4800 | V44: =SUM(J44:U44) -> 57600 | X44: ='Base FTE'!$I76 -> 3 | Y44: ='Base FTE'!$I76 -> 3 | Z44: ='Base FTE'!$I76 -> 3 | AA44: ='Base FTE'!$I76 -> 3 | AB44: ='Base FTE'!$I76 -> 3 | AC44: ='Base FTE'!$I76 -> 3 | AD44: ='Base FTE'!$I76 -> 3 | AE44: ='Base FTE'!$I76 -> 3 | ... AI44: ='Base FTE'!$I76 -> 3 | AJ44: =SUM(X44:AI44) -> 36 | AL44: =X44/$AL$4 -> 3.75 | AM44: =Y44/$AL$4 -> 3.75 | AN44: =Z44/$AL$4 -> 3.75 | AO44: =AA44/$AL$4 -> 3.75 | AP44: =AB44/$AL$4 -> 3.75 | AQ44: =AC44/$AL$4 -> 3.75 | AR44: =AD44/$AL$4 -> 3.75 | AS44: =AE44/$AL$4 -> 3.75 | ... AW44: =AI44/$AL$4 -> 3.75 | AX44: =SUM(AL44:AW44) -> 45 | AY44: =AX44/12 -> 3.75 | BA44: =AY44/'2. Headcount Buildup'!$D$36 -> 0.25 | BB44: =AY44/'2. Headcount Buildup'!$D$37 -> 0.075 | BC44: =AY44/'2. Headcount Buildup'!$D$38 -> 0.0375 | BD44: =AY44/'2. Headcount Buildup'!$D$43 -> 0.0375 | BE44: =(SUM('2. Headcount Buildup'!$F$44:$Q$44)/12)*('Base Revenue'!$AY44/'Base Revenue'!$AY$61) -> 0.072814757 | BF44: =(SUM('2. Headcount Buildup'!$F$45:$Q$45)/12)*('Base Revenue'!$AY44/'Base Revenue'!$AY$61) -> 0.12135793 | BG44: =(SUM('2. Headcount Buildup'!$F$46:$Q$46)/12)*('Base Revenue'!$AY44/'Base Revenue'!$AY$61) -> 0.19417269 | BH44: =SUM(BA44:BG44) -> 0.78834537 | BK44: Procle Healthworks | BN44: =IFERROR(BL44/BM44,0) -> 0
B45: Base | C45: BayLife | E45: Auth | F45: Transaction | H45: 4.5 | I45: 100 | J45: 450 | K45: 450 | L45: 450 | M45: 450 | N45: 450 | O45: 450 | P45: 450 | Q45: 450 | R45: 450 | S45: 450 | T45: 450 | U45: 450 | V45: =SUM(J45:U45) -> 5400 | X45: ='Base FTE'!$I77 -> 0.11904762 | Y45: ='Base FTE'!$I77 -> 0.11904762 | Z45: ='Base FTE'!$I77 -> 0.11904762 | AA45: ='Base FTE'!$I77 -> 0.11904762 | AB45: ='Base FTE'!$I77 -> 0.11904762 | AC45: ='Base FTE'!$I77 -> 0.11904762 | AD45: ='Base FTE'!$I77 -> 0.11904762 | AE45: ='Base FTE'!$I77 -> 0.11904762 | ... AI45: ='Base FTE'!$I77 -> 0.11904762 | AJ45: =SUM(X45:AI45) -> 1.4285714 | AL45: =X45/$AL$4 -> 0.14880952 | AM45: =Y45/$AL$4 -> 0.14880952 | AN45: =Z45/$AL$4 -> 0.14880952 | AO45: =AA45/$AL$4 -> 0.14880952 | AP45: =AB45/$AL$4 -> 0.14880952 | AQ45: =AC45/$AL$4 -> 0.14880952 | AR45: =AD45/$AL$4 -> 0.14880952 | AS45: =AE45/$AL$4 -> 0.14880952 | ... AW45: =AI45/$AL$4 -> 0.14880952 | AX45: =SUM(AL45:AW45) -> 1.7857143 | AY45: =AX45/12 -> 0.14880952 | BA45: =AY45/'2. Headcount Buildup'!$D$36 -> 0.0099206349 | BB45: =AY45/'2. Headcount Buildup'!$D$37 -> 0.0029761905 | BC45: =AY45/'2. Headcount Buildup'!$D$38 -> 0.0014880952 | BD45: =AY45/'2. Headcount Buildup'!$D$43 -> 0.0014880952 | BE45: =(SUM('2. Headcount Buildup'!$F$44:$Q$44)/12)*('Base Revenue'!$AY45/'Base Revenue'!$AY$61) -> 0.0028894745 | BF45: =(SUM('2. Headcount Buildup'!$F$45:$Q$45)/12)*('Base Revenue'!$AY45/'Base Revenue'!$AY$61) -> 0.0048157908 | BG45: =(SUM('2. Headcount Buildup'!$F$46:$Q$46)/12)*('Base Revenue'!$AY45/'Base Revenue'!$AY$61) -> 0.0077052653 | BH45: =SUM(BA45:BG45) -> 0.031283547 | BK45: BayLife | BN45: =IFERROR(BL45/BM45,0) -> 0
B46: Base | C46: Premier Sleep Center | E46: AR Follow-up | F46: FTE | G46: 130 | H46: 1750 | I46: 1 | J46: 1750 | K46: 1750 | L46: 1750 | M46: 1750 | N46: 1750 | O46: 1750 | P46: 1750 | Q46: 1750 | R46: 1750 | S46: 1750 | T46: 1750 | U46: 1750 | V46: =SUM(J46:U46) -> 21000 | X46: ='Base FTE'!$I70 -> 1 | Y46: ='Base FTE'!$I70 -> 1 | Z46: ='Base FTE'!$I70 -> 1 | AA46: ='Base FTE'!$I70 -> 1 | AB46: ='Base FTE'!$I70 -> 1 | AC46: ='Base FTE'!$I70 -> 1 | AD46: ='Base FTE'!$I70 -> 1 | AE46: ='Base FTE'!$I70 -> 1 | ... AI46: ='Base FTE'!$I70 -> 1 | AJ46: =SUM(X46:AI46) -> 12 | AL46: =X46/$AL$4 -> 1.25 | AM46: =Y46/$AL$4 -> 1.25 | AN46: =Z46/$AL$4 -> 1.25 | AO46: =AA46/$AL$4 -> 1.25 | AP46: =AB46/$AL$4 -> 1.25 | AQ46: =AC46/$AL$4 -> 1.25 | AR46: =AD46/$AL$4 -> 1.25 | AS46: =AE46/$AL$4 -> 1.25 | ... AW46: =AI46/$AL$4 -> 1.25 | AX46: =SUM(AL46:AW46) -> 15 | AY46: =AX46/12 -> 1.25 | BA46: =AY46/'2. Headcount Buildup'!$D$36 -> 0.083333333 | BB46: =AY46/'2. Headcount Buildup'!$D$37 -> 0.025 | BC46: =AY46/'2. Headcount Buildup'!$D$38 -> 0.0125 | BD46: =AY46/'2. Headcount Buildup'!$D$43 -> 0.0125 | BE46: =(SUM('2. Headcount Buildup'!$F$44:$Q$44)/12)*('Base Revenue'!$AY46/'Base Revenue'!$AY$61) -> 0.024271586 | BF46: =(SUM('2. Headcount Buildup'!$F$45:$Q$45)/12)*('Base Revenue'!$AY46/'Base Revenue'!$AY$61) -> 0.040452643 | BG46: =(SUM('2. Headcount Buildup'!$F$46:$Q$46)/12)*('Base Revenue'!$AY46/'Base Revenue'!$AY$61) -> 0.064724229 | BH46: =SUM(BA46:BG46) -> 0.26278179 | BK46: Premier Sleep Center | BN46: =IFERROR(BL46/BM46,0) -> 0
B47: Base | C47: Premier Sleep Center | E47: End to End | F47: Collection | H47: 0.05 | I47: 100000 | J47: 5000 | K47: 5000 | L47: 5000 | M47: 5000 | N47: 5000 | O47: 5000 | P47: 5000 | Q47: 5000 | R47: 5000 | S47: 5000 | T47: 5000 | U47: 5000 | V47: =SUM(J47:U47) -> 60000 | X47: ='Base FTE'!$I71 -> 0.37238095 | Y47: ='Base FTE'!$I71 -> 0.37238095 | Z47: ='Base FTE'!$I71 -> 0.37238095 | AA47: ='Base FTE'!$I71 -> 0.37238095 | AB47: ='Base FTE'!$I71 -> 0.37238095 | AC47: ='Base FTE'!$I71 -> 0.37238095 | AD47: ='Base FTE'!$I71 -> 0.37238095 | AE47: ='Base FTE'!$I71 -> 0.37238095 | ... AI47: ='Base FTE'!$I71 -> 0.37238095 | AJ47: =SUM(X47:AI47) -> 4.4685714 | AL47: =X47/$AL$4 -> 0.46547619 | AM47: =Y47/$AL$4 -> 0.46547619 | AN47: =Z47/$AL$4 -> 0.46547619 | AO47: =AA47/$AL$4 -> 0.46547619 | AP47: =AB47/$AL$4 -> 0.46547619 | AQ47: =AC47/$AL$4 -> 0.46547619 | AR47: =AD47/$AL$4 -> 0.46547619 | AS47: =AE47/$AL$4 -> 0.46547619 | ... AW47: =AI47/$AL$4 -> 0.46547619 | AX47: =SUM(AL47:AW47) -> 5.5857143 | AY47: =AX47/12 -> 0.46547619 | BA47: =AY47/'2. Headcount Buildup'!$D$36 -> 0.031031746 | BB47: =AY47/'2. Headcount Buildup'!$D$37 -> 0.0093095238 | BC47: =AY47/'2. Headcount Buildup'!$D$38 -> 0.0046547619 | BD47: =AY47/'2. Headcount Buildup'!$D$43 -> 0.0046547619 | BE47: =(SUM('2. Headcount Buildup'!$F$44:$Q$44)/12)*('Base Revenue'!$AY47/'Base Revenue'!$AY$61) -> 0.0090382762 | BF47: =(SUM('2. Headcount Buildup'!$F$45:$Q$45)/12)*('Base Revenue'!$AY47/'Base Revenue'!$AY$61) -> 0.015063794 | BG47: =(SUM('2. Headcount Buildup'!$F$46:$Q$46)/12)*('Base Revenue'!$AY47/'Base Revenue'!$AY$61) -> 0.02410207 | BH47: =SUM(BA47:BG47) -> 0.097854934 | BK47: Emergence Health Holdings | BN47: =IFERROR(BL47/BM47,0) -> 0
B48: Base | C48: Emergence Health Holdings | E48: AR Calling & Denials | F48: FTE | G48: 30 | H48: 2500 | I48: 10 | J48: 25000 | K48: 25000 | L48: 22500 | M48: 20000 | N48: 20000 | O48: 20000 | P48: 20000 | Q48: 20000 | R48: 20000 | S48: 20000 | T48: 20000 | U48: 20000 | V48: =SUM(J48:U48) -> 252500 | X48: 10 | Y48: 10 | Z48: 10 | AA48: 10 | AB48: 10 | AC48: 10 | AD48: 10 | AE48: 10 | AF48: 10 | AG48: 10 | AH48: 10 | AI48: 10 | AJ48: =SUM(X48:AI48) -> 120 | AL48: =X48/$AL$4 -> 12.5 | AM48: =Y48/$AL$4 -> 12.5 | AN48: =Z48/$AL$4 -> 12.5 | AO48: =AA48/$AL$4 -> 12.5 | AP48: =AB48/$AL$4 -> 12.5 | AQ48: =AC48/$AL$4 -> 12.5 | AR48: =AD48/$AL$4 -> 12.5 | AS48: =AE48/$AL$4 -> 12.5 | ... AW48: =AI48/$AL$4 -> 12.5 | AX48: =SUM(AL48:AW48) -> 150 | AY48: =AX48/12 -> 12.5 | BA48: =AY48/'2. Headcount Buildup'!$D$36 -> 0.83333333 | BB48: =AY48/'2. Headcount Buildup'!$D$37 -> 0.25 | BC48: =AY48/'2. Headcount Buildup'!$D$38 -> 0.125 | BD48: =AY48/'2. Headcount Buildup'!$D$43 -> 0.125 | BE48: =(SUM('2. Headcount Buildup'!$F$44:$Q$44)/12)*('Base Revenue'!$AY48/'Base Revenue'!$AY$61) -> 0.24271586 | BF48: =(SUM('2. Headcount Buildup'!$F$45:$Q$45)/12)*('Base Revenue'!$AY48/'Base Revenue'!$AY$61) -> 0.40452643 | BG48: =(SUM('2. Headcount Buildup'!$F$46:$Q$46)/12)*('Base Revenue'!$AY48/'Base Revenue'!$AY$61) -> 0.64724229 | BH48: =SUM(BA48:BG48) -> 2.6278179 | BK48: Nova Physician Wellness | BN48: =IFERROR(BL48/BM48,0) -> 0
B49: Base | C49: Nova Physician Wellness | E49: AR Follow-up | F49: FTE | G49: 40 | H49: 1450 | I49: 1 | J49: 1450 | K49: 1450 | L49: 1450 | M49: 1450 | N49: 1450 | O49: 1450 | P49: 1450 | Q49: 1450 | R49: 1450 | S49: 1450 | T49: 1450 | U49: 1450 | V49: =SUM(J49:U49) -> 17400 | X49: 1 | Y49: 1 | Z49: 1 | AA49: 1 | AB49: 1 | AC49: 1 | AD49: 1 | AE49: 1 | AF49: 1 | AG49: 1 | AH49: 1 | AI49: 1 | AJ49: =SUM(X49:AI49) -> 12 | AL49: =X49/$AL$4 -> 1.25 | AM49: =Y49/$AL$4 -> 1.25 | AN49: =Z49/$AL$4 -> 1.25 | AO49: =AA49/$AL$4 -> 1.25 | AP49: =AB49/$AL$4 -> 1.25 | AQ49: =AC49/$AL$4 -> 1.25 | AR49: =AD49/$AL$4 -> 1.25 | AS49: =AE49/$AL$4 -> 1.25 | ... AW49: =AI49/$AL$4 -> 1.25 | AX49: =SUM(AL49:AW49) -> 15 | AY49: =AX49/12 -> 1.25 | BA49: =AY49/'2. Headcount Buildup'!$D$36 -> 0.083333333 | BB49: =AY49/'2. Headcount Buildup'!$D$37 -> 0.025 | BC49: =AY49/'2. Headcount Buildup'!$D$38 -> 0.0125 | BD49: =AY49/'2. Headcount Buildup'!$D$43 -> 0.0125 | BE49: =(SUM('2. Headcount Buildup'!$F$44:$Q$44)/12)*('Base Revenue'!$AY49/'Base Revenue'!$AY$61) -> 0.024271586 | BF49: =(SUM('2. Headcount Buildup'!$F$45:$Q$45)/12)*('Base Revenue'!$AY49/'Base Revenue'!$AY$61) -> 0.040452643 | BG49: =(SUM('2. Headcount Buildup'!$F$46:$Q$46)/12)*('Base Revenue'!$AY49/'Base Revenue'!$AY$61) -> 0.064724229 | BH49: =SUM(BA49:BG49) -> 0.26278179 | BK49: Medrina Document Retrival | BN49: =IFERROR(BL49/BM49,0) -> 0
B50: Base | C50: Medrina Document Retrival | E50: Document Retrival | F50: FTE | G50: 400 | H50: 18 | I50: 352 | J50: 6336 | K50: 6336 | L50: 6336 | M50: 6336 | N50: 6336 | O50: 6336 | P50: 6336 | Q50: 6336 | R50: 6336 | S50: 6336 | T50: 6336 | U50: 6336 | V50: =SUM(J50:U50) -> 76032 | X50: ='Base FTE'!$I81 -> 0.034285714 | Y50: ='Base FTE'!$I81 -> 0.034285714 | Z50: ='Base FTE'!$I81 -> 0.034285714 | AA50: ='Base FTE'!$I81 -> 0.034285714 | AB50: ='Base FTE'!$I81 -> 0.034285714 | AC50: ='Base FTE'!$I81 -> 0.034285714 | AD50: ='Base FTE'!$I81 -> 0.034285714 | AE50: ='Base FTE'!$I81 -> 0.034285714 | ... AI50: ='Base FTE'!$I81 -> 0.034285714 | AJ50: =SUM(X50:AI50) -> 0.41142857 | AL50: =X50/$AL$4 -> 0.042857143 | AM50: =Y50/$AL$4 -> 0.042857143 | AN50: =Z50/$AL$4 -> 0.042857143 | AO50: =AA50/$AL$4 -> 0.042857143 | AP50: =AB50/$AL$4 -> 0.042857143 | AQ50: =AC50/$AL$4 -> 0.042857143 | AR50: =AD50/$AL$4 -> 0.042857143 | AS50: =AE50/$AL$4 -> 0.042857143 | ... AW50: =AI50/$AL$4 -> 0.042857143 | AX50: =SUM(AL50:AW50) -> 0.51428571 | AY50: =AX50/12 -> 0.042857143 | BA50: =AY50/'2. Headcount Buildup'!$D$36 -> 0.0028571429 | BB50: =AY50/'2. Headcount Buildup'!$D$37 -> 0.00085714286 | BC50: =AY50/'2. Headcount Buildup'!$D$38 -> 0.00042857143 | BD50: =AY50/'2. Headcount Buildup'!$D$43 -> 0.00042857143 | BE50: =(SUM('2. Headcount Buildup'!$F$44:$Q$44)/12)*('Base Revenue'!$AY50/'Base Revenue'!$AY$61) -> 0.00083216866 | BF50: =(SUM('2. Headcount Buildup'!$F$45:$Q$45)/12)*('Base Revenue'!$AY50/'Base Revenue'!$AY$61) -> 0.0013869478 | BG50: =(SUM('2. Headcount Buildup'!$F$46:$Q$46)/12)*('Base Revenue'!$AY50/'Base Revenue'!$AY$61) -> 0.0022191164 | BH50: =SUM(BA50:BG50) -> 0.0090096614 | BK50: Medrina Coding | BN50: =IFERROR(BL50/BM50,0) -> 0
B51: Base | C51: Medrina Coding | E51: Coding | F51: FTE | G51: 70 | H51: 1.35 | I51: 3500 | J51: 4725 | K51: 4725 | L51: 4725 | M51: 4725 | N51: 4725 | O51: 4725 | P51: 4725 | Q51: 4725 | R51: 4725 | S51: 4725 | T51: 4725 | U51: 4725 | V51: =SUM(J51:U51) -> 56700 | X51: =$I51/$G51/21 -> 2.3809524 | Y51: =$I51/$G51/21 -> 2.3809524 | Z51: =$I51/$G51/21 -> 2.3809524 | AA51: =$I51/$G51/21 -> 2.3809524 | AB51: =$I51/$G51/21 -> 2.3809524 | AC51: =$I51/$G51/21 -> 2.3809524 | AD51: =$I51/$G51/21 -> 2.3809524 | AE51: =$I51/$G51/21 -> 2.3809524 | ... AI51: =$I51/$G51/21 -> 2.3809524 | AJ51: =SUM(X51:AI51) -> 28.571429 | AL51: =X51/$AL$4 -> 2.9761905 | AM51: =Y51/$AL$4 -> 2.9761905 | AN51: =Z51/$AL$4 -> 2.9761905 | AO51: =AA51/$AL$4 -> 2.9761905 | AP51: =AB51/$AL$4 -> 2.9761905 | AQ51: =AC51/$AL$4 -> 2.9761905 | AR51: =AD51/$AL$4 -> 2.9761905 | AS51: =AE51/$AL$4 -> 2.9761905 | ... AW51: =AI51/$AL$4 -> 2.9761905 | AX51: =SUM(AL51:AW51) -> 35.714286 | AY51: =AX51/12 -> 2.9761905 | BA51: =AY51/'2. Headcount Buildup'!$D$36 -> 0.1984127 | BB51: =AY51/'2. Headcount Buildup'!$D$37 -> 0.05952381 | BC51: =AY51/'2. Headcount Buildup'!$D$38 -> 0.029761905 | BD51: =AY51/'2. Headcount Buildup'!$D$43 -> 0.029761905 | BE51: =(SUM('2. Headcount Buildup'!$F$44:$Q$44)/12)*('Base Revenue'!$AY51/'Base Revenue'!$AY$61) -> 0.05778949 | BF51: =(SUM('2. Headcount Buildup'!$F$45:$Q$45)/12)*('Base Revenue'!$AY51/'Base Revenue'!$AY$61) -> 0.096315817 | BG51: =(SUM('2. Headcount Buildup'!$F$46:$Q$46)/12)*('Base Revenue'!$AY51/'Base Revenue'!$AY$61) -> 0.15410531 | BH51: =SUM(BA51:BG51) -> 0.62567093 | BK51: MBMS | BN51: =IFERROR(BL51/BM51,0) -> 0
B52: Base | C52: MBMS | E52: End to End | F52: Transaction | G52: 25 | H52: 0.38 | I52: 30975 | J52: 11770.5 | K52: 11770.5 | L52: 11770.5 | M52: 11770.5 | N52: 11770.5 | O52: 11770.5 | P52: 11770.5 | Q52: 11770.5 | R52: 11770.5 | S52: 11770.5 | T52: 11770.5 | U52: 11770.5 | V52: =SUM(J52:U52) -> 141246 | X52: 5 | Y52: 5 | Z52: 5 | AA52: 5 | AB52: 5 | AC52: 5 | AD52: 5 | AE52: 5 | AF52: 5 | AG52: 5 | AH52: 5 | AI52: 5 | AJ52: =SUM(X52:AI52) -> 60 | AL52: =X52/$AL$4 -> 6.25 | AM52: =Y52/$AL$4 -> 6.25 | AN52: =Z52/$AL$4 -> 6.25 | AO52: =AA52/$AL$4 -> 6.25 | AP52: =AB52/$AL$4 -> 6.25 | AQ52: =AC52/$AL$4 -> 6.25 | AR52: =AD52/$AL$4 -> 6.25 | AS52: =AE52/$AL$4 -> 6.25 | ... AW52: =AI52/$AL$4 -> 6.25 | AX52: =SUM(AL52:AW52) -> 75 | AY52: =AX52/12 -> 6.25 | BA52: =AY52/'2. Headcount Buildup'!$D$36 -> 0.41666667 | BB52: =AY52/'2. Headcount Buildup'!$D$37 -> 0.125 | BC52: =AY52/'2. Headcount Buildup'!$D$38 -> 0.0625 | BD52: =AY52/'2. Headcount Buildup'!$D$43 -> 0.0625 | BE52: =(SUM('2. Headcount Buildup'!$F$44:$Q$44)/12)*('Base Revenue'!$AY52/'Base Revenue'!$AY$61) -> 0.12135793 | BF52: =(SUM('2. Headcount Buildup'!$F$45:$Q$45)/12)*('Base Revenue'!$AY52/'Base Revenue'!$AY$61) -> 0.20226321 | BG52: =(SUM('2. Headcount Buildup'!$F$46:$Q$46)/12)*('Base Revenue'!$AY52/'Base Revenue'!$AY$61) -> 0.32362114 | BH52: =SUM(BA52:BG52) -> 1.313909 | BK52: All Medical Revenue Solutions | BN52: =IFERROR(BL52/BM52,0) -> 0
B53: Base | C53: MBMS | E53: Insurance | F53: Transaction | G53: 120 | H53: 1675 | I53: 1 | J53: 1675 | V53: =SUM(J53:U53) -> 1675 | X53: 1 | AJ53: =SUM(X53:AI53) -> 1 | AL53: =X53/$AL$4 -> 1.25 | AM53: =Y53/$AL$4 -> 0 | AN53: =Z53/$AL$4 -> 0 | AO53: =AA53/$AL$4 -> 0 | AP53: =AB53/$AL$4 -> 0 | AQ53: =AC53/$AL$4 -> 0 | AR53: =AD53/$AL$4 -> 0 | AS53: =AE53/$AL$4 -> 0 | ... AW53: =AI53/$AL$4 -> 0 | AX53: =SUM(AL53:AW53) -> 1.25 | AY53: =AX53/12 -> 0.10416667 | BA53: =AY53/'2. Headcount Buildup'!$D$36 -> 0.0069444444 | BB53: =AY53/'2. Headcount Buildup'!$D$37 -> 0.0020833333 | BC53: =AY53/'2. Headcount Buildup'!$D$38 -> 0.0010416667 | BD53: =AY53/'2. Headcount Buildup'!$D$43 -> 0.0010416667 | BE53: =(SUM('2. Headcount Buildup'!$F$44:$Q$44)/12)*('Base Revenue'!$AY53/'Base Revenue'!$AY$61) -> 0.0020226321 | BF53: =(SUM('2. Headcount Buildup'!$F$45:$Q$45)/12)*('Base Revenue'!$AY53/'Base Revenue'!$AY$61) -> 0.0033710536 | BG53: =(SUM('2. Headcount Buildup'!$F$46:$Q$46)/12)*('Base Revenue'!$AY53/'Base Revenue'!$AY$61) -> 0.0053936857 | BH53: =SUM(BA53:BG53) -> 0.021898483 | BK53: Serenity Bay Hospice | BN53: =IFERROR(BL53/BM53,0) -> 0
B54: Base | C54: MBMS | E54: FTE | F54: FTE | H54: 1250 | I54: 4 | K54: =$I$54*$H$54 -> 5000 | V54: =SUM(J54:U54) -> 5000
B55: New Addition | C55: MBMS | E55: IVR Coding | F55: Transaction | K55: 800 | L55: 800 | M55: 800 | N55: 800 | O55: 800 | P55: 800 | Q55: 800 | R55: 800 | S55: 800 | T55: 800 | U55: 800 | V55: =SUM(J55:U55) -> 8800
B56: New Addition | C56: MBMS | E56: Backlog Volume (Non-End to End) | F56: Transaction | H56: 1250 | I56: 3 | K56: =H56*I56 -> 3750 | V56: =SUM(J56:U56) -> 3750
B57: Base | C57: All Medical Revenue Solutions | E57: AR Follow-up | F57: FTE | G57: 40 | H57: 1300 | I57: 2 | J57: 2600 | K57: 2600 | L57: 2600 | M57: 2600 | N57: 2600 | O57: 2600 | P57: 2600 | Q57: 2600 | R57: 2600 | S57: 2600 | T57: 2600 | U57: 2600 | V57: =SUM(J57:U57) -> 31200 | X57: ='Base FTE'!$I85 -> 2 | Y57: ='Base FTE'!$I85 -> 2 | Z57: ='Base FTE'!$I85 -> 2 | AA57: ='Base FTE'!$I85 -> 2 | AB57: ='Base FTE'!$I85 -> 2 | AC57: ='Base FTE'!$I85 -> 2 | AD57: ='Base FTE'!$I85 -> 2 | AE57: ='Base FTE'!$I85 -> 2 | ... AI57: ='Base FTE'!$I85 -> 2 | AJ57: =SUM(X57:AI57) -> 24 | AL57: =X57/$AL$4 -> 2.5 | AM57: =Y57/$AL$4 -> 2.5 | AN57: =Z57/$AL$4 -> 2.5 | AO57: =AA57/$AL$4 -> 2.5 | AP57: =AB57/$AL$4 -> 2.5 | AQ57: =AC57/$AL$4 -> 2.5 | AR57: =AD57/$AL$4 -> 2.5 | AS57: =AE57/$AL$4 -> 2.5 | ... AW57: =AI57/$AL$4 -> 2.5 | AX57: =SUM(AL57:AW57) -> 30 | AY57: =AX57/12 -> 2.5 | BA57: =AY57/'2. Headcount Buildup'!$D$36 -> 0.16666667 | BB57: =AY57/'2. Headcount Buildup'!$D$37 -> 0.05 | BC57: =AY57/'2. Headcount Buildup'!$D$38 -> 0.025 | BD57: =AY57/'2. Headcount Buildup'!$D$43 -> 0.025 | BE57: =(SUM('2. Headcount Buildup'!$F$44:$Q$44)/12)*('Base Revenue'!$AY57/'Base Revenue'!$AY$61) -> 0.048543172 | BF57: =(SUM('2. Headcount Buildup'!$F$45:$Q$45)/12)*('Base Revenue'!$AY57/'Base Revenue'!$AY$61) -> 0.080905286 | BG57: =(SUM('2. Headcount Buildup'!$F$46:$Q$46)/12)*('Base Revenue'!$AY57/'Base Revenue'!$AY$61) -> 0.12944846 | BH57: =SUM(BA57:BG57) -> 0.52556358 | BN57: =IFERROR(BL57/BM57,0) -> 0
B58: Base | C58: All Medical Revenue Solutions | E58: Credentials | F58: FTE | G58: 40 | H58: 200 | I58: 5 | J58: 1000 | K58: 1000 | L58: 1000 | M58: 1000 | N58: 1000 | O58: 1000 | P58: 1000 | Q58: 1000 | R58: 1000 | S58: 1000 | T58: 1000 | U58: 1000 | V58: =SUM(J58:U58) -> 12000 | X58: ='Base FTE'!$I84 -> 0.75 | Y58: ='Base FTE'!$I84 -> 0.75 | Z58: ='Base FTE'!$I84 -> 0.75 | AA58: ='Base FTE'!$I84 -> 0.75 | AB58: ='Base FTE'!$I84 -> 0.75 | AC58: ='Base FTE'!$I84 -> 0.75 | AD58: ='Base FTE'!$I84 -> 0.75 | AE58: ='Base FTE'!$I84 -> 0.75 | ... AI58: ='Base FTE'!$I84 -> 0.75 | AJ58: =SUM(X58:AI58) -> 9 | AL58: =X58/$AL$4 -> 0.9375 | AM58: =Y58/$AL$4 -> 0.9375 | AN58: =Z58/$AL$4 -> 0.9375 | AO58: =AA58/$AL$4 -> 0.9375 | AP58: =AB58/$AL$4 -> 0.9375 | AQ58: =AC58/$AL$4 -> 0.9375 | AR58: =AD58/$AL$4 -> 0.9375 | AS58: =AE58/$AL$4 -> 0.9375 | ... AW58: =AI58/$AL$4 -> 0.9375 | AX58: =SUM(AL58:AW58) -> 11.25 | AY58: =AX58/12 -> 0.9375 | BA58: =AY58/'2. Headcount Buildup'!$D$36 -> 0.0625 | BB58: =AY58/'2. Headcount Buildup'!$D$37 -> 0.01875 | BC58: =AY58/'2. Headcount Buildup'!$D$38 -> 0.009375 | BD58: =AY58/'2. Headcount Buildup'!$D$43 -> 0.009375 | BE58: =(SUM('2. Headcount Buildup'!$F$44:$Q$44)/12)*('Base Revenue'!$AY58/'Base Revenue'!$AY$61) -> 0.018203689 | BF58: =(SUM('2. Headcount Buildup'!$F$45:$Q$45)/12)*('Base Revenue'!$AY58/'Base Revenue'!$AY$61) -> 0.030339482 | BG58: =(SUM('2. Headcount Buildup'!$F$46:$Q$46)/12)*('Base Revenue'!$AY58/'Base Revenue'!$AY$61) -> 0.048543172 | BH58: =SUM(BA58:BG58) -> 0.19708634 | BK58: Total | BL58: =SUM(BL31:BL57) -> 0 | BM58: =SUM(BM31:BM57) -> 0 | BN58: =IFERROR(BL58/BM58,0) -> 0
B59: Base | C59: The Physical Therapy Institute | E59: Demo & Eligibility Verification | F59: FTE | G59: 24 | H59: 1450 | I59: 1 | J59: 1450 | K59: =1450*50% -> 725 | L59: 0 | M59: 0 | N59: 0 | O59: 0 | P59: 0 | Q59: 0 | R59: 0 | S59: 0 | T59: 0 | U59: 0 | V59: =SUM(J59:U59) -> 2175 | X59: ='Base FTE'!$I49 -> 2 | Y59: ='Base FTE'!$I49 -> 2 | Z59: ='Base FTE'!$I49 -> 2 | AA59: ='Base FTE'!$I49 -> 2 | AB59: ='Base FTE'!$I49 -> 2 | AC59: ='Base FTE'!$I49 -> 2 | AD59: ='Base FTE'!$I49 -> 2 | AE59: ='Base FTE'!$I49 -> 2 | ... AI59: ='Base FTE'!$I49 -> 2 | AJ59: =SUM(X59:AI59) -> 24 | AL59: =X59/$AL$4 -> 2.5 | AM59: =Y59/$AL$4 -> 2.5 | AN59: =Z59/$AL$4 -> 2.5 | AO59: =AA59/$AL$4 -> 2.5 | AP59: =AB59/$AL$4 -> 2.5 | AQ59: =AC59/$AL$4 -> 2.5 | AR59: =AD59/$AL$4 -> 2.5 | AS59: =AE59/$AL$4 -> 2.5 | ... AW59: =AI59/$AL$4 -> 2.5 | AX59: =SUM(AL59:AW59) -> 30 | AY59: =AX59/12 -> 2.5 | BA59: =AY59/'2. Headcount Buildup'!$D$36 -> 0.16666667 | BB59: =AY59/'2. Headcount Buildup'!$D$37 -> 0.05 | BC59: =AY59/'2. Headcount Buildup'!$D$38 -> 0.025 | BD59: =AY59/'2. Headcount Buildup'!$D$43 -> 0.025 | BE59: =(SUM('2. Headcount Buildup'!$F$44:$Q$44)/12)*('Base Revenue'!$AY59/'Base Revenue'!$AY$61) -> 0.048543172 | BF59: =(SUM('2. Headcount Buildup'!$F$45:$Q$45)/12)*('Base Revenue'!$AY59/'Base Revenue'!$AY$61) -> 0.080905286 | BG59: =(SUM('2. Headcount Buildup'!$F$46:$Q$46)/12)*('Base Revenue'!$AY59/'Base Revenue'!$AY$61) -> 0.12944846 | BH59: =SUM(BA59:BG59) -> 0.52556358
B60: Base | C60: Serenity Bay Hospice | E60: Credentials | H60: 200 | I60: 0 | J60: =$H60*$I60 -> 0 | K60: =J60 -> 0 | L60: =K60 -> 0 | M60: =L60 -> 0 | N60: =M60 -> 0 | O60: =N60 -> 0 | P60: =O60 -> 0 | Q60: =P60 -> 0 | R60: =Q60 -> 0 | ... U60: =T60 -> 0 | V60: =SUM(J60:U60) -> 0 | AJ60: =SUM(X60:AI60) -> 0 | AX60: =SUM(AL60:AW60) -> 0 | AY60: =AX60/12 -> 0 | BA60: =AY60/'2. Headcount Buildup'!$D$36 -> 0 | BB60: =AY60/'2. Headcount Buildup'!$D$37 -> 0 | BC60: =AY60/'2. Headcount Buildup'!$D$38 -> 0 | BD60: =AY60/'2. Headcount Buildup'!$D$43 -> 0 | BE60: =(SUM('2. Headcount Buildup'!$F$44:$Q$44)/12)*('Base Revenue'!$AY60/'Base Revenue'!$AY$61) -> 0 | BF60: =(SUM('2. Headcount Buildup'!$F$45:$Q$45)/12)*('Base Revenue'!$AY60/'Base Revenue'!$AY$61) -> 0 | BG60: =(SUM('2. Headcount Buildup'!$F$46:$Q$46)/12)*('Base Revenue'!$AY60/'Base Revenue'!$AY$61) -> 0 | BH60: =SUM(BA60:BG60) -> 0 | BK60: AR | BL60: Rev | BM60: Base FTE | BN60: Pricing
C61: Total | J61: =SUM(J6:J60) -> 232184.62 | K61: =SUM(K6:K60) -> 244265.5 | L61: =SUM(L6:L60) -> 230847.86 | M61: =SUM(M6:M60) -> 198603.86 | N61: =SUM(N6:N60) -> 194015.5 | O61: =SUM(O6:O60) -> 198603.86 | P61: =SUM(P6:P60) -> 198603.86 | Q61: =SUM(Q6:Q60) -> 196937.7 | ... V61: =SUM(V6:V60) -> 2483777.7 | X61: =SUM(X6:X60) -> 128.70132 | Y61: =SUM(Y6:Y60) -> 132.20132 | Z61: =SUM(Z6:Z60) -> 122.23132 | AA61: =SUM(AA6:AA60) -> 122.23132 | AB61: =SUM(AB6:AB60) -> 122.23132 | AC61: =SUM(AC6:AC60) -> 122.23132 | AD61: =SUM(AD6:AD60) -> 122.23132 | AE61: =SUM(AE6:AE60) -> 122.23132 | ... AJ61: =SUM(AJ6:AJ60) -> 1483.2158 | AL61: =SUM(AL6:AL60) -> 160.87665 | AM61: =SUM(AM6:AM60) -> 165.25165 | AN61: =SUM(AN6:AN60) -> 152.78915 | AO61: =SUM(AO6:AO60) -> 152.78915 | AP61: =SUM(AP6:AP60) -> 152.78915 | AQ61: =SUM(AQ6:AQ60) -> 152.78915 | AR61: =SUM(AR6:AR60) -> 152.78915 | AS61: =SUM(AS6:AS60) -> 152.78915 | ... AZ61: =SUM(AZ6:AZ60) -> 0 | BA61: =ROUNDUP(SUM(BA6:BA60),0) -> 11 | BB61: =ROUNDUP(SUM(BB6:BB60),0) -> 4 | BC61: =ROUNDUP(SUM(BC6:BC60),0) -> 2 | BD61: =ROUNDUP(SUM(BD6:BD60),0) -> 2 | BE61: =ROUNDUP(SUM(BE6:BE60),0) -> 3 | BF61: =ROUNDUP(SUM(BF6:BF60),0) -> 5 | BG61: =ROUNDUP(SUM(BG6:BG60),0) -> 8 | BH61: =SUM(BA61:BG61) -> 35 | BK61: eC3 LLC | BN61: =IFERROR(BL61/BM61,0) -> 0
BK62: D'Souza & Associates, Inc | BN62: =IFERROR(BL62/BM62,0) -> 0
BK63: Univ. Of Delaware | BN63: =IFERROR(BL63/BM63,0) -> 0
BK64: Staff a Dental LLC | BN64: =IFERROR(BL64/BM64,0) -> 0
BK65: Source It Dental | BN65: =IFERROR(BL65/BM65,0) -> 0
BK66: Physical Therapy & Sports Medicine Center | BN66: =IFERROR(BL66/BM66,0) -> 0
BK67: Primetime Physical Therapy | BN67: =IFERROR(BL67/BM67,0) -> 0
BK68: Comprehensive Sleep Care Center | BN68: =IFERROR(BL68/BM68,0) -> 0
BK69: Your Docs In | BN69: =IFERROR(BL69/BM69,0) -> 0
BK70: The Physical Therapy Institute | BN70: =IFERROR(BL70/BM70,0) -> 0
BK71: Procle Healthworks | BN71: =IFERROR(BL71/BM71,0) -> 0
BK72: BayLife | BN72: =IFERROR(BL72/BM72,0) -> 0
BK73: Premier Sleep Center | BN73: =IFERROR(BL73/BM73,0) -> 0
... BK80: Serenity Bay Hospice | BN80: =IFERROR(BL80/BM80,0) -> 0
BK81: Total | BL81: =SUM(BL61:BL80) -> 0 | BM81: =SUM(BM61:BM80) -> 0 | BN81: =IFERROR(BL81/BM81,0) -> 0

Sheet 2. Headcount Buildup
B1: Imagnum India Private Limited | E1: Data Input
B2: Headcount Buildup
B3: Partiuclars | E3: Salaries | F3: 46023 | G3: 46054 | H3: 46082 | I3: 46113 | J3: 46143 | K3: 46174 | L3: 46204 | M3: 46235 | N3: 46266 | O3: 46296 | P3: 46327 | Q3: 46357
B4: Directs
A5: 1 | B5: Deployed as per Revenue Plan | F5: ='1. Revenue Buildup 2026'!D16 -> 151.41332 | G5: ='1. Revenue Buildup 2026'!E16 -> 155.53096 | H5: ='1. Revenue Buildup 2026'!F16 -> 143.80155 | I5: ='1. Revenue Buildup 2026'!G16 -> 143.80155 | J5: ='1. Revenue Buildup 2026'!H16 -> 152.03684 | K5: ='1. Revenue Buildup 2026'!I16 -> 152.03684 | L5: ='1. Revenue Buildup 2026'!J16 -> 157.9192 | M5: ='1. Revenue Buildup 2026'!K16 -> 190.86037 | ... Q5: ='1. Revenue Buildup 2026'!O16 -> 214.38979
A7: 2 | B7: Existing Headcount | E7: 26343 | F7: ='India Expenses - Detailed'!E13+19 -> 185 | G7: ='India Expenses - Detailed'!F13+19 -> 185 | H7: ='India Expenses - Detailed'!G13+19 -> 176 | I7: ='India Expenses - Detailed'!H13+19 -> 176 | J7: ='India Expenses - Detailed'!I13+19 -> 183 | K7: ='India Expenses - Detailed'!J13+19 -> 183 | L7: ='India Expenses - Detailed'!K13+19 -> 188 | M7: ='India Expenses - Detailed'!L13+19 -> 216 | ... Q7: ='India Expenses - Detailed'!P13+19 -> 236
B8: Available AR | F8: ='Base FTE'!F105 -> 11.2 | G8: ='Base FTE'!G105 -> 11.2 | H8: ='Base FTE'!H105 -> 11.2 | I8: ='Base FTE'!I105 -> 16.8 | J8: ='Base FTE'!J105 -> 16.8 | K8: ='Base FTE'!K105 -> 16.8 | L8: ='Base FTE'!L105 -> 22.4 | M8: ='Base FTE'!M105 -> 22.4 | ... Q8: ='Base FTE'!Q105 -> 28
A10: 3 | B10: New Headcount to be Hired | F10: =IF((F5-F7)<0,0,(F5-F7)) -> 0 | G10: =IF((G5-G7)<0,0,(G5-G7)) -> 0 | H10: =IF((H5-H7)<0,0,(H5-H7)) -> 0 | I10: =IF((I5-I7)<0,0,(I5-I7)) -> 0 | J10: =IF((J5-J7)<0,0,(J5-J7)) -> 0 | K10: =IF((K5-K7)<0,0,(K5-K7)) -> 0 | L10: =IF((L5-L7)<0,0,(L5-L7)) -> 0 | M10: =IF((M5-M7)<0,0,(M5-M7)) -> 0 | ... Q10: =IF((Q5-Q7)<0,0,(Q5-Q7)) -> 0
A12: 3.a | B12: AR Required | E12: 0.7 | F12: =F10*$E$12 -> 0 | G12: =G10*$E$12 -> 0 | H12: =H10*$E$12 -> 0 | I12: =I10*$E$12 -> 0 | J12: =J10*$E$12 -> 0 | K12: =K10*$E$12 -> 0 | L12: =L10*$E$12 -> 0 | M12: =M10*$E$12 -> 0 | ... Q12: =Q10*$E$12 -> 0
A13: 3.b | B13: DE Required | E13: 0.3 | F13: =F10-F12 -> 0 | G13: =G10-G12 -> 0 | H13: =H10-H12 -> 0 | I13: =I10-I12 -> 0 | J13: =J10-J12 -> 0 | K13: =K10-K12 -> 0 | L13: =L10-L12 -> 0 | M13: =M10-M12 -> 0 | ... Q13: =Q10-Q12 -> 0
A15: 3.a.1 | B15: AR | D15: %ge
B16: Experience | D16: 0.3 | E16: 35000 | F16: =F12*$D$16 -> 0 | G16: =G13*$D$16 -> 0 | H16: =H13*$D$16 -> 0 | I16: =I13*$D$16 -> 0 | J16: =J13*$D$16 -> 0 | K16: =K13*$D$16 -> 0 | L16: =L13*$D$16 -> 0 | M16: =M13*$D$16 -> 0 | N16: =N13*$D$16 -> 0 | ... Q16: =Q13*$D$16 -> 0
B17: Fresher | D17: 0.7 | E17: 18000 | F17: =H12-H16-F8 -> -11.2 | G17: =I12-I16-G8 -> -11.2 | H17: =J12-J16-H8 -> -11.2 | I17: =K12-K16-I8 -> -16.8 | J17: =L12-L16-J8 -> -16.8 | K17: =M12-M16-K8 -> -16.8 | L17: =N12-N16-L8 -> -22.4 | M17: =O12-O16-M8 -> -22.4 | ... O17: =Q12-Q16-O8 -> -28 | P17: =O17 -> -28 | Q17: =P17 -> -28 | R17: Adjusted the AR people here
A18: 3.a.2 | B18: DE
B19: Experience | D19: 0.2 | E19: 28000 | F19: =$D$19*F13 -> 0 | G19: =$D$19*G13 -> 0 | H19: =$D$19*H13 -> 0 | I19: =$D$19*I13 -> 0 | J19: =$D$19*J13 -> 0 | K19: =$D$19*K13 -> 0 | L19: =$D$19*L13 -> 0 | M19: =$D$19*M13 -> 0 | ... Q19: =$D$19*Q13 -> 0
B20: Fresher | D20: 0.8 | E20: 16000 | F20: =H13-H19 -> 0 | G20: =I13-I19 -> 0 | H20: =J13-J19 -> 0 | I20: =K13-K19 -> 0 | J20: =L13-L19 -> 0 | K20: =M13-M19 -> 0 | L20: =N13-N19 -> 0 | M20: =O13-O19 -> 0 | N20: =P13-P19 -> 0 | O20: =N20 -> 0 | P20: =O20 -> 0 | Q20: =P20 -> 0
A22: 3.a.3 | B22: Coder | E22: 25000 | F22: 2 | G22: 2 | H22: 2 | I22: 2 | J22: 2 | K22: 2 | L22: 2 | M22: 2 | N22: 2 | O22: 2 | P22: 2 | Q22: 2
B24: Headcount
B25: Existing | F25: =F7 -> 185 | G25: =G7 -> 185 | H25: =H7 -> 176 | I25: =I7 -> 176 | J25: =J7 -> 183 | K25: =K7 -> 183 | L25: =L7 -> 188 | M25: =M7 -> 216 | ... Q25: =Q7 -> 236
B26: Additons | F26: =SUM(F16:F20) -> -11.2 | G26: =SUM(G16:G20) -> -11.2 | H26: =SUM(H16:H20) -> -11.2 | I26: =SUM(I16:I20) -> -16.8 | J26: =SUM(J16:J20) -> -16.8 | K26: =SUM(K16:K20) -> -16.8 | L26: =SUM(L16:L20) -> -22.4 | M26: =SUM(M16:M20) -> -22.4 | ... Q26: =SUM(Q16:Q20) -> -28
B27: Total | F27: =SUM(F25:F26) -> 173.8 | G27: =SUM(G25:G26) -> 173.8 | H27: =SUM(H25:H26) -> 164.8 | I27: =SUM(I25:I26) -> 159.2 | J27: =SUM(J25:J26) -> 166.2 | K27: =SUM(K25:K26) -> 166.2 | L27: =SUM(L25:L26) -> 165.6 | M27: =SUM(M25:M26) -> 193.6 | ... Q27: =SUM(Q25:Q26) -> 208
B28: Cost
B29: Existing | F29: =F7*$E$7 -> 4873455 | G29: =G7*$E$7 -> 4873455 | H29: =H7*$E$7 -> 4636368 | I29: =I7*$E$7 -> 4636368 | J29: =J7*$E$7 -> 4820769 | K29: =K7*$E$7 -> 4820769 | L29: =L7*$E$7 -> 4952484 | M29: =M7*$E$7 -> 5690088 | ... Q29: =Q7*$E$7 -> 6216948
B30: Additons | F30: =SUMPRODUCT(F16:F20,$E$16:$E$20) -> -201600 | G30: =SUMPRODUCT(G16:G20,$E$16:$E$20) -> -201600 | H30: =SUMPRODUCT(H16:H20,$E$16:$E$20) -> -201600 | I30: =SUMPRODUCT(I16:I20,$E$16:$E$20) -> -302400 | J30: =SUMPRODUCT(J16:J20,$E$16:$E$20) -> -302400 | K30: =SUMPRODUCT(K16:K20,$E$16:$E$20) -> -302400 | L30: =SUMPRODUCT(L16:L20,$E$16:$E$20) -> -403200 | M30: =SUMPRODUCT(M16:M20,$E$16:$E$20) -> -403200 | ... Q30: =SUMPRODUCT(Q16:Q20,$E$16:$E$20) -> -504000
B31: Total | F31: =SUM(F29:F30) -> 4671855 | G31: =SUM(G29:G30) -> 4671855 | H31: =SUM(H29:H30) -> 4434768 | I31: =SUM(I29:I30) -> 4333968 | J31: =SUM(J29:J30) -> 4518369 | K31: =SUM(K29:K30) -> 4518369 | L31: =SUM(L29:L30) -> 4549284 | M31: =SUM(M29:M30) -> 5286888 | ... Q31: =SUM(Q29:Q30) -> 5712948
R32: 6 month training
B33: Indirect
A34: 4 | B34: Required as per the plan | R34: Month | S34: 1 | T34: 2 | U34: 3 | V34: 4 | W34: 5 | X34: 6
B35: Ops Support | D35: Span | R35: FTE | S35: 0 | T35: 0 | U35: 0.25 | V35: 0.5 | W35: 0.75 | X35: 1
A36: a | B36: AM & MT | C36: Ops Support | D36: 15 | F36: =ROUNDUP(F$5/$D36,0) -> 11 | G36: =ROUNDUP(G$5/$D36,0) -> 11 | H36: =ROUNDUP(H$5/$D36,0) -> 10 | I36: =ROUNDUP(I$5/$D36,0) -> 10 | J36: =ROUNDUP(J$5/$D36,0) -> 11 | K36: =ROUNDUP(K$5/$D36,0) -> 11 | L36: =ROUNDUP(L$5/$D36,0) -> 11 | M36: =ROUNDUP(M$5/$D36,0) -> 13 | ... Q36: =ROUNDUP(Q$5/$D36,0) -> 15
A37: b | B37: DM | C37: Ops Support | D37: 50 | F37: =ROUNDUP(F$5/$D37,0) -> 4 | G37: =ROUNDUP(G$5/$D37,0) -> 4 | H37: =ROUNDUP(H$5/$D37,0) -> 3 | I37: =ROUNDUP(I$5/$D37,0) -> 3 | J37: =ROUNDUP(J$5/$D37,0) -> 4 | K37: =ROUNDUP(K$5/$D37,0) -> 4 | L37: =ROUNDUP(L$5/$D37,0) -> 4 | M37: =ROUNDUP(M$5/$D37,0) -> 4 | ... Q37: =ROUNDUP(Q$5/$D37,0) -> 5
A38: c | B38: Manager | C38: Ops Support | D38: 100 | F38: =ROUNDUP(F$5/$D38,0) -> 2 | G38: =ROUNDUP(G$5/$D38,0) -> 2 | H38: =ROUNDUP(H$5/$D38,0) -> 2 | I38: =ROUNDUP(I$5/$D38,0) -> 2 | J38: =ROUNDUP(J$5/$D38,0) -> 2 | K38: =ROUNDUP(K$5/$D38,0) -> 2 | L38: =ROUNDUP(L$5/$D38,0) -> 2 | M38: =ROUNDUP(M$5/$D38,0) -> 2 | ... Q38: =ROUNDUP(Q$5/$D38,0) -> 3
A39: d | B39: SM | C39: Ops Leadership | D39: Fixed | F39: 1 | G39: 1 | H39: 1 | I39: 1 | J39: 1 | K39: 1 | L39: 1 | M39: 1 | N39: 1 | O39: 1 | P39: 1 | Q39: 1
A40: e | B40: GM | C40: Ops Leadership | D40: Fixed | F40: 1 | G40: 1 | H40: 1 | I40: 1 | J40: 1 | K40: 1 | L40: 1 | M40: 1 | N40: 1 | O40: 1 | P40: 1 | Q40: 1
A41: f | B41: SD | C41: Ops Leadership | D41: Fixed
A42: g | B42: QA | C42: Quality | D42: 10 | F42: =ROUNDUP(F$5/$D42,0) -> 16 | G42: =ROUNDUP(G$5/$D42,0)+1 -> 17 | H42: =ROUNDUP(H$5/$D42,0)+1 -> 16 | I42: =ROUNDUP(I$5/$D42,0)+1 -> 16 | J42: =ROUNDUP(J$5/$D42,0)+1 -> 17 | K42: =ROUNDUP(K$5/$D42,0)+1 -> 17 | L42: =ROUNDUP(L$5/$D42,0)+1 -> 17 | M42: =ROUNDUP(M$5/$D42,0)+1 -> 21 | N42: =ROUNDUP(N$5/$D42,0)+1 -> 21 | ... Q42: =ROUNDUP(Q$5/$D42,0)+1 -> 23
A43: h | B43: Training | C43: Ops Support | D43: 100 | F43: =ROUNDUP(F$5/$D43,0) -> 2 | G43: =ROUNDUP(G$5/$D43,0) -> 2 | H43: =ROUNDUP(H$5/$D43,0) -> 2 | I43: =ROUNDUP(I$5/$D43,0) -> 2 | J43: =ROUNDUP(J$5/$D43,0) -> 2 | K43: =ROUNDUP(K$5/$D43,0) -> 2 | L43: =ROUNDUP(L$5/$D43,0) -> 2 | M43: =ROUNDUP(M$5/$D43,0) -> 2 | ... Q43: =ROUNDUP(Q$5/$D43,0) -> 3
A44: i | B44: SWAT (Business Excellence) | C44: Ops Support | D44: Fixed | F44: 3 | G44: 3 | H44: 3 | I44: 3 | J44: 3 | K44: 3 | L44: 3 | M44: 3 | N44: 3 | O44: 3 | P44: 3 | Q44: 3 | S44: =E44*F44 -> 0
A45: j | B45: MIS | C45: Ops Support | D45: Fixed | F45: 5 | G45: 5 | H45: 5 | I45: 5 | J45: 5 | K45: 5 | L45: 5 | M45: 5 | N45: 5 | O45: 5 | P45: 5 | Q45: 5
A46: k | B46: Development(Internal Tech) | C46: Ops Support | D46: Fixed | F46: 8 | G46: 8 | H46: 8 | I46: 8 | J46: 8 | K46: 8 | L46: 8 | M46: 8 | N46: 8 | O46: 8 | P46: 8 | Q46: 8
A47: l | B47: R&D Team | D47: Fixed | S47: =E47*F47 -> 0
F48: =SUM(F36:F47) -> 53 | G48: =SUM(G36:G47) -> 54 | H48: =SUM(H36:H47) -> 51 | I48: =SUM(I36:I47) -> 51 | J48: =SUM(J36:J47) -> 54 | K48: =SUM(K36:K47) -> 54 | L48: =SUM(L36:L47) -> 54 | M48: =SUM(M36:M47) -> 60 | ... Q48: =SUM(Q36:Q47) -> 67
A50: 5 | B50: Actual as of Dec 2025 | D50: Span
A51: a | B51: AM & MT | C51: Ops Support | D51: 15 | E51: 57569 | F51: 14 | G51: 14 | H51: 14 | I51: 14 | J51: 14 | K51: 14 | L51: 14 | M51: 14 | N51: 14 | O51: 14 | P51: 14 | Q51: 14 | S51: =E51*F51 -> 805966
A52: b | B52: DM | C52: Ops Support | D52: 50 | E52: 75421 | F52: 5 | G52: 5 | H52: 5 | I52: 5 | J52: 5 | K52: 5 | L52: 5 | M52: 5 | N52: 5 | O52: 5 | P52: 5 | Q52: 5 | S52: =E52*F52 -> 377105
A53: c | B53: Manager | C53: Ops Support | D53: 100 | E53: 81480 | F53: 2 | G53: 2 | H53: 2 | I53: 2 | J53: 2 | K53: 2 | L53: 2 | M53: 2 | N53: 2 | O53: 2 | P53: 2 | Q53: 2 | S53: =E53*F53 -> 162960
A54: d | B54: SM | C54: Ops Leadership | D54: Fixed | E54: 123292 | F54: 2 | G54: 2 | H54: 2 | I54: 2 | J54: 2 | K54: 2 | L54: 2 | M54: 2 | N54: 2 | O54: 2 | P54: 2 | Q54: 2 | S54: =E54*F54 -> 246584
A55: e | B55: GM | C55: Ops Leadership | D55: Fixed | E55: 145000 | F55: 1 | G55: 1 | H55: 1 | I55: 1 | J55: 1 | K55: 1 | L55: 1 | M55: 1 | N55: 1 | O55: 1 | P55: 1 | Q55: 1 | S55: =E55*F55 -> 145000
A56: f | B56: AGM | C56: Ops Leadership | D56: Fixed | E56: 170000 | F56: 1 | G56: 1 | H56: 1 | I56: 1 | J56: 1 | K56: 1 | L56: 1 | M56: 1 | N56: 1 | O56: 1 | P56: 1 | Q56: 1 | S56: =E56*F56 -> 170000
A57: g | B57: QA | C57: Quality | D57: 10 | E57: 40000 | F57: 18 | G57: 18 | H57: 18 | I57: 18 | J57: 18 | K57: 18 | L57: 18 | M57: 18 | N57: 18 | O57: 18 | P57: 18 | Q57: 18 | S57: =E57*F57 -> 720000
A58: h | B58: Training | C58: Ops Support | D58: 100 | E58: 40000 | F58: 2 | G58: 2 | H58: 2 | I58: 2 | J58: 2 | K58: 2 | L58: 2 | M58: 2 | N58: 2 | O58: 2 | P58: 2 | Q58: 2 | S58: =E58*F58 -> 80000
A59: i | B59: SWAT (Business Excellence) | C59: Ops Support | D59: Fixed | E59: 28000 | F59: 3 | G59: 3 | H59: 3 | I59: 3 | J59: 3 | K59: 3 | L59: 3 | M59: 3 | N59: 3 | O59: 3 | P59: 3 | Q59: 3 | S59: =E59*F59 -> 84000
A60: j | B60: MIS | C60: Ops Support | D60: Fixed | E60: 15938 | F60: 6 | G60: 6 | H60: 6 | I60: 6 | J60: 6 | K60: 6 | L60: 6 | M60: 6 | N60: 6 | O60: 6 | P60: 6 | Q60: 6 | S60: =E60*F60 -> 95628
A61: k | B61: Development(Internal Tech) | C61: Ops Support | D61: Fixed | E61: 16934 | F61: 9 | G61: 9 | H61: 9 | I61: 9 | J61: 9 | K61: 9 | L61: 9 | M61: 9 | N61: 9 | O61: 9 | P61: 9 | Q61: 9 | S61: =E61*F61 -> 152406
A62: l | B62: Development(Internal Tech) | D62: Fixed | E62: 50000 | S62: =E62*F62 -> 0
B63: Total Ops Support & Management | F63: =SUM(F51:F62) -> 63 | G63: =SUM(G51:G62) -> 63 | H63: =SUM(H51:H62) -> 63 | I63: =SUM(I51:I62) -> 63 | J63: =SUM(J51:J62) -> 63 | K63: =SUM(K51:K62) -> 63 | L63: =SUM(L51:L62) -> 63 | M63: =SUM(M51:M62) -> 63 | ... Q63: =SUM(Q51:Q62) -> 63 | U63: =SUM(S51:S62,S7,#REF!) -> #REF!
F64: =SUMPRODUCT(F51:F62,$E$51:$E$62) -> 3039649 | G64: =SUMPRODUCT(G51:G62,$E$51:$E$62) -> 3039649 | H64: =SUMPRODUCT(H51:H62,$E$51:$E$62) -> 3039649 | I64: =SUMPRODUCT(I51:I62,$E$51:$E$62) -> 3039649 | J64: =SUMPRODUCT(J51:J62,$E$51:$E$62) -> 3039649 | K64: =SUMPRODUCT(K51:K62,$E$51:$E$62) -> 3039649 | L64: =SUMPRODUCT(L51:L62,$E$51:$E$62) -> 3039649 | M64: =SUMPRODUCT(M51:M62,$E$51:$E$62) -> 3039649 | ... Q64: =SUMPRODUCT(Q51:Q62,$E$51:$E$62) -> 3039649
A65: 6 | B65: Excess Headcount
A66: a | B66: AM & MT | E66: 57569 | F66: =F51-F36 -> 3 | G66: =G51-G36 -> 3 | H66: =H51-H36 -> 4 | I66: =I51-I36 -> 4 | J66: =J51-J36 -> 3 | K66: =K51-K36 -> 3 | L66: =L51-L36 -> 3 | M66: =M51-M36 -> 1 | ... Q66: =Q51-Q36 -> -1
A67: b | B67: DM | E67: 75421 | F67: =F52-F37 -> 1 | G67: =G52-G37 -> 1 | H67: =H52-H37 -> 2 | I67: =I52-I37 -> 2 | J67: =J52-J37 -> 1 | K67: =K52-K37 -> 1 | L67: =L52-L37 -> 1 | M67: =M52-M37 -> 1 | ... Q67: =Q52-Q37 -> 0
A68: c | B68: Manager | E68: 81480 | F68: =F53-F38 -> 0 | G68: =G53-G38 -> 0 | H68: =H53-H38 -> 0 | I68: =I53-I38 -> 0 | J68: =J53-J38 -> 0 | K68: =K53-K38 -> 0 | L68: =L53-L38 -> 0 | M68: =M53-M38 -> 0 | ... Q68: =Q53-Q38 -> -1
A69: d | B69: SM | E69: 123292 | F69: =F54-F39 -> 1 | G69: =G54-G39 -> 1 | H69: =H54-H39 -> 1 | I69: =I54-I39 -> 1 | J69: =J54-J39 -> 1 | K69: =K54-K39 -> 1 | L69: =L54-L39 -> 1 | M69: =M54-M39 -> 1 | ... Q69: =Q54-Q39 -> 1 | T69: 10 | U69: 2 | V69: 5
A70: e | B70: GM | E70: 145000 | F70: =F55-F40 -> 0 | G70: =G55-G40 -> 0 | H70: =H55-H40 -> 0 | I70: =I55-I40 -> 0 | J70: =J55-J40 -> 0 | K70: =K55-K40 -> 0 | L70: =L55-L40 -> 0 | M70: =M55-M40 -> 0 | ... Q70: =Q55-Q40 -> 0 | T70: 16 | U70: 4 | V70: 4
A71: f | B71: SD | E71: 170000 | F71: =F56-F41 -> 1 | G71: =G56-G41 -> 1 | H71: =H56-H41 -> 1 | I71: =I56-I41 -> 1 | J71: =J56-J41 -> 1 | K71: =K56-K41 -> 1 | L71: =L56-L41 -> 1 | M71: =M56-M41 -> 1 | ... Q71: =Q56-Q41 -> 1
A72: g | B72: QA | E72: 40000 | F72: =F57-F42 -> 2 | G72: =G57-G42 -> 1 | H72: =H57-H42 -> 2 | I72: =I57-I42 -> 2 | J72: =J57-J42 -> 1 | K72: =K57-K42 -> 1 | L72: =L57-L42 -> 1 | M72: =M57-M42 -> -3 | ... Q72: =Q57-Q42 -> -5 | U72: =SUMPRODUCT(U69:U70,V69:V70) -> 26
A73: h | B73: Training | E73: 40000 | F73: =F58-F43 -> 0 | G73: =G58-G43 -> 0 | H73: =H58-H43 -> 0 | I73: =I58-I43 -> 0 | J73: =J58-J43 -> 0 | K73: =K58-K43 -> 0 | L73: =L58-L43 -> 0 | M73: =M58-M43 -> 0 | ... Q73: =Q58-Q43 -> -1
A74: i | B74: SWAT (Business Excellence) | E74: 28000 | F74: =F59-F44 -> 0 | G74: =G59-G44 -> 0 | H74: =H59-H44 -> 0 | I74: =I59-I44 -> 0 | J74: =J59-J44 -> 0 | K74: =K59-K44 -> 0 | L74: =L59-L44 -> 0 | M74: =M59-M44 -> 0 | ... Q74: =Q59-Q44 -> 0 | S74: =E74*F74 -> 0
A75: j | B75: MIS | E75: 15938 | F75: =F60-F45 -> 1 | G75: =G60-G45 -> 1 | H75: =H60-H45 -> 1 | I75: =I60-I45 -> 1 | J75: =J60-J45 -> 1 | K75: =K60-K45 -> 1 | L75: =L60-L45 -> 1 | M75: =M60-M45 -> 1 | ... Q75: =Q60-Q45 -> 1
A76: k | B76: Dvelopment(Internal Tech) | E76: 16934 | F76: =F61-F46 -> 1 | G76: =G61-G46 -> 1 | H76: =H61-H46 -> 1 | I76: =I61-I46 -> 1 | J76: =J61-J46 -> 1 | K76: =K61-K46 -> 1 | L76: =L61-L46 -> 1 | M76: =M61-M46 -> 1 | ... Q76: =Q61-Q46 -> 1 | S76: =E76*F76 -> 16934
A77: l | B77: Total Ops Support & Management | F77: =SUM(F66:F76) -> 10 | G77: =SUM(G66:G76) -> 9 | H77: =SUM(H66:H76) -> 12 | I77: =SUM(I66:I76) -> 12 | J77: =SUM(J66:J76) -> 9 | K77: =SUM(K66:K76) -> 9 | L77: =SUM(L66:L76) -> 9 | M77: =SUM(M66:M76) -> 3 | ... Q77: =SUM(Q66:Q76) -> -4
F78: =SUMPRODUCT(F66:F76,$E$66:$E$76) -> 654292 | G78: =SUMPRODUCT(G66:G76,$E$66:$E$76) -> 614292 | H78: =SUMPRODUCT(H66:H76,$E$66:$E$76) -> 787282 | I78: =SUMPRODUCT(I66:I76,$E$66:$E$76) -> 787282 | J78: =SUMPRODUCT(J66:J76,$E$66:$E$76) -> 614292 | K78: =SUMPRODUCT(K66:K76,$E$66:$E$76) -> 614292 | L78: =SUMPRODUCT(L66:L76,$E$66:$E$76) -> 614292 | M78: =SUMPRODUCT(M66:M76,$E$66:$E$76) -> 339154 | ... Q78: =SUMPRODUCT(Q66:Q76,$E$66:$E$76) -> -52885
B79: Count
B80: Current | F80: =F63 -> 63 | G80: =G63 -> 63 | H80: =H63 -> 63 | I80: =I63 -> 63 | J80: =J63 -> 63 | K80: =K63 -> 63 | L80: =L63 -> 63 | M80: =M63 -> 63 | ... Q80: =Q63 -> 63
B81: excess Headcount | F81: =F77 -> 10 | G81: =G77 -> 9 | H81: =H77 -> 12 | I81: =I77 -> 12 | J81: =J77 -> 9 | K81: =K77 -> 9 | L81: =L77 -> 9 | M81: =M77 -> 3 | ... Q81: =Q77 -> -4
B82: Total | F82: =F81+F80 -> 73 | G82: =G81+G80 -> 72 | H82: =H81+H80 -> 75 | I82: =I81+I80 -> 75 | J82: =J81+J80 -> 72 | K82: =K81+K80 -> 72 | L82: =L81+L80 -> 72 | M82: =M81+M80 -> 66 | ... Q82: =Q81+Q80 -> 59
B83: Cost
B84: Current | F84: =F64 -> 3039649 | G84: =G64 -> 3039649 | H84: =H64 -> 3039649 | I84: =I64 -> 3039649 | J84: =J64 -> 3039649 | K84: =K64 -> 3039649 | L84: =L64 -> 3039649 | M84: =M64 -> 3039649 | ... Q84: =Q64 -> 3039649
B85: excess Headcount | F85: =F78 -> 654292 | G85: =G78 -> 614292 | H85: =H78 -> 787282 | I85: =I78 -> 787282 | J85: =J78 -> 614292 | K85: =K78 -> 614292 | L85: =L78 -> 614292 | M85: =M78 -> 339154 | ... Q85: =Q78 -> -52885
B86: Total | F86: =F85+F84 -> 3693941 | G86: =G85+G84 -> 3653941 | H86: =H85+H84 -> 3826931 | I86: =I85+I84 -> 3826931 | J86: =J85+J84 -> 3653941 | K86: =K85+K84 -> 3653941 | L86: =L85+L84 -> 3653941 | M86: =M85+M84 -> 3378803 | ... Q86: =Q85+Q84 -> 2986764
B88: SG&A Headcount
B89: Current
B90: Sales
B91: S&M | E91: 15656 | F91: 8 | G91: 8 | H91: 8 | I91: 8 | J91: 8 | K91: 8 | L91: 8 | M91: 8 | N91: 8 | O91: 8 | P91: 8 | Q91: 8
B92: S&M - Leadership | E92: 115000 | F92: 2 | G92: 2 | H92: 2 | I92: 2 | J92: 2 | K92: 2 | L92: 2 | M92: 2 | N92: 2 | O92: 2 | P92: 2 | Q92: 2
B93: Business development
B94: Lead Gen
B95: G&A
B96: HR & Admin | E96: 23436 | F96: 5 | G96: 5 | H96: 5 | I96: 5 | J96: 5 | K96: 5 | L96: 5 | M96: 5 | N96: 5 | O96: 5 | P96: 5 | Q96: 5
B97: HR Manager | E97: 95000 | F97: 1 | G97: 1 | H97: 1 | I97: 1 | J97: 1 | K97: 1 | L97: 1 | M97: 1 | N97: 1 | O97: 1 | P97: 1 | Q97: 1
B98: IT Support | E98: 30000 | F98: 3 | G98: 3 | H98: 3 | I98: 3 | J98: 3 | K98: 3 | L98: 3 | M98: 3 | N98: 3 | O98: 3 | P98: 3 | Q98: 3
B99: Finance & Legal
B100: SMCS Global
B101: Prashanth BM-Ekam Legal | E101: 30000 | F101: 1 | G101: 1 | H101: 1 | I101: 1 | J101: 1 | K101: 1 | L101: 1 | M101: 1 | N101: 1 | O101: 1 | P101: 1 | Q101: 1
B102: SRF | E102: 125000 | F102: 1 | G102: 1 | H102: 1 | I102: 1 | J102: 1 | K102: 1 | L102: 1 | M102: 1 | N102: 1 | O102: 1 | P102: 1 | Q102: 1
B103: SG&A Headcount | F103: =SUM(F91:F102) -> 21 | G103: =SUM(G91:G102) -> 21 | H103: =SUM(H91:H102) -> 21 | I103: =SUM(I91:I102) -> 21 | J103: =SUM(J91:J102) -> 21 | K103: =SUM(K91:K102) -> 21 | L103: =SUM(L91:L102) -> 21 | M103: =SUM(M91:M102) -> 21 | ... Q103: =SUM(Q91:Q102) -> 21
B104: Salaries | F104: =SUMPRODUCT(F91:F102,$E$91:$E$102) -> 812428 | G104: =SUMPRODUCT(G91:G102,$E$91:$E$102) -> 812428 | H104: =SUMPRODUCT(H91:H102,$E$91:$E$102) -> 812428 | I104: =SUMPRODUCT(I91:I102,$E$91:$E$102) -> 812428 | J104: =SUMPRODUCT(J91:J102,$E$91:$E$102) -> 812428 | K104: =SUMPRODUCT(K91:K102,$E$91:$E$102) -> 812428 | L104: =SUMPRODUCT(L91:L102,$E$91:$E$102) -> 812428 | M104: =SUMPRODUCT(M91:M102,$E$91:$E$102) -> 812428 | ... Q104: =SUMPRODUCT(Q91:Q102,$E$91:$E$102) -> 812428
B106: Additions
B107: Sales
B108: S&M | E108: 20000
B109: S&M - Leadership | E109: 55928
...

Sheet 2. Headcount Buildup - MBMS
B1: Imagnum India Private Limited | D1: Data Input
B2: Headcount Buildup
B3: Partiuclars | D3: Salaries | E3: 46023 | F3: 46054 | G3: 46082 | H3: 46113 | I3: 46143 | J3: 46174 | K3: 46204 | L3: 46235 | M3: 46266 | N3: 46296 | O3: 46327 | P3: 46357
B4: Directs
A5: 1 | B5: Deployed as per Revenue Plan | E5: ='1. Revenue Buildup 2026'!#REF! -> #REF! | F5: ='1. Revenue Buildup 2026'!#REF! -> #REF! | G5: ='1. Revenue Buildup 2026'!#REF! -> #REF! | H5: ='1. Revenue Buildup 2026'!#REF! -> #REF! | I5: ='1. Revenue Buildup 2026'!#REF! -> #REF! | J5: ='1. Revenue Buildup 2026'!#REF! -> #REF! | K5: ='1. Revenue Buildup 2026'!#REF! -> #REF! | L5: ='1. Revenue Buildup 2026'!#REF! -> #REF! | ... P5: ='1. Revenue Buildup 2026'!#REF! -> #REF!
A7: 2 | B7: Existing Headcount | D7: 0 | E7: 0 | F7: 0 | G7: 0 | H7: 0 | I7: 0 | J7: 0 | K7: 0 | L7: 0 | M7: 0 | N7: 0 | O7: 0 | P7: 0
A9: 3 | B9: New Headcount to be Hired | E9: =IF((E5-E7)<0,0,(E5-E7)) -> #REF! | F9: =IF((F5-F7)<0,0,(F5-F7)) -> #REF! | G9: =IF((G5-G7)<0,0,(G5-G7)) -> #REF! | H9: =IF((H5-H7)<0,0,(H5-H7)) -> #REF! | I9: =IF((I5-I7)<0,0,(I5-I7)) -> #REF! | J9: =IF((J5-J7)<0,0,(J5-J7)) -> #REF! | K9: =IF((K5-K7)<0,0,(K5-K7)) -> #REF! | L9: =IF((L5-L7)<0,0,(L5-L7)) -> #REF! | ... P9: =IF((P5-P7)<0,0,(P5-P7)) -> #REF!
A11: 3.a | B11: AR Required | C11: 0.85 | E11: ='1. Revenue Buildup 2026'!#REF!/$C$11 -> #REF! | F11: ='1. Revenue Buildup 2026'!#REF!/$C$11 -> #REF! | G11: ='1. Revenue Buildup 2026'!#REF!/$C$11 -> #REF! | H11: ='1. Revenue Buildup 2026'!#REF!/$C$11 -> #REF! | I11: ='1. Revenue Buildup 2026'!#REF!/$C$11 -> #REF! | J11: ='1. Revenue Buildup 2026'!#REF!/$C$11 -> #REF! | K11: ='1. Revenue Buildup 2026'!#REF!/$C$11 -> #REF! | L11: ='1. Revenue Buildup 2026'!#REF!/$C$11 -> #REF! | ... P11: ='1. Revenue Buildup 2026'!#REF!/$C$11 -> #REF!
A12: 3.b | B12: DE Required | C12: 0.85 | E12: ='1. Revenue Buildup 2026'!#REF!/$C$12 -> #REF! | F12: ='1. Revenue Buildup 2026'!#REF!/$C$12 -> #REF! | G12: ='1. Revenue Buildup 2026'!#REF!/$C$12 -> #REF! | H12: ='1. Revenue Buildup 2026'!#REF!/$C$12 -> #REF! | I12: ='1. Revenue Buildup 2026'!#REF!/$C$12 -> #REF! | J12: ='1. Revenue Buildup 2026'!#REF!/$C$12 -> #REF! | K12: ='1. Revenue Buildup 2026'!#REF!/$C$12 -> #REF! | L12: ='1. Revenue Buildup 2026'!#REF!/$C$12 -> #REF! | ... P12: ='1. Revenue Buildup 2026'!#REF!/$C$12 -> #REF!
A13: 3.c | B13: Coding Required | C13: 0.85 | E13: ='1. Revenue Buildup 2026'!#REF!/$C$13 -> #REF! | F13: ='1. Revenue Buildup 2026'!#REF!/$C$13 -> #REF! | G13: ='1. Revenue Buildup 2026'!#REF!/$C$13 -> #REF! | H13: ='1. Revenue Buildup 2026'!#REF!/$C$13 -> #REF! | I13: ='1. Revenue Buildup 2026'!#REF!/$C$13 -> #REF! | J13: ='1. Revenue Buildup 2026'!#REF!/$C$13 -> #REF! | K13: ='1. Revenue Buildup 2026'!#REF!/$C$13 -> #REF! | L13: ='1. Revenue Buildup 2026'!#REF!/$C$13 -> #REF! | ... P13: ='1. Revenue Buildup 2026'!#REF!/$C$13 -> #REF!
A15: 3.a.1 | B15: AR | C15: %ge
B16: Experience | C16: 0.5 | D16: 35000 | E16: =E11 -> #REF! | F16: =F11 -> #REF! | G16: =G11 -> #REF! | H16: =H11 -> #REF! | I16: =I11 -> #REF! | J16: =J11 -> #REF! | K16: =K12*$C$16 -> #REF! | L16: =L12*$C$16 -> #REF! | M16: =M12*$C$16 -> #REF! | N16: =N12*$C$16 -> #REF! | O16: =O12*$C$16 -> #REF! | P16: =P12*$C$16 -> #REF! | R16: Till June, the hiring of experience will be only done, and later on the 50:50 ratio of exp and fresher ratio
B17: Fresher | C17: 0.5 | D17: 18000 | K17: =M11-M16 -> #REF! | L17: =N11-N16 -> #REF! | M17: =O11-O16 -> #REF! | N17: =P11-P16 -> #REF! | O17: =N17 -> #REF! | P17: =O17 -> #REF!
A18: 3.a.2 | B18: Billing
B19: Experience | C19: 0.5 | D19: 28000 | E19: =E12 -> #REF! | F19: =F12 -> #REF! | G19: =G12 -> #REF! | H19: =H12 -> #REF! | I19: =I12 -> #REF! | J19: =J12 -> #REF! | K19: =$C$19*K12 -> #REF! | L19: =$C$19*L12 -> #REF! | M19: =$C$19*M12 -> #REF! | N19: =$C$19*N12 -> #REF! | O19: =$C$19*O12 -> #REF! | P19: =$C$19*P12 -> #REF!
B20: Fresher | C20: 0.5 | D20: 16000 | K20: =M12-M19 -> #REF! | L20: =N12-N19 -> #REF! | M20: =O12-O19 -> #REF! | N20: =M20 -> #REF! | O20: =N20 -> #REF! | P20: =O20 -> #REF!
A21: 3.a.3 | B21: Coders
B22: Experience | C22: 0.7 | D22: 35000 | E22: =E13 -> #REF! | F22: =F13 -> #REF! | G22: =G13 -> #REF! | H22: =H13 -> #REF! | I22: =I13 -> #REF! | J22: =J13 -> #REF! | K22: =$C$22*K13 -> #REF! | L22: =$C$22*L13 -> #REF! | M22: =$C$22*M13 -> #REF! | N22: =$C$22*N13 -> #REF! | O22: =$C$22*O13 -> #REF! | P22: =$C$22*P13 -> #REF!
B23: Fresher | C23: 0.3 | D23: 18000 | K23: =M13-M20 -> #REF! | L23: =N13-N20 -> #REF! | M23: =O13-O20 -> #REF! | N23: =P13-P20 -> #REF! | O23: =N23 -> #REF! | P23: =O23 -> #REF!
B25: Headcount
B26: Existing | E26: =E7 -> 0 | F26: =F7 -> 0 | G26: =G7 -> 0 | H26: =H7 -> 0 | I26: =I7 -> 0 | J26: =J7 -> 0 | K26: =K7 -> 0 | L26: =L7 -> 0 | ... P26: =P7 -> 0
B27: Additons | E27: =SUM(E16:E23) -> #REF! | F27: =SUM(F16:F23) -> #REF! | G27: =SUM(G16:G23) -> #REF! | H27: =SUM(H16:H23) -> #REF! | I27: =SUM(I16:I23) -> #REF! | J27: =SUM(J16:J23) -> #REF! | K27: =SUM(K16:K23) -> #REF! | L27: =SUM(L16:L23) -> #REF! | ... P27: =SUM(P16:P23) -> #REF!
B28: Total | E28: =SUM(E26:E27) -> #REF! | F28: =SUM(F26:F27) -> #REF! | G28: =SUM(G26:G27) -> #REF! | H28: =SUM(H26:H27) -> #REF! | I28: =SUM(I26:I27) -> #REF! | J28: =SUM(J26:J27) -> #REF! | K28: =SUM(K26:K27) -> #REF! | L28: =SUM(L26:L27) -> #REF! | ... P28: =SUM(P26:P27) -> #REF!
B29: Cost
B30: Existing | E30: =E7*$D$7 -> 0 | F30: =F7*$D$7 -> 0 | G30: =G7*$D$7 -> 0 | H30: =H7*$D$7 -> 0 | I30: =I7*$D$7 -> 0 | J30: =J7*$D$7 -> 0 | K30: =K7*$D$7 -> 0 | L30: =L7*$D$7 -> 0 | ... P30: =P7*$D$7 -> 0
B31: Additons | E31: =SUMPRODUCT(E16:E23,$D$16:$D$23) -> #REF! | F31: =SUMPRODUCT(F16:F23,$D$16:$D$23) -> #REF! | G31: =SUMPRODUCT(G16:G23,$D$16:$D$23) -> #REF! | H31: =SUMPRODUCT(H16:H23,$D$16:$D$23) -> #REF! | I31: =SUMPRODUCT(I16:I23,$D$16:$D$23) -> #REF! | J31: =SUMPRODUCT(J16:J23,$D$16:$D$23) -> #REF! | K31: =SUMPRODUCT(K16:K23,$D$16:$D$23) -> #REF! | L31: =SUMPRODUCT(L16:L23,$D$16:$D$23) -> #REF! | ... P31: =SUMPRODUCT(P16:P23,$D$16:$D$23) -> #REF!
B32: Total | E32: =SUM(E30:E31) -> #REF! | F32: =SUM(F30:F31) -> #REF! | G32: =SUM(G30:G31) -> #REF! | H32: =SUM(H30:H31) -> #REF! | I32: =SUM(I30:I31) -> #REF! | J32: =SUM(J30:J31) -> #REF! | K32: =SUM(K30:K31) -> #REF! | L32: =SUM(L30:L31) -> #REF! | ... P32: =SUM(P30:P31) -> #REF!
B34: Indirect
A35: 4 | B35: Required as per the plan
B36: Ops Support | C36: Span
A37: a | B37: AM & MT (AR) | C37: 15 | E37: =ROUNDUP(SUM(E16:E17)/$C$37,0) -> #REF! | F37: =ROUNDUP(SUM(F16:F17)/$C$37,0) -> #REF! | G37: =ROUNDUP(SUM(G16:G17)/$C$37,0) -> #REF! | H37: =ROUNDUP(SUM(H16:H17)/$C$37,0) -> #REF! | I37: =ROUNDUP(SUM(I16:I17)/$C$37,0) -> #REF! | J37: =ROUNDUP(SUM(J16:J17)/$C$37,0) -> #REF! | K37: =ROUNDUP(SUM(K16:K17)/$C$37,0) -> #REF! | L37: =ROUNDUP(SUM(L16:L17)/$C$37,0) -> #REF! | ... P37: =ROUNDUP(SUM(P16:P17)/$C$37,0) -> #REF! | R37: requirement to be arrived considering the span and also lining thaat to the line of department (say AR< DE, coding etc)
A38: b | B38: GM | C38: 500 | E38: =ROUNDUP(E$5/$C38,0) -> #REF! | F38: =ROUNDUP(F$5/$C38,0) -> #REF! | G38: =ROUNDUP(G$5/$C38,0) -> #REF! | H38: =ROUNDUP(H$5/$C38,0) -> #REF! | I38: =ROUNDUP(I$5/$C38,0) -> #REF! | J38: =ROUNDUP(J$5/$C38,0) -> #REF! | K38: =ROUNDUP(K$5/$C38,0) -> #REF! | L38: =ROUNDUP(L$5/$C38,0) -> #REF! | ... P38: =ROUNDUP(P$5/$C38,0) -> #REF!
A39: c | B39: Manager | C39: 100 | E39: =ROUNDUP(E$5/$C39,0) -> #REF! | F39: =ROUNDUP(F$5/$C39,0) -> #REF! | G39: =ROUNDUP(G$5/$C39,0) -> #REF! | H39: =ROUNDUP(H$5/$C39,0) -> #REF! | I39: =ROUNDUP(I$5/$C39,0) -> #REF! | J39: =ROUNDUP(J$5/$C39,0) -> #REF! | K39: =ROUNDUP(K$5/$C39,0) -> #REF! | L39: =ROUNDUP(L$5/$C39,0) -> #REF! | ... P39: =ROUNDUP(P$5/$C39,0) -> #REF!
A40: d | B40: SM | C40: Fixed
A41: e | B41: AM & MT (Coding) | C41: 15 | E41: =ROUNDUP(SUM(E19:E20)/$C$41,0) -> #REF! | F41: =ROUNDUP(SUM(F19:F20)/$C$41,0) -> #REF! | G41: =ROUNDUP(SUM(G19:G20)/$C$41,0) -> #REF! | H41: =ROUNDUP(SUM(H19:H20)/$C$41,0) -> #REF! | I41: =ROUNDUP(SUM(I19:I20)/$C$41,0) -> #REF! | J41: =ROUNDUP(SUM(J19:J20)/$C$41,0) -> #REF! | K41: =ROUNDUP(SUM(K19:K20)/$C$41,0) -> #REF! | L41: =ROUNDUP(SUM(L19:L20)/$C$41,0) -> #REF! | ... P41: =ROUNDUP(SUM(P19:P20)/$C$41,0) -> #REF!
A42: f | B42: AM & MT (Billing) | C42: 15 | E42: =ROUNDUP(SUM(E22:E23)/$C$42,0) -> #REF! | F42: =ROUNDUP(SUM(F22:F23)/$C$42,0) -> #REF! | G42: =ROUNDUP(SUM(G22:G23)/$C$42,0) -> #REF! | H42: =ROUNDUP(SUM(H22:H23)/$C$42,0) -> #REF! | I42: =ROUNDUP(SUM(I22:I23)/$C$42,0) -> #REF! | J42: =ROUNDUP(SUM(J22:J23)/$C$42,0) -> #REF! | K42: =ROUNDUP(SUM(K22:K23)/$C$42,0) -> #REF! | L42: =ROUNDUP(SUM(L22:L23)/$C$42,0) -> #REF! | ... P42: =ROUNDUP(SUM(P22:P23)/$C$42,0) -> #REF!
A43: g | B43: QA (AR) | C43: 10 | E43: =ROUNDUP(SUM(E16:E17)/$C43,0) -> #REF! | F43: =ROUNDUP(SUM(F16:F17)/$C43,0) -> #REF! | G43: =ROUNDUP(SUM(G16:G17)/$C43,0) -> #REF! | H43: =ROUNDUP(SUM(H16:H17)/$C43,0) -> #REF! | I43: =ROUNDUP(SUM(I16:I17)/$C43,0) -> #REF! | J43: =ROUNDUP(SUM(J16:J17)/$C43,0) -> #REF! | K43: =ROUNDUP(SUM(K16:K17)/$C43,0) -> #REF! | L43: =ROUNDUP(SUM(L16:L17)/$C43,0) -> #REF! | ... P43: =ROUNDUP(SUM(P16:P17)/$C43,0) -> #REF!
B44: QA (Billing) | C44: 10 | E44: =ROUNDUP(SUM(E19:E20)/$C44,0) -> #REF! | F44: =ROUNDUP(SUM(F19:F20)/$C44,0) -> #REF! | G44: =ROUNDUP(SUM(G19:G20)/$C44,0) -> #REF! | H44: =ROUNDUP(SUM(H19:H20)/$C44,0) -> #REF! | I44: =ROUNDUP(SUM(I19:I20)/$C44,0) -> #REF! | J44: =ROUNDUP(SUM(J19:J20)/$C44,0) -> #REF! | K44: =ROUNDUP(SUM(K19:K20)/$C44,0) -> #REF! | L44: =ROUNDUP(SUM(L19:L20)/$C44,0) -> #REF! | ... P44: =ROUNDUP(SUM(P19:P20)/$C44,0) -> #REF!
B45: QA (Coding) | C45: 10 | E45: =ROUNDUP(SUM(E22:E23)/$C45,0) -> #REF! | F45: =ROUNDUP(SUM(F22:F23)/$C45,0) -> #REF! | G45: =ROUNDUP(SUM(G22:G23)/$C45,0) -> #REF! | H45: =ROUNDUP(SUM(H22:H23)/$C45,0) -> #REF! | I45: =ROUNDUP(SUM(I22:I23)/$C45,0) -> #REF! | J45: =ROUNDUP(SUM(J22:J23)/$C45,0) -> #REF! | K45: =ROUNDUP(SUM(K22:K23)/$C45,0) -> #REF! | L45: =ROUNDUP(SUM(L22:L23)/$C45,0) -> #REF! | ... P45: =ROUNDUP(SUM(P22:P23)/$C45,0) -> #REF!
A46: h | B46: Training (Billing & AR) | C46: 100 | E46: =ROUNDUP(SUM(E16:E20)/$C46,0) -> #REF! | F46: =ROUNDUP(SUM(F16:F20)/$C46,0) -> #REF! | G46: =ROUNDUP(SUM(G16:G20)/$C46,0) -> #REF! | H46: =ROUNDUP(SUM(H16:H20)/$C46,0) -> #REF! | I46: =ROUNDUP(SUM(I16:I20)/$C46,0) -> #REF! | J46: =ROUNDUP(SUM(J16:J20)/$C46,0) -> #REF! | K46: =ROUNDUP(SUM(K16:K20)/$C46,0) -> #REF! | L46: =ROUNDUP(SUM(L16:L20)/$C46,0) -> #REF! | ... P46: =ROUNDUP(SUM(P16:P20)/$C46,0) -> #REF!
A47: i | B47: Training (Coding) | C47: 100 | E47: =ROUNDUP(SUM(E22:E23)/$C47,0) -> #REF! | F47: =ROUNDUP(SUM(F22:F23)/$C47,0) -> #REF! | G47: =ROUNDUP(SUM(G22:G23)/$C47,0) -> #REF! | H47: =ROUNDUP(SUM(H22:H23)/$C47,0) -> #REF! | I47: =ROUNDUP(SUM(I22:I23)/$C47,0) -> #REF! | J47: =ROUNDUP(SUM(J22:J23)/$C47,0) -> #REF! | K47: =ROUNDUP(SUM(K22:K23)/$C47,0) -> #REF! | L47: =ROUNDUP(SUM(L22:L23)/$C47,0) -> #REF! | ... P47: =ROUNDUP(SUM(P22:P23)/$C47,0) -> #REF! | R47: remove Jan and Feb costing
A48: j | B48: MIS | C48: Fixed | E48: 2 | F48: 2 | G48: 2 | H48: 2 | I48: 2 | J48: 2 | K48: 2 | L48: 2 | M48: 2 | N48: 2 | O48: 2 | P48: 2
E49: =SUM(E37:E48) -> #REF! | F49: =SUM(F37:F48) -> #REF! | G49: =SUM(G37:G48) -> #REF! | H49: =SUM(H37:H48) -> #REF! | I49: =SUM(I37:I48) -> #REF! | J49: =SUM(J37:J48) -> #REF! | K49: =SUM(K37:K48) -> #REF! | L49: =SUM(L37:L48) -> #REF! | ... P49: =SUM(P37:P48) -> #REF!
A51: 5 | B51: Actual as of Nov 2024 | C51: Span
A52: a | B52: =B37 -> AM & MT (AR) | C52: 15 | D52: 65000
A53: b | B53: =B38 -> GM | C53: 50 | D53: ='Manpower Existing'!K171 -> 85100
A54: c | B54: =B39 -> Manager | C54: 100 | D54: ='Manpower Existing'!K174 -> 95688.257
A55: d | B55: =B40 -> SM | C55: Fixed | D55: ='Manpower Existing'!K185 -> 132250
A56: e | B56: =B41 -> AM & MT (Coding) | C56: Fixed | D56: ='Manpower Existing'!K186 -> 132187.33
A57: f | B57: =B42 -> AM & MT (Billing) | C57: Fixed | D57: ='Manpower Existing'!K184 -> 268332.95
A58: g | B58: =B43 -> QA (AR) | C58: 10 | D58: ='Manpower Existing'!K178 -> 31854.969
A59: h | B59: =B44 -> QA (Billing) | C59: 100 | D59: ='Manpower Existing'!K181 -> 69000
B60: =B45 -> QA (Coding)
B61: =B46 -> Training (Billing & AR)
A62: i | B62: =B47 -> Training (Coding) | C62: Fixed | D62: ='Manpower Existing'!K180 -> 29419.13
A63: j | B63: =B48 -> MIS | C63: Fixed | D63: ='Manpower Existing'!K175 -> 20014.439
B64: Total Ops Support & Management | E64: =SUM(E52:E63) -> 0 | F64: =SUM(F52:F63) -> 0 | G64: =SUM(G52:G63) -> 0 | H64: =SUM(H52:H63) -> 0 | I64: =SUM(I52:I63) -> 0 | J64: =SUM(J52:J63) -> 0 | K64: =SUM(K52:K63) -> 0 | L64: =SUM(L52:L63) -> 0 | ... P64: =SUM(P52:P63) -> 0
E65: =SUMPRODUCT(E52:E63,$D$52:$D$63) -> 0 | F65: =SUMPRODUCT(F52:F63,$D$52:$D$63) -> 0 | G65: =SUMPRODUCT(G52:G63,$D$52:$D$63) -> 0 | H65: =SUMPRODUCT(H52:H63,$D$52:$D$63) -> 0 | I65: =SUMPRODUCT(I52:I63,$D$52:$D$63) -> 0 | J65: =SUMPRODUCT(J52:J63,$D$52:$D$63) -> 0 | K65: =SUMPRODUCT(K52:K63,$D$52:$D$63) -> 0 | L65: =SUMPRODUCT(L52:L63,$D$52:$D$63) -> 0 | ... P65: =SUMPRODUCT(P52:P63,$D$52:$D$63) -> 0
A66: 6 | B66: To be Hired | C66: Span
A67: a | B67: =B37 -> AM & MT (AR) | C67: =C37 -> 15 | D67: =D52 -> 65000 | E67: =IF((E37-E52)<0,0,(E37-E52)) -> #REF! | F67: =IF((F37-F52)<0,0,(F37-F52)) -> #REF! | G67: =IF((G37-G52)<0,0,(G37-G52)) -> #REF! | H67: =IF((H37-H52)<0,0,(H37-H52)) -> #REF! | I67: =IF((I37-I52)<0,0,(I37-I52)) -> #REF! | J67: =IF((J37-J52)<0,0,(J37-J52)) -> #REF! | K67: =IF((K37-K52)<0,0,(K37-K52)) -> #REF! | L67: =IF((L37-L52)<0,0,(L37-L52)) -> #REF! | ... P67: =IF((P37-P52)<0,0,(P37-P52)) -> #REF!
A68: b | B68: =B38 -> GM | C68: =C38 -> 500 | D68: =20*10^5/12 -> 166666.67 | E68: =IF((E38-E53)<0,0,(E38-E53)) -> #REF! | F68: =IF((F38-F53)<0,0,(F38-F53)) -> #REF! | G68: =IF((G38-G53)<0,0,(G38-G53)) -> #REF! | H68: =IF((H38-H53)<0,0,(H38-H53)) -> #REF! | I68: =IF((I38-I53)<0,0,(I38-I53)) -> #REF! | J68: =IF((J38-J53)<0,0,(J38-J53)) -> #REF! | K68: =IF((K38-K53)<0,0,(K38-K53)) -> #REF! | L68: =IF((L38-L53)<0,0,(L38-L53)) -> #REF! | ... P68: =IF((P38-P53)<0,0,(P38-P53)) -> #REF!
A69: c | B69: =B39 -> Manager | C69: =C39 -> 100 | D69: =10*10^5/12 -> 83333.333 | E69: =IF((E39-E54)<0,0,(E39-E54)) -> #REF! | F69: =IF((F39-F54)<0,0,(F39-F54)) -> #REF! | G69: =IF((G39-G54)<0,0,(G39-G54)) -> #REF! | H69: =IF((H39-H54)<0,0,(H39-H54)) -> #REF! | I69: =IF((I39-I54)<0,0,(I39-I54)) -> #REF! | J69: =IF((J39-J54)<0,0,(J39-J54)) -> #REF! | K69: =IF((K39-K54)<0,0,(K39-K54)) -> #REF! | L69: =IF((L39-L54)<0,0,(L39-L54)) -> #REF! | ... P69: =IF((P39-P54)<0,0,(P39-P54)) -> #REF!
A70: d | B70: =B40 -> SM | C70: Fixed | D70: =20*10^5/12 -> 166666.67 | E70: =IF((E40-E55)<0,0,(E40-E55)) -> 0 | F70: =IF((F40-F55)<0,0,(F40-F55)) -> 0 | G70: =IF((G40-G55)<0,0,(G40-G55)) -> 0 | H70: =IF((H40-H55)<0,0,(H40-H55)) -> 0 | I70: =IF((I40-I55)<0,0,(I40-I55)) -> 0 | J70: =IF((J40-J55)<0,0,(J40-J55)) -> 0 | K70: =IF((K40-K55)<0,0,(K40-K55)) -> 0 | L70: =IF((L40-L55)<0,0,(L40-L55)) -> 0 | ... P70: =IF((P40-P55)<0,0,(P40-P55)) -> 0
A71: e | B71: =B41 -> AM & MT (Coding) | C71: Fixed | D71: 65000 | E71: =IF((E41-E56)<0,0,(E41-E56)) -> #REF! | F71: =IF((F41-F56)<0,0,(F41-F56)) -> #REF! | G71: =IF((G41-G56)<0,0,(G41-G56)) -> #REF! | H71: =IF((H41-H56)<0,0,(H41-H56)) -> #REF! | I71: =IF((I41-I56)<0,0,(I41-I56)) -> #REF! | J71: =IF((J41-J56)<0,0,(J41-J56)) -> #REF! | K71: =IF((K41-K56)<0,0,(K41-K56)) -> #REF! | L71: =IF((L41-L56)<0,0,(L41-L56)) -> #REF! | ... P71: =IF((P41-P56)<0,0,(P41-P56)) -> #REF!
A72: f | B72: =B42 -> AM & MT (Billing) | C72: Fixed | D72: 65000 | E72: =IF((E42-E57)<0,0,(E42-E57)) -> #REF! | F72: =IF((F42-F57)<0,0,(F42-F57)) -> #REF! | G72: =IF((G42-G57)<0,0,(G42-G57)) -> #REF! | H72: =IF((H42-H57)<0,0,(H42-H57)) -> #REF! | I72: =IF((I42-I57)<0,0,(I42-I57)) -> #REF! | J72: =IF((J42-J57)<0,0,(J42-J57)) -> #REF! | K72: =IF((K42-K57)<0,0,(K42-K57)) -> #REF! | L72: =IF((L42-L57)<0,0,(L42-L57)) -> #REF! | ... P72: =IF((P42-P57)<0,0,(P42-P57)) -> #REF!
A73: g | B73: =B43 -> QA (AR) | D73: 50000 | E73: =IF((E43-E58)<0,0,(E43-E58)) -> #REF! | F73: =IF((F43-F58)<0,0,(F43-F58)) -> #REF! | G73: =IF((G43-G58)<0,0,(G43-G58)) -> #REF! | H73: =IF((H43-H58)<0,0,(H43-H58)) -> #REF! | I73: =IF((I43-I58)<0,0,(I43-I58)) -> #REF! | J73: =IF((J43-J58)<0,0,(J43-J58)) -> #REF! | K73: =IF((K43-K58)<0,0,(K43-K58)) -> #REF! | L73: =IF((L43-L58)<0,0,(L43-L58)) -> #REF! | ... P73: =IF((P43-P58)<0,0,(P43-P58)) -> #REF!
A74: h | B74: =B44 -> QA (Billing) | D74: 50000 | E74: =IF((E44-E59)<0,0,(E44-E59)) -> #REF! | F74: =IF((F44-F59)<0,0,(F44-F59)) -> #REF! | G74: =IF((G44-G59)<0,0,(G44-G59)) -> #REF! | H74: =IF((H44-H59)<0,0,(H44-H59)) -> #REF! | I74: =IF((I44-I59)<0,0,(I44-I59)) -> #REF! | J74: =IF((J44-J59)<0,0,(J44-J59)) -> #REF! | K74: =IF((K44-K59)<0,0,(K44-K59)) -> #REF! | L74: =IF((L44-L59)<0,0,(L44-L59)) -> #REF! | ... P74: =IF((P44-P59)<0,0,(P44-P59)) -> #REF!
B75: =B45 -> QA (Coding) | D75: 50000 | E75: =IF((E45-E60)<0,0,(E45-E60)) -> #REF! | F75: =IF((F45-F60)<0,0,(F45-F60)) -> #REF! | G75: =IF((G45-G60)<0,0,(G45-G60)) -> #REF! | H75: =IF((H45-H60)<0,0,(H45-H60)) -> #REF! | I75: =IF((I45-I60)<0,0,(I45-I60)) -> #REF! | J75: =IF((J45-J60)<0,0,(J45-J60)) -> #REF! | K75: =IF((K45-K60)<0,0,(K45-K60)) -> #REF! | L75: =IF((L45-L60)<0,0,(L45-L60)) -> #REF! | ... P75: =IF((P45-P60)<0,0,(P45-P60)) -> #REF!
B76: =B46 -> Training (Billing & AR) | D76: ='2. Headcount Buildup'!E73 -> 40000 | E76: =IF((E46-E61)<0,0,(E46-E61)) -> #REF! | F76: =IF((F46-F61)<0,0,(F46-F61)) -> #REF! | G76: =IF((G46-G61)<0,0,(G46-G61)) -> #REF! | H76: =IF((H46-H61)<0,0,(H46-H61)) -> #REF! | I76: =IF((I46-I61)<0,0,(I46-I61)) -> #REF! | J76: =IF((J46-J61)<0,0,(J46-J61)) -> #REF! | K76: =IF((K46-K61)<0,0,(K46-K61)) -> #REF! | L76: =IF((L46-L61)<0,0,(L46-L61)) -> #REF! | ... P76: =IF((P46-P61)<0,0,(P46-P61)) -> #REF!
A77: i | B77: =B47 -> Training (Coding) | C77: Fixed | D77: =D76 -> 40000 | E77: =IF((E47-E62)<0,0,(E47-E62)) -> #REF! | F77: =IF((F47-F62)<0,0,(F47-F62)) -> #REF! | G77: =IF((G47-G62)<0,0,(G47-G62)) -> #REF! | H77: =IF((H47-H62)<0,0,(H47-H62)) -> #REF! | I77: =IF((I47-I62)<0,0,(I47-I62)) -> #REF! | J77: =IF((J47-J62)<0,0,(J47-J62)) -> #REF! | K77: =IF((K47-K62)<0,0,(K47-K62)) -> #REF! | L77: =IF((L47-L62)<0,0,(L47-L62)) -> #REF! | ... P77: =IF((P47-P62)<0,0,(P47-P62)) -> #REF!
A78: j | B78: =B48 -> MIS | C78: Fixed | D78: =D63 -> 20014.439 | E78: =IF((E48-E63)<0,0,(E48-E63)) -> 2 | F78: =IF((F48-F63)<0,0,(F48-F63)) -> 2 | G78: =IF((G48-G63)<0,0,(G48-G63)) -> 2 | H78: =IF((H48-H63)<0,0,(H48-H63)) -> 2 | I78: =IF((I48-I63)<0,0,(I48-I63)) -> 2 | J78: =IF((J48-J63)<0,0,(J48-J63)) -> 2 | K78: =IF((K48-K63)<0,0,(K48-K63)) -> 2 | L78: =IF((L48-L63)<0,0,(L48-L63)) -> 2 | ... P78: =IF((P48-P63)<0,0,(P48-P63)) -> 2
B79: Total Ops Support & Management | E79: =SUM(E67:E78) -> #REF! | F79: =SUM(F67:F78) -> #REF! | G79: =SUM(G67:G78) -> #REF! | H79: =SUM(H67:H78) -> #REF! | I79: =SUM(I67:I78) -> #REF! | J79: =SUM(J67:J78) -> #REF! | K79: =SUM(K67:K78) -> #REF! | L79: =SUM(L67:L78) -> #REF! | ... P79: =SUM(P67:P78) -> #REF!
E80: =SUMPRODUCT(E67:E78,$D$67:$D$78) -> #REF! | F80: =SUMPRODUCT(F67:F78,$D$67:$D$78) -> #REF! | G80: =SUMPRODUCT(G67:G78,$D$67:$D$78) -> #REF! | H80: =SUMPRODUCT(H67:H78,$D$67:$D$78) -> #REF! | I80: =SUMPRODUCT(I67:I78,$D$67:$D$78) -> #REF! | J80: =SUMPRODUCT(J67:J78,$D$67:$D$78) -> #REF! | K80: =SUMPRODUCT(K67:K78,$D$67:$D$78) -> #REF! | L80: =SUMPRODUCT(L67:L78,$D$67:$D$78) -> #REF! | ... P80: =SUMPRODUCT(P67:P78,$D$67:$D$78) -> #REF!
B81: Count
B82: Current | E82: =E64 -> 0 | F82: =F64 -> 0 | G82: =G64 -> 0 | H82: =H64 -> 0 | I82: =I64 -> 0 | J82: =J64 -> 0 | K82: =K64 -> 0 | L82: =L64 -> 0 | ... P82: =P64 -> 0
B83: To be Hired | E83: =E79 -> #REF! | F83: =F79 -> #REF! | G83: =G79 -> #REF! | H83: =H79 -> #REF! | I83: =I79 -> #REF! | J83: =J79 -> #REF! | K83: =K79 -> #REF! | L83: =L79 -> #REF! | ... P83: =P79 -> #REF!
B84: Total | E84: =E83+E82 -> #REF! | F84: =F83+F82 -> #REF! | G84: =G83+G82 -> #REF! | H84: =H83+H82 -> #REF! | I84: =I83+I82 -> #REF! | J84: =J83+J82 -> #REF! | K84: =K83+K82 -> #REF! | L84: =L83+L82 -> #REF! | ... P84: =P83+P82 -> #REF!
B85: Cost
B86: Current | E86: =E65 -> 0 | F86: =F65 -> 0 | G86: =G65 -> 0 | H86: =H65 -> 0 | I86: =I65 -> 0 | J86: =J65 -> 0 | K86: =K65 -> 0 | L86: =L65 -> 0 | ... P86: =P65 -> 0
B87: To be Hired | E87: =E80 -> #REF! | F87: =F80 -> #REF! | G87: =G80 -> #REF! | H87: =H80 -> #REF! | I87: =I80 -> #REF! | J87: =J80 -> #REF! | K87: =K80 -> #REF! | L87: =L80 -> #REF! | ... P87: =P80 -> #REF!
B88: Total | E88: =E87+E86 -> #REF! | F88: =F87+F86 -> #REF! | G88: =G87+G86 -> #REF! | H88: =H87+H86 -> #REF! | I88: =I87+I86 -> #REF! | J88: =J87+J86 -> #REF! | K88: =K87+K86 -> #REF! | L88: =L87+L86 -> #REF! | ... P88: =P87+P86 -> #REF!
B90: SG&A Headcount
B91: Current
B92: Sales
B93: S&M | D93: ='Manpower Existing'!K179 -> 47263.357
B94: G&A
B95: HR & Admin | D95: ='Manpower Existing'!K172 -> 20236.55
B96: IT Support | D96: ='Manpower Existing'!K173 -> 18285
B97: Coder | D97: ='Manpower Existing'!K169 -> 13800
B98: Finance & Legal
B100: Prashanth BM-Ekam Legal | D100: 30000
B101: SRF | D101: 60000
B102: SG&A Headcount | E102: =SUM(E93:E101) -> 0 | F102: =SUM(F93:F101) -> 0 | G102: =SUM(G93:G101) -> 0 | H102: =SUM(H93:H101) -> 0 | I102: =SUM(I93:I101) -> 0 | J102: =SUM(J93:J101) -> 0 | K102: =SUM(K93:K101) -> 0 | L102: =SUM(L93:L101) -> 0 | ... P102: =SUM(P93:P101) -> 0
B103: Salaries | E103: =SUMPRODUCT(E93:E101,$D$93:$D$101) -> 0 | F103: =SUMPRODUCT(F93:F101,$D$93:$D$101) -> 0 | G103: =SUMPRODUCT(G93:G101,$D$93:$D$101) -> 0 | H103: =SUMPRODUCT(H93:H101,$D$93:$D$101) -> 0 | I103: =SUMPRODUCT(I93:I101,$D$93:$D$101) -> 0 | J103: =SUMPRODUCT(J93:J101,$D$93:$D$101) -> 0 | K103: =SUMPRODUCT(K93:K101,$D$93:$D$101) -> 0 | L103: =SUMPRODUCT(L93:L101,$D$93:$D$101) -> 0 | ... P103: =SUMPRODUCT(P93:P101,$D$93:$D$101) -> 0
B105: Additions
B106: Sales
B107: S&M | D107: 47263
B108: G&A
B109: HR & Admin | D109: 30000 | E109: 1 | F109: 1 | G109: 1 | H109: 1 | I109: 1 | J109: 1 | K109: 1 | L109: 1 | M109: 1 | N109: 1 | O109: 1 | P109: 1
B110: IT Support | D110: 18285
...

Sheet Payroll 2025
A1: Employee Name | B1: ID | C1: DOJ | D1: Department | E1: Designation | F1: Total Earnings - Dec 2025 | G1: CTC
A2: SivaKumar Subramanian | B2: 3 | C2: 43066 | D2: Support | E2: Senior Quality Analyst | F2: 42881 | G2: 46631
A3: Mohamed Ejas Ali Muhamed Hussain | B3: 7 | C3: 43430 | D3: Support | E3: Deputy Manager | F3: 76410 | G3: 75150
A4: Rajesh Murugesan M | B4: 31 | C4: 43850 | D4: Operations | E4: Senior Process Associate | F4: 37708 | G4: 41458
A5: SriRamachandran Levan R | B5: 32 | C5: 43850 | D5: Support | E5: Deputy Manager | F5: 72079 | G5: 75829
A6: Vijaya Anandhi Bilavendran A | B6: 33 | C6: 43850 | D6: Support | E6: Quality Analyst | F6: 31063 | G6: 34813
A7: Rekha Ramachandra Raju | B7: 52 | C7: 44060 | D7: Operations | E7: Senior AR Analyst | F7: 25776 | G7: 29462
A8: Krishna Raj Vasudevan R | B8: 55 | C8: 44077 | D8: Support | E8: Quality Analyst | F8: 34044 | G8: 37794
A9: Sureshkumar Ekambaram | B9: 60 | C9: 44179 | D9: Support | E9: Management Trainee | F9: 48720 | G9: 52470
A10: Janani Murali | B10: 64 | C10: 44179 | D10: Operations | E10: Senior AR Analyst | F10: 27312 | G10: 31062
A11: Rajeshwaran Raja | B11: 66 | C11: 44200 | D11: Support | E11: Deputy Manager | F11: 58468 | G11: 56218
A12: Ashok Kumar Pazhani | B12: 74 | C12: 44228 | D12: Support | E12: Management Trainee | F12: 53989.167 | G12: 45205
A13: Gokul kumar Durai Raj M | B13: 86 | C13: 44245 | D13: Business Development | E13: Senior Process Associate | F13: 21980 | G13: 25148
... A129: Surya Karthikeyan | B129: 663 | C129: 45621 | D129: Operations | E129: Coder | F129: 32250 | G129: 34500
A130: Madan Kumar Guna sekar | B130: 669 | C130: 06/01/2025 | D130: Operations | E130: Senior Patient Calling Associate | F130: 51533.333 | G130: 53500
A131: Edward Bosco Pereira | B131: 671 | C131: 13/01/2025 | D131: Operations | E131: Patient Calling Associate | F131: 47400 | G131: 49500
A132: Dhanapal Govindan | B132: 675 | C132: 03/02/2025 | D132: Support | E132: Quality Analyst | F132: 71750 | G132: 75500
A133: Kumar Mohandoss | B133: 682 | C133: 10/02/2025 | D133: Support | E133: Assistant Manager | F133: 68500 | G133: 72250
A134: Manohar Mandolla | B134: 684 | C134: 12/02/2025 | D134: Operations | E134: Coder | F134: 51750 | G134: 53000
A135: Sai Charan Suresh Babu | B135: 685 | C135: 12/02/2025 | D135: Operations | E135: Coder | F135: 42750 | G135: 46500
A136: Sakthivel Rammoorthi | B136: 686 | C136: 12/02/2025 | D136: Operations | E136: Coder | F136: 45750 | G136: 44000
A137: Ananth Rajalingam | B137: 688 | C137: 17/02/2025 | D137: Operations | E137: Coder | F137: 31750 | G137: 35500
A138: Charlotte D'cruz Wallace D'silva | B138: 689 | C138: 17/02/2025 | D138: Operations | E138: Patient Calling Associate | F138: 48125 | G138: 47500
A139: Mohana Priyanka Sivakumar | B139: 692 | C139: 25/02/2025 | D139: Operations | E139: Patient Calling Associate | F139: 50333.333 | G139: 47500
A140: Gerald Thomas Mcleod M J Mcleod | B140: 693 | C140: 26/02/2025 | D140: Operations | E140: Patient Calling Associate | F140: 35550 | G140: 39300
A141: Madhan Kumar Ravikumar | B141: 694 | C141: 03/03/2025 | D141: Operations | E141: Senior Process Associate | F141: 26250 | G141: 28296
... A266: Sakthi Kolanchi | B266: 873 | C266: 23/10/2025 | D266: Operations | E266: Senior AR Analyst | F266: 32750 | G266: 36500
A267: Adithya Vasudevan | B267: 875 | C267: 45788 | D267: Support | E267: Assistant Manager | F267: 59750 | G267: 63500
A268: Ganesh Irulappan | B268: 876 | C268: 45788 | D268: Operations | E268: Senior AR Caller | F268: 35750 | G268: 39500
A269: Cyril James | B269: 877 | C269: 45819 | D269: Operations | E269: Senior AR Caller | F269: 35750 | G269: 39500
A270: Muthuraju Anandakumar | B270: 878 | C270: 45819 | D270: Operations | E270: Senior AR Caller | F270: 31750 | G270: 35500
A271: Jason chatelier Richard chatelier | B271: 879 | C271: 45819 | D271: Operations | E271: Patient Calling Associate | F271: 44541.667 | G271: 47500
A272: Saravanan Murthy | B272: 880 | C272: 45941 | D272: IT | E272: Junior IT Executive | F272: 15750 | G272: 18929
A273: Rudolph Dominic Anderson Ralph Anthony Anderson | B273: 881 | C273: 46002 | D273: Operations | E273: Senior Patient Calling Associate | F273: 46750 | G273: 50500
A274: Prisilla Jenifer Ravindran | B274: 882 | C274: 19/11/2025 | D274: HR | E274: Senior Recruiter | F274: 22150 | G274: 25342
A275: Muralikrishnan Rajendran | B275: 883 | C275: 19/11/2025 | D275: Operations | E275: Senior AR Caller | F275: 33450 | G275: 37200
A276: Samantha Steven Sedrick William steven | B276: 884 | C276: 24/11/2025 | D276: Operations | E276: Senior Patient Calling Associate | F276: 50250 | G276: 54000
A277: Ranjith Raghavan | B277: 885 | C277: 01/12/2025 | D277: Support | E277: Senior IT Executive | F277: 30750 | G277: 34500
A278: Mokksha Kalyanasundaram | B278: 886 | C278: 02/12/2025 | D278: Support | E278: Process Associate | F278: 14340 | G278: 17144
A279: Karthikeyan Selvam | B279: 888 | C279: 04/12/2025 | D279: Support | E279: Junior IT Executive | F279: 16042 | G279: 18929
A280: Karthick Rao Mohan | B280: 889 | C280: 08/12/2025 | D280: Support | E280: Assistant Manager | F280: 65257 | G280: 69007
A281: Rakesh Selvam Thiravida Selvam | B281: 890 | C281: 08/12/2025 | D281: Support | E281: Process Coach | F281: 41000 | G281: 44750
A282: Kalyan Kumar Mohan Babu | B282: 891 | C282: 08/12/2025 | D282: Support | E282: Junior Web developer | F282: 16435 | G282: 18929
A283: Mohamed Halith Mohaideen Meeran | B283: 892 | C283: 08/12/2025 | D283: Operations | E283: Senior Coder | F283: 53550 | G283: 57300
A284: Periyakaruppan Murugan | B284: 893 | C284: 08/12/2025 | D284: Operations | E284: Senior Coder | F284: 39250 | G284: 43000
A285: Sudershan Vairaval Ramnath | B285: 894 | C285: 10/12/2025 | D285: Support | E285: Assistant Manager | F285: 62745 | G285: 66495
... A309: Premkumar Senthilkumar | B309: 918 | C309: 22/12/2025 | D309: Support | E309: Quality Analyst | F309: 41090 | G309: 42900
F310: =SUM(F2:F309) -> 11032230 | G310: =SUM(G2:G309) -> 11706648

Sheet 3. P&L Summary
A1: Imagnum Health
A2: Consolidated Income Statement
A3: USD/INR | B3: 87 | C3: 87 | D3: 87 | E3: 87 | F3: 87 | G3: 87 | H3: 87 | I3: 87 | J3: 87 | K3: 87 | L3: 87 | M3: 87
A4: Particulars | B4: 46023 | C4: 46054 | D4: 46082 | E4: 46113 | F4: 46143 | G4: 46174 | H4: 46204 | I4: 46235 | J4: 46266 | K4: 46296 | L4: 46327 | M4: 46357 | N4: Total | Q4: 2024 Actuals | R4: % | S4: 2024 Budget | T4: % | U4: Bud Variance | V4: Actual Variance
A5: Current
A6: Revenue | B6: ='1. Revenue Buildup 2026'!D13 -> 225414.12 | C6: ='1. Revenue Buildup 2026'!E13 -> 238765.5 | D6: ='1. Revenue Buildup 2026'!F13 -> 239597.86 | E6: ='1. Revenue Buildup 2026'!G13 -> 203603.86 | F6: ='1. Revenue Buildup 2026'!H13 -> 212815.5 | G6: ='1. Revenue Buildup 2026'!I13 -> 215403.86 | H6: ='1. Revenue Buildup 2026'!J13 -> 215753.86 | I6: ='1. Revenue Buildup 2026'!K13 -> 246487.7 | ... M6: ='1. Revenue Buildup 2026'!O13 -> 256153.86 | N6: =SUM(B6:M6) -> 2809757.2 | O6: =N6/140000 -> 20.069694 | Q6: 2116756.6 | S6: 1186417.5
A7: Salaries | B7: ='India Expenses - Detailed'!E30 -> 107468.67 | C7: ='India Expenses - Detailed'!F30 -> 107468.67 | D7: ='India Expenses - Detailed'!G30 -> 97886.472 | E7: ='India Expenses - Detailed'!H30 -> 97886.472 | F7: ='India Expenses - Detailed'!I30 -> 102053.98 | G7: ='India Expenses - Detailed'!J30 -> 102053.98 | H7: ='India Expenses - Detailed'!K30 -> 105030.78 | I7: ='India Expenses - Detailed'!L30 -> 121700.82 | ... M7: ='India Expenses - Detailed'!P30 -> 133608 | N7: =SUM(B7:M7) -> 1358121.1 | Q7: 836770.98 | R7: 0.39530808 | S7: 524458.73
A8: Facilities | B8: ='India Expenses - Detailed'!E42 -> 15550.932 | C8: ='India Expenses - Detailed'!F42 -> 15550.932 | D8: ='India Expenses - Detailed'!G42 -> 15550.932 | E8: ='India Expenses - Detailed'!H42 -> 15550.932 | F8: ='India Expenses - Detailed'!I42 -> 15550.932 | G8: ='India Expenses - Detailed'!J42 -> 15550.932 | H8: ='India Expenses - Detailed'!K42 -> 20211.518 | I8: ='India Expenses - Detailed'!L42 -> 20211.518 | ... M8: ='India Expenses - Detailed'!P42 -> 20211.518 | N8: =SUM(B8:M8) -> 214574.7 | Q8: 109080.05 | R8: 0.051531694 | S8: 101610.99
A9: Telecom/Data & others | B9: ='India Expenses - Detailed'!E53+'India Expenses - Detailed'!E69 -> 4060.8983 | C9: ='India Expenses - Detailed'!F53+'India Expenses - Detailed'!F69 -> 5760.8983 | D9: ='India Expenses - Detailed'!G53+'India Expenses - Detailed'!G69 -> 5397.3815 | E9: ='India Expenses - Detailed'!H53+'India Expenses - Detailed'!H69 -> 5397.3815 | F9: ='India Expenses - Detailed'!I53+'India Expenses - Detailed'!I69 -> 5415.1716 | G9: ='India Expenses - Detailed'!J53+'India Expenses - Detailed'!J69 -> 6034.5624 | H9: ='India Expenses - Detailed'!K53+'India Expenses - Detailed'!K69 -> 5785.35 | I9: ='India Expenses - Detailed'!L53+'India Expenses - Detailed'!L69 -> 5856.5104 | ... M9: ='India Expenses - Detailed'!P53+'India Expenses - Detailed'!P69 -> 5907.3393 | N9: =SUM(B9:M9) -> 67261.268 | Q9: 38074.979 | R9: 0.017987415 | S9: 23641.274
A10: Transport | B10: ='India Expenses - Detailed'!E74 -> 3034.4828 | C10: ='India Expenses - Detailed'!F74 -> 3034.4828 | D10: ='India Expenses - Detailed'!G74 -> 3034.4828 | E10: ='India Expenses - Detailed'!H74 -> 3034.4828 | F10: ='India Expenses - Detailed'!I74 -> 3944.8276 | G10: ='India Expenses - Detailed'!J74 -> 3944.8276 | H10: ='India Expenses - Detailed'!K74 -> 3944.8276 | I10: ='India Expenses - Detailed'!L74 -> 3944.8276 | ... M10: ='India Expenses - Detailed'!P74 -> 3944.8276 | N10: =SUM(B10:M10) -> 43696.552 | Q10: 29439.337 | R10: 0.013907758 | S10: 30109.94
A11: Other Cogs | B11: ='India Expenses - Detailed'!$Q$86/12 -> 7506.3276 | C11: ='India Expenses - Detailed'!$Q$86/12 -> 7506.3276 | D11: ='India Expenses - Detailed'!$Q$86/12 -> 7506.3276 | E11: ='India Expenses - Detailed'!$Q$86/12 -> 7506.3276 | F11: ='India Expenses - Detailed'!$Q$86/12 -> 7506.3276 | G11: ='India Expenses - Detailed'!$Q$86/12 -> 7506.3276 | H11: ='India Expenses - Detailed'!$Q$86/12 -> 7506.3276 | I11: ='India Expenses - Detailed'!$Q$86/12 -> 7506.3276 | ... M11: ='India Expenses - Detailed'!$Q$86/12 -> 7506.3276 | N11: =SUM(B11:M11) -> 90075.931 | Q11: 193079.67 | R11: 0.091214869 | S11: 1749.2242
A12: Total Cogs | B12: =SUM(B7:B11) -> 137621.31 | C12: =SUM(C7:C11) -> 139321.31 | D12: =SUM(D7:D11) -> 129375.6 | E12: =SUM(E7:E11) -> 129375.6 | F12: =SUM(F7:F11) -> 134471.24 | G12: =SUM(G7:G11) -> 135090.63 | H12: =SUM(H7:H11) -> 142478.8 | I12: =SUM(I7:I11) -> 159220 | ... N12: =SUM(N7:N11) -> 1773729.5 | Q12: 1206445 | S12: 681570.15
A13: GM | B13: =B6-B12 -> 87792.812 | C13: =C6-C12 -> 99444.192 | D13: =D6-D12 -> 110222.26 | E13: =E6-E12 -> 74228.265 | F13: =F6-F12 -> 78344.259 | G13: =G6-G12 -> 80313.228 | H13: =H6-H12 -> 73275.06 | I13: =I6-I12 -> 87267.695 | ... N13: =N6-N12 -> 1036027.7 | Q13: 910311.56 | S13: 504847.37
A14: GM% | B14: =B13/B6 -> 0.38947343 | C14: =C13/C6 -> 0.41649313 | D14: =D13/D6 -> 0.46003025 | E14: =E13/E6 -> 0.36457199 | F14: =F13/F6 -> 0.3681323 | G14: =G13/G6 -> 0.37284953 | H14: =H13/H6 -> 0.3396234 | I14: =I13/I6 -> 0.35404483 | ... N14: =N13/N6 -> 0.36872498 | Q14: 0.43005018 | S14: 0.42552252
A16: Incremental P&L
A17: Revenue | B17: ='1. Revenue Buildup 2026'!D9 -> 0 | C17: ='1. Revenue Buildup 2026'!E9 -> 0 | D17: ='1. Revenue Buildup 2026'!F9 -> 0 | E17: ='1. Revenue Buildup 2026'!G9 -> 0 | F17: ='1. Revenue Buildup 2026'!H9 -> 13800 | G17: ='1. Revenue Buildup 2026'!I9 -> 16800 | H17: ='1. Revenue Buildup 2026'!J9 -> 17150 | I17: ='1. Revenue Buildup 2026'!K9 -> 49550 | ... M17: ='1. Revenue Buildup 2026'!O9 -> 57550 | N17: =SUM(B17:M17) -> 319500 | S17: 3816468.6
A18: Salaries | S18: 1233644.8
A19: Facilities | S19: 24883.119
A20: Telcom/Data & others | S20: 13156.29
A21: Transport | S21: 71009.275
A22: Other Cogs | O22: Includes mBMS insurance as well | S22: 4125.2538
A23: Total Cogs | B23: =SUM(B18:B22) -> 0 | C23: =SUM(C18:C22) -> 0 | D23: =SUM(D18:D22) -> 0 | E23: =SUM(E18:E22) -> 0 | F23: =SUM(F18:F22) -> 0 | G23: =SUM(G18:G22) -> 0 | H23: =SUM(H18:H22) -> 0 | I23: =SUM(I18:I22) -> 0 | ... N23: =SUM(N18:N22) -> 0 | S23: 1346818.8
A24: GM | B24: =B17-B23 -> 0 | C24: =C17-C23 -> 0 | D24: =D17-D23 -> 0 | E24: =E17-E23 -> 0 | F24: =F17-F23 -> 13800 | G24: =G17-G23 -> 16800 | H24: =H17-H23 -> 17150 | I24: =I17-I23 -> 49550 | ... M24: =M17-M23 -> 57550 | N24: =SUM(B24:M24) -> 319500 | S24: 2469649.8
A25: GM% | B25: =IFERROR(B24/B17,0) -> 0 | C25: =IFERROR(C24/C17,0) -> 0 | D25: =IFERROR(D24/D17,0) -> 0 | E25: =IFERROR(E24/E17,0) -> 0 | F25: =IFERROR(F24/F17,0) -> 1 | G25: =IFERROR(G24/G17,0) -> 1 | H25: =IFERROR(H24/H17,0) -> 1 | I25: =IFERROR(I24/I17,0) -> 1 | ... N25: =IFERROR(N24/N17,0) -> 1 | S25: 0.6471034
A27: US
A28: Revenue | N28: =SUM(B28:M28) -> 0
A29: Salaries | N29: =SUM(B29:M29) -> 0
A30: Facilities | B30: ='5. US Expenses'!D8 -> 1000 | C30: ='5. US Expenses'!E8 -> 1000 | D30: ='5. US Expenses'!F8 -> 1000 | E30: ='5. US Expenses'!G8 -> 1000 | F30: ='5. US Expenses'!H8 -> 1000 | G30: ='5. US Expenses'!I8 -> 1000 | H30: ='5. US Expenses'!J8 -> 1000 | I30: ='5. US Expenses'!K8 -> 1000 | ... M30: ='5. US Expenses'!O8 -> 1000 | N30: =SUM(B30:M30) -> 12000
A31: Telecom | B31: ='5. US Expenses'!D24 -> 1472.83 | C31: ='5. US Expenses'!E24 -> 1472.83 | D31: ='5. US Expenses'!F24 -> 1378.83 | E31: ='5. US Expenses'!G24 -> 1378.83 | F31: ='5. US Expenses'!H24 -> 1330.83 | G31: ='5. US Expenses'!I24 -> 1330.83 | H31: ='5. US Expenses'!J24 -> 1330.83 | I31: ='5. US Expenses'!K24 -> 1330.83 | ... M31: ='5. US Expenses'!O24 -> 1330.83 | N31: =SUM(B31:M31) -> 16562.22
A32: Transport | N32: =SUM(B32:M32) -> 0
A33: Other Cogs | B33: ='5. US Expenses'!D39 -> 20175.43 | C33: ='5. US Expenses'!E39 -> 20175.43 | D33: ='5. US Expenses'!F39 -> 8175.43 | E33: ='5. US Expenses'!G39 -> 8175.43 | F33: ='5. US Expenses'!H39 -> 8175.43 | G33: ='5. US Expenses'!I39 -> 8175.43 | H33: ='5. US Expenses'!J39 -> 6064.43 | I33: ='5. US Expenses'!K39 -> 6064.43 | ... M33: ='5. US Expenses'!O39 -> 6064.43 | N33: =SUM(B33:M33) -> 109439.16
A34: Total Cogs | B34: =SUM(B29:B33) -> 22648.26 | C34: =SUM(C29:C33) -> 22648.26 | D34: =SUM(D29:D33) -> 10554.26 | E34: =SUM(E29:E33) -> 10554.26 | F34: =SUM(F29:F33) -> 10506.26 | G34: =SUM(G29:G33) -> 10506.26 | H34: =SUM(H29:H33) -> 8395.26 | I34: =SUM(I29:I33) -> 8395.26 | ... N34: =SUM(N29:N33) -> 138001.38
A35: GM | B35: =B28-B34 -> -22648.26 | C35: =C28-C34 -> -22648.26 | D35: =D28-D34 -> -10554.26 | E35: =E28-E34 -> -10554.26 | F35: =F28-F34 -> -10506.26 | G35: =G28-G34 -> -10506.26 | H35: =H28-H34 -> -8395.26 | I35: =I28-I34 -> -8395.26 | ... M35: =M28-M34 -> -8395.26 | N35: =SUM(B35:M35) -> -138001.38
A36: GM% | B36: =IFERROR(B35/B28,0) -> 0 | C36: =IFERROR(C35/C28,0) -> 0 | D36: =IFERROR(D35/D28,0) -> 0 | E36: =IFERROR(E35/E28,0) -> 0 | F36: =IFERROR(F35/F28,0) -> 0 | G36: =IFERROR(G35/G28,0) -> 0 | H36: =IFERROR(H35/H28,0) -> 0 | I36: =IFERROR(I35/I28,0) -> 0 | ... N36: =IFERROR(N35/N28,0) -> 0
A38: Revenue | B38: =B17+B6 -> 225414.12 | C38: =C17+C6 -> 238765.5 | D38: =D17+D6 -> 239597.86 | E38: =E17+E6 -> 203603.86 | F38: =F17+F6 -> 226615.5 | G38: =G17+G6 -> 232203.86 | H38: =H17+H6 -> 232903.86 | I38: =I17+I6 -> 296037.7 | ... M38: =M17+M6 -> 313703.86 | N38: =SUM(B38:M38) -> 3129257.2 | Q38: ='3. P&L Summary Actual'!N28 -> 2116756.6 | S38: 5002886.1
A39: Salaries | B39: =B18+B7+B29 -> 107468.67 | C39: =C18+C7+C29 -> 107468.67 | D39: =D18+D7+D29 -> 97886.472 | E39: =E18+E7+E29 -> 97886.472 | F39: =F18+F7+F29 -> 102053.98 | G39: =G18+G7+G29 -> 102053.98 | H39: =H18+H7+H29 -> 105030.78 | I39: =I18+I7+I29 -> 121700.82 | ... M39: =M18+M7+M29 -> 133608 | N39: =SUM(B39:M39) -> 1358121.1 | O39: =N39/$N$38 -> 0.43400749 | Q39: ='3. P&L Summary Actual'!N29 -> 836770.98 | R39: =Q39/$Q$38 -> 0.39530808 | S39: 1758103.6 | T39: =S39/$S$38 -> 0.35141787
A40: Facilities | B40: =B19+B8+B30 -> 16550.932 | C40: =C19+C8+C30 -> 16550.932 | D40: =D19+D8+D30 -> 16550.932 | E40: =E19+E8+E30 -> 16550.932 | F40: =F19+F8+F30 -> 16550.932 | G40: =G19+G8+G30 -> 16550.932 | H40: =H19+H8+H30 -> 21211.518 | I40: =I19+I8+I30 -> 21211.518 | ... M40: =M19+M8+M30 -> 21211.518 | N40: =SUM(B40:M40) -> 226574.7 | O40: =N40/$N$38 -> 0.072405267 | Q40: ='3. P&L Summary Actual'!N30 -> 109080.05 | R40: =Q40/$Q$38 -> 0.051531694 | S40: 126494.1 | T40: =S40/$S$38 -> 0.025284226 | Z40: Headcount buildup comparison by dept level
A41: Telcom/Data & others | B41: =B20+B9+B31 -> 5533.7283 | C41: =C20+C9+C31 -> 7233.7283 | D41: =D20+D9+D31 -> 6776.2115 | E41: =E20+E9+E31 -> 6776.2115 | F41: =F20+F9+F31 -> 6746.0016 | G41: =G20+G9+G31 -> 7365.3924 | H41: =H20+H9+H31 -> 7116.18 | I41: =I20+I9+I31 -> 7187.3404 | ... M41: =M20+M9+M31 -> 7238.1693 | N41: =SUM(B41:M41) -> 83823.488 | O41: =N41/$N$38 -> 0.026787024 | Q41: ='3. P&L Summary Actual'!N31 -> 38074.979 | R41: =Q41/$Q$38 -> 0.017987415 | S41: 36797.564 | T41: =S41/$S$38 -> 0.0073552672
