Workbook
Name \: #REF!
Name \: #REF!
Name \: #REF!
Name \: #REF!
Name \0: #REF!
Name \0: #REF!
Name \0: #REF!
Name \0: #REF!
Name \A: #REF!
Name \A: #REF!
Name \A: #REF!
Name \A: #REF!
Name \B: #REF!
Name \B: #REF!
Name \B: #REF!
Name \B: #REF!
Name \E: #REF!
Name \E: #REF!
Name \E: #REF!
Name \E: #REF!
Name \G: #REF!
Name \G: #REF!
Name \G: #REF!
Name \G: #REF!
Name \L: #REF!
Name \L: #REF!
Name \L: #REF!
Name \L: #REF!
Name \q: #REF!
Name \q: #REF!
Name \q: #REF!
Name \q: #REF!
Name \S: #REF!
Name \S: #REF!
Name \S: #REF!
Name \S: #REF!
Name \T: #REF!
Name \T: #REF!
Name \T: #REF!
Name \T: #REF!
Name \U: #REF!
Name \U: #REF!
Name \U: #REF!
Name \U: #REF!
Name ________DAT7: #REF!
Name ________DAT7: #REF!
Name ________DAT7: #REF!
Name ________DAT7: #REF!
Name ________DAT8: #REF!
Name ________DAT8: #REF!
Name ________DAT8: #REF!
Name ________DAT8: #REF!
Name ________DAT9: #REF!
Name ________DAT9: #REF!
Name ________DAT9: #REF!
Name ________DAT9: #REF!
Name _______DAT13: #REF!
Name _______DAT13: #REF!
Name _______DAT13: #REF!
Name _______DAT13: #REF!

Sheet MIS-Actuals
B5: MIS Actuals
B7: >>>>

Sheet MIS Actuals Jan-Jun
A1: I-Magnum Healthcare Solution Inc.
A2: MIS Actuals - Consolidated P&L, Jan to June 2026 (USD, post-elimination Total)
A6: Particulars | B6: 46023 | C6: 46054 | D6: 46082 | E6: 46113 | F6: 46143 | G6: 46174 | H6: 46204 | I6: Total
A7: =IF('Jun''26'!B7="","",'Jun''26'!B7) -> Service Income | B7: =IFERROR(IF(INDEX(Jan!$E:$E,MATCH(TRIM($A7),Jan!$B:$B,0))="","",INDEX(Jan!$E:$E,MATCH(TRIM($A7),Jan!$B:$B,0))),"") | C7: =IFERROR(IF(INDEX('March-Feb'!$I:$I,MATCH($A7,'March-Feb'!$B:$B,0))="","",INDEX('March-Feb'!$I:$I,MATCH($A7,'March-Feb'!$B:$B,0))),"") | D7: =IFERROR(IF(INDEX('March-Feb'!$E:$E,MATCH($A7,'March-Feb'!$B:$B,0))="","",INDEX('March-Feb'!$E:$E,MATCH($A7,'March-Feb'!$B:$B,0))),"") | E7: =IFERROR(IF(INDEX('April-March'!$F:$F,MATCH($A7,'April-March'!$B:$B,0))="","",INDEX('April-March'!$F:$F,MATCH($A7,'April-March'!$B:$B,0))),"") | F7: =IFERROR(IF(INDEX('May-April'!$F:$F,MATCH($A7,'May-April'!$B:$B,0))="","",INDEX('May-April'!$F:$F,MATCH($A7,'May-April'!$B:$B,0))),"") | G7: =IF('Jun''26'!F7="","",'Jun''26'!F7) | H7: =IFERROR(IF(INDEX('Jul''26'!$F:$F,MATCH($A7,'Jul''26'!$B:$B,0))="","",INDEX('Jul''26'!$F:$F,MATCH($A7,'Jul''26'!$B:$B,0))),"") | I7: =IF(COUNT(B7:G7)=0,"",SUM(B7:G7))
A8: =IF('Jun''26'!B8="","",'Jun''26'!B8) -> Sales | B8: =IFERROR(IF(INDEX(Jan!$E:$E,MATCH(TRIM($A8),Jan!$B:$B,0))="","",INDEX(Jan!$E:$E,MATCH(TRIM($A8),Jan!$B:$B,0))),"") -> 226814 | C8: =IFERROR(IF(INDEX('March-Feb'!$I:$I,MATCH($A8,'March-Feb'!$B:$B,0))="","",INDEX('March-Feb'!$I:$I,MATCH($A8,'March-Feb'!$B:$B,0))),"") -> 227771 | D8: =IFERROR(IF(INDEX('March-Feb'!$E:$E,MATCH($A8,'March-Feb'!$B:$B,0))="","",INDEX('March-Feb'!$E:$E,MATCH($A8,'March-Feb'!$B:$B,0))),"") -> 221215 | E8: =IFERROR(IF(INDEX('April-March'!$F:$F,MATCH($A8,'April-March'!$B:$B,0))="","",INDEX('April-March'!$F:$F,MATCH($A8,'April-March'!$B:$B,0))),"") -> 195207 | F8: =IFERROR(IF(INDEX('May-April'!$F:$F,MATCH($A8,'May-April'!$B:$B,0))="","",INDEX('May-April'!$F:$F,MATCH($A8,'May-April'!$B:$B,0))),"") -> 209918 | G8: =IF('Jun''26'!F8="","",'Jun''26'!F8) -> 232311 | H8: =IFERROR(IF(INDEX('Jul''26'!$F:$F,MATCH($A8,'Jul''26'!$B:$B,0))="","",INDEX('Jul''26'!$F:$F,MATCH($A8,'Jul''26'!$B:$B,0))),"") -> 250672 | I8: =SUM(B8:H8) -> 1563908
A9: =IF('Jun''26'!B9="","",'Jun''26'!B9) -> Sales | B9: =IFERROR(IF(INDEX(Jan!$E:$E,MATCH(TRIM($A9),Jan!$B:$B,0))="","",INDEX(Jan!$E:$E,MATCH(TRIM($A9),Jan!$B:$B,0))),"") -> 226814 | C9: =IFERROR(IF(INDEX('March-Feb'!$I:$I,MATCH($A9,'March-Feb'!$B:$B,0))="","",INDEX('March-Feb'!$I:$I,MATCH($A9,'March-Feb'!$B:$B,0))),"") -> 227770 | D9: =IFERROR(IF(INDEX('March-Feb'!$E:$E,MATCH($A9,'March-Feb'!$B:$B,0))="","",INDEX('March-Feb'!$E:$E,MATCH($A9,'March-Feb'!$B:$B,0))),"") -> 221215 | E9: =IFERROR(IF(INDEX('April-March'!$F:$F,MATCH($A9,'April-March'!$B:$B,0))="","",INDEX('April-March'!$F:$F,MATCH($A9,'April-March'!$B:$B,0))),"") -> 194902 | F9: =IFERROR(IF(INDEX('May-April'!$F:$F,MATCH($A9,'May-April'!$B:$B,0))="","",INDEX('May-April'!$F:$F,MATCH($A9,'May-April'!$B:$B,0))),"") -> 209920 | G9: =IF('Jun''26'!F9="","",'Jun''26'!F9) -> 225714 | H9: =IFERROR(IF(INDEX('Jul''26'!$F:$F,MATCH($A9,'Jul''26'!$B:$B,0))="","",INDEX('Jul''26'!$F:$F,MATCH($A9,'Jul''26'!$B:$B,0))),"") -> 250400 | I9: =SUM(B9:H9) -> 1556735
A10: =IF('Jun''26'!B10="","",'Jun''26'!B10) -> Other Charges | B10: =IFERROR(IF(INDEX(Jan!$E:$E,MATCH(TRIM($A10),Jan!$B:$B,0))="","",INDEX(Jan!$E:$E,MATCH(TRIM($A10),Jan!$B:$B,0))),"") -> 0 | C10: =IFERROR(IF(INDEX('March-Feb'!$I:$I,MATCH($A10,'March-Feb'!$B:$B,0))="","",INDEX('March-Feb'!$I:$I,MATCH($A10,'March-Feb'!$B:$B,0))),"") -> 1 | D10: =IFERROR(IF(INDEX('March-Feb'!$E:$E,MATCH($A10,'March-Feb'!$B:$B,0))="","",INDEX('March-Feb'!$E:$E,MATCH($A10,'March-Feb'!$B:$B,0))),"") -> 0 | E10: =IFERROR(IF(INDEX('April-March'!$F:$F,MATCH($A10,'April-March'!$B:$B,0))="","",INDEX('April-March'!$F:$F,MATCH($A10,'April-March'!$B:$B,0))),"") -> 0 | F10: =IFERROR(IF(INDEX('May-April'!$F:$F,MATCH($A10,'May-April'!$B:$B,0))="","",INDEX('May-April'!$F:$F,MATCH($A10,'May-April'!$B:$B,0))),"") -> 0 | G10: =IF('Jun''26'!F10="","",'Jun''26'!F10) -> 0 | H10: =IFERROR(IF(INDEX('Jul''26'!$F:$F,MATCH($A10,'Jul''26'!$B:$B,0))="","",INDEX('Jul''26'!$F:$F,MATCH($A10,'Jul''26'!$B:$B,0))),"") -> 0 | I10: =SUM(B10:H10) -> 1
A11: =IF('Jun''26'!B11="","",'Jun''26'!B11) -> Buyout | B11: =IFERROR(IF(INDEX(Jan!$E:$E,MATCH(TRIM($A11),Jan!$B:$B,0))="","",INDEX(Jan!$E:$E,MATCH(TRIM($A11),Jan!$B:$B,0))),"") -> 0 | C11: =IFERROR(IF(INDEX('March-Feb'!$I:$I,MATCH($A11,'March-Feb'!$B:$B,0))="","",INDEX('March-Feb'!$I:$I,MATCH($A11,'March-Feb'!$B:$B,0))),"") | D11: =IFERROR(IF(INDEX('March-Feb'!$E:$E,MATCH($A11,'March-Feb'!$B:$B,0))="","",INDEX('March-Feb'!$E:$E,MATCH($A11,'March-Feb'!$B:$B,0))),"") | E11: =IFERROR(IF(INDEX('April-March'!$F:$F,MATCH($A11,'April-March'!$B:$B,0))="","",INDEX('April-March'!$F:$F,MATCH($A11,'April-March'!$B:$B,0))),"") | F11: =IFERROR(IF(INDEX('May-April'!$F:$F,MATCH($A11,'May-April'!$B:$B,0))="","",INDEX('May-April'!$F:$F,MATCH($A11,'May-April'!$B:$B,0))),"") | G11: =IF('Jun''26'!F11="","",'Jun''26'!F11) | H11: =IFERROR(IF(INDEX('Jul''26'!$F:$F,MATCH($A11,'Jul''26'!$B:$B,0))="","",INDEX('Jul''26'!$F:$F,MATCH($A11,'Jul''26'!$B:$B,0))),"") -> 224 | I11: =SUM(B11:H11) -> 224
A12: =IF('Jun''26'!B12="","",'Jun''26'!B12) -> General Income | B12: =IFERROR(IF(INDEX(Jan!$E:$E,MATCH(TRIM($A12),Jan!$B:$B,0))="","",INDEX(Jan!$E:$E,MATCH(TRIM($A12),Jan!$B:$B,0))),"") -> 287 | C12: =IFERROR(IF(INDEX('March-Feb'!$I:$I,MATCH($A12,'March-Feb'!$B:$B,0))="","",INDEX('March-Feb'!$I:$I,MATCH($A12,'March-Feb'!$B:$B,0))),"") -> 0 | D12: =IFERROR(IF(INDEX('March-Feb'!$E:$E,MATCH($A12,'March-Feb'!$B:$B,0))="","",INDEX('March-Feb'!$E:$E,MATCH($A12,'March-Feb'!$B:$B,0))),"") -> 0 | E12: =IFERROR(IF(INDEX('April-March'!$F:$F,MATCH($A12,'April-March'!$B:$B,0))="","",INDEX('April-March'!$F:$F,MATCH($A12,'April-March'!$B:$B,0))),"") -> 16 | F12: =IFERROR(IF(INDEX('May-April'!$F:$F,MATCH($A12,'May-April'!$B:$B,0))="","",INDEX('May-April'!$F:$F,MATCH($A12,'May-April'!$B:$B,0))),"") -> 0 | G12: =IF('Jun''26'!F12="","",'Jun''26'!F12) -> 294 | H12: =IFERROR(IF(INDEX('Jul''26'!$F:$F,MATCH($A12,'Jul''26'!$B:$B,0))="","",INDEX('Jul''26'!$F:$F,MATCH($A12,'Jul''26'!$B:$B,0))),"") -> 16 | I12: =SUM(B12:H12) -> 613
A13: =IF('Jun''26'!B13="","",'Jun''26'!B13) -> Interest Income | B13: =IFERROR(IF(INDEX(Jan!$E:$E,MATCH(TRIM($A13),Jan!$B:$B,0))="","",INDEX(Jan!$E:$E,MATCH(TRIM($A13),Jan!$B:$B,0))),"") -> 0 | C13: =IFERROR(IF(INDEX('March-Feb'!$I:$I,MATCH($A13,'March-Feb'!$B:$B,0))="","",INDEX('March-Feb'!$I:$I,MATCH($A13,'March-Feb'!$B:$B,0))),"") | D13: =IFERROR(IF(INDEX('March-Feb'!$E:$E,MATCH($A13,'March-Feb'!$B:$B,0))="","",INDEX('March-Feb'!$E:$E,MATCH($A13,'March-Feb'!$B:$B,0))),"") | E13: =IFERROR(IF(INDEX('April-March'!$F:$F,MATCH($A13,'April-March'!$B:$B,0))="","",INDEX('April-March'!$F:$F,MATCH($A13,'April-March'!$B:$B,0))),"") -> 289 | F13: =IFERROR(IF(INDEX('May-April'!$F:$F,MATCH($A13,'May-April'!$B:$B,0))="","",INDEX('May-April'!$F:$F,MATCH($A13,'May-April'!$B:$B,0))),"") -> -2 | G13: =IF('Jun''26'!F13="","",'Jun''26'!F13) -> -1 | H13: =IFERROR(IF(INDEX('Jul''26'!$F:$F,MATCH($A13,'Jul''26'!$B:$B,0))="","",INDEX('Jul''26'!$F:$F,MATCH($A13,'Jul''26'!$B:$B,0))),"") -> 54 | I13: =SUM(B13:H13) -> 340
A14: =IF('Jun''26'!B14="","",'Jun''26'!B14) -> Governments Grant Income | B14: =IFERROR(IF(INDEX(Jan!$E:$E,MATCH(TRIM($A14),Jan!$B:$B,0))="","",INDEX(Jan!$E:$E,MATCH(TRIM($A14),Jan!$B:$B,0))),"") | C14: =IFERROR(IF(INDEX('March-Feb'!$I:$I,MATCH($A14,'March-Feb'!$B:$B,0))="","",INDEX('March-Feb'!$I:$I,MATCH($A14,'March-Feb'!$B:$B,0))),"") | D14: =IFERROR(IF(INDEX('March-Feb'!$E:$E,MATCH($A14,'March-Feb'!$B:$B,0))="","",INDEX('March-Feb'!$E:$E,MATCH($A14,'March-Feb'!$B:$B,0))),"") | E14: =IFERROR(IF(INDEX('April-March'!$F:$F,MATCH($A14,'April-March'!$B:$B,0))="","",INDEX('April-March'!$F:$F,MATCH($A14,'April-March'!$B:$B,0))),"") | F14: =IFERROR(IF(INDEX('May-April'!$F:$F,MATCH($A14,'May-April'!$B:$B,0))="","",INDEX('May-April'!$F:$F,MATCH($A14,'May-April'!$B:$B,0))),"") | G14: =IF('Jun''26'!F14="","",'Jun''26'!F14) -> 6304 | H14: =IFERROR(IF(INDEX('Jul''26'!$F:$F,MATCH($A14,'Jul''26'!$B:$B,0))="","",INDEX('Jul''26'!$F:$F,MATCH($A14,'Jul''26'!$B:$B,0))),"") -> -21 | I14: =SUM(B14:H14) -> 6283
A15: =IF('Jun''26'!B15="","",'Jun''26'!B15) -> Total Revenue | B15: =IFERROR(IF(INDEX(Jan!$E:$E,MATCH(TRIM($A15),Jan!$B:$B,0))="","",INDEX(Jan!$E:$E,MATCH(TRIM($A15),Jan!$B:$B,0))),"") -> 226814 | C15: =IFERROR(IF(INDEX('March-Feb'!$I:$I,MATCH($A15,'March-Feb'!$B:$B,0))="","",INDEX('March-Feb'!$I:$I,MATCH($A15,'March-Feb'!$B:$B,0))),"") -> 227771 | D15: =IFERROR(IF(INDEX('March-Feb'!$E:$E,MATCH($A15,'March-Feb'!$B:$B,0))="","",INDEX('March-Feb'!$E:$E,MATCH($A15,'March-Feb'!$B:$B,0))),"") -> 221215 | E15: =IFERROR(IF(INDEX('April-March'!$F:$F,MATCH($A15,'April-March'!$B:$B,0))="","",INDEX('April-March'!$F:$F,MATCH($A15,'April-March'!$B:$B,0))),"") -> 195207 | F15: =IFERROR(IF(INDEX('May-April'!$F:$F,MATCH($A15,'May-April'!$B:$B,0))="","",INDEX('May-April'!$F:$F,MATCH($A15,'May-April'!$B:$B,0))),"") -> 209918 | G15: =IF('Jun''26'!F15="","",'Jun''26'!F15) -> 232311 | H15: =IFERROR(IF(INDEX('Jul''26'!$F:$F,MATCH($A15,'Jul''26'!$B:$B,0))="","",INDEX('Jul''26'!$F:$F,MATCH($A15,'Jul''26'!$B:$B,0))),"") -> 250672 | I15: =SUM(B15:H15) -> 1563908
A16: =IF('Jun''26'!B16="","",'Jun''26'!B16) -> Overall Operational cost | B16: =IFERROR(IF(INDEX(Jan!$E:$E,MATCH(TRIM($A16),Jan!$B:$B,0))="","",INDEX(Jan!$E:$E,MATCH(TRIM($A16),Jan!$B:$B,0))),"") | C16: =IFERROR(IF(INDEX('March-Feb'!$I:$I,MATCH($A16,'March-Feb'!$B:$B,0))="","",INDEX('March-Feb'!$I:$I,MATCH($A16,'March-Feb'!$B:$B,0))),"") | D16: =IFERROR(IF(INDEX('March-Feb'!$E:$E,MATCH($A16,'March-Feb'!$B:$B,0))="","",INDEX('March-Feb'!$E:$E,MATCH($A16,'March-Feb'!$B:$B,0))),"") | E16: =IFERROR(IF(INDEX('April-March'!$F:$F,MATCH($A16,'April-March'!$B:$B,0))="","",INDEX('April-March'!$F:$F,MATCH($A16,'April-March'!$B:$B,0))),"") | F16: =IFERROR(IF(INDEX('May-April'!$F:$F,MATCH($A16,'May-April'!$B:$B,0))="","",INDEX('May-April'!$F:$F,MATCH($A16,'May-April'!$B:$B,0))),"") | G16: =IF('Jun''26'!F16="","",'Jun''26'!F16) | H16: =IFERROR(IF(INDEX('Jul''26'!$F:$F,MATCH($A16,'Jul''26'!$B:$B,0))="","",INDEX('Jul''26'!$F:$F,MATCH($A16,'Jul''26'!$B:$B,0))),"") | I16: =SUM(B16:H16) -> 0
A17: =IF('Jun''26'!B17="","",'Jun''26'!B17) -> Manpower | B17: =IFERROR(IF(INDEX(Jan!$E:$E,MATCH(TRIM($A17),Jan!$B:$B,0))="","",INDEX(Jan!$E:$E,MATCH(TRIM($A17),Jan!$B:$B,0))),"") -> 114851.43 | C17: =IFERROR(IF(INDEX('March-Feb'!$I:$I,MATCH($A17,'March-Feb'!$B:$B,0))="","",INDEX('March-Feb'!$I:$I,MATCH($A17,'March-Feb'!$B:$B,0))),"") -> 108834 | D17: =IFERROR(IF(INDEX('March-Feb'!$E:$E,MATCH($A17,'March-Feb'!$B:$B,0))="","",INDEX('March-Feb'!$E:$E,MATCH($A17,'March-Feb'!$B:$B,0))),"") -> 120509 | E17: =IFERROR(IF(INDEX('April-March'!$F:$F,MATCH($A17,'April-March'!$B:$B,0))="","",INDEX('April-March'!$F:$F,MATCH($A17,'April-March'!$B:$B,0))),"") -> 100793 | F17: =IFERROR(IF(INDEX('May-April'!$F:$F,MATCH($A17,'May-April'!$B:$B,0))="","",INDEX('May-April'!$F:$F,MATCH($A17,'May-April'!$B:$B,0))),"") -> 92483 | G17: =IF('Jun''26'!F17="","",'Jun''26'!F17) -> 94790 | H17: =IFERROR(IF(INDEX('Jul''26'!$F:$F,MATCH($A17,'Jul''26'!$B:$B,0))="","",INDEX('Jul''26'!$F:$F,MATCH($A17,'Jul''26'!$B:$B,0))),"") -> 100703 | I17: =SUM(B17:H17) -> 732963.43
A18: =IF('Jun''26'!B18="","",'Jun''26'!B18) -> India Cost | B18: =IFERROR(IF(INDEX(Jan!$E:$E,MATCH(TRIM($A18),Jan!$B:$B,0))="","",INDEX(Jan!$E:$E,MATCH(TRIM($A18),Jan!$B:$B,0))),"") | C18: =IFERROR(IF(INDEX('March-Feb'!$I:$I,MATCH($A18,'March-Feb'!$B:$B,0))="","",INDEX('March-Feb'!$I:$I,MATCH($A18,'March-Feb'!$B:$B,0))),"") | D18: =IFERROR(IF(INDEX('March-Feb'!$E:$E,MATCH($A18,'March-Feb'!$B:$B,0))="","",INDEX('March-Feb'!$E:$E,MATCH($A18,'March-Feb'!$B:$B,0))),"") | E18: =IFERROR(IF(INDEX('April-March'!$F:$F,MATCH($A18,'April-March'!$B:$B,0))="","",INDEX('April-March'!$F:$F,MATCH($A18,'April-March'!$B:$B,0))),"") | F18: =IFERROR(IF(INDEX('May-April'!$F:$F,MATCH($A18,'May-April'!$B:$B,0))="","",INDEX('May-April'!$F:$F,MATCH($A18,'May-April'!$B:$B,0))),"") | G18: =IF('Jun''26'!F18="","",'Jun''26'!F18) | H18: =IFERROR(IF(INDEX('Jul''26'!$F:$F,MATCH($A18,'Jul''26'!$B:$B,0))="","",INDEX('Jul''26'!$F:$F,MATCH($A18,'Jul''26'!$B:$B,0))),"") -> 0 | I18: =SUM(B18:H18) -> 0
A19: =IF('Jun''26'!B19="","",'Jun''26'!B19) -> Consultancy fee | B19: =IFERROR(IF(INDEX(Jan!$E:$E,MATCH(TRIM($A19),Jan!$B:$B,0))="","",INDEX(Jan!$E:$E,MATCH(TRIM($A19),Jan!$B:$B,0))),"") -> 0 | C19: =IFERROR(IF(INDEX('March-Feb'!$I:$I,MATCH($A19,'March-Feb'!$B:$B,0))="","",INDEX('March-Feb'!$I:$I,MATCH($A19,'March-Feb'!$B:$B,0))),"") -> 5914 | D19: =IFERROR(IF(INDEX('March-Feb'!$E:$E,MATCH($A19,'March-Feb'!$B:$B,0))="","",INDEX('March-Feb'!$E:$E,MATCH($A19,'March-Feb'!$B:$B,0))),"") -> 7575 | E19: =IFERROR(IF(INDEX('April-March'!$F:$F,MATCH($A19,'April-March'!$B:$B,0))="","",INDEX('April-March'!$F:$F,MATCH($A19,'April-March'!$B:$B,0))),"") -> 0 | F19: =IFERROR(IF(INDEX('May-April'!$F:$F,MATCH($A19,'May-April'!$B:$B,0))="","",INDEX('May-April'!$F:$F,MATCH($A19,'May-April'!$B:$B,0))),"") -> 0 | G19: =IF('Jun''26'!F19="","",'Jun''26'!F19) -> 0 | H19: =IFERROR(IF(INDEX('Jul''26'!$F:$F,MATCH($A19,'Jul''26'!$B:$B,0))="","",INDEX('Jul''26'!$F:$F,MATCH($A19,'Jul''26'!$B:$B,0))),"") -> 0 | I19: =SUM(B19:H19) -> 13489
... A66: =IF('Jun''26'!B66="","",'Jun''26'!B66) -> Total COGS | B66: =IFERROR(IF(INDEX(Jan!$E:$E,MATCH(TRIM($A66),Jan!$B:$B,0))="","",INDEX(Jan!$E:$E,MATCH(TRIM($A66),Jan!$B:$B,0))),"") -> 160435.18 | C66: =IFERROR(IF(INDEX('March-Feb'!$I:$I,MATCH($A66,'March-Feb'!$B:$B,0))="","",INDEX('March-Feb'!$I:$I,MATCH($A66,'March-Feb'!$B:$B,0))),"") -> 166233 | D66: =IFERROR(IF(INDEX('March-Feb'!$E:$E,MATCH($A66,'March-Feb'!$B:$B,0))="","",INDEX('March-Feb'!$E:$E,MATCH($A66,'March-Feb'!$B:$B,0))),"") -> 189430 | E66: =IFERROR(IF(INDEX('April-March'!$F:$F,MATCH($A66,'April-March'!$B:$B,0))="","",INDEX('April-March'!$F:$F,MATCH($A66,'April-March'!$B:$B,0))),"") -> 154650 | F66: =IFERROR(IF(INDEX('May-April'!$F:$F,MATCH($A66,'May-April'!$B:$B,0))="","",INDEX('May-April'!$F:$F,MATCH($A66,'May-April'!$B:$B,0))),"") -> 144550 | G66: =IF('Jun''26'!F66="","",'Jun''26'!F66) -> 148327 | H66: =IFERROR(IF(INDEX('Jul''26'!$F:$F,MATCH($A66,'Jul''26'!$B:$B,0))="","",INDEX('Jul''26'!$F:$F,MATCH($A66,'Jul''26'!$B:$B,0))),"") -> 152984 | I66: =SUM(B66:H66) -> 1116609.2
A67: =IF('Jun''26'!B67="","",'Jun''26'!B67) -> GM | B67: =Jan!E16 -> 66378.82 | C67: =IFERROR(IF(INDEX('March-Feb'!$I:$I,MATCH($A67,'March-Feb'!$B:$B,0))="","",INDEX('March-Feb'!$I:$I,MATCH($A67,'March-Feb'!$B:$B,0))),"") -> 61538 | D67: =IFERROR(IF(INDEX('March-Feb'!$E:$E,MATCH($A67,'March-Feb'!$B:$B,0))="","",INDEX('March-Feb'!$E:$E,MATCH($A67,'March-Feb'!$B:$B,0))),"") -> 31785 | E67: =IFERROR(IF(INDEX('April-March'!$F:$F,MATCH($A67,'April-March'!$B:$B,0))="","",INDEX('April-March'!$F:$F,MATCH($A67,'April-March'!$B:$B,0))),"") -> 40557 | F67: =IFERROR(IF(INDEX('May-April'!$F:$F,MATCH($A67,'May-April'!$B:$B,0))="","",INDEX('May-April'!$F:$F,MATCH($A67,'May-April'!$B:$B,0))),"") -> 65368 | G67: =IF('Jun''26'!F67="","",'Jun''26'!F67) -> 83983 | H67: =IFERROR(IF(INDEX('Jul''26'!$F:$F,MATCH($A67,'Jul''26'!$B:$B,0))="","",INDEX('Jul''26'!$F:$F,MATCH($A67,'Jul''26'!$B:$B,0))),"") -> 97689 | I67: =SUM(B67:H67) -> 447298.82
A68: =IF('Jun''26'!B68="","",'Jun''26'!B68) -> GM% | B68: =IFERROR(B$67/B$15,"") -> 0.29265751 | C68: =IFERROR(C$67/C$15,"") -> 0.27017487 | D68: =IFERROR(D$67/D$15,"") -> 0.14368375 | E68: =IFERROR(E$67/E$15,"") -> 0.20776407 | F68: =IFERROR(F$67/F$15,"") -> 0.31139778 | G68: =IFERROR(G$67/G$15,"") -> 0.36151108 | H68: =IFERROR(H$67/H$15,"") -> 0.38970846 | I68: =SUM(B68:H68) -> 1.9768975
A69: =IF('Jun''26'!B69="","",'Jun''26'!B69) -> SG&A | B69: =IFERROR(IF(INDEX(Jan!$E:$E,MATCH(TRIM($A69),Jan!$B:$B,0))="","",INDEX(Jan!$E:$E,MATCH(TRIM($A69),Jan!$B:$B,0))),"") | C69: =IFERROR(IF(INDEX('March-Feb'!$I:$I,MATCH($A69,'March-Feb'!$B:$B,0))="","",INDEX('March-Feb'!$I:$I,MATCH($A69,'March-Feb'!$B:$B,0))),"") | D69: =IFERROR(IF(INDEX('March-Feb'!$E:$E,MATCH($A69,'March-Feb'!$B:$B,0))="","",INDEX('March-Feb'!$E:$E,MATCH($A69,'March-Feb'!$B:$B,0))),"") | E69: =IFERROR(IF(INDEX('April-March'!$F:$F,MATCH($A69,'April-March'!$B:$B,0))="","",INDEX('April-March'!$F:$F,MATCH($A69,'April-March'!$B:$B,0))),"") | F69: =IFERROR(IF(INDEX('May-April'!$F:$F,MATCH($A69,'May-April'!$B:$B,0))="","",INDEX('May-April'!$F:$F,MATCH($A69,'May-April'!$B:$B,0))),"") | G69: =IF('Jun''26'!F69="","",'Jun''26'!F69) | H69: =IFERROR(IF(INDEX('Jul''26'!$F:$F,MATCH($A69,'Jul''26'!$B:$B,0))="","",INDEX('Jul''26'!$F:$F,MATCH($A69,'Jul''26'!$B:$B,0))),"") | I69: =SUM(B69:H69) -> 0
A70: =IF('Jun''26'!B70="","",'Jun''26'!B70) -> Selling Expenses | B70: =IFERROR(IF(INDEX(Jan!$E:$E,MATCH(TRIM($A70),Jan!$B:$B,0))="","",INDEX(Jan!$E:$E,MATCH(TRIM($A70),Jan!$B:$B,0))),"") -> 5200.478 | C70: =IFERROR(IF(INDEX('March-Feb'!$I:$I,MATCH($A70,'March-Feb'!$B:$B,0))="","",INDEX('March-Feb'!$I:$I,MATCH($A70,'March-Feb'!$B:$B,0))),"") -> 3273 | D70: =IFERROR(IF(INDEX('March-Feb'!$E:$E,MATCH($A70,'March-Feb'!$B:$B,0))="","",INDEX('March-Feb'!$E:$E,MATCH($A70,'March-Feb'!$B:$B,0))),"") -> 2839 | E70: =IFERROR(IF(INDEX('April-March'!$F:$F,MATCH($A70,'April-March'!$B:$B,0))="","",INDEX('April-March'!$F:$F,MATCH($A70,'April-March'!$B:$B,0))),"") -> 2109 | F70: =IFERROR(IF(INDEX('May-April'!$F:$F,MATCH($A70,'May-April'!$B:$B,0))="","",INDEX('May-April'!$F:$F,MATCH($A70,'May-April'!$B:$B,0))),"") -> 1407 | G70: =IF('Jun''26'!F70="","",'Jun''26'!F70) -> 6679 | H70: =IFERROR(IF(INDEX('Jul''26'!$F:$F,MATCH($A70,'Jul''26'!$B:$B,0))="","",INDEX('Jul''26'!$F:$F,MATCH($A70,'Jul''26'!$B:$B,0))),"") -> 3342 | I70: =SUM(B70:H70) -> 24849.478
A71: =IF('Jun''26'!B71="","",'Jun''26'!B71) -> Travel Expense | B71: =IFERROR(IF(INDEX(Jan!$E:$E,MATCH(TRIM($A71),Jan!$B:$B,0))="","",INDEX(Jan!$E:$E,MATCH(TRIM($A71),Jan!$B:$B,0))),"") -> 1498.83 | C71: =IFERROR(IF(INDEX('March-Feb'!$I:$I,MATCH($A71,'March-Feb'!$B:$B,0))="","",INDEX('March-Feb'!$I:$I,MATCH($A71,'March-Feb'!$B:$B,0))),"") | D71: =IFERROR(IF(INDEX('March-Feb'!$E:$E,MATCH($A71,'March-Feb'!$B:$B,0))="","",INDEX('March-Feb'!$E:$E,MATCH($A71,'March-Feb'!$B:$B,0))),"") | E71: =IFERROR(IF(INDEX('April-March'!$F:$F,MATCH($A71,'April-March'!$B:$B,0))="","",INDEX('April-March'!$F:$F,MATCH($A71,'April-March'!$B:$B,0))),"") | F71: =IFERROR(IF(INDEX('May-April'!$F:$F,MATCH($A71,'May-April'!$B:$B,0))="","",INDEX('May-April'!$F:$F,MATCH($A71,'May-April'!$B:$B,0))),"") | G71: =IF('Jun''26'!F71="","",'Jun''26'!F71) | H71: =IFERROR(IF(INDEX('Jul''26'!$F:$F,MATCH($A71,'Jul''26'!$B:$B,0))="","",INDEX('Jul''26'!$F:$F,MATCH($A71,'Jul''26'!$B:$B,0))),"") -> 0 | I71: =SUM(B71:H71) -> 1498.83
A72: =IF('Jun''26'!B72="","",'Jun''26'!B72) -> Cyber Security Insurance | B72: =IFERROR(IF(INDEX(Jan!$E:$E,MATCH(TRIM($A72),Jan!$B:$B,0))="","",INDEX(Jan!$E:$E,MATCH(TRIM($A72),Jan!$B:$B,0))),"") -> 0 | C72: =IFERROR(IF(INDEX('March-Feb'!$I:$I,MATCH($A72,'March-Feb'!$B:$B,0))="","",INDEX('March-Feb'!$I:$I,MATCH($A72,'March-Feb'!$B:$B,0))),"") | D72: =IFERROR(IF(INDEX('March-Feb'!$E:$E,MATCH($A72,'March-Feb'!$B:$B,0))="","",INDEX('March-Feb'!$E:$E,MATCH($A72,'March-Feb'!$B:$B,0))),"") | E72: =IFERROR(IF(INDEX('April-March'!$F:$F,MATCH($A72,'April-March'!$B:$B,0))="","",INDEX('April-March'!$F:$F,MATCH($A72,'April-March'!$B:$B,0))),"") | F72: =IFERROR(IF(INDEX('May-April'!$F:$F,MATCH($A72,'May-April'!$B:$B,0))="","",INDEX('May-April'!$F:$F,MATCH($A72,'May-April'!$B:$B,0))),"") | G72: =IF('Jun''26'!F72="","",'Jun''26'!F72) | H72: =IFERROR(IF(INDEX('Jul''26'!$F:$F,MATCH($A72,'Jul''26'!$B:$B,0))="","",INDEX('Jul''26'!$F:$F,MATCH($A72,'Jul''26'!$B:$B,0))),"") -> 0 | I72: =SUM(B72:H72) -> 0
A73: =IF('Jun''26'!B73="","",'Jun''26'!B73) -> Rewards and recognition | B73: =IFERROR(IF(INDEX(Jan!$E:$E,MATCH(TRIM($A73),Jan!$B:$B,0))="","",INDEX(Jan!$E:$E,MATCH(TRIM($A73),Jan!$B:$B,0))),"") -> 0 | C73: =IFERROR(IF(INDEX('March-Feb'!$I:$I,MATCH($A73,'March-Feb'!$B:$B,0))="","",INDEX('March-Feb'!$I:$I,MATCH($A73,'March-Feb'!$B:$B,0))),"") | D73: =IFERROR(IF(INDEX('March-Feb'!$E:$E,MATCH($A73,'March-Feb'!$B:$B,0))="","",INDEX('March-Feb'!$E:$E,MATCH($A73,'March-Feb'!$B:$B,0))),"") | E73: =IFERROR(IF(INDEX('April-March'!$F:$F,MATCH($A73,'April-March'!$B:$B,0))="","",INDEX('April-March'!$F:$F,MATCH($A73,'April-March'!$B:$B,0))),"") | F73: =IFERROR(IF(INDEX('May-April'!$F:$F,MATCH($A73,'May-April'!$B:$B,0))="","",INDEX('May-April'!$F:$F,MATCH($A73,'May-April'!$B:$B,0))),"") | G73: =IF('Jun''26'!F73="","",'Jun''26'!F73) -> 1314 | H73: =IFERROR(IF(INDEX('Jul''26'!$F:$F,MATCH($A73,'Jul''26'!$B:$B,0))="","",INDEX('Jul''26'!$F:$F,MATCH($A73,'Jul''26'!$B:$B,0))),"") -> -4 | I73: =SUM(B73:H73) -> 1310
A74: =IF('Jun''26'!B74="","",'Jun''26'!B74) -> Meals and Entertainment | B74: =IFERROR(IF(INDEX(Jan!$E:$E,MATCH(TRIM($A74),Jan!$B:$B,0))="","",INDEX(Jan!$E:$E,MATCH(TRIM($A74),Jan!$B:$B,0))),"") -> 605.17804 | C74: =IFERROR(IF(INDEX('March-Feb'!$I:$I,MATCH($A74,'March-Feb'!$B:$B,0))="","",INDEX('March-Feb'!$I:$I,MATCH($A74,'March-Feb'!$B:$B,0))),"") -> 1070 | D74: =IFERROR(IF(INDEX('March-Feb'!$E:$E,MATCH($A74,'March-Feb'!$B:$B,0))="","",INDEX('March-Feb'!$E:$E,MATCH($A74,'March-Feb'!$B:$B,0))),"") -> 152 | E74: =IFERROR(IF(INDEX('April-March'!$F:$F,MATCH($A74,'April-March'!$B:$B,0))="","",INDEX('April-March'!$F:$F,MATCH($A74,'April-March'!$B:$B,0))),"") -> 734 | F74: =IFERROR(IF(INDEX('May-April'!$F:$F,MATCH($A74,'May-April'!$B:$B,0))="","",INDEX('May-April'!$F:$F,MATCH($A74,'May-April'!$B:$B,0))),"") -> 318 | G74: =IF('Jun''26'!F74="","",'Jun''26'!F74) -> 3194 | H74: =IFERROR(IF(INDEX('Jul''26'!$F:$F,MATCH($A74,'Jul''26'!$B:$B,0))="","",INDEX('Jul''26'!$F:$F,MATCH($A74,'Jul''26'!$B:$B,0))),"") -> 1005 | I74: =SUM(B74:H74) -> 7078.178
A75: =IF('Jun''26'!B75="","",'Jun''26'!B75) -> VISA charges | B75: =IFERROR(IF(INDEX(Jan!$E:$E,MATCH(TRIM($A75),Jan!$B:$B,0))="","",INDEX(Jan!$E:$E,MATCH(TRIM($A75),Jan!$B:$B,0))),"") -> 0 | C75: =IFERROR(IF(INDEX('March-Feb'!$I:$I,MATCH($A75,'March-Feb'!$B:$B,0))="","",INDEX('March-Feb'!$I:$I,MATCH($A75,'March-Feb'!$B:$B,0))),"") | D75: =IFERROR(IF(INDEX('March-Feb'!$E:$E,MATCH($A75,'March-Feb'!$B:$B,0))="","",INDEX('March-Feb'!$E:$E,MATCH($A75,'March-Feb'!$B:$B,0))),"") | E75: =IFERROR(IF(INDEX('April-March'!$F:$F,MATCH($A75,'April-March'!$B:$B,0))="","",INDEX('April-March'!$F:$F,MATCH($A75,'April-March'!$B:$B,0))),"") | F75: =IFERROR(IF(INDEX('May-April'!$F:$F,MATCH($A75,'May-April'!$B:$B,0))="","",INDEX('May-April'!$F:$F,MATCH($A75,'May-April'!$B:$B,0))),"") | G75: =IF('Jun''26'!F75="","",'Jun''26'!F75) | H75: =IFERROR(IF(INDEX('Jul''26'!$F:$F,MATCH($A75,'Jul''26'!$B:$B,0))="","",INDEX('Jul''26'!$F:$F,MATCH($A75,'Jul''26'!$B:$B,0))),"") -> 0 | I75: =SUM(B75:H75) -> 0
A76: =IF('Jun''26'!B76="","",'Jun''26'!B76) -> Conference & Events | B76: =IFERROR(IF(INDEX(Jan!$E:$E,MATCH(TRIM($A76),Jan!$B:$B,0))="","",INDEX(Jan!$E:$E,MATCH(TRIM($A76),Jan!$B:$B,0))),"") | C76: =IFERROR(IF(INDEX('March-Feb'!$I:$I,MATCH($A76,'March-Feb'!$B:$B,0))="","",INDEX('March-Feb'!$I:$I,MATCH($A76,'March-Feb'!$B:$B,0))),"") | D76: =IFERROR(IF(INDEX('March-Feb'!$E:$E,MATCH($A76,'March-Feb'!$B:$B,0))="","",INDEX('March-Feb'!$E:$E,MATCH($A76,'March-Feb'!$B:$B,0))),"") | E76: =IFERROR(IF(INDEX('April-March'!$F:$F,MATCH($A76,'April-March'!$B:$B,0))="","",INDEX('April-March'!$F:$F,MATCH($A76,'April-March'!$B:$B,0))),"") | F76: =IFERROR(IF(INDEX('May-April'!$F:$F,MATCH($A76,'May-April'!$B:$B,0))="","",INDEX('May-April'!$F:$F,MATCH($A76,'May-April'!$B:$B,0))),"") | G76: =IF('Jun''26'!F76="","",'Jun''26'!F76) | H76: =IFERROR(IF(INDEX('Jul''26'!$F:$F,MATCH($A76,'Jul''26'!$B:$B,0))="","",INDEX('Jul''26'!$F:$F,MATCH($A76,'Jul''26'!$B:$B,0))),"") -> 0 | I76: =SUM(B76:H76) -> 0
A77: =IF('Jun''26'!B77="","",'Jun''26'!B77) -> Advertisement and marketing | B77: =IFERROR(IF(INDEX(Jan!$E:$E,MATCH(TRIM($A77),Jan!$B:$B,0))="","",INDEX(Jan!$E:$E,MATCH(TRIM($A77),Jan!$B:$B,0))),"") -> 0 | C77: =IFERROR(IF(INDEX('March-Feb'!$I:$I,MATCH($A77,'March-Feb'!$B:$B,0))="","",INDEX('March-Feb'!$I:$I,MATCH($A77,'March-Feb'!$B:$B,0))),"") | D77: =IFERROR(IF(INDEX('March-Feb'!$E:$E,MATCH($A77,'March-Feb'!$B:$B,0))="","",INDEX('March-Feb'!$E:$E,MATCH($A77,'March-Feb'!$B:$B,0))),"") | E77: =IFERROR(IF(INDEX('April-March'!$F:$F,MATCH($A77,'April-March'!$B:$B,0))="","",INDEX('April-March'!$F:$F,MATCH($A77,'April-March'!$B:$B,0))),"") | F77: =IFERROR(IF(INDEX('May-April'!$F:$F,MATCH($A77,'May-April'!$B:$B,0))="","",INDEX('May-April'!$F:$F,MATCH($A77,'May-April'!$B:$B,0))),"") | G77: =IF('Jun''26'!F77="","",'Jun''26'!F77) | H77: =IFERROR(IF(INDEX('Jul''26'!$F:$F,MATCH($A77,'Jul''26'!$B:$B,0))="","",INDEX('Jul''26'!$F:$F,MATCH($A77,'Jul''26'!$B:$B,0))),"") -> 0 | I77: =SUM(B77:H77) -> 0
A78: =IF('Jun''26'!B78="","",'Jun''26'!B78) -> Sales and marketing | B78: =IFERROR(IF(INDEX(Jan!$E:$E,MATCH(TRIM($A78),Jan!$B:$B,0))="","",INDEX(Jan!$E:$E,MATCH(TRIM($A78),Jan!$B:$B,0))),"") -> 1361.97 | C78: =IFERROR(IF(INDEX('March-Feb'!$I:$I,MATCH($A78,'March-Feb'!$B:$B,0))="","",INDEX('March-Feb'!$I:$I,MATCH($A78,'March-Feb'!$B:$B,0))),"") -> 1188 | D78: =IFERROR(IF(INDEX('March-Feb'!$E:$E,MATCH($A78,'March-Feb'!$B:$B,0))="","",INDEX('March-Feb'!$E:$E,MATCH($A78,'March-Feb'!$B:$B,0))),"") -> 1211 | E78: =IFERROR(IF(INDEX('April-March'!$F:$F,MATCH($A78,'April-March'!$B:$B,0))="","",INDEX('April-March'!$F:$F,MATCH($A78,'April-March'!$B:$B,0))),"") -> 128 | F78: =IFERROR(IF(INDEX('May-April'!$F:$F,MATCH($A78,'May-April'!$B:$B,0))="","",INDEX('May-April'!$F:$F,MATCH($A78,'May-April'!$B:$B,0))),"") -> 0 | G78: =IF('Jun''26'!F78="","",'Jun''26'!F78) -> 1083 | H78: =IFERROR(IF(INDEX('Jul''26'!$F:$F,MATCH($A78,'Jul''26'!$B:$B,0))="","",INDEX('Jul''26'!$F:$F,MATCH($A78,'Jul''26'!$B:$B,0))),"") -> 1346 | I78: =SUM(B78:H78) -> 6317.97
A79: =IF('Jun''26'!B79="","",'Jun''26'!B79) -> Business Promotion | B79: =IFERROR(IF(INDEX(Jan!$E:$E,MATCH(TRIM($A79),Jan!$B:$B,0))="","",INDEX(Jan!$E:$E,MATCH(TRIM($A79),Jan!$B:$B,0))),"") -> 0 | C79: =IFERROR(IF(INDEX('March-Feb'!$I:$I,MATCH($A79,'March-Feb'!$B:$B,0))="","",INDEX('March-Feb'!$I:$I,MATCH($A79,'March-Feb'!$B:$B,0))),"") | D79: =IFERROR(IF(INDEX('March-Feb'!$E:$E,MATCH($A79,'March-Feb'!$B:$B,0))="","",INDEX('March-Feb'!$E:$E,MATCH($A79,'March-Feb'!$B:$B,0))),"") | E79: =IFERROR(IF(INDEX('April-March'!$F:$F,MATCH($A79,'April-March'!$B:$B,0))="","",INDEX('April-March'!$F:$F,MATCH($A79,'April-March'!$B:$B,0))),"") | F79: =IFERROR(IF(INDEX('May-April'!$F:$F,MATCH($A79,'May-April'!$B:$B,0))="","",INDEX('May-April'!$F:$F,MATCH($A79,'May-April'!$B:$B,0))),"") | G79: =IF('Jun''26'!F79="","",'Jun''26'!F79) | H79: =IFERROR(IF(INDEX('Jul''26'!$F:$F,MATCH($A79,'Jul''26'!$B:$B,0))="","",INDEX('Jul''26'!$F:$F,MATCH($A79,'Jul''26'!$B:$B,0))),"") -> 0 | I79: =SUM(B79:H79) -> 0
A80: =IF('Jun''26'!B80="","",'Jun''26'!B80) -> S&M Salaries | B80: =IFERROR(IF(INDEX(Jan!$E:$E,MATCH(TRIM($A80),Jan!$B:$B,0))="","",INDEX(Jan!$E:$E,MATCH(TRIM($A80),Jan!$B:$B,0))),"") -> 1153.75 | C80: =IFERROR(IF(INDEX('March-Feb'!$I:$I,MATCH($A80,'March-Feb'!$B:$B,0))="","",INDEX('March-Feb'!$I:$I,MATCH($A80,'March-Feb'!$B:$B,0))),"") -> 1015 | D80: =IFERROR(IF(INDEX('March-Feb'!$E:$E,MATCH($A80,'March-Feb'!$B:$B,0))="","",INDEX('March-Feb'!$E:$E,MATCH($A80,'March-Feb'!$B:$B,0))),"") -> 1476 | E80: =IFERROR(IF(INDEX('April-March'!$F:$F,MATCH($A80,'April-March'!$B:$B,0))="","",INDEX('April-March'!$F:$F,MATCH($A80,'April-March'!$B:$B,0))),"") -> 1247 | F80: =IFERROR(IF(INDEX('May-April'!$F:$F,MATCH($A80,'May-April'!$B:$B,0))="","",INDEX('May-April'!$F:$F,MATCH($A80,'May-April'!$B:$B,0))),"") -> 1093 | G80: =IF('Jun''26'!F80="","",'Jun''26'!F80) -> 1090 | H80: =IFERROR(IF(INDEX('Jul''26'!$F:$F,MATCH($A80,'Jul''26'!$B:$B,0))="","",INDEX('Jul''26'!$F:$F,MATCH($A80,'Jul''26'!$B:$B,0))),"") -> 997 | I80: =SUM(B80:H80) -> 8071.75
... A98: =IF('Jun''26'!B98="","",'Jun''26'!B98) -> Coder | B98: =IFERROR(IF(INDEX(Jan!$E:$E,MATCH(TRIM($A98),Jan!$B:$B,0))="","",INDEX(Jan!$E:$E,MATCH(TRIM($A98),Jan!$B:$B,0))),"") -> 0 | C98: =IFERROR(IF(INDEX('March-Feb'!$I:$I,MATCH($A98,'March-Feb'!$B:$B,0))="","",INDEX('March-Feb'!$I:$I,MATCH($A98,'March-Feb'!$B:$B,0))),"") | D98: =IFERROR(IF(INDEX('March-Feb'!$E:$E,MATCH($A98,'March-Feb'!$B:$B,0))="","",INDEX('March-Feb'!$E:$E,MATCH($A98,'March-Feb'!$B:$B,0))),"") | E98: =IFERROR(IF(INDEX('April-March'!$F:$F,MATCH($A98,'April-March'!$B:$B,0))="","",INDEX('April-March'!$F:$F,MATCH($A98,'April-March'!$B:$B,0))),"") | F98: =IFERROR(IF(INDEX('May-April'!$F:$F,MATCH($A98,'May-April'!$B:$B,0))="","",INDEX('May-April'!$F:$F,MATCH($A98,'May-April'!$B:$B,0))),"") | G98: =IF('Jun''26'!F98="","",'Jun''26'!F98) | H98: =IFERROR(IF(INDEX('Jul''26'!$F:$F,MATCH($A98,'Jul''26'!$B:$B,0))="","",INDEX('Jul''26'!$F:$F,MATCH($A98,'Jul''26'!$B:$B,0))),"") -> 0 | I98: =SUM(B98:H98) -> 0
A99: =IF('Jun''26'!B99="","",'Jun''26'!B99) -> Gen & Admin Expenses | B99: =Jan!E26 -> 16548.773 | C99: =IFERROR(IF(INDEX('March-Feb'!$I:$I,MATCH($A99,'March-Feb'!$B:$B,0))="","",INDEX('March-Feb'!$I:$I,MATCH($A99,'March-Feb'!$B:$B,0))),"") -> 9435 | D99: =IFERROR(IF(INDEX('March-Feb'!$E:$E,MATCH($A99,'March-Feb'!$B:$B,0))="","",INDEX('March-Feb'!$E:$E,MATCH($A99,'March-Feb'!$B:$B,0))),"") -> 15990 | E99: =IFERROR(IF(INDEX('April-March'!$F:$F,MATCH($A99,'April-March'!$B:$B,0))="","",INDEX('April-March'!$F:$F,MATCH($A99,'April-March'!$B:$B,0))),"") -> 9176 | F99: =IFERROR(IF(INDEX('May-April'!$F:$F,MATCH($A99,'May-April'!$B:$B,0))="","",INDEX('May-April'!$F:$F,MATCH($A99,'May-April'!$B:$B,0))),"") -> 10040 | G99: =IF('Jun''26'!F99="","",'Jun''26'!F99) -> 13142 | H99: =IFERROR(IF(INDEX('Jul''26'!$F:$F,MATCH($A99,'Jul''26'!$B:$B,0))="","",INDEX('Jul''26'!$F:$F,MATCH($A99,'Jul''26'!$B:$B,0))),"") -> 19905 | I99: =SUM(B99:H99) -> 94236.773
A100: =IF('Jun''26'!B100="","",'Jun''26'!B100) -> Consultancy Fees | B100: =IFERROR(IF(INDEX(Jan!$E:$E,MATCH(TRIM($A100),Jan!$B:$B,0))="","",INDEX(Jan!$E:$E,MATCH(TRIM($A100),Jan!$B:$B,0))),"") -> 6383.42 | C100: =IFERROR(IF(INDEX('March-Feb'!$I:$I,MATCH($A100,'March-Feb'!$B:$B,0))="","",INDEX('March-Feb'!$I:$I,MATCH($A100,'March-Feb'!$B:$B,0))),"") | D100: =IFERROR(IF(INDEX('March-Feb'!$E:$E,MATCH($A100,'March-Feb'!$B:$B,0))="","",INDEX('March-Feb'!$E:$E,MATCH($A100,'March-Feb'!$B:$B,0))),"") | E100: =IFERROR(IF(INDEX('April-March'!$F:$F,MATCH($A100,'April-March'!$B:$B,0))="","",INDEX('April-March'!$F:$F,MATCH($A100,'April-March'!$B:$B,0))),"") | F100: =IFERROR(IF(INDEX('May-April'!$F:$F,MATCH($A100,'May-April'!$B:$B,0))="","",INDEX('May-April'!$F:$F,MATCH($A100,'May-April'!$B:$B,0))),"") | G100: =IF('Jun''26'!F100="","",'Jun''26'!F100) | H100: =IFERROR(IF(INDEX('Jul''26'!$F:$F,MATCH($A100,'Jul''26'!$B:$B,0))="","",INDEX('Jul''26'!$F:$F,MATCH($A100,'Jul''26'!$B:$B,0))),"") -> 0 | I100: =SUM(B100:H100) -> 6383.42
A101: =IF('Jun''26'!B101="","",'Jun''26'!B101) -> Comission Paid-Scinet Inc | B101: =IFERROR(IF(INDEX(Jan!$E:$E,MATCH(TRIM($A101),Jan!$B:$B,0))="","",INDEX(Jan!$E:$E,MATCH(TRIM($A101),Jan!$B:$B,0))),"") -> 0 | C101: =IFERROR(IF(INDEX('March-Feb'!$I:$I,MATCH($A101,'March-Feb'!$B:$B,0))="","",INDEX('March-Feb'!$I:$I,MATCH($A101,'March-Feb'!$B:$B,0))),"") | D101: =IFERROR(IF(INDEX('March-Feb'!$E:$E,MATCH($A101,'March-Feb'!$B:$B,0))="","",INDEX('March-Feb'!$E:$E,MATCH($A101,'March-Feb'!$B:$B,0))),"") | E101: =IFERROR(IF(INDEX('April-March'!$F:$F,MATCH($A101,'April-March'!$B:$B,0))="","",INDEX('April-March'!$F:$F,MATCH($A101,'April-March'!$B:$B,0))),"") | F101: =IFERROR(IF(INDEX('May-April'!$F:$F,MATCH($A101,'May-April'!$B:$B,0))="","",INDEX('May-April'!$F:$F,MATCH($A101,'May-April'!$B:$B,0))),"") | G101: =IF('Jun''26'!F101="","",'Jun''26'!F101) | H101: =IFERROR(IF(INDEX('Jul''26'!$F:$F,MATCH($A101,'Jul''26'!$B:$B,0))="","",INDEX('Jul''26'!$F:$F,MATCH($A101,'Jul''26'!$B:$B,0))),"") -> 0 | I101: =SUM(B101:H101) -> 0
A102: =IF('Jun''26'!B102="","",'Jun''26'!B102) -> Leadership engagemnet | B102: =IFERROR(IF(INDEX(Jan!$E:$E,MATCH(TRIM($A102),Jan!$B:$B,0))="","",INDEX(Jan!$E:$E,MATCH(TRIM($A102),Jan!$B:$B,0))),"") -> 0 | C102: =IFERROR(IF(INDEX('March-Feb'!$I:$I,MATCH($A102,'March-Feb'!$B:$B,0))="","",INDEX('March-Feb'!$I:$I,MATCH($A102,'March-Feb'!$B:$B,0))),"") | D102: =IFERROR(IF(INDEX('March-Feb'!$E:$E,MATCH($A102,'March-Feb'!$B:$B,0))="","",INDEX('March-Feb'!$E:$E,MATCH($A102,'March-Feb'!$B:$B,0))),"") | E102: =IFERROR(IF(INDEX('April-March'!$F:$F,MATCH($A102,'April-March'!$B:$B,0))="","",INDEX('April-March'!$F:$F,MATCH($A102,'April-March'!$B:$B,0))),"") | F102: =IFERROR(IF(INDEX('May-April'!$F:$F,MATCH($A102,'May-April'!$B:$B,0))="","",INDEX('May-April'!$F:$F,MATCH($A102,'May-April'!$B:$B,0))),"") | G102: =IF('Jun''26'!F102="","",'Jun''26'!F102) | H102: =IFERROR(IF(INDEX('Jul''26'!$F:$F,MATCH($A102,'Jul''26'!$B:$B,0))="","",INDEX('Jul''26'!$F:$F,MATCH($A102,'Jul''26'!$B:$B,0))),"") -> 0 | I102: =SUM(B102:H102) -> 0
A103: =IF('Jun''26'!B103="","",'Jun''26'!B103) -> Charitable Donations | B103: =IFERROR(IF(INDEX(Jan!$E:$E,MATCH(TRIM($A103),Jan!$B:$B,0))="","",INDEX(Jan!$E:$E,MATCH(TRIM($A103),Jan!$B:$B,0))),"") -> 0 | C103: =IFERROR(IF(INDEX('March-Feb'!$I:$I,MATCH($A103,'March-Feb'!$B:$B,0))="","",INDEX('March-Feb'!$I:$I,MATCH($A103,'March-Feb'!$B:$B,0))),"") | D103: =IFERROR(IF(INDEX('March-Feb'!$E:$E,MATCH($A103,'March-Feb'!$B:$B,0))="","",INDEX('March-Feb'!$E:$E,MATCH($A103,'March-Feb'!$B:$B,0))),"") | E103: =IFERROR(IF(INDEX('April-March'!$F:$F,MATCH($A103,'April-March'!$B:$B,0))="","",INDEX('April-March'!$F:$F,MATCH($A103,'April-March'!$B:$B,0))),"") | F103: =IFERROR(IF(INDEX('May-April'!$F:$F,MATCH($A103,'May-April'!$B:$B,0))="","",INDEX('May-April'!$F:$F,MATCH($A103,'May-April'!$B:$B,0))),"") | G103: =IF('Jun''26'!F103="","",'Jun''26'!F103) | H103: =IFERROR(IF(INDEX('Jul''26'!$F:$F,MATCH($A103,'Jul''26'!$B:$B,0))="","",INDEX('Jul''26'!$F:$F,MATCH($A103,'Jul''26'!$B:$B,0))),"") -> 0 | I103: =SUM(B103:H103) -> 0
A104: =IF('Jun''26'!B104="","",'Jun''26'!B104) -> Fuel/Mileage Expenses | B104: =IFERROR(IF(INDEX(Jan!$E:$E,MATCH(TRIM($A104),Jan!$B:$B,0))="","",INDEX(Jan!$E:$E,MATCH(TRIM($A104),Jan!$B:$B,0))),"") -> 132.06 | C104: =IFERROR(IF(INDEX('March-Feb'!$I:$I,MATCH($A104,'March-Feb'!$B:$B,0))="","",INDEX('March-Feb'!$I:$I,MATCH($A104,'March-Feb'!$B:$B,0))),"") -> 125 | D104: =IFERROR(IF(INDEX('March-Feb'!$E:$E,MATCH($A104,'March-Feb'!$B:$B,0))="","",INDEX('March-Feb'!$E:$E,MATCH($A104,'March-Feb'!$B:$B,0))),"") -> 97 | E104: =IFERROR(IF(INDEX('April-March'!$F:$F,MATCH($A104,'April-March'!$B:$B,0))="","",INDEX('April-March'!$F:$F,MATCH($A104,'April-March'!$B:$B,0))),"") -> 89 | F104: =IFERROR(IF(INDEX('May-April'!$F:$F,MATCH($A104,'May-April'!$B:$B,0))="","",INDEX('May-April'!$F:$F,MATCH($A104,'May-April'!$B:$B,0))),"") -> 0 | G104: =IF('Jun''26'!F104="","",'Jun''26'!F104) -> 0 | H104: =IFERROR(IF(INDEX('Jul''26'!$F:$F,MATCH($A104,'Jul''26'!$B:$B,0))="","",INDEX('Jul''26'!$F:$F,MATCH($A104,'Jul''26'!$B:$B,0))),"") -> 157 | I104: =SUM(B104:H104) -> 600.06
A105: =IF('Jun''26'!B105="","",'Jun''26'!B105) -> Payroll Processing Fees | B105: =IFERROR(IF(INDEX(Jan!$E:$E,MATCH(TRIM($A105),Jan!$B:$B,0))="","",INDEX(Jan!$E:$E,MATCH(TRIM($A105),Jan!$B:$B,0))),"") -> 962.65 | C105: =IFERROR(IF(INDEX('March-Feb'!$I:$I,MATCH($A105,'March-Feb'!$B:$B,0))="","",INDEX('March-Feb'!$I:$I,MATCH($A105,'March-Feb'!$B:$B,0))),"") -> 468 | D105: =IFERROR(IF(INDEX('March-Feb'!$E:$E,MATCH($A105,'March-Feb'!$B:$B,0))="","",INDEX('March-Feb'!$E:$E,MATCH($A105,'March-Feb'!$B:$B,0))),"") -> 608 | E105: =IFERROR(IF(INDEX('April-March'!$F:$F,MATCH($A105,'April-March'!$B:$B,0))="","",INDEX('April-March'!$F:$F,MATCH($A105,'April-March'!$B:$B,0))),"") -> 523 | F105: =IFERROR(IF(INDEX('May-April'!$F:$F,MATCH($A105,'May-April'!$B:$B,0))="","",INDEX('May-April'!$F:$F,MATCH($A105,'May-April'!$B:$B,0))),"") -> 537 | G105: =IF('Jun''26'!F105="","",'Jun''26'!F105) -> 528 | H105: =IFERROR(IF(INDEX('Jul''26'!$F:$F,MATCH($A105,'Jul''26'!$B:$B,0))="","",INDEX('Jul''26'!$F:$F,MATCH($A105,'Jul''26'!$B:$B,0))),"") -> 933 | I105: =SUM(B105:H105) -> 4559.65
A106: =IF('Jun''26'!B106="","",'Jun''26'!B106) -> Parking | B106: =IFERROR(IF(INDEX(Jan!$E:$E,MATCH(TRIM($A106),Jan!$B:$B,0))="","",INDEX(Jan!$E:$E,MATCH(TRIM($A106),Jan!$B:$B,0))),"") -> 0 | C106: =IFERROR(IF(INDEX('March-Feb'!$I:$I,MATCH($A106,'March-Feb'!$B:$B,0))="","",INDEX('March-Feb'!$I:$I,MATCH($A106,'March-Feb'!$B:$B,0))),"") | D106: =IFERROR(IF(INDEX('March-Feb'!$E:$E,MATCH($A106,'March-Feb'!$B:$B,0))="","",INDEX('March-Feb'!$E:$E,MATCH($A106,'March-Feb'!$B:$B,0))),"") | E106: =IFERROR(IF(INDEX('April-March'!$F:$F,MATCH($A106,'April-March'!$B:$B,0))="","",INDEX('April-March'!$F:$F,MATCH($A106,'April-March'!$B:$B,0))),"") | F106: =IFERROR(IF(INDEX('May-April'!$F:$F,MATCH($A106,'May-April'!$B:$B,0))="","",INDEX('May-April'!$F:$F,MATCH($A106,'May-April'!$B:$B,0))),"") | G106: =IF('Jun''26'!F106="","",'Jun''26'!F106) | H106: =IFERROR(IF(INDEX('Jul''26'!$F:$F,MATCH($A106,'Jul''26'!$B:$B,0))="","",INDEX('Jul''26'!$F:$F,MATCH($A106,'Jul''26'!$B:$B,0))),"") -> 58 | I106: =SUM(B106:H106) -> 58
A107: =IF('Jun''26'!B107="","",'Jun''26'!B107) -> Toll Fee | B107: =IFERROR(IF(INDEX(Jan!$E:$E,MATCH(TRIM($A107),Jan!$B:$B,0))="","",INDEX(Jan!$E:$E,MATCH(TRIM($A107),Jan!$B:$B,0))),"") -> 25 | C107: =IFERROR(IF(INDEX('March-Feb'!$I:$I,MATCH($A107,'March-Feb'!$B:$B,0))="","",INDEX('March-Feb'!$I:$I,MATCH($A107,'March-Feb'!$B:$B,0))),"") -> 25 | D107: =IFERROR(IF(INDEX('March-Feb'!$E:$E,MATCH($A107,'March-Feb'!$B:$B,0))="","",INDEX('March-Feb'!$E:$E,MATCH($A107,'March-Feb'!$B:$B,0))),"") -> 0 | E107: =IFERROR(IF(INDEX('April-March'!$F:$F,MATCH($A107,'April-March'!$B:$B,0))="","",INDEX('April-March'!$F:$F,MATCH($A107,'April-March'!$B:$B,0))),"") -> 25 | F107: =IFERROR(IF(INDEX('May-April'!$F:$F,MATCH($A107,'May-April'!$B:$B,0))="","",INDEX('May-April'!$F:$F,MATCH($A107,'May-April'!$B:$B,0))),"") -> 0 | G107: =IF('Jun''26'!F107="","",'Jun''26'!F107) -> 0 | H107: =IFERROR(IF(INDEX('Jul''26'!$F:$F,MATCH($A107,'Jul''26'!$B:$B,0))="","",INDEX('Jul''26'!$F:$F,MATCH($A107,'Jul''26'!$B:$B,0))),"") -> 75 | I107: =SUM(B107:H107) -> 150
A108: =IF('Jun''26'!B108="","",'Jun''26'!B108) -> Travelling Expenses | B108: =IFERROR(IF(INDEX(Jan!$E:$E,MATCH(TRIM($A108),Jan!$B:$B,0))="","",INDEX(Jan!$E:$E,MATCH(TRIM($A108),Jan!$B:$B,0))),"") -> 266.30554 | C108: =IFERROR(IF(INDEX('March-Feb'!$I:$I,MATCH($A108,'March-Feb'!$B:$B,0))="","",INDEX('March-Feb'!$I:$I,MATCH($A108,'March-Feb'!$B:$B,0))),"") -> 2658 | D108: =IFERROR(IF(INDEX('March-Feb'!$E:$E,MATCH($A108,'March-Feb'!$B:$B,0))="","",INDEX('March-Feb'!$E:$E,MATCH($A108,'March-Feb'!$B:$B,0))),"") -> 2571 | E108: =IFERROR(IF(INDEX('April-March'!$F:$F,MATCH($A108,'April-March'!$B:$B,0))="","",INDEX('April-March'!$F:$F,MATCH($A108,'April-March'!$B:$B,0))),"") -> 447 | F108: =IFERROR(IF(INDEX('May-April'!$F:$F,MATCH($A108,'May-April'!$B:$B,0))="","",INDEX('May-April'!$F:$F,MATCH($A108,'May-April'!$B:$B,0))),"") -> 162 | G108: =IF('Jun''26'!F108="","",'Jun''26'!F108) -> 428 | H108: =IFERROR(IF(INDEX('Jul''26'!$F:$F,MATCH($A108,'Jul''26'!$B:$B,0))="","",INDEX('Jul''26'!$F:$F,MATCH($A108,'Jul''26'!$B:$B,0))),"") -> 7427 | I108: =SUM(B108:H108) -> 13959.306
A109: =IF('Jun''26'!B109="","",'Jun''26'!B109) -> Insurance Expense | B109: =IFERROR(IF(INDEX(Jan!$E:$E,MATCH(TRIM($A109),Jan!$B:$B,0))="","",INDEX(Jan!$E:$E,MATCH(TRIM($A109),Jan!$B:$B,0))),"") -> 6727.8 | C109: =IFERROR(IF(INDEX('March-Feb'!$I:$I,MATCH($A109,'March-Feb'!$B:$B,0))="","",INDEX('March-Feb'!$I:$I,MATCH($A109,'March-Feb'!$B:$B,0))),"") -> 4338 | D109: =IFERROR(IF(INDEX('March-Feb'!$E:$E,MATCH($A109,'March-Feb'!$B:$B,0))="","",INDEX('March-Feb'!$E:$E,MATCH($A109,'March-Feb'!$B:$B,0))),"") -> 10409 | E109: =IFERROR(IF(INDEX('April-March'!$F:$F,MATCH($A109,'April-March'!$B:$B,0))="","",INDEX('April-March'!$F:$F,MATCH($A109,'April-March'!$B:$B,0))),"") -> 3781 | F109: =IFERROR(IF(INDEX('May-April'!$F:$F,MATCH($A109,'May-April'!$B:$B,0))="","",INDEX('May-April'!$F:$F,MATCH($A109,'May-April'!$B:$B,0))),"") -> 6181 | G109: =IF('Jun''26'!F109="","",'Jun''26'!F109) -> 6154 | H109: =IFERROR(IF(INDEX('Jul''26'!$F:$F,MATCH($A109,'Jul''26'!$B:$B,0))="","",INDEX('Jul''26'!$F:$F,MATCH($A109,'Jul''26'!$B:$B,0))),"") -> 5846 | I109: =SUM(B109:H109) -> 43436.8
A110: =IF('Jun''26'!B110="","",'Jun''26'!B110) -> Postage | B110: =IFERROR(IF(INDEX(Jan!$E:$E,MATCH(TRIM($A110),Jan!$B:$B,0))="","",INDEX(Jan!$E:$E,MATCH(TRIM($A110),Jan!$B:$B,0))),"") -> 14.99 | C110: =IFERROR(IF(INDEX('March-Feb'!$I:$I,MATCH($A110,'March-Feb'!$B:$B,0))="","",INDEX('March-Feb'!$I:$I,MATCH($A110,'March-Feb'!$B:$B,0))),"") -> 15 | D110: =IFERROR(IF(INDEX('March-Feb'!$E:$E,MATCH($A110,'March-Feb'!$B:$B,0))="","",INDEX('March-Feb'!$E:$E,MATCH($A110,'March-Feb'!$B:$B,0))),"") -> 15 | E110: =IFERROR(IF(INDEX('April-March'!$F:$F,MATCH($A110,'April-March'!$B:$B,0))="","",INDEX('April-March'!$F:$F,MATCH($A110,'April-March'!$B:$B,0))),"") -> 0 | F110: =IFERROR(IF(INDEX('May-April'!$F:$F,MATCH($A110,'May-April'!$B:$B,0))="","",INDEX('May-April'!$F:$F,MATCH($A110,'May-April'!$B:$B,0))),"") -> 0 | G110: =IF('Jun''26'!F110="","",'Jun''26'!F110) -> 0 | H110: =IFERROR(IF(INDEX('Jul''26'!$F:$F,MATCH($A110,'Jul''26'!$B:$B,0))="","",INDEX('Jul''26'!$F:$F,MATCH($A110,'Jul''26'!$B:$B,0))),"") -> 0 | I110: =SUM(B110:H110) -> 44.99
A111: =IF('Jun''26'!B111="","",'Jun''26'!B111) -> Printing and stationery | B111: =IFERROR(IF(INDEX(Jan!$E:$E,MATCH(TRIM($A111),Jan!$B:$B,0))="","",INDEX(Jan!$E:$E,MATCH(TRIM($A111),Jan!$B:$B,0))),"") -> 0 | C111: =IFERROR(IF(INDEX('March-Feb'!$I:$I,MATCH($A111,'March-Feb'!$B:$B,0))="","",INDEX('March-Feb'!$I:$I,MATCH($A111,'March-Feb'!$B:$B,0))),"") -> 12 | D111: =IFERROR(IF(INDEX('March-Feb'!$E:$E,MATCH($A111,'March-Feb'!$B:$B,0))="","",INDEX('March-Feb'!$E:$E,MATCH($A111,'March-Feb'!$B:$B,0))),"") -> 0 | E111: =IFERROR(IF(INDEX('April-March'!$F:$F,MATCH($A111,'April-March'!$B:$B,0))="","",INDEX('April-March'!$F:$F,MATCH($A111,'April-March'!$B:$B,0))),"") -> 0 | F111: =IFERROR(IF(INDEX('May-April'!$F:$F,MATCH($A111,'May-April'!$B:$B,0))="","",INDEX('May-April'!$F:$F,MATCH($A111,'May-April'!$B:$B,0))),"") -> 0 | G111: =IF('Jun''26'!F111="","",'Jun''26'!F111) -> 0 | H111: =IFERROR(IF(INDEX('Jul''26'!$F:$F,MATCH($A111,'Jul''26'!$B:$B,0))="","",INDEX('Jul''26'!$F:$F,MATCH($A111,'Jul''26'!$B:$B,0))),"") -> 0 | I111: =SUM(B111:H111) -> 12
... A134: =IF('Jun''26'!B134="","",'Jun''26'!B134) -> EBITDA | B134: =IFERROR(IF(INDEX(Jan!$E:$E,MATCH(TRIM($A134),Jan!$B:$B,0))="","",INDEX(Jan!$E:$E,MATCH(TRIM($A134),Jan!$B:$B,0))),"") -> -26213.63 | C134: =IFERROR(IF(INDEX('March-Feb'!$I:$I,MATCH($A134,'March-Feb'!$B:$B,0))="","",INDEX('March-Feb'!$I:$I,MATCH($A134,'March-Feb'!$B:$B,0))),"") -> -4632 | D134: =IFERROR(IF(INDEX('March-Feb'!$E:$E,MATCH($A134,'March-Feb'!$B:$B,0))="","",INDEX('March-Feb'!$E:$E,MATCH($A134,'March-Feb'!$B:$B,0))),"") -> -26714 | E134: =IFERROR(IF(INDEX('April-March'!$F:$F,MATCH($A134,'April-March'!$B:$B,0))="","",INDEX('April-March'!$F:$F,MATCH($A134,'April-March'!$B:$B,0))),"") -> -13135 | F134: =IFERROR(IF(INDEX('May-April'!$F:$F,MATCH($A134,'May-April'!$B:$B,0))="","",INDEX('May-April'!$F:$F,MATCH($A134,'May-April'!$B:$B,0))),"") -> 18423 | G134: =IF('Jun''26'!F134="","",'Jun''26'!F134) -> 24852 | H134: =IFERROR(IF(INDEX('Jul''26'!$F:$F,MATCH($A134,'Jul''26'!$B:$B,0))="","",INDEX('Jul''26'!$F:$F,MATCH($A134,'Jul''26'!$B:$B,0))),"") -> 31686 | I134: =SUM(B134:H134) -> 4266.3699
A135: =IF('Jun''26'!B135="","",'Jun''26'!B135) -> EBITDA% | B135: =IFERROR(B$134/B$15,"") -> -0.11557325 | C135: =IFERROR(C$134/C$15,"") -> -0.020336215 | D135: =IFERROR(D$134/D$15,"") -> -0.12076035 | E135: =IFERROR(E$134/E$15,"") -> -0.067287546 | F135: =IFERROR(F$134/F$15,"") -> 0.087762841 | G135: =IFERROR(G$134/G$15,"") -> 0.10697728 | H135: =IFERROR(H$134/H$15,"") -> 0.12640423 | I135: =SUM(B135:H135) -> -0.0028130018
A136: =IF('Jun''26'!B136="","",'Jun''26'!B136) | B136: =IFERROR(IF(INDEX(Jan!$E:$E,MATCH(TRIM($A136),Jan!$B:$B,0))="","",INDEX(Jan!$E:$E,MATCH(TRIM($A136),Jan!$B:$B,0))),"") | C136: =IFERROR(IF(INDEX('March-Feb'!$I:$I,MATCH($A136,'March-Feb'!$B:$B,0))="","",INDEX('March-Feb'!$I:$I,MATCH($A136,'March-Feb'!$B:$B,0))),"") | D136: =IFERROR(IF(INDEX('March-Feb'!$E:$E,MATCH($A136,'March-Feb'!$B:$B,0))="","",INDEX('March-Feb'!$E:$E,MATCH($A136,'March-Feb'!$B:$B,0))),"") | E136: =IFERROR(IF(INDEX('April-March'!$F:$F,MATCH($A136,'April-March'!$B:$B,0))="","",INDEX('April-March'!$F:$F,MATCH($A136,'April-March'!$B:$B,0))),"") | F136: =IFERROR(IF(INDEX('May-April'!$F:$F,MATCH($A136,'May-April'!$B:$B,0))="","",INDEX('May-April'!$F:$F,MATCH($A136,'May-April'!$B:$B,0))),"") | G136: =IF('Jun''26'!F136="","",'Jun''26'!F136) | H136: =IFERROR(IF(INDEX('Jul''26'!$F:$F,MATCH($A136,'Jul''26'!$B:$B,0))="","",INDEX('Jul''26'!$F:$F,MATCH($A136,'Jul''26'!$B:$B,0))),"") | I136: =SUM(B136:H136) -> 0
A137: =IF('Jun''26'!B137="","",'Jun''26'!B137) -> Finance Cost | B137: =IFERROR(IF(INDEX(Jan!$E:$E,MATCH(TRIM($A137),Jan!$B:$B,0))="","",INDEX(Jan!$E:$E,MATCH(TRIM($A137),Jan!$B:$B,0))),"") -> -1342.3096 | C137: =IFERROR(IF(INDEX('March-Feb'!$I:$I,MATCH($A137,'March-Feb'!$B:$B,0))="","",INDEX('March-Feb'!$I:$I,MATCH($A137,'March-Feb'!$B:$B,0))),"") -> -1027 | D137: =IFERROR(IF(INDEX('March-Feb'!$E:$E,MATCH($A137,'March-Feb'!$B:$B,0))="","",INDEX('March-Feb'!$E:$E,MATCH($A137,'March-Feb'!$B:$B,0))),"") -> -5973 | E137: =IFERROR(IF(INDEX('April-March'!$F:$F,MATCH($A137,'April-March'!$B:$B,0))="","",INDEX('April-March'!$F:$F,MATCH($A137,'April-March'!$B:$B,0))),"") -> -622 | F137: =IFERROR(IF(INDEX('May-April'!$F:$F,MATCH($A137,'May-April'!$B:$B,0))="","",INDEX('May-April'!$F:$F,MATCH($A137,'May-April'!$B:$B,0))),"") -> -3671 | G137: =IF('Jun''26'!F137="","",'Jun''26'!F137) -> -1067 | H137: =IFERROR(IF(INDEX('Jul''26'!$F:$F,MATCH($A137,'Jul''26'!$B:$B,0))="","",INDEX('Jul''26'!$F:$F,MATCH($A137,'Jul''26'!$B:$B,0))),"") -> -1328 | I137: =SUM(B137:H137) -> -15030.31
A138: =IF('Jun''26'!B138="","",'Jun''26'!B138) -> Bank Fees and Charges | B138: =IFERROR(IF(INDEX(Jan!$E:$E,MATCH(TRIM($A138),Jan!$B:$B,0))="","",INDEX(Jan!$E:$E,MATCH(TRIM($A138),Jan!$B:$B,0))),"") -> 6 | C138: =IFERROR(IF(INDEX('March-Feb'!$I:$I,MATCH($A138,'March-Feb'!$B:$B,0))="","",INDEX('March-Feb'!$I:$I,MATCH($A138,'March-Feb'!$B:$B,0))),"") | D138: =IFERROR(IF(INDEX('March-Feb'!$E:$E,MATCH($A138,'March-Feb'!$B:$B,0))="","",INDEX('March-Feb'!$E:$E,MATCH($A138,'March-Feb'!$B:$B,0))),"") | E138: =IFERROR(IF(INDEX('April-March'!$F:$F,MATCH($A138,'April-March'!$B:$B,0))="","",INDEX('April-March'!$F:$F,MATCH($A138,'April-March'!$B:$B,0))),"") | F138: =IFERROR(IF(INDEX('May-April'!$F:$F,MATCH($A138,'May-April'!$B:$B,0))="","",INDEX('May-April'!$F:$F,MATCH($A138,'May-April'!$B:$B,0))),"") | G138: =IF('Jun''26'!F138="","",'Jun''26'!F138) | H138: =IFERROR(IF(INDEX('Jul''26'!$F:$F,MATCH($A138,'Jul''26'!$B:$B,0))="","",INDEX('Jul''26'!$F:$F,MATCH($A138,'Jul''26'!$B:$B,0))),"") -> 0 | I138: =SUM(B138:H138) -> 6
A139: =IF('Jun''26'!B139="","",'Jun''26'!B139) -> Bank Charges | B139: =IFERROR(IF(INDEX(Jan!$E:$E,MATCH(TRIM($A139),Jan!$B:$B,0))="","",INDEX(Jan!$E:$E,MATCH(TRIM($A139),Jan!$B:$B,0))),"") -> 14.35087 | C139: =IFERROR(IF(INDEX('March-Feb'!$I:$I,MATCH($A139,'March-Feb'!$B:$B,0))="","",INDEX('March-Feb'!$I:$I,MATCH($A139,'March-Feb'!$B:$B,0))),"") -> 1096 | D139: =IFERROR(IF(INDEX('March-Feb'!$E:$E,MATCH($A139,'March-Feb'!$B:$B,0))="","",INDEX('March-Feb'!$E:$E,MATCH($A139,'March-Feb'!$B:$B,0))),"") -> 8 | E139: =IFERROR(IF(INDEX('April-March'!$F:$F,MATCH($A139,'April-March'!$B:$B,0))="","",INDEX('April-March'!$F:$F,MATCH($A139,'April-March'!$B:$B,0))),"") -> 107 | F139: =IFERROR(IF(INDEX('May-April'!$F:$F,MATCH($A139,'May-April'!$B:$B,0))="","",INDEX('May-April'!$F:$F,MATCH($A139,'May-April'!$B:$B,0))),"") -> 23 | G139: =IF('Jun''26'!F139="","",'Jun''26'!F139) -> 116 | H139: =IFERROR(IF(INDEX('Jul''26'!$F:$F,MATCH($A139,'Jul''26'!$B:$B,0))="","",INDEX('Jul''26'!$F:$F,MATCH($A139,'Jul''26'!$B:$B,0))),"") -> 626 | I139: =SUM(B139:H139) -> 1990.3509
A140: =IF('Jun''26'!B140="","",'Jun''26'!B140) -> Exchange Gain or Loss | B140: =IFERROR(IF(INDEX(Jan!$E:$E,MATCH(TRIM($A140),Jan!$B:$B,0))="","",INDEX(Jan!$E:$E,MATCH(TRIM($A140),Jan!$B:$B,0))),"") -> -6246.1804 | C140: =IFERROR(IF(INDEX('March-Feb'!$I:$I,MATCH($A140,'March-Feb'!$B:$B,0))="","",INDEX('March-Feb'!$I:$I,MATCH($A140,'March-Feb'!$B:$B,0))),"") -> -4642 | D140: =IFERROR(IF(INDEX('March-Feb'!$E:$E,MATCH($A140,'March-Feb'!$B:$B,0))="","",INDEX('March-Feb'!$E:$E,MATCH($A140,'March-Feb'!$B:$B,0))),"") -> -8482 | E140: =IFERROR(IF(INDEX('April-March'!$F:$F,MATCH($A140,'April-March'!$B:$B,0))="","",INDEX('April-March'!$F:$F,MATCH($A140,'April-March'!$B:$B,0))),"") -> -4176 | F140: =IFERROR(IF(INDEX('May-April'!$F:$F,MATCH($A140,'May-April'!$B:$B,0))="","",INDEX('May-April'!$F:$F,MATCH($A140,'May-April'!$B:$B,0))),"") -> -7054 | G140: =IF('Jun''26'!F140="","",'Jun''26'!F140) -> -4493 | H140: =IFERROR(IF(INDEX('Jul''26'!$F:$F,MATCH($A140,'Jul''26'!$B:$B,0))="","",INDEX('Jul''26'!$F:$F,MATCH($A140,'Jul''26'!$B:$B,0))),"") -> -5282 | I140: =SUM(B140:H140) -> -40375.18
A141: =IF('Jun''26'!B141="","",'Jun''26'!B141) -> Amex card charges | B141: =IFERROR(IF(INDEX(Jan!$E:$E,MATCH(TRIM($A141),Jan!$B:$B,0))="","",INDEX(Jan!$E:$E,MATCH(TRIM($A141),Jan!$B:$B,0))),"") -> 0 | C141: =IFERROR(IF(INDEX('March-Feb'!$I:$I,MATCH($A141,'March-Feb'!$B:$B,0))="","",INDEX('March-Feb'!$I:$I,MATCH($A141,'March-Feb'!$B:$B,0))),"") | D141: =IFERROR(IF(INDEX('March-Feb'!$E:$E,MATCH($A141,'March-Feb'!$B:$B,0))="","",INDEX('March-Feb'!$E:$E,MATCH($A141,'March-Feb'!$B:$B,0))),"") | E141: =IFERROR(IF(INDEX('April-March'!$F:$F,MATCH($A141,'April-March'!$B:$B,0))="","",INDEX('April-March'!$F:$F,MATCH($A141,'April-March'!$B:$B,0))),"") | F141: =IFERROR(IF(INDEX('May-April'!$F:$F,MATCH($A141,'May-April'!$B:$B,0))="","",INDEX('May-April'!$F:$F,MATCH($A141,'May-April'!$B:$B,0))),"") | G141: =IF('Jun''26'!F141="","",'Jun''26'!F141) | H141: =IFERROR(IF(INDEX('Jul''26'!$F:$F,MATCH($A141,'Jul''26'!$B:$B,0))="","",INDEX('Jul''26'!$F:$F,MATCH($A141,'Jul''26'!$B:$B,0))),"") -> 0 | I141: =SUM(B141:H141) -> 0
A142: =IF('Jun''26'!B142="","",'Jun''26'!B142) -> Interest on Car loan | B142: =IFERROR(IF(INDEX(Jan!$E:$E,MATCH(TRIM($A142),Jan!$B:$B,0))="","",INDEX(Jan!$E:$E,MATCH(TRIM($A142),Jan!$B:$B,0))),"") -> 162.72 | C142: =IFERROR(IF(INDEX('March-Feb'!$I:$I,MATCH($A142,'March-Feb'!$B:$B,0))="","",INDEX('March-Feb'!$I:$I,MATCH($A142,'March-Feb'!$B:$B,0))),"") -> 159 | D142: =IFERROR(IF(INDEX('March-Feb'!$E:$E,MATCH($A142,'March-Feb'!$B:$B,0))="","",INDEX('March-Feb'!$E:$E,MATCH($A142,'March-Feb'!$B:$B,0))),"") -> 140 | E142: =IFERROR(IF(INDEX('April-March'!$F:$F,MATCH($A142,'April-March'!$B:$B,0))="","",INDEX('April-March'!$F:$F,MATCH($A142,'April-March'!$B:$B,0))),"") -> 139 | F142: =IFERROR(IF(INDEX('May-April'!$F:$F,MATCH($A142,'May-April'!$B:$B,0))="","",INDEX('May-April'!$F:$F,MATCH($A142,'May-April'!$B:$B,0))),"") -> 147 | G142: =IF('Jun''26'!F142="","",'Jun''26'!F142) -> 139 | H142: =IFERROR(IF(INDEX('Jul''26'!$F:$F,MATCH($A142,'Jul''26'!$B:$B,0))="","",INDEX('Jul''26'!$F:$F,MATCH($A142,'Jul''26'!$B:$B,0))),"") -> 122 | I142: =SUM(B142:H142) -> 1008.72
A143: =IF('Jun''26'!B143="","",'Jun''26'!B143) -> Forex gain/loss | B143: =IFERROR(IF(INDEX(Jan!$E:$E,MATCH(TRIM($A143),Jan!$B:$B,0))="","",INDEX(Jan!$E:$E,MATCH(TRIM($A143),Jan!$B:$B,0))),"") | C143: =IFERROR(IF(INDEX('March-Feb'!$I:$I,MATCH($A143,'March-Feb'!$B:$B,0))="","",INDEX('March-Feb'!$I:$I,MATCH($A143,'March-Feb'!$B:$B,0))),"") | D143: =IFERROR(IF(INDEX('March-Feb'!$E:$E,MATCH($A143,'March-Feb'!$B:$B,0))="","",INDEX('March-Feb'!$E:$E,MATCH($A143,'March-Feb'!$B:$B,0))),"") | E143: =IFERROR(IF(INDEX('April-March'!$F:$F,MATCH($A143,'April-March'!$B:$B,0))="","",INDEX('April-March'!$F:$F,MATCH($A143,'April-March'!$B:$B,0))),"") | F143: =IFERROR(IF(INDEX('May-April'!$F:$F,MATCH($A143,'May-April'!$B:$B,0))="","",INDEX('May-April'!$F:$F,MATCH($A143,'May-April'!$B:$B,0))),"") | G143: =IF('Jun''26'!F143="","",'Jun''26'!F143) | H143: =IFERROR(IF(INDEX('Jul''26'!$F:$F,MATCH($A143,'Jul''26'!$B:$B,0))="","",INDEX('Jul''26'!$F:$F,MATCH($A143,'Jul''26'!$B:$B,0))),"") -> 0 | I143: =SUM(B143:H143) -> 0
A144: =IF('Jun''26'!B144="","",'Jun''26'!B144) -> Interest Paid | B144: =IFERROR(IF(INDEX(Jan!$E:$E,MATCH(TRIM($A144),Jan!$B:$B,0))="","",INDEX(Jan!$E:$E,MATCH(TRIM($A144),Jan!$B:$B,0))),"") -> 4720.8 | C144: =IFERROR(IF(INDEX('March-Feb'!$I:$I,MATCH($A144,'March-Feb'!$B:$B,0))="","",INDEX('March-Feb'!$I:$I,MATCH($A144,'March-Feb'!$B:$B,0))),"") -> 2360 | D144: =IFERROR(IF(INDEX('March-Feb'!$E:$E,MATCH($A144,'March-Feb'!$B:$B,0))="","",INDEX('March-Feb'!$E:$E,MATCH($A144,'March-Feb'!$B:$B,0))),"") -> 2360 | E144: =IFERROR(IF(INDEX('April-March'!$F:$F,MATCH($A144,'April-March'!$B:$B,0))="","",INDEX('April-March'!$F:$F,MATCH($A144,'April-March'!$B:$B,0))),"") -> 2360 | F144: =IFERROR(IF(INDEX('May-April'!$F:$F,MATCH($A144,'May-April'!$B:$B,0))="","",INDEX('May-April'!$F:$F,MATCH($A144,'May-April'!$B:$B,0))),"") -> 2360 | G144: =IF('Jun''26'!F144="","",'Jun''26'!F144) -> 2360 | H144: =IFERROR(IF(INDEX('Jul''26'!$F:$F,MATCH($A144,'Jul''26'!$B:$B,0))="","",INDEX('Jul''26'!$F:$F,MATCH($A144,'Jul''26'!$B:$B,0))),"") -> 2360 | I144: =SUM(B144:H144) -> 18880.8
A145: =IF('Jun''26'!B145="","",'Jun''26'!B145) -> Interest on OD | B145: =IFERROR(IF(INDEX(Jan!$E:$E,MATCH(TRIM($A145),Jan!$B:$B,0))="","",INDEX(Jan!$E:$E,MATCH(TRIM($A145),Jan!$B:$B,0))),"") -> 638.68478 | C145: =IFERROR(IF(INDEX('March-Feb'!$I:$I,MATCH($A145,'March-Feb'!$B:$B,0))="","",INDEX('March-Feb'!$I:$I,MATCH($A145,'March-Feb'!$B:$B,0))),"") -> 746 | D145: =IFERROR(IF(INDEX('March-Feb'!$E:$E,MATCH($A145,'March-Feb'!$B:$B,0))="","",INDEX('March-Feb'!$E:$E,MATCH($A145,'March-Feb'!$B:$B,0))),"") -> 1417 | E145: =IFERROR(IF(INDEX('April-March'!$F:$F,MATCH($A145,'April-March'!$B:$B,0))="","",INDEX('April-March'!$F:$F,MATCH($A145,'April-March'!$B:$B,0))),"") -> 949 | F145: =IFERROR(IF(INDEX('May-April'!$F:$F,MATCH($A145,'May-April'!$B:$B,0))="","",INDEX('May-April'!$F:$F,MATCH($A145,'May-April'!$B:$B,0))),"") -> 853 | G145: =IF('Jun''26'!F145="","",'Jun''26'!F145) -> 811 | H145: =IFERROR(IF(INDEX('Jul''26'!$F:$F,MATCH($A145,'Jul''26'!$B:$B,0))="","",INDEX('Jul''26'!$F:$F,MATCH($A145,'Jul''26'!$B:$B,0))),"") -> 846 | I145: =SUM(B145:H145) -> 6260.6848
A146: =IF('Jun''26'!B146="","",'Jun''26'!B146) -> Rates & Taxes | B146: =IFERROR(IF(INDEX(Jan!$E:$E,MATCH(TRIM($A146),Jan!$B:$B,0))="","",INDEX(Jan!$E:$E,MATCH(TRIM($A146),Jan!$B:$B,0))),"") -> 0 | C146: =IFERROR(IF(INDEX('March-Feb'!$I:$I,MATCH($A146,'March-Feb'!$B:$B,0))="","",INDEX('March-Feb'!$I:$I,MATCH($A146,'March-Feb'!$B:$B,0))),"") -> 0 | D146: =IFERROR(IF(INDEX('March-Feb'!$E:$E,MATCH($A146,'March-Feb'!$B:$B,0))="","",INDEX('March-Feb'!$E:$E,MATCH($A146,'March-Feb'!$B:$B,0))),"") -> 517 | E146: =IFERROR(IF(INDEX('April-March'!$F:$F,MATCH($A146,'April-March'!$B:$B,0))="","",INDEX('April-March'!$F:$F,MATCH($A146,'April-March'!$B:$B,0))),"") -> 709 | F146: =IFERROR(IF(INDEX('May-April'!$F:$F,MATCH($A146,'May-April'!$B:$B,0))="","",INDEX('May-April'!$F:$F,MATCH($A146,'May-April'!$B:$B,0))),"") -> 0 | G146: =IF('Jun''26'!F146="","",'Jun''26'!F146) -> 1 | H146: =IFERROR(IF(INDEX('Jul''26'!$F:$F,MATCH($A146,'Jul''26'!$B:$B,0))="","",INDEX('Jul''26'!$F:$F,MATCH($A146,'Jul''26'!$B:$B,0))),"") -> 2 | I146: =SUM(B146:H146) -> 1229
A147: =IF('Jun''26'!B147="","",'Jun''26'!B147) -> Rates & Taxes | B147: =IFERROR(IF(INDEX(Jan!$E:$E,MATCH(TRIM($A147),Jan!$B:$B,0))="","",INDEX(Jan!$E:$E,MATCH(TRIM($A147),Jan!$B:$B,0))),"") -> 0 | C147: =IFERROR(IF(INDEX('March-Feb'!$I:$I,MATCH($A147,'March-Feb'!$B:$B,0))="","",INDEX('March-Feb'!$I:$I,MATCH($A147,'March-Feb'!$B:$B,0))),"") | D147: =IFERROR(IF(INDEX('March-Feb'!$E:$E,MATCH($A147,'March-Feb'!$B:$B,0))="","",INDEX('March-Feb'!$E:$E,MATCH($A147,'March-Feb'!$B:$B,0))),"") -> 517 | E147: =IFERROR(IF(INDEX('April-March'!$F:$F,MATCH($A147,'April-March'!$B:$B,0))="","",INDEX('April-March'!$F:$F,MATCH($A147,'April-March'!$B:$B,0))),"") -> 709 | F147: =IFERROR(IF(INDEX('May-April'!$F:$F,MATCH($A147,'May-April'!$B:$B,0))="","",INDEX('May-April'!$F:$F,MATCH($A147,'May-April'!$B:$B,0))),"") -> 0 | G147: =IF('Jun''26'!F147="","",'Jun''26'!F147) -> 1 | H147: =IFERROR(IF(INDEX('Jul''26'!$F:$F,MATCH($A147,'Jul''26'!$B:$B,0))="","",INDEX('Jul''26'!$F:$F,MATCH($A147,'Jul''26'!$B:$B,0))),"") -> 2 | I147: =SUM(B147:H147) -> 1229
... A151: =IF('Jun''26'!B151="","",'Jun''26'!B151) -> Depreciation | B151: =IFERROR(IF(INDEX(Jan!$E:$E,MATCH(TRIM($A151),Jan!$B:$B,0))="","",INDEX(Jan!$E:$E,MATCH(TRIM($A151),Jan!$B:$B,0))),"") -> 0 | C151: =IFERROR(IF(INDEX('March-Feb'!$I:$I,MATCH($A151,'March-Feb'!$B:$B,0))="","",INDEX('March-Feb'!$I:$I,MATCH($A151,'March-Feb'!$B:$B,0))),"") | D151: =IFERROR(IF(INDEX('March-Feb'!$E:$E,MATCH($A151,'March-Feb'!$B:$B,0))="","",INDEX('March-Feb'!$E:$E,MATCH($A151,'March-Feb'!$B:$B,0))),"") | E151: =IFERROR(IF(INDEX('April-March'!$F:$F,MATCH($A151,'April-March'!$B:$B,0))="","",INDEX('April-March'!$F:$F,MATCH($A151,'April-March'!$B:$B,0))),"") | F151: =IFERROR(IF(INDEX('May-April'!$F:$F,MATCH($A151,'May-April'!$B:$B,0))="","",INDEX('May-April'!$F:$F,MATCH($A151,'May-April'!$B:$B,0))),"") -> -61 | G151: =IF('Jun''26'!F151="","",'Jun''26'!F151) -> -24 | H151: =IFERROR(IF(INDEX('Jul''26'!$F:$F,MATCH($A151,'Jul''26'!$B:$B,0))="","",INDEX('Jul''26'!$F:$F,MATCH($A151,'Jul''26'!$B:$B,0))),"") -> -31 | I151: =SUM(B151:H151) -> -116
A152: =IF('Jun''26'!B152="","",'Jun''26'!B152) -> Total Cost | B152: =Jan!E37 -> -1342.3096 | C152: =IFERROR(IF(INDEX('March-Feb'!$I:$I,MATCH($A152,'March-Feb'!$B:$B,0))="","",INDEX('March-Feb'!$I:$I,MATCH($A152,'March-Feb'!$B:$B,0))),"") -> -1027 | D152: =IFERROR(IF(INDEX('March-Feb'!$E:$E,MATCH($A152,'March-Feb'!$B:$B,0))="","",INDEX('March-Feb'!$E:$E,MATCH($A152,'March-Feb'!$B:$B,0))),"") -> -5457 | E152: =IFERROR(IF(INDEX('April-March'!$F:$F,MATCH($A152,'April-March'!$B:$B,0))="","",INDEX('April-March'!$F:$F,MATCH($A152,'April-March'!$B:$B,0))),"") -> 87 | F152: =IFERROR(IF(INDEX('May-April'!$F:$F,MATCH($A152,'May-April'!$B:$B,0))="","",INDEX('May-April'!$F:$F,MATCH($A152,'May-April'!$B:$B,0))),"") -> -3732 | G152: =IF('Jun''26'!F152="","",'Jun''26'!F152) -> -1090 | H152: =IFERROR(IF(INDEX('Jul''26'!$F:$F,MATCH($A152,'Jul''26'!$B:$B,0))="","",INDEX('Jul''26'!$F:$F,MATCH($A152,'Jul''26'!$B:$B,0))),"") -> -1357 | I152: =SUM(B152:H152) -> -13918.31
A153: =IF('Jun''26'!B153="","",'Jun''26'!B153) -> PBT | B153: =IFERROR(IF(INDEX(Jan!$E:$E,MATCH(TRIM($A153),Jan!$B:$B,0))="","",INDEX(Jan!$E:$E,MATCH(TRIM($A153),Jan!$B:$B,0))),"") -> -24871.321 | C153: =IFERROR(IF(INDEX('March-Feb'!$I:$I,MATCH($A153,'March-Feb'!$B:$B,0))="","",INDEX('March-Feb'!$I:$I,MATCH($A153,'March-Feb'!$B:$B,0))),"") -> -3604 | D153: =IFERROR(IF(INDEX('March-Feb'!$E:$E,MATCH($A153,'March-Feb'!$B:$B,0))="","",INDEX('March-Feb'!$E:$E,MATCH($A153,'March-Feb'!$B:$B,0))),"") -> -21258 | E153: =IFERROR(IF(INDEX('April-March'!$F:$F,MATCH($A153,'April-March'!$B:$B,0))="","",INDEX('April-March'!$F:$F,MATCH($A153,'April-March'!$B:$B,0))),"") -> -13222 | F153: =IFERROR(IF(INDEX('May-April'!$F:$F,MATCH($A153,'May-April'!$B:$B,0))="","",INDEX('May-April'!$F:$F,MATCH($A153,'May-April'!$B:$B,0))),"") -> 22155 | G153: =IF('Jun''26'!F153="","",'Jun''26'!F153) -> 25942 | H153: =IFERROR(IF(INDEX('Jul''26'!$F:$F,MATCH($A153,'Jul''26'!$B:$B,0))="","",INDEX('Jul''26'!$F:$F,MATCH($A153,'Jul''26'!$B:$B,0))),"") -> 38043 | I153: =SUM(B153:H153) -> 23184.679
A156: Memo - months that appear in two MIS packs (restatement check)
A157: This sheet uses each month's OWN dedicated MIS pack (the month in the left-hand block). Mar / Apr / May also appear as comparatives in the following month's pack, with different numbers.
D158: =D$6 -> 46082 | E158: =E$6 -> 46113 | F158: =F$6 -> 46143
A159: Total Revenue - per this sheet (own pack) | D159: =D15 -> 221215 | E159: =E15 -> 195207 | F159: =F15 -> 209918
A160: Total Revenue - as restated in following month's pack | D160: =INDEX('April-March'!$J:$J,MATCH("Total Revenue",'April-March'!$B:$B,0)) -> 237839 | E160: =INDEX('May-April'!$J:$J,MATCH("Total Revenue",'May-April'!$B:$B,0)) -> 195207 | F160: =INDEX('Jun''26'!$J:$J,MATCH("Total Revenue",'Jun''26'!$B:$B,0)) -> 209918
A161: Difference | D161: =D160-D159 -> 16624 | E161: =E160-E159 -> 0 | F161: =F160-F159 -> 0
A163: EBITDA - per this sheet (own pack) | D163: =D134 -> -26714 | E163: =E134 -> -13135 | F163: =F134 -> 18423
A164: EBITDA - as restated in following month's pack | D164: =INDEX('April-March'!$J:$J,MATCH("EBITDA",'April-March'!$B:$B,0)) -> -4254 | E164: =INDEX('May-April'!$J:$J,MATCH("EBITDA",'May-April'!$B:$B,0)) -> -15696 | F164: =INDEX('Jun''26'!$J:$J,MATCH("EBITDA",'Jun''26'!$B:$B,0)) -> 11957
A165: Difference | D165: =D164-D163 -> 22460 | E165: =E164-E163 -> -2561 | F165: =F164-F163 -> -6466

Sheet Jul'26
B2: iMagnum US | C2: Period: July 2026 | H2: Period: June 2026
B3: FTM_CurrentYear_CV_SPL | E3: ( USD in Whole Number ) | J3: ( USD in Whole Number )
B6: particulars | C6: iMagnum India | D6: iMagnum US | E6: Elimination-iMagnum Segment | F6: Total | G6: iMagnum India | H6: iMagnum US | I6: Elimination-iMagnum Segment | J6: Total
B7: Service Income
B8: Sales | C8: 169130 | D8: 250110 | E8: -168568 | F8: 250672 | G8: 163489 | H8: 226261 | I8: -157139 | J8: 232611
B9: Sales | C9: 168858 | D9: 250110 | E9: -168568 | F9: 250400 | G9: 157186 | H9: 225967 | I9: -157139 | J9: 226014
B10: Other Charges | C10: 0 | D10: 0 | E10: 0 | F10: 0 | G10: 0 | H10: 0 | I10: 0 | J10: 0
B11: Buyout | C11: 224 | E11: 0 | F11: 224 | I11: 0 | J11: 0
B12: General Income | C12: 16 | D12: 0 | E12: 0 | F12: 16 | G12: 0 | H12: 294 | I12: 0 | J12: 294
B13: Interest Income | C13: 54 | E13: 0 | F13: 54 | G13: -1 | I13: 0 | J13: -1
B14: Governments Grant Income | C14: -21 | E14: 0 | F14: -21 | G14: 6304 | I14: 0 | J14: 6304
B15: Total Revenue | C15: 169130 | D15: 250110 | E15: -168568 | F15: 250672 | G15: 163489 | H15: 226261 | I15: -157139 | J15: 232611
B16: Overall Operational cost
B17: Manpower | C17: 100703 | D17: 168568 | E17: -168568 | F17: 100703 | G17: 94790 | H17: 157139 | I17: -157139 | J17: 94790
B18: India Cost | E18: 0 | F18: 0 | I18: 0 | J18: 0
B19: Consultancy fee | D19: 0 | E19: 0 | F19: 0 | H19: 0 | I19: 0 | J19: 0
B20: Operation salaries | C20: 64832 | E20: 0 | F20: 64832 | G20: 60587 | I20: 0 | J20: 60587
B21: Ops Support Salaries | C21: 33513 | E21: 0 | F21: 33513 | G21: 33990 | I21: 0 | J21: 33990
B22: Contract employee salaries | C22: 211 | D22: 168568 | E22: -168568 | F22: 211 | G22: 213 | H22: 157139 | I22: -157139 | J22: 213
B23: Coding charges | C23: 2147 | E23: 0 | F23: 2147 | G23: 0 | I23: 0 | J23: 0
B24: Employee statutory expenses | C24: 11693 | E24: 0 | F24: 11693 | G24: 11260 | I24: 0 | J24: 11260
B25: Employee ESI | E25: 0 | F25: 0 | I25: 0 | J25: 0
B26: EPF Admin Charges | C26: 413 | E26: 0 | F26: 413 | G26: 396 | I26: 0 | J26: 396
B27: Employee PF | C27: 10249 | E27: 0 | F27: 10249 | G27: 9833 | I27: 0 | J27: 9833
B28: Employer ESI | C28: 341 | E28: 0 | F28: 341 | G28: 381 | I28: 0 | J28: 381
B29: Employer PF | E29: 0 | F29: 0 | I29: 0 | J29: 0
B30: Professional tax | C30: 690 | E30: 0 | F30: 690 | G30: 651 | I30: 0 | J30: 651
B31: Interest on TDS | C31: 0 | E31: 0 | F31: 0 | G31: 0 | I31: 0 | J31: 0
B32: Interest on employee statutory dues | E32: 0 | F32: 0 | I32: 0 | J32: 0
B33: Interest on Advance Tax | C33: 0 | E33: 0 | F33: 0 | G33: 0 | I33: 0 | J33: 0
B34: Facility Cost | C34: 15220 | D34: 3125 | E34: 0 | F34: 18345 | G34: 15275 | H34: 0 | I34: 0 | J34: 15275
B35: Electricity | E35: 0 | F35: 0 | I35: 0 | J35: 0
B36: Electricity Expense | C36: 4842 | E36: 0 | F36: 4842 | G36: 3476 | I36: 0 | J36: 3476
B37: Computer maintenance | E37: 0 | F37: 0 | I37: 0 | J37: 0
B38: Janani Property Maintenance Charges | C38: 317 | E38: 0 | F38: 317 | G38: 727 | I38: 0 | J38: 727
B39: Janani Property Rental Charges | C39: 1834 | E39: 0 | F39: 1834 | G39: 4210 | I39: 0 | J39: 4210
B40: Laptop Rental Charges | C40: 2148 | E40: 0 | F40: 2148 | G40: 2049 | I40: 0 | J40: 2049
B41: Thiruttani rental charges | C41: 276 | E41: 0 | F41: 276 | G41: 293 | I41: 0 | J41: 293
B42: Max Office rental charges | C42: 4209 | E42: 0 | F42: 4209 | G42: 4255 | I42: 0 | J42: 4255
B43: Rent Expense | C43: 263 | D43: 3125 | E43: 0 | F43: 3388 | G43: 266 | H43: 0 | I43: 0 | J43: 266
B44: Trichy rental charges | E44: 0 | F44: 0 | I44: 0 | J44: 0
B45: RK Raj Property Rental Charges | C45: 597 | E45: 0 | F45: 597 | G45: 0 | H45: 0 | I45: 0 | J45: 0
B46: RK Raj Property Maintenance Charges | C46: 734 | E46: 0 | F46: 734 | G46: 0 | H46: 0 | I46: 0 | J46: 0
B47: Telcom/Data & others | C47: 1295 | D47: 1161 | E47: 0 | F47: 2456 | G47: 1830 | H47: 908 | I47: 0 | J47: 2737
B48: Telephone Expense | D48: 602 | E48: 0 | F48: 602 | H48: 329 | I48: 0 | J48: 329
B49: Dues and Subscriptions | D49: 247 | E49: 0 | F49: 247 | H49: 366 | I49: 0 | J49: 366
B50: IT and Internet Expenses | C50: 461 | D50: 312 | E50: 0 | F50: 773 | G50: 473 | H50: 213 | I50: 0 | J50: 686
B51: Telecom Charges | C51: 25 | E51: 0 | F51: 25 | G51: 28 | I51: 0 | J51: 28
B52: Telephone Rental Charges | C52: 205 | E52: 0 | F52: 205 | G52: 208 | I52: 0 | J52: 208
B53: License/Subscription Charges | C53: 603 | E53: 0 | F53: 603 | G53: 1121 | I53: 0 | J53: 1121
B54: Transport | C54: 6651 | E54: 0 | F54: 6651 | G54: 5760 | I54: 0 | J54: 5760
B55: Staff Transportation Charges | C55: 6651 | E55: 0 | F55: 6651 | G55: 5760 | I55: 0 | J55: 5760
B56: Other COGS | C56: 7362 | D56: 5773 | E56: 0 | F56: 13135 | G56: 8196 | H56: 10333 | I56: 0 | J56: 18529
B57: General Insurance | E57: 0 | F57: 0 | I57: 0 | J57: 0
B58: Insurance | E58: 0 | F58: 0 | I58: 0 | J58: 0
B59: Donation | E59: 0 | F59: 0 | I59: 0 | J59: 0
B60: Software development and Hosting charges | C60: 965 | E60: 0 | F60: 965 | G60: 802 | I60: 0 | J60: 802
B61: Other Cogs- MD | E61: 0 | F61: 0 | I61: 0 | J61: 0
B62: Employee Engagement | C62: 29 | E62: 0 | F62: 29 | I62: 0 | J62: 0
B63: Staff Welfare Expenses | C63: 3238 | E63: 0 | F63: 3238 | G63: 4401 | I63: 0 | J63: 4401
B64: Fuel expenses | E64: 0 | F64: 0 | I64: 0 | J64: 0
B65: Obo Health Inc | E65: 0 | F65: 0 | I65: 0 | J65: 0
B66: Food Coupon-Happay Wallet | C66: 3130 | E66: 0 | F66: 3130 | G66: 2993 | I66: 0 | J66: 2993
B67: Software Expenses | D67: 10773 | E67: 0 | F67: 10773 | H67: 10333 | I67: 0 | J67: 10333
B68: Total COGS | C68: 142924 | D68: 178627 | E68: -168568 | F68: 152984 | G68: 137111 | H68: 168380 | I68: -157139 | J68: 148351
B69: GM | C69: 26206 | D69: 71483 | E69: 0 | F69: 97689 | G69: 26378 | H69: 57881 | I69: 0 | J69: 84259
B70: GM% | C70: 15 % | D70: 29 % | E70: 0 | F70: 39 % | G70: 16 % | H70: 26 % | I70: 0 | J70: 36 %
B71: SG&A
B72: Selling Expenses | C72: 1374 | D72: 1968 | E72: 0 | F72: 3342 | G72: 5596 | H72: 1132 | I72: 0 | J72: 6728
B73: Travel Expense | E73: 0 | F73: 0 | I73: 0 | J73: 0
B74: Cyber Security Insurance | E74: 0 | F74: 0 | I74: 0 | J74: 0
B75: Rewards and recognition | C75: -4 | E75: 0 | F75: -4 | G75: 1314 | I75: 0 | J75: 1314
B76: Meals and Entertainment | C76: 383 | D76: 622 | E76: 0 | F76: 1005 | G76: 3194 | H76: 49 | I76: 0 | J76: 3243
B77: VISA charges | E77: 0 | F77: 0 | I77: 0 | J77: 0
B78: Conference & Events | E78: 0 | F78: 0 | I78: 0 | J78: 0
B79: Advertisement and marketing | E79: 0 | F79: 0 | I79: 0 | J79: 0
B80: Sales and marketing | D80: 1346 | E80: 0 | F80: 1346 | H80: 1083 | I80: 0 | J80: 1083
B81: Business Promotion | E81: 0 | F81: 0 | I81: 0 | J81: 0
B82: S&M Salaries | C82: 997 | E82: 0 | F82: 997 | G82: 1090 | I82: 0 | J82: 1090
B83: Gratuity | C83: -2 | E83: 0 | F83: -2 | G83: -1 | I83: 0 | J83: -1
B84: New Tools and Accesses - Needed | E84: 0 | F84: 0 | I84: 0 | J84: 0
B85: Customs Duty | E85: 0 | F85: 0 | I85: 0 | J85: 0
B86: G&A Expenses
B87: Salaries-Management & Others | C87: 9330 | D87: 16190 | E87: 0 | F87: 25520 | G87: 9433 | H87: 17888 | I87: 0 | J87: 27321
B88: Bonus and Incentives | C88: -1 | E88: 0 | F88: -1 | G88: 0 | I88: 0 | J88: 0
B89: Management Salaries | C89: 9331 | D89: 16190 | E89: 0 | F89: 25520 | G89: 9433 | H89: 17888 | I89: 0 | J89: 27321
B90: Legal & Professional Fees | C90: 188 | D90: 6437 | E90: 0 | F90: 6624 | G90: 1330 | H90: 5000 | I90: 0 | J90: 6330
B91: Professional fees | E91: 0 | F91: 0 | I91: 0 | J91: 0
B92: FPO Charges - SRF | C92: -27 | D92: 1350 | E92: 0 | F92: 1323 | G92: 1330 | I92: 0 | J92: 1330
B93: Legal & Professional Services | D93: 5087 | E93: 0 | F93: 5087 | H93: 5000 | I93: 0 | J93: 5000
B94: FPO Charges-SMCS GLOBAL | C94: 215 | E94: 0 | F94: 215 | I94: 0 | J94: 0
B95: G&A salaries | C95: 1937 | D95: 3675 | E95: 0 | F95: 5612 | G95: 1984 | H95: 3675 | I95: 0 | J95: 5660
B96: Payroll taxes | D96: 3675 | E96: 0 | F96: 3675 | H96: 3675 | I96: 0 | J96: 3675
B97: HR Salaries | C97: 534 | E97: 0 | F97: 534 | G97: 566 | I97: 0 | J97: 566
B98: Admin Salaries | C98: 700 | E98: 0 | F98: 700 | G98: 708 | I98: 0 | J98: 708
B99: IT Salaries | C99: 703 | E99: 0 | F99: 703 | G99: 711 | I99: 0 | J99: 711
B100: Coder | E100: 0 | F100: 0 | I100: 0 | J100: 0
B101: Gen & Admin Expenses | C101: 3985 | D101: 15919 | E101: 0 | F101: 19905 | G101: 4224 | H101: 8918 | I101: 0 | J101: 13142
B102: Consultancy Fees | E102: 0 | F102: 0 | I102: 0 | J102: 0
B103: Comission Paid-Scinet Inc | E103: 0 | F103: 0 | I103: 0 | J103: 0
...

Sheet Jun'26
B2: iMagnum US | C2: Period: June 2026 | G2: Period: May 2026
B3: FTM_CurrentYear_CV_SPL | E3: ( USD in Whole Number ) | I3: ( USD in Whole Number )
B6: particulars | C6: iMagnum India | D6: iMagnum US | E6: Elimination-iMagnum Segment | F6: Total | G6: iMagnum India | H6: iMagnum US | I6: Elimination-iMagnum Segment | J6: Total | K6: Variance
B7: Service Income
B8: Sales | C8: 163489 | D8: 225961 | E8: -157139 | F8: 232311 | G8: 158437 | H8: 209920 | I8: -158439 | J8: 209918 | K8: =F8-J8 -> 22393
B9: Sales | C9: 157186 | D9: 225667 | E9: -157139 | F9: 225714 | G9: 158439 | H9: 209920 | I9: -158439 | J9: 209920 | K9: =F9-J9 -> 15794
B10: Other Charges | C10: 0 | D10: 0 | F10: 0 | G10: 0 | H10: 0 | I10: 0 | J10: 0 | K10: =F10-J10 -> 0
B11: Buyout | I11: 0 | J11: 0
B12: General Income | C12: 0 | D12: 294 | F12: 294 | G12: 0 | H12: 0 | I12: 0 | J12: 0 | K12: =F12-J12 -> 294
B13: Interest Income | C13: -1 | F13: -1 | G13: -2 | I13: 0 | J13: -2 | K13: =F13-J13 -> 1
B14: Governments Grant Income | C14: 6304 | F14: 6304 | I14: 0 | J14: 0 | K14: =F14-J14 -> 6304
B15: Total Revenue | C15: 163489 | D15: 225961 | E15: -157139 | F15: 232311 | G15: 158437 | H15: 209920 | I15: -158439 | J15: 209918 | K15: =F15-J15 -> 22393
B16: Overall Operational cost
B17: Manpower | C17: 94790 | D17: 157139 | E17: -157139 | F17: 94790 | G17: 92642 | H17: 158280 | I17: -158439 | J17: 92483 | K17: =F17-J17 -> 2307
B18: India Cost | I18: 0 | J18: 0
B19: Consultancy fee | D19: 0 | F19: 0 | H19: 0 | I19: 0 | J19: 0 | K19: =F19-J19 -> 0
B20: Operation salaries | C20: 60587 | F20: 60587 | G20: 57391 | I20: 0 | J20: 57391 | K20: =F20-J20 -> 3196
B21: Ops Support Salaries | C21: 33990 | F21: 33990 | G21: 35040 | I21: 0 | J21: 35040 | K21: =F21-J21 -> -1050
B22: Contract employee salaries | C22: 213 | D22: 157139 | E22: -157139 | F22: 213 | G22: 212 | H22: 158280 | I22: -158439 | J22: 53 | K22: =F22-J22 -> 160
B23: Coding charges | C23: 0 | F23: 0 | G23: -1 | I23: 0 | J23: -1 | K23: =F23-J23 -> 1
B24: Employee statutory expenses | C24: 11261 | F24: 11261 | G24: 10954 | I24: 0 | J24: 10954 | K24: =F24-J24 -> 307
B25: Employee ESI | I25: 0 | J25: 0
B26: EPF Admin Charges | C26: 396 | F26: 396 | G26: 369 | I26: 0 | J26: 369 | K26: =F26-J26 -> 27
B27: Employee PF | C27: 9833 | F27: 9833 | G27: 9488 | I27: 0 | J27: 9488 | K27: =F27-J27 -> 345
B28: Employer ESI | C28: 381 | F28: 381 | G28: 365 | I28: 0 | J28: 365 | K28: =F28-J28 -> 16
B29: Employer PF | I29: 0 | J29: 0
B30: Professional tax | C30: 651 | F30: 651 | G30: 597 | I30: 0 | J30: 597 | K30: =F30-J30 -> 54
B31: Interest on TDS | C31: 0 | F31: 0 | G31: 8 | I31: 0 | J31: 8 | K31: =F31-J31 -> -8
B32: Interest on employee statutory dues | I32: 0 | J32: 0
B33: Interest on Advance Tax | C33: 0 | F33: 0 | G33: 127 | I33: 0 | J33: 127 | K33: =F33-J33 -> -127
B34: Facility Cost | C34: 15275 | D34: 0 | F34: 15275 | G34: 14229 | H34: 3000 | I34: 0 | J34: 17229 | K34: =F34-J34 -> -1954
B35: Electricity | I35: 0 | J35: 0
B36: Electricity Expense | C36: 3476 | F36: 3476 | G36: 2663 | I36: 0 | J36: 2663 | K36: =F36-J36 -> 813
B37: Computer maintenance | I37: 0 | J37: 0
B38: Janani Property Maintenance Charges | C38: 727 | F38: 727 | G38: 719 | I38: 0 | J38: 719 | K38: =F38-J38 -> 8
B39: Janani Property Rental Charges | C39: 4210 | F39: 4210 | G39: 4162 | I39: 0 | J39: 4162 | K39: =F39-J39 -> 48
B40: Laptop Rental Charges | C40: 2049 | F40: 2049 | G40: 1924 | I40: 0 | J40: 1924 | K40: =F40-J40 -> 125
B41: Thiruttani rental charges | C41: 293 | F41: 293 | G41: 290 | I41: 0 | J41: 290 | K41: =F41-J41 -> 3
B42: Max Office rental charges | C42: 4255 | F42: 4255 | G42: 4207 | I42: 0 | J42: 4207 | K42: =F42-J42 -> 48
B43: Rent Expense | C43: 266 | D43: 0 | F43: 266 | G43: 263 | H43: 3000 | I43: 0 | J43: 3263 | K43: =F43-J43 -> -2997
B44: Trichy rental charges | I44: 0 | J44: 0
B45: Telcom/Data & others | C45: 1806 | D45: 908 | F45: 2713 | G45: 1464 | H45: 875 | I45: 0 | J45: 2339 | K45: =F45-J45 -> 374
B46: Telephone Expense | D46: 329 | F46: 329 | H46: 285 | I46: 0 | J46: 285 | K46: =F46-J46 -> 44
B47: Dues and Subscriptions | D47: 366 | F47: 366 | H47: 377 | I47: 0 | J47: 377 | K47: =F47-J47 -> -11
B48: IT and Internet Expenses | C48: 473 | D48: 213 | F48: 686 | G48: 688 | H48: 213 | I48: 0 | J48: 901 | K48: =F48-J48 -> -215
B49: Telecom Charges | C49: 28 | F49: 28 | G49: 27 | I49: 0 | J49: 27 | K49: =F49-J49 -> 1
B50: Telephone Rental Charges | C50: 208 | F50: 208 | G50: 210 | I50: 0 | J50: 210 | K50: =F50-J50 -> -2
B51: License/Subscription Charges | C51: 1097 | F51: 1097 | G51: 539 | I51: 0 | J51: 539 | K51: =F51-J51 -> 558
B52: Transport | C52: 5760 | F52: 5760 | G52: 4254 | I52: 0 | J52: 4254 | K52: =F52-J52 -> 1506
B53: Staff Transportation Charges | C53: 5760 | F53: 5760 | G53: 4254 | I53: 0 | J53: 4254 | K53: =F53-J53 -> 1506
B54: Other COGS | C54: 8196 | D54: 10333 | F54: 18529 | G54: 5117 | H54: 17533 | I54: 0 | J54: 22650 | K54: =F54-J54 -> -4121
B55: General Insurance | I55: 0 | J55: 0
B56: Insurance | I56: 0 | J56: 0
B57: Donation | I57: 0 | J57: 0
B58: Software development and Hosting charges | C58: 802 | F58: 802 | G58: 427 | I58: 0 | J58: 427 | K58: =F58-J58 -> 375
B59: Other Cogs- MD | I59: 0 | J59: 0
B60: Employee Engagement | I60: 0 | J60: 0
B61: Staff Welfare Expenses | C61: 4401 | F61: 4401 | G61: 1873 | I61: 0 | J61: 1873 | K61: =F61-J61 -> 2528
B62: Fuel expenses | I62: 0 | J62: 0
B63: Obo Health Inc | I63: 0 | J63: 0
B64: Food Coupon-Happay Wallet | C64: 2993 | F64: 2993 | G64: 2818 | I64: 0 | J64: 2818 | K64: =F64-J64 -> 175
B65: Software Expenses | D65: 10333 | F65: 10333 | H65: 17533 | I65: 0 | J65: 17533 | K65: =F65-J65 -> -7200
B66: Total COGS | C66: 137087 | D66: 168380 | E66: -157139 | F66: 148327 | G66: 128659 | H66: 179688 | I66: -158439 | J66: 149908 | K66: =F66-J66 -> -1581
B67: GM | C67: 26402 | D67: 57581 | E67: 0 | F67: 83983 | G67: 29777 | H67: 30232 | I67: 0 | J67: 60010 | K67: =F67-J67 -> 23973
B68: GM% | C68: 16 % | D68: 25 % | E68: 0 | F68: 36 % | G68: 19 % | H68: 14 % | I68: 0 | J68: 29 % | K68: =F68-J68 -> 0.07
B69: SG&A
B70: Selling Expenses | C70: 5596 | D70: 1083 | F70: 6679 | G70: 1358 | H70: 1132 | I70: 0 | J70: 2490 | K70: =F70-J70 -> 4189
B71: Travel Expense | I71: 0 | J71: 0
B72: Cyber Security Insurance | I72: 0 | J72: 0
B73: Rewards and recognition | C73: 1314 | F73: 1314 | I73: 0 | J73: 0 | K73: =F73-J73 -> 1314
B74: Meals and Entertainment | C74: 3194 | D74: 0 | F74: 3194 | G74: 269 | H74: 49 | I74: 0 | J74: 318 | K74: =F74-J74 -> 2876
B75: VISA charges | I75: 0 | J75: 0
B76: Conference & Events | I76: 0 | J76: 0
B77: Advertisement and marketing | I77: 0 | J77: 0
B78: Sales and marketing | D78: 1083 | F78: 1083 | H78: 1083 | I78: 0 | J78: 1083 | K78: =F78-J78 -> 0
B79: Business Promotion | I79: 0 | J79: 0
B80: S&M Salaries | C80: 1090 | F80: 1090 | G80: 1093 | I80: 0 | J80: 1093 | K80: =F80-J80 -> -3
B81: Gratuity | C81: -1 | F81: -1 | G81: -4 | I81: 0 | J81: -4 | K81: =F81-J81 -> 3
B82: New Tools and Accesses - Needed | I82: 0 | J82: 0
B83: Customs Duty | I83: 0 | J83: 0
B84: G&A Expenses
B85: Salaries-Management & Others | C85: 9433 | D85: 17888 | F85: 27321 | G85: 9326 | H85: 16293 | I85: 0 | J85: 25618 | K85: =F85-J85 -> 1703
B86: Bonus and Incentives | C86: 0 | F86: 0 | G86: -1 | I86: 0 | J86: -1 | K86: =F86-J86 -> 1
B87: Management Salaries | C87: 9433 | D87: 17888 | F87: 27321 | G87: 9327 | H87: 16293 | I87: 0 | J87: 25619 | K87: =F87-J87 -> 1702
B88: Legal & Professional Fees | C88: 1330 | D88: 5000 | F88: 6330 | G88: 1315 | H88: 1025 | I88: 0 | J88: 2340 | K88: =F88-J88 -> 3990
B89: Professional fees | I89: 0 | J89: 0
B90: FPO Charges - SRF | C90: 1330 | F90: 1330 | G90: 1315 | I90: 0 | J90: 1315 | K90: =F90-J90 -> 15
B91: Legal & Professional Services | D91: 5000 | F91: 5000 | H91: 1025 | I91: 0 | J91: 1025 | K91: =F91-J91 -> 3975
B92: FPO Charges-SMCS GLOBAL | I92: 0 | J92: 0
B93: G&A salaries | C93: 1984 | D93: 3675 | F93: 5660 | G93: 2028 | H93: 5513 | I93: 0 | J93: 7541 | K93: =F93-J93 -> -1881
B94: Payroll taxes | D94: 3675 | F94: 3675 | H94: 5513 | I94: 0 | J94: 5513 | K94: =F94-J94 -> -1838
B95: HR Salaries | C95: 566 | F95: 566 | G95: 557 | I95: 0 | J95: 557 | K95: =F95-J95 -> 9
B96: Admin Salaries | C96: 708 | F96: 708 | G96: 693 | I96: 0 | J96: 693 | K96: =F96-J96 -> 15
B97: IT Salaries | C97: 711 | F97: 711 | G97: 777 | I97: 0 | J97: 777 | K97: =F97-J97 -> -66
B98: Coder | I98: 0 | J98: 0
B99: Gen & Admin Expenses | C99: 4224 | D99: 8918 | F99: 13142 | G99: 2255 | H99: 7810 | I99: 0 | J99: 10065 | K99: =F99-J99 -> 3077
B100: Consultancy Fees | I100: 0 | J100: 0
B101: Comission Paid-Scinet Inc | I101: 0 | J101: 0
B102: Leadership engagemnet | I102: 0 | J102: 0
B103: Charitable Donations | I103: 0 | J103: 0
...

Sheet May-April
B2: iMagnum US | C2: Period: May 2026 | G2: Period: April 2026
B3: FTM_CurrentYear_CV_SPL | E3: ( USD in Whole Number ) | I3: ( USD in Whole Number )
B6: particulars | C6: iMagnum India | D6: iMagnum US | E6: Elimination-iMagnum Segment | F6: Total | G6: iMagnum India | H6: iMagnum US | I6: Elimination-iMagnum Segment | J6: Total | K6: Variance
B7: Service Income
B8: Sales | C8: 158437 | D8: 209920 | E8: -158439 | F8: 209918 | G8: 176206 | H8: 194902 | I8: -175901 | J8: 195207 | K8: =F8-J8 -> 14711
B9: Sales | C9: 158439 | D9: 209920 | E9: -158439 | F9: 209920 | G9: 175901 | H9: 194902 | I9: -175901 | J9: 194902 | K9: =F9-J9 -> 15018
B10: Other Charges | C10: 0 | D10: 0 | F10: 0 | G10: 0 | H10: 0 | J10: 0 | K10: =F10-J10 -> 0
B11: Buyout
B12: General Income | C12: 0 | D12: 0 | F12: 0 | G12: 16 | H12: 0 | J12: 16 | K12: =F12-J12 -> -16
B13: Interest Income | C13: -2 | F13: -2 | G13: 289 | J13: 289 | K13: =F13-J13 -> -291
B14: Total Revenue | C14: 158437 | D14: 209920 | E14: -158439 | F14: 209918 | G14: 176206 | H14: 194902 | I14: -175901 | J14: 195207 | K14: =F14-J14 -> 14711
B15: Overall Operational cost
B16: Manpower | C16: 92642 | D16: 158280 | E16: -158439 | F16: 92483 | G16: 101010 | H16: 175901 | I16: -175901 | J16: 101010 | K16: =F16-J16 -> -8527
B17: India Cost
B18: Consultancy fee | D18: 0 | F18: 0 | H18: 0 | J18: 0 | K18: =F18-J18 -> 0
B19: Operation salaries | C19: 57391 | F19: 57391 | G19: 62706 | J19: 62706 | K19: =F19-J19 -> -5315
B20: Ops Support Salaries | C20: 35040 | F20: 35040 | G20: 38087 | J20: 38087 | K20: =F20-J20 -> -3047
B21: Contract employee salaries | C21: 212 | D21: 158280 | E21: -158439 | F21: 53 | G21: 217 | H21: 175901 | I21: -175901 | J21: 217 | K21: =F21-J21 -> -164
B22: Coding charges | C22: -1 | F22: -1 | G22: 0 | J22: 0 | K22: =F22-J22 -> -1
B23: Employee statutory expenses | C23: 10965 | F23: 10965 | G23: 11375 | J23: 11375 | K23: =F23-J23 -> -410
B24: Employee ESI
B25: EPF Admin Charges | C25: 381 | F25: 381 | G25: 415 | J25: 415 | K25: =F25-J25 -> -34
B26: Employee PF | C26: 9488 | F26: 9488 | G26: 9958 | J26: 9958 | K26: =F26-J26 -> -470
B27: Employer ESI | C27: 365 | F27: 365 | G27: 391 | J27: 391 | K27: =F27-J27 -> -26
B28: Employer PF
B29: Professional tax | C29: 597 | F29: 597 | G29: 610 | J29: 610 | K29: =F29-J29 -> -13
B30: Interest on TDS | C30: 8 | F30: 8
B31: Interest on employee statutory dues
B32: Interest on Advance Tax | C32: 127 | F32: 127
B33: Facility Cost | C33: 14229 | D33: 3000 | F33: 17229 | G33: 14894 | H33: 0 | J33: 14894 | K33: =F33-J33 -> 2335
B34: Electricity
B35: Electricity Expense | C35: 2663 | F35: 2663 | G35: 2980 | J35: 2980 | K35: =F35-J35 -> -317
B36: Computer maintenance
B37: Janani Property Maintenance Charges | C37: 719 | F37: 719 | G37: 743 | J37: 743 | K37: =F37-J37 -> -24
B38: Janani Property Rental Charges | C38: 4162 | F38: 4162 | G38: 4302 | J38: 4302 | K38: =F38-J38 -> -140
B39: Laptop Rental Charges | C39: 1924 | F39: 1924 | G39: 1964 | J39: 1964 | K39: =F39-J39 -> -40
B40: Thiruttani rental charges | C40: 290 | F40: 290 | G40: 285 | J40: 285 | K40: =F40-J40 -> 5
B41: Max Office rental charges | C41: 4207 | F41: 4207 | G41: 4348 | J41: 4348 | K41: =F41-J41 -> -141
B42: Rent Expense | C42: 263 | D42: 3000 | F42: 3263 | G42: 272 | H42: 0 | J42: 272 | K42: =F42-J42 -> 2991
B43: Trichy rental charges
B44: Telcom/Data & others | C44: 1464 | D44: 505 | F44: 1969 | G44: 1496 | H44: 638 | J44: 2134 | K44: =F44-J44 -> -165
B45: Telephone Expense | D45: 285 | F45: 285 | H45: 285 | J45: 285 | K45: =F45-J45 -> 0
B46: Dues and Subscriptions | D46: 220 | F46: 220 | H46: 352 | J46: 352 | K46: =F46-J46 -> -132
B47: IT and Internet Expenses | C47: 688 | D47: 0 | F47: 688 | G47: 479 | H47: 0 | J47: 479 | K47: =F47-J47 -> 209
B48: Telecom Charges | C48: 27 | F48: 27 | G48: 29 | J48: 29 | K48: =F48-J48 -> -2
B49: Telephone Rental Charges | C49: 210 | F49: 210 | G49: 213 | J49: 213 | K49: =F49-J49 -> -3
B50: License/Subscription Charges | C50: 539 | F50: 539 | G50: 775 | J50: 775 | K50: =F50-J50 -> -236
B51: Transport | C51: 4254 | F51: 4254 | G51: 4084 | J51: 4084 | K51: =F51-J51 -> 170
B52: Staff Transportation Charges | C52: 4254 | F52: 4254 | G52: 4084 | J52: 4084 | K52: =F52-J52 -> 170
B53: Other COGS | C53: 5117 | D53: 12533 | F53: 17650 | G53: 5091 | H53: 16922 | J53: 22012 | K53: =F53-J53 -> -4362
B54: General Insurance
B55: Insurance
B56: Donation
B57: Software development and Hosting charges | C57: 427 | F57: 427 | G57: 163 | J57: 163 | K57: =F57-J57 -> 264
B58: Other Cogs- MD
B59: Employee Engagement
B60: Staff Welfare Expenses | C60: 1873 | F60: 1873 | G60: 1977 | J60: 1977 | K60: =F60-J60 -> -104
B61: Fuel expenses
B62: Obo Health Inc
B63: Food Coupon-Happay Wallet | C63: 2818 | F63: 2818 | G63: 2951 | J63: 2951 | K63: =F63-J63 -> -133
B64: Software Expenses | D64: 12533 | F64: 12533 | H64: 16922 | J64: 16922 | K64: =F64-J64 -> -4389
B65: Total COGS | C65: 128671 | D65: 174318 | E65: -158439 | F65: =F53+F44+F33+F23+F16+F51 -> 144550 | G65: 137951 | H65: 193460 | I65: -175901 | J65: 155510 | K65: =F65-J65 -> -10960
B66: GM | C66: 29766 | D66: 35602 | F66: 65368 | G66: 38256 | H66: 1442 | I66: 0 | J66: 39697 | K66: =F66-J66 -> 25671
B67: GM% | C67: 19 % | D67: 17 % | E67: 0 | F67: 31 % | G67: 22 % | H67: 1 % | I67: 0 | J67: 20 % | K67: =F67-J67 -> 0.11
B68: SG&A
B69: Selling Expenses | C69: 1358 | D69: 49 | F69: 1407 | G69: 1354 | H69: 2076 | J69: 3430 | K69: =F69-J69 -> -2023
B70: Travel Expense
B71: Cyber Security Insurance
B72: Rewards and recognition
B73: Meals and Entertainment | C73: 269 | D73: 49 | F73: 318 | G73: 107 | H73: 888 | J73: 994 | K73: =F73-J73 -> -676
B74: VISA charges
B75: Conference & Events
B76: Advertisement and marketing
B77: Sales and marketing | D77: 0 | F77: 0 | H77: 1188 | J77: 1188 | K77: =F77-J77 -> -1188
B78: Business Promotion
B79: S&M Salaries | C79: 1093 | F79: 1093 | G79: 1247 | J79: 1247 | K79: =F79-J79 -> -154
B80: Gratuity | C80: -4 | F80: -4 | G80: 0 | J80: 0 | K80: =F80-J80 -> -4
B81: New Tools and Accesses - Needed
B82: Customs Duty
B83: G&A Expenses
B84: Salaries-Management & Others | C84: 9326 | D84: 16293 | F84: 25618 | G84: 9641 | H84: 23165 | J84: 32806 | K84: =F84-J84 -> -7188
B85: Bonus and Incentives | C85: -1 | F85: -1 | G85: 0 | J85: 0 | K85: =F85-J85 -> -1
B86: Management Salaries | C86: 9327 | D86: 16293 | F86: 25619 | G86: 9641 | H86: 23165 | J86: 32806 | K86: =F86-J86 -> -7187
B87: Legal & Professional Fees | C87: 1315 | D87: 1025 | F87: 2340 | G87: 1359 | H87: 2326 | J87: 3685 | K87: =F87-J87 -> -1345
B88: Professional fees
B89: FPO Charges - SRF | C89: 1315 | F89: 1315 | G89: 1359 | J89: 1359 | K89: =F89-J89 -> -44
B90: Legal & Professional Services | D90: 1025 | F90: 1025 | H90: 2326 | J90: 2326 | K90: =F90-J90 -> -1301
B91: FPO Charges-SMCS GLOBAL
B92: G&A salaries | C92: 2028 | D92: 5513 | F92: 7541 | G92: 2242 | H92: 3675 | J92: 5917 | K92: =F92-J92 -> 1624
B93: Payroll taxes | D93: 5513 | F93: 5513 | H93: 3675 | J93: 3675 | K93: =F93-J93 -> 1838
B94: HR Salaries | C94: 557 | F94: 557 | G94: 632 | J94: 632 | K94: =F94-J94 -> -75
B95: Admin Salaries | C95: 693 | F95: 693 | G95: 774 | J95: 774 | K95: =F95-J95 -> -81
B96: IT Salaries | C96: 777 | F96: 777 | G96: 836 | J96: 836 | K96: =F96-J96 -> -59
B97: Coder
B98: Gen & Admin Expenses | C98: 2255 | D98: 7785 | F98: 10040 | G98: 2776 | H98: 6780 | J98: 9556 | K98: =F98-J98 -> 484
B99: Consultancy Fees
B100: Comission Paid-Scinet Inc
B101: Leadership engagemnet
B102: Charitable Donations
B103: Fuel/Mileage Expenses | D103: 0 | F103: 0 | H103: 212 | J103: 212 | K103: =F103-J103 -> -212
...

Sheet April-March
B2: iMagnum US | C2: Period: April 2026 | G2: Period: March 2026
B3: FTM_CurrentYear_CV_SPL | E3: ( USD in Whole Number ) | I3: ( USD in Whole Number )
B6: particulars | C6: iMagnum India | D6: iMagnum US | E6: Elimination-iMagnum Segment | F6: Total | G6: iMagnum India | H6: iMagnum US | I6: Elimination-iMagnum Segment | J6: Total | K6: Variance
B7: Service Income
B8: Sales | C8: 176206 | D8: 194902 | E8: -175901 | F8: 195207 | G8: 75319 | H8: 237839 | I8: -75319 | J8: 237839 | K8: =F8-J8 -> -42632
B9: Sales | C9: 175901 | D9: 194902 | E9: -175901 | F9: 194902 | G9: 75319 | H9: 237839 | I9: -75319 | J9: 237839 | K9: =F9-J9 -> -42937
B10: Other Charges | C10: 0 | D10: 0 | F10: 0 | G10: 0 | H10: 0 | J10: 0 | K10: =F10-J10 -> 0
B11: Buyout
B12: General Income | C12: 16 | D12: 0 | F12: 16 | H12: 0 | J12: 0 | K12: =F12-J12 -> 16
B13: Interest Income | C13: 289 | F13: 289
B14: Total Revenue | C14: 176206 | D14: 194902 | E14: -175901 | F14: 195207 | G14: 75319 | H14: 237839 | I14: -75319 | J14: 237839 | K14: =F14-J14 -> -42632
B15: Overall Operational cost
B16: Manpower | C16: 100793 | D16: 175901 | E16: -175901 | F16: 100793 | G16: 104521 | H16: 75394 | I16: -75319 | J16: 104596 | K16: =F16-J16 -> -3803
B17: India Cost
B18: Consultancy fee | D18: 0 | F18: 0 | H18: 75 | J18: 75 | K18: =F18-J18 -> -75
B19: Operation salaries | C19: 62706 | F19: 62706 | G19: 65666 | J19: 65666 | K19: =F19-J19 -> -2960
B20: Ops Support Salaries | C20: 38087 | F20: 38087 | G20: 38517 | J20: 38517 | K20: =F20-J20 -> -430
B21: Contract employee salaries | C21: 0 | D21: 175901 | E21: -175901 | F21: 0 | G21: 217 | H21: 75319 | I21: -75319 | J21: 217 | K21: =F21-J21 -> -217
B22: Coding charges | C22: 0 | F22: 0 | G22: 121 | J22: 121 | K22: =F22-J22 -> -121
B23: Employee statutory expenses | C23: 11371 | F23: 11371 | G23: 10999 | J23: 10999 | K23: =F23-J23 -> 372
B24: Employee ESI
B25: EPF Admin Charges | C25: 411 | F25: 411 | G25: 383 | J25: 383 | K25: =F25-J25 -> 28
B26: Employee PF | C26: 9958 | F26: 9958 | G26: 9573 | J26: 9573 | K26: =F26-J26 -> 385
B27: Employer ESI | C27: 391 | F27: 391 | G27: 404 | J27: 404 | K27: =F27-J27 -> -13
B28: Employer PF
B29: Professional tax | C29: 610 | F29: 610 | G29: 639 | J29: 639 | K29: =F29-J29 -> -29
B30: Interest on TDS
B31: Interest on employee statutory dues
B32: Facility Cost | C32: 14894 | D32: 0 | F32: 14894 | G32: 14533 | H32: 1000 | J32: 15533 | K32: =F32-J32 -> -639
B33: Electricity
B34: Electricity Expense | C34: 2980 | F34: 2980 | G34: 2676 | J34: 2676 | K34: =F34-J34 -> 304
B35: Computer maintenance
B36: Janani Property Maintenance Charges | C36: 743 | F36: 743 | G36: 743 | J36: 743 | K36: =F36-J36 -> 0
B37: Janani Property Rental Charges | C37: 4302 | F37: 4302 | G37: 4302 | J37: 4302 | K37: =F37-J37 -> 0
B38: Laptop Rental Charges | C38: 1964 | F38: 1964 | G38: 1907 | J38: 1907 | K38: =F38-J38 -> 57
B39: Thiruttani rental charges | C39: 285 | F39: 285 | G39: 285 | J39: 285 | K39: =F39-J39 -> 0
B40: Max Office rental charges | C40: 4348 | F40: 4348 | G40: 4348 | J40: 4348 | K40: =F40-J40 -> 0
B41: Rent Expense | C41: 272 | D41: 0 | F41: 272 | G41: 272 | H41: 1000 | J41: 1272 | K41: =F41-J41 -> -1000
B42: Trichy rental charges
B43: Telcom/Data & others | C43: 1475 | D43: 506 | F43: 1981 | G43: 1603 | H43: 1255 | J43: 2858 | K43: =F43-J43 -> -877
B44: Telephone Expense | D44: 285 | F44: 285 | H44: 295 | J44: 295 | K44: =F44-J44 -> -10
B45: Dues and Subscriptions | D45: 220 | F45: 220 | H45: 459 | J45: 459 | K45: =F45-J45 -> -239
B46: IT and Internet Expenses | C46: 479 | D46: 0 | F46: 479 | G46: 485 | H46: 501 | J46: 985 | K46: =F46-J46 -> -506
B47: Telecom Charges | C47: 29 | F47: 29 | G47: 41 | J47: 41 | K47: =F47-J47 -> -12
B48: Telephone Rental Charges | C48: 213 | F48: 213 | G48: 189 | J48: 189 | K48: =F48-J48 -> 24
B49: License/Subscription Charges | C49: 754 | F49: 754 | G49: 889 | J49: 889 | K49: =F49-J49 -> -135
B50: Transport | C50: 4084 | F50: 4084 | G50: 4376 | J50: 4376 | K50: =F50-J50 -> -292
B51: Staff Transportation Charges | C51: 4084 | F51: 4084 | G51: 4376 | J51: 4376 | K51: =F51-J51 -> -292
B52: Other COGS | C52: 4841 | D52: 16686 | F52: 21527 | G52: 7740 | H52: 29152 | J52: 36892 | K52: =F52-J52 -> -15365
B53: General Insurance
B54: Insurance
B55: Donation
B56: Software development and Hosting charges | C56: 163 | F56: 163 | G56: 515 | J56: 515 | K56: =F56-J56 -> -352
B57: Other Cogs- MD
B58: Employee Engagement
B59: Staff Welfare Expenses | C59: 1727 | F59: 1727 | G59: 4155 | J59: 4155 | K59: =F59-J59 -> -2428
B60: Fuel expenses
B61: Obo Health Inc
B62: Food Coupon-Happay Wallet | C62: 2951 | F62: 2951 | G62: 3070 | J62: 3070 | K62: =F62-J62 -> -119
B63: Software Expenses | D63: 16686 | F63: 16686 | H63: 29152 | J63: 29152 | K63: =F63-J63 -> -12466
B64: Total COGS | C64: 137458 | D64: 193093 | E64: -175901 | F64: 154650 | G64: 143772 | H64: 106800 | I64: -75319 | J64: 175254 | K64: =F64-J64 -> -20604
B65: GM | C65: 38748 | D65: 1809 | E65: 0 | F65: 40557 | G65: -68453 | H65: 131039 | I65: 0 | J65: 62585 | K65: =F65-J65 -> -22028
B66: GM% | C66: 22 % | D66: 1 % | E66: 0 | F66: 21 % | G66: (91 %) | H66: 55 % | I66: 0 | J66: 26 % | K66: =F66-J66 -> -0.05
B67: SG&A
B68: Selling Expenses | C68: 1354 | D68: 755 | F68: 2109 | G68: 1427 | H68: 1361 | J68: 2788 | K68: =F68-J68 -> -679
B69: Travel Expense
B70: Cyber Security Insurance
B71: Rewards and recognition
B72: Meals and Entertainment | C72: 107 | D72: 627 | F72: 734 | G72: 160 | H72: 150 | J72: 310 | K72: =F72-J72 -> 424
B73: VISA charges
B74: Conference & Events
B75: Advertisement and marketing
B76: Sales and marketing | D76: 128 | F76: 128 | H76: 1211 | J76: 1211 | K76: =F76-J76 -> -1083
B77: Business Promotion
B78: S&M Salaries | C78: 1247 | F78: 1247 | G78: 1267 | J78: 1267 | K78: =F78-J78 -> -20
B79: Gratuity | C79: 0 | F79: 0 | G79: 0 | J79: 0 | K79: =F79-J79 -> 0
B80: New Tools and Accesses - Needed
B81: Customs Duty
B82: G&A Expenses
B83: Salaries-Management & Others | C83: 9641 | D83: 23165 | F83: 32806 | G83: 9729 | H83: 17422 | J83: 27151 | K83: =F83-J83 -> 5655
B84: Bonus and Incentives | C84: 0 | F84: 0 | G84: 0 | J84: 0 | K84: =F84-J84 -> 0
B85: Management Salaries | C85: 9641 | D85: 23165 | F85: 32806 | G85: 9729 | H85: 17422 | J85: 27151 | K85: =F85-J85 -> 5655
B86: Legal & Professional Fees | C86: 1359 | D86: 2326 | F86: 3685 | G86: 2011 | H86: 3976 | J86: 5987 | K86: =F86-J86 -> -2302
B87: Professional fees
B88: FPO Charges - SRF | C88: 1359 | F88: 1359 | G88: 2011 | J88: 2011 | K88: =F88-J88 -> -652
B89: Legal & Professional Services | D89: 2326 | F89: 2326 | H89: 3976 | J89: 3976 | K89: =F89-J89 -> -1650
B90: FPO Charges-SMCS GLOBAL
B91: G&A salaries | C91: 2242 | D91: 3675 | F91: 5917 | G91: 2500 | H91: 3764 | J91: 6265 | K91: =F91-J91 -> -348
B92: Payroll taxes | D92: 3675 | F92: 3675 | H92: 3764 | J92: 3764 | K92: =F92-J92 -> -89
B93: HR Salaries | C93: 632 | F93: 632 | G93: 840 | J93: 840 | K93: =F93-J93 -> -208
B94: Admin Salaries | C94: 774 | F94: 774 | G94: 779 | J94: 779 | K94: =F94-J94 -> -5
B95: IT Salaries | C95: 836 | F95: 836 | G95: 881 | J95: 881 | K95: =F95-J95 -> -45
B96: Coder
B97: Gen & Admin Expenses | C97: 2741 | D97: 6434 | F97: 9176 | G97: 4915 | H97: 19734 | J97: 24649 | K97: =F97-J97 -> -15473
B98: Consultancy Fees
B99: Comission Paid-Scinet Inc
B100: Leadership engagemnet
B101: Charitable Donations
B102: Fuel/Mileage Expenses | D102: 89 | F102: 89 | H102: 148 | J102: 148 | K102: =F102-J102 -> -59
B103: Payroll Processing Fees | D103: 523 | F103: 523 | H103: 608 | J103: 608 | K103: =F103-J103 -> -85
...

Sheet March-Feb
B2: iMagnum US | C2: Period: March 2026 | G2: Period: February 2026
B3: FTM_CurrentYear_CV_SPL | F3: ( USD in Whole Number ) | J3: ( USD in Whole Number )
B6: particulars | C6: iMagnum India | D6: iMagnum US | E6: Total | F6: Elimination-iMagnum Segment | G6: iMagnum India | H6: iMagnum US | I6: Total | J6: Elimination-iMagnum Segment | K6: Variance
B7: Service Income
B8: Sales | C8: 123319 | D8: 221215 | E8: 221215 | F8: -123319 | G8: 184916 | H8: 227771 | I8: 227771 | J8: -184916 | K8: =E8-I8 -> -6556
B9: Sales | C9: 123319 | D9: 221215 | E9: 221215 | F9: -123319 | G9: 184916 | H9: 227770 | I9: 227770 | J9: -184916
B10: Other Charges | C10: 0 | D10: 0 | E10: 0 | G10: 0 | H10: 1 | I10: 1
B11: Buyout
B12: General Income | D12: 0 | E12: 0 | H12: 0 | I12: 0
B13: Interest Income
B14: Total Revenue | C14: 123319 | D14: 221215 | E14: 221215 | F14: -123319 | G14: 184916 | H14: 227771 | I14: 227771 | J14: -184916
B15: Overall Operational cost
B16: Manpower | C16: 112934 | D16: 130894 | E16: 120509 | F16: -123319 | G16: 102920 | H16: 190830 | I16: 108834 | J16: -184916 | K16: =I16-E16 -> -11675
B17: India Cost
B18: Consultancy fee | D18: 7575 | E18: 7575 | H18: 5914 | I18: 5914
B19: Operation salaries | C19: 71381 | E19: 71381 | G19: 66470 | I19: 66470
B20: Ops Support Salaries | C20: 41215 | E20: 41215 | G20: 36233 | I20: 36233
B21: Contract employee salaries | C21: 217 | D21: 123319 | E21: 217 | F21: -123319 | G21: 217 | H21: 184916 | I21: 217 | J21: -184916
B22: Coding charges | C22: 121 | E22: 121
B23: Employee statutory expenses | C23: 11400 | E23: 11400 | G23: 10714 | I23: 10714 | K23: =I23-E23 -> -686
B24: Employee ESI
B25: EPF Admin Charges | C25: 392 | E25: 392 | G25: 370 | I25: 370
B26: Employee PF | C26: 9964 | E26: 9964 | G26: 9273 | I26: 9273
B27: Employer ESI | C27: 404 | E27: 404 | G27: 428 | I27: 428
B28: Employer PF
B29: Professional tax | C29: 639 | E29: 639 | G29: 644 | I29: 644
B30: Interest on TDS
B31: Interest on employee statutory dues
B32: Facility Cost | C32: 14533 | D32: 1000 | E32: 15533 | G32: 15082 | H32: 0 | I32: 15082 | K32: =I32-E32 -> -451
B33: Electricity
B34: Electricity Expense | C34: 2676 | E34: 2676 | G34: 3064 | I34: 3064
B35: Computer maintenance
B36: Janani Property Maintenance Charges | C36: 743 | E36: 743 | G36: 743 | I36: 743
B37: Janani Property Rental Charges | C37: 4302 | E37: 4302 | G37: 4302 | I37: 4302
B38: Laptop Rental Charges | C38: 1907 | E38: 1907 | G38: 2068 | I38: 2068
B39: Thiruttani rental charges | C39: 285 | E39: 285 | G39: 285 | I39: 285
B40: Max Office rental charges | C40: 4348 | E40: 4348 | G40: 4348 | I40: 4348
B41: Rent Expense | C41: 272 | D41: 1000 | E41: 1272 | G41: 272 | H41: 0 | I41: 272
B42: Trichy rental charges
B43: Telcom/Data & others | C43: 1546 | D43: 25406 | E43: 26953 | G43: 1464 | H43: 18105 | I43: 19569 | K43: =I43-E43 -> -7384
B44: Telephone Expense | D44: 295 | E44: 295 | H44: 541 | I44: 541 | K44: =I44-E44 -> 246
B45: Dues and Subscriptions | D45: 459 | E45: 459 | H45: 393 | I45: 393 | K45: =I45-E45 -> -66
B46: Software Expenses | D46: 24152 | E46: 24152 | H46: 16666 | I46: 16666 | K46: =I46-E46 -> -7486
B47: IT and Internet Expenses | C47: 485 | D47: 501 | E47: 985 | G47: 466 | H47: 506 | I47: 973 | K47: =I47-E47 -> -12
B48: Telecom Charges | C48: 34 | E48: 34 | G48: 146 | I48: 146 | K48: =I48-E48 -> 112
B49: Telephone Rental Charges | C49: 189 | E49: 189 | G49: 189 | I49: 189 | K49: =I49-E49 -> 0
B50: License/Subscription Charges | C50: 838 | E50: 838 | G50: 662 | I50: 662 | K50: =I50-E50 -> -176
B51: Transport | C51: 5351 | E51: 5351 | G51: 4371 | I51: 4371 | K51: =I51-E51 -> -980
B52: Staff Transportation Charges | C52: 5351 | E52: 5351 | G52: 4371 | I52: 4371 | K52: =I52-E52 -> -980
B53: Other COGS | C53: 9684 | E53: 9684 | G53: 7664 | I53: 7664 | K53: =I53-E53 -> -2020
B54: General Insurance
B55: Insurance
B56: Donation
B57: Software development and Hosting charges | C57: 1304 | E57: 1304 | G57: 360 | I57: 360
B58: Other Cogs- MD
B59: Employee Engagement
B60: Staff Welfare Expenses | C60: 3892 | E60: 3892 | G60: 3655 | I60: 3655
B61: Interest on OD | C61: 1417 | E61: 1417 | G61: 746 | I61: 746
B62: Fuel expenses
B63: Obo Health Inc
B64: Food Coupon-Happay Wallet | C64: 3070 | E64: 3070 | G64: 2902 | I64: 2902
B65: Software expense
B66: Total COGS | C66: 155448 | D66: 157300 | E66: 189430 | F66: -123319 | G66: 142214 | H66: 208935 | I66: 166233 | J66: -184916 | K66: =I66-E66 -> -23197
B67: GM | C67: -32129 | D67: 63915 | E67: 31785 | F67: 0 | G67: 42702 | H67: 18836 | I67: 61538 | J67: 0
B68: GM% | C68: (26 %) | D68: 29 % | E68: 14 % | F68: 0 | G68: 23 % | H68: 8 % | I68: 27 % | J68: 0
B69: SG&A
B70: Selling Expenses | C70: 1538 | D70: 1301 | E70: 2839 | G70: 1368 | H70: 1905 | I70: 3273 | K70: =I70-E70 -> 434
B71: Travel Expense
B72: Cyber Security Insurance
B73: Rewards and recognition
B74: Meals and Entertainment | C74: 62 | D74: 90 | E74: 152 | G74: 353 | H74: 717 | I74: 1070
B75: VISA charges
B76: Conference & Events
B77: Advertisement and marketing
B78: Sales and marketing | D78: 1211 | E78: 1211 | H78: 1188 | I78: 1188
B79: Business Promotion
B80: S&M Salaries | C80: 1476 | E80: 1476 | G80: 1015 | I80: 1015
B81: Gratuity | C81: 0 | E81: 0 | G81: 0 | I81: 0
B82: New Tools and Accesses - Needed
B83: Customs Duty
B84: G&A Expenses
B85: Salaries-Management & Others | C85: 9729 | D85: 17422 | E85: 27151 | G85: 9729 | H85: 28132 | I85: 37861 | K85: =I85-E85 -> 10710
B86: Bonus and Incentives | C86: 0 | E86: 0 | G86: 0 | I86: 0 | K86: =I86-E86 -> 0
B87: Management Salaries | C87: 9729 | D87: 17422 | E87: 27151 | G87: 9729 | H87: 28132 | I87: 37861 | K87: =I87-E87 -> 10710
B88: Legal & Professional Fees | C88: 2011 | D88: 3976 | E88: 5987 | G88: 1359 | H88: 4519 | I88: 5878 | K88: =I88-E88 -> -109
B89: Professional fees | K89: =I89-E89 -> #VALUE!
B90: FPO Charges - SRF | C90: 2011 | E90: 2011 | G90: 1359 | I90: 1359 | K90: =I90-E90 -> -652
B91: Legal & Professional Services | D91: 3976 | E91: 3976 | H91: 4519 | I91: 4519 | K91: =I91-E91 -> 543
B92: FPO Charges-SMCS GLOBAL | C92: 0 | E92: 0 | G92: 0 | I92: 0 | K92: =I92-E92 -> 0
B93: G&A salaries | C93: 2768 | D93: 3764 | E93: 6533 | G93: 2366 | H93: 7357 | I93: 9723 | K93: =I93-E93 -> 3190
B94: Payroll taxes | D94: 3764 | E94: 3764 | H94: 7357 | I94: 7357 | K94: =I94-E94 -> 3593
B95: HR Salaries | C95: 951 | E95: 951 | G95: 750 | I95: 750 | K95: =I95-E95 -> -201
B96: Admin Salaries | C96: 860 | E96: 860 | G96: 943 | I96: 943 | K96: =I96-E96 -> 83
B97: IT Salaries | C97: 958 | E97: 958 | G97: 673 | I97: 673 | K97: =I97-E97 -> -285
B98: Coder | K98: =I98-E98 -> #VALUE!
B99: Gen & Admin Expenses | C99: 3126 | D99: 12864 | E99: 15990 | G99: 2690 | H99: 6744 | I99: 9435 | K99: =I99-E99 -> -6555
B100: Consultancy Fees | K100: =I100-E100 -> #VALUE!
B101: Comission Paid-Scinet Inc | K101: =I101-E101 -> #VALUE!
B102: Leadership engagemnet | K102: =I102-E102 -> #VALUE!
B103: Charitable Donations | K103: =I103-E103 -> #VALUE!
...

Sheet Jan
B1: IMAGNUM HEALTHCARE SOLUTION PRIVATE LIMITED
B2: =MID(CELL("filename",B1),FIND("]",CELL("filename",B1))+1,250) -> Jan
B4: Particulars | C4: Jan-US | D4: Jan-India | E4: Jan Consolidation | F4: Budget Remarks
B5: Service Income
B6: Sales | C6: =C77 -> 226814 | D6: =D77 -> 0 | E6: =C6+D6 -> 226814
B7: Total Revenue | C7: =SUM(C6) -> 226814 | D7: =SUM(D6) -> 0 | E7: =C7+D7 -> 226814
B9: Overall Operational cost
B10: Manpower | C10: =C99 -> 0 | D10: =D99 -> 114851.43 | E10: =E99 -> 114851.43 | F10: Budgeted HC for operations & ops support is 208 whereas Actual HC is 270
B11: Facility Cost | C11: =C112 -> 2000 | D11: =D112 -> 13975.718 | E11: =C11+D11 -> 15975.718
B12: Telcom/Data & others | C12: =C123 -> 3270.23 | D12: =D123 -> 1668.7611 | E12: =C12+D12 -> 4938.9911
B13: Transport | C13: =C127 -> 0 | D13: =D127 -> 4438.587 | E13: =C13+D13 -> 4438.587 | F13: Transport cost budgeted in proportion with HC
B14: Other COGS | C14: =C142 -> 14832.9 | D14: =D142 -> 5397.5486 | E14: =C14+D14 -> 20230.449 | F14: Software Expense budgeted for $9,393 whereas actual it is $20,656
B15: Total COGS | C15: =SUM(C10:C14) -> 20103.13 | D15: =SUM(D10:D14) -> 140332.05 | E15: =SUM(E10:E14) -> 160435.18
B16: GP | C16: =C7-C15 -> 206710.87 | D16: =D7-D15 -> -140332.05 | E16: =E7-E15 -> 66378.82
B17: GM% | E17: =E16/E7 -> 0.29265751
B20: SG&A
B21: Selling Expenses | C21: =C159 -> 3440.69 | D21: =D159 -> 1759.788 | E21: =C21+D21 -> 5200.478
B22: G&A Expenses
B23: Salaries-Management & Others | C23: =C210 -> 37269.02 | D23: =D210 -> 9892.1087 | E23: =C23+D23 -> 47161.129
B24: Legal & Professional Fees | C24: =C205 -> 7940.38 | D24: =D205 -> 1413.0435 | E24: =C24+D24 -> 9353.4235
B25: G&A salaries | C25: =C198 -> 11722.56 | D25: =D198 -> 2606.087 | E25: =C25+D25 -> 14328.647
B26: Gen & Admin. Expenses | C26: =C190 -> 15020.47 | D26: =D190 -> 1528.303 | E26: =C26+D26 -> 16548.773 | F26: Insurance expense budgeted for $1,400 whereas actual it is $6,487 Consultancy fees not budgeted whereas actual it $3,750
B27: Total | C27: =SUM(C23:C26) -> 71952.43 | D27: =SUM(D23:D26) -> 15439.542 | E27: =C27+D27 -> 87391.972
B29: Overall SG&A | C29: =+C21+C27 -> 75393.12 | D29: =+D21+D27 -> 17199.33 | E29: =C29+D29 -> 92592.45
B31: EBITDA | C31: =C16-C29 -> 131317.75 | D31: =D16-D29 -> -157531.38 | E31: =E16-E29 -> -26213.63
B32: EBITDA% | E32: =E31/E7 -> -0.11557325
B34: Finance Cost | C34: =C219 -> 4889.52 | D34: =D219 -> -6231.8296 | E34: =C34+D34 -> -1342.3096
B35: Rates & Taxes | C35: =C221 -> 0 | D35: =D221 -> 0 | E35: =C35+D35 -> 0
B36: Depreciation | C36: =C222 -> 0 | D36: =D222 -> 0 | E36: =C36+D36 -> 0
B37: Total | C37: =SUM(C34:C36) -> 4889.52 | D37: =SUM(D34:D36) -> -6231.8296 | E37: =C37+D37 -> -1342.3096
B39: PBT | C39: =C31-C37 -> 126428.23 | D39: =D31-D37 -> -151299.55 | E39: =E31-E37 -> -24871.321
E40: =E39/E7 -> -0.10965514
B41: Check point
B42: Revenue | E42: =C72 -> 226527
B43: India cost | E43: 151604.88
B44: US cost | E44: =C7-C39 -> 100385.77
B45: Profit | E45: =E42-E43-E44 -> -25463.647
E46: =E45-E39 -> -592.32609
B49: Total Revenue | E49: =E7 -> 226814
B50: Directs | E50: 197
B51: Overall HC | E51: 281
B54: Rev/FTE (Pricing) | E54: =E49/E50 -> 1151.3401
B55: Cost/FTE | E55: =E15/E50 -> 814.39178
B56: Gross Profit/FTE | E56: =E54-E55 -> 336.94833
E57: =E56/E54 -> 0.29265751
B60: Rev/Head | E60: =E49/E51 -> 807.16726
B61: Cost/Head | E61: =(E7-E39)/E51 -> 895.6773
B62: Margin/Head | E62: =E60-E61 -> -88.510038
E63: =E62/E60 -> -0.10965514
B68: Detailed Break up
C69: 27
B70: =B4 -> Particulars | C70: =C4 -> Jan-US | D70: =D4 -> Jan-India | E70: =E4 -> Jan Consolidation | F70: =F4 -> Budget Remarks
B71: Service Income
B72: Sales | C72: 226527 | E72: =C72+D72 -> 226527
B73: Other Charges | C73: 0 | E73: =C73+D73 -> 0
B74: Buyout | C74: 0 | D74: 0 | E74: =C74+D74 -> 0
B75: Interest Income | C75: 0 | D75: 0 | E75: =C75+D75 -> 0
B76: General Income | C76: 287 | E76: =C76+D76 -> 287
B77: Direct Incomes | C77: =SUM(C72:C76) -> 226814 | D77: =SUM(D72:D76) -> 0 | E77: =SUM(E72:E76) -> 226814
B79: Manpower
B80: India cost
B81: Consultancy fee | C81: 0 | D81: 0 | E81: =C81+D81 -> 0
B82: Operation salaries | C82: 0 | D82: 65898.685 | E82: =C82+D82 -> 65898.685
B83: Ops Support Salaries | C83: 0 | D83: 37200.967 | E83: =C83+D83 -> 37200.967
B84: Contract employee salaries | C84: 0 | D84: 0 | E84: =C84+D84 -> 0
B85: Coding charges | C85: 0 | D85: 0 | E85: =C85+D85 -> 0
B86: Total | C86: =SUM(C81:C85) -> 0 | D86: =SUM(D81:D85) -> 103099.65 | E86: =SUM(E81:E85) -> 103099.65
B88: Employee statutory expenses
B89: Employee ESI | C89: 0 | D89: 82.630435 | E89: =C89+D89 -> 82.630435
B90: EPF Admin Charges | C90: 0 | D90: 406.91304 | E90: =C90+D90 -> 406.91304
B91: Employee PF | C91: 0 | D91: 5078.7174 | E91: =C91+D91 -> 5078.7174
B92: Employer ESI | C92: 0 | D92: 356.8913 | E92: =C92+D92 -> 356.8913
B93: Employer PF | C93: 0 | D93: 5078.7174 | E93: =C93+D93 -> 5078.7174
B94: Professional tax | C94: 0 | D94: 747.91304 | E94: =C94+D94 -> 747.91304
B95: Interest on TDS | C95: 0 | D95: 0 | E95: =C95+D95 -> 0
B96: Interest on employee statutory dues | C96: 0 | D96: 0 | E96: =C96+D96 -> 0
B97: Total | C97: =SUM(C88:C96) -> 0 | D97: =SUM(D88:D96) -> 11751.783 | E97: =C97+D97 -> 11751.783
B99: Total Manpower | C99: =C86+C97 -> 0 | D99: =D86+D97 -> 114851.43 | E99: =E86+E97 -> 114851.43
B101: Facility Cost
B102: Electricity | C102: 0 | D102: 0 | E102: =C102+D102 -> 0
B103: Electricity Expense | C103: 0 | D103: 1968.0435 | E103: =C103+D103 -> 1968.0435
B104: Computer maintenance | C104: 0 | D104: 0 | E104: =C104+D104 -> 0
B105: Janani Property Maintenance Charges | C105: 0 | D105: 743.04348 | E105: =C105+D105 -> 743.04348
B106: Janani Property Rental Charges | C106: 0 | D106: 4301.837 | E106: =C106+D106 -> 4301.837
B107: Laptop Rental Charges | C107: 0 | D107: 2057.9033 | E107: =C107+D107 -> 2057.9033
B108: Trichy rental charges | C108: 0 | D108: 271.73913 | E108: =C108+D108 -> 271.73913
B109: Thiruttani rental charges | C109: 0 | D109: 285.32609 | E109: =C109+D109 -> 285.32609
B110: Max Office rental charges | C110: 0 | D110: 4347.8261 | E110: =C110+D110 -> 4347.8261
B111: Rent Expense | C111: 2000 | D111: 0 | E111: =C111+D111 -> 2000
B112: Total | C112: =SUM(C102:C111) -> 2000 | D112: =SUM(D102:D111) -> 13975.718 | E112: =C112+D112 -> 15975.718
B115: Telecom Charges
B116: Telephone Expense | C116: 2335.84 | D116: 0 | E116: =C116+D116 -> 2335.84
B117: Dues and Subscriptions | C117: 435.09 | D117: 0 | E117: =C117+D117 -> 435.09
B118: Software Expenses | C118: 0 | D118: 0 | E118: =C118+D118 -> 0
B119: License/Subscription/Certification Charges | C119: 0 | D119: 988.9913 | E119: =C119+D119 -> 988.9913
B120: IT and Internet Expenses | C120: 499.3 | D120: 466.48913 | E120: =C120+D120 -> 965.78913
B121: Telecom Charges | C121: 0 | D121: 24.150217 | E121: =C121+D121 -> 24.150217
B122: Telephone Rental Charges | C122: 0 | D122: 189.13043 | E122: =C122+D122 -> 189.13043
B123: Total | C123: =SUM(C116:C122) -> 3270.23 | D123: =SUM(D116:D122) -> 1668.7611 | E123: =C123+D123 -> 4938.9911
B125: Transportation Costs
...

Sheet Holding Detailed Exp summary
A2: IMAGNUM HEALTHCARE SOLUTION PRIVATE LIMITED
B3: Sum of Amount | C3: Column Labels
B4: Row Labels | C4: 45688 | D4: 45716 | E4: 45747 | F4: 45777 | G4: 45808 | H4: 45838 | I4: 45869 | J4: 45900 | K4: 45930 | L4: 45961 | M4: 45991 | N4: 46022 | O4: 46053 | P4: 46081 | Q4: 46112 | R4: 46142 | S4: 46173 | T4: 46203 | U4: Jun Vs May
B5: Operational Cost | C5: 140372.38 | D5: 156066.25 | E5: 163126.01 | F5: 182521.71 | G5: 172967.17 | H5: 217751.89 | I5: 187196.35 | J5: 211746.73 | K5: 209436.87 | L5: 208717.45 | M5: 216280.72 | N5: 209450.3 | O5: 211311.47 | P5: 203313.12 | Q5: 106950.86 | R5: 193910.08 | S5: 179687.53 | T5: 163379.68 | U5: =S5-T5 -> 16307.85
B6: India Cost | C6: 137139 | D6: 141484 | E6: 140018 | F6: 164649 | G6: 151760 | H6: 200674 | I6: 158956 | J6: 173054 | K6: 187101 | L6: 183412 | M6: 190966 | N6: 187035 | O6: 184697 | P6: 184916 | Q6: 75319 | R6: 175901 | S6: 158280 | T6: 157139 | U6: =S6-T6 -> 1141
B7: Contractors | C7: 137139 | D7: 141484 | E7: 140018 | F7: 164649 | G7: 151760 | H7: 200674 | I7: 158956 | J7: 173054 | K7: 187101 | L7: 183412 | M7: 190966 | N7: 187035 | O7: 184697 | P7: 184916 | Q7: 75319 | R7: 175901 | S7: 158280 | T7: 157139 | U7: =S7-T7 -> 1141
B8: iMagnum Healthcare Solutions Pvt Ltd | C8: 137139 | D8: 141484 | E8: 140018 | F8: 164649 | G8: 151760 | H8: 200674 | I8: 158956 | J8: 173054 | K8: 187101 | L8: 183412 | M8: 190966 | N8: 187035 | O8: 184697 | P8: 184916 | Q8: 75319 | R8: 175901 | S8: 158280 | T8: 157139 | U8: =S8-T8 -> 1141
B9: Facility Cost | F9: 1050 | H9: 2000 | K9: 2000 | M9: 2000 | O9: 2000 | Q9: 1000 | S9: 3000 | U9: =S9-T9 -> 3000
B10: Rent Expense | F10: 1050 | H10: 2000 | K10: 2000 | M10: 2000 | O10: 2000 | Q10: 1000 | S10: 3000 | U10: =S10-T10 -> 3000
B11: Lynx Realty | F11: 1050 | H11: 2000 | K11: 2000 | M11: 2000 | O11: 2000 | Q11: 1000 | S11: 3000 | U11: =S11-T11 -> 3000
B12: Telecom Data & Others | C12: 1990.87 | D12: 613.96 | E12: 673.09 | F12: 924.82 | G12: 1687.9 | H12: 1193.92 | I12: 2480.76 | J12: 1380.49 | K12: 1568.84 | L12: 1388.64 | M12: 1260.19 | N12: 967.9 | O12: 3270.23 | P12: 1439.74 | Q12: 1254.75 | R12: 850.88 | S12: 874.67 | T12: 907.78 | U12: =S12-T12 -> -33.11
B13: Dues and Subscriptions | C13: 314.84 | D13: 321.81 | E13: 431.18 | F13: 309.74 | G13: 1155.59 | H13: 447.56 | I13: 375.97 | J13: 492.04 | K13: 610.89 | L13: 494.47 | M13: 426.89 | N13: 403.23 | O13: 435.09 | P13: 392.63 | Q13: 459.2 | R13: 352.46 | S13: 376.67 | T13: 366.03 | U13: =S13-T13 -> 10.64
B14: A2Webhost | K14: 212.26 | U14: =S14-T14 -> 0
B15: Adobe Systems | C15: 13.8 | D15: 13.8 | E15: 13.8 | F15: 13.8 | G15: 13.8 | H15: 13.8 | I15: 13.8 | J15: 13.8 | K15: 13.8 | L15: 13.8 | M15: 13.8 | N15: 13.8 | O15: 45.66 | P15: 13.8 | Q15: 13.8 | R15: 13.8 | S15: 13.8 | T15: 13.8 | U15: =S15-T15 -> 0
B16: Availity | G16: 26.65 | U16: =S16-T16 -> 0
B17: Calendly | C17: 25.3 | D17: 25.3 | E17: 25.3 | F17: 25.3 | G17: 25.3 | H17: 25.3 | I17: 25.3 | J17: 25.54 | K17: 25.54 | L17: 25.54 | M17: 25.54 | N17: 25.54 | O17: 25.54 | P17: 25.54 | Q17: 25.54 | R17: 25.54 | S17: 25.54 | T17: 25.54 | U17: =S17-T17 -> 0
B18: Chatgpt | C18: 180.88 | D18: 180.88 | E18: 180.88 | F18: 180.88 | G18: 180.88 | H18: 180.88 | I18: 186.2 | J18: 159.6 | K18: 159.6 | L18: 203.77 | M18: 191.52 | N18: 191.52 | O18: 191.52 | P18: 159.6 | Q18: 159.6 | R18: 119.43 | S18: 143.64 | T18: 133 | U18: =S18-T18 -> 10.64
B19: DROPBOX | C19: 12.78 | E19: 25.56 | F19: 12.78 | G19: 12.78 | H19: 12.78 | I19: 12.78 | J19: 12.78 | K19: 12.78 | L19: 12.78 | M19: 12.78 | N19: 12.78 | O19: 12.78 | P19: 12.78 | Q19: 12.78 | R19: 12.78 | S19: 12.78 | T19: 12.78 | U19: =S19-T19 -> 0
B20: MICROSOFT | J20: 137.79 | U20: =S20-T20 -> 0
B21: MongoDB | G21: 814.4 | U21: =S21-T21 -> 0
B22: Zoho Corp | C22: 82.08 | D22: 82.08 | E22: 82.08 | P22: 21.32 | Q22: 21.32 | R22: 21.32 | S22: 21.32 | T22: 21.32 | U22: =S22-T22 -> 0
B23: READ - MEETING | D23: 19.75 | E23: 21.01 | F23: 21.01 | G23: 21.01 | H23: 21.01 | I23: 21.01 | J23: 21.01 | K23: 21.01 | L23: 21.01 | M23: 21.01 | N23: 21.01 | O23: 21.01 | P23: 21.01 | Q23: 21.01 | R23: 21.01 | S23: 21.01 | T23: 21.01 | U23: =S23-T23 -> 0
B24: Bluefin | E24: 56.57 | U24: =S24-T24 -> 0
B25: GoDaddy | E25: 25.98 | H25: 133.02 | K25: 44.38 | Q25: 66.57 | U25: =S25-T25 -> 0
B26: QuickBooks Payments | F26: 55.97 | G26: 60.77 | H26: 60.77 | I26: 116.88 | J26: 121.52 | K26: 121.52 | L26: 138.58 | M26: 138.58 | N26: 138.58 | O26: 138.58 | P26: 138.58 | Q26: 138.58 | R26: 138.58 | S26: 138.58 | T26: 138.58 | U26: =S26-T26 -> 0
B27: McAfee | L27: 49.99 | U27: =S27-T27 -> 0
B28: Awaz | L28: 29 | U28: =S28-T28 -> 0
B29: Tailwind | M29: 23.66 | U29: =S29-T29 -> 0
B30: IT and Internet Expenses | C30: 31.92 | D30: 31.92 | F30: 227.68 | G30: 274.94 | H30: 509.84 | I30: 1726.01 | J30: 511.61 | K30: 586.55 | L30: 582.65 | M30: 540.68 | N30: 255.71 | O30: 499.3 | P30: 506.14 | Q30: 500.65 | R30: 213.15 | S30: 213.15 | T30: 213.15 | U30: =S30-T30 -> 0
B31: Digital Ocean | F31: 227.68 | G31: 274.94 | H31: 275.53 | I31: 303.7 | J31: 277.3 | K31: 283.79 | L31: 284.38 | M31: 284.97 | O31: 286.15 | P31: 292.99 | Q31: 287.5 | U31: =S31-T31 -> 0
B32: Figma | C32: 31.92 | D32: 31.92 | H32: 85.12 | I32: 85.12 | J32: 85.12 | K32: 85.12 | L32: 85.12 | M32: 42.56 | N32: 42.56 | U32: =S32-T32 -> 0
B33: Scalela | I33: 1188 | U33: =S33-T33 -> 0
B34: Semrush | H34: 149.19 | I34: 149.19 | J34: 149.19 | K34: 217.64 | L34: 213.15 | M34: 213.15 | N34: 213.15 | O34: 213.15 | P34: 213.15 | Q34: 213.15 | R34: 213.15 | S34: 213.15 | T34: 213.15 | U34: =S34-T34 -> 0
B35: Telephone Expense | C35: 1644.11 | D35: 260.23 | E35: 241.91 | F35: 387.4 | G35: 257.37 | H35: 236.52 | I35: 378.78 | J35: 376.84 | K35: 371.4 | L35: 311.52 | M35: 292.62 | N35: 308.96 | O35: 2335.84 | P35: 540.97 | Q35: 294.9 | R35: 285.27 | S35: 284.85 | T35: 328.6 | U35: =S35-T35 -> -43.75
B36: RINGCENTRAL INC | C36: 1427.47 | N36: 32.25 | O36: 2036.8 | U36: =S36-T36 -> 0
B37: Verizon | C37: 216.64 | D37: 260.23 | E37: 241.91 | F37: 387.4 | G37: 257.37 | H37: 236.52 | I37: 378.78 | J37: 376.84 | K37: 371.4 | L37: 311.52 | M37: 292.62 | N37: 276.71 | O37: 299.04 | P37: 540.97 | Q37: 294.9 | R37: 285.27 | S37: 284.85 | T37: 328.6 | U37: =S37-T37 -> -43.75
B38: Other COGS | C38: 1007.56 | D38: 13069.29 | E38: 14339.92 | F38: 15297.89 | G38: 17266.72 | H38: 13768.54 | I38: 18080.94 | J38: 37312.24 | K38: 15322.03 | L38: 20416.81 | M38: 20804.53 | N38: 17697.4 | O38: 14960.82 | P38: 16793.61 | Q38: 29302.11 | R38: 17158.2 | S38: 17532.86 | T38: 5332.9 | U38: =S38-T38 -> 12199.96
B39: Software Expenses | C39: 1007.56 | D39: 13069.29 | E39: 14339.92 | F39: 15297.89 | G39: 17266.72 | H39: 13768.54 | I39: 18080.94 | J39: 37312.24 | K39: 15322.03 | L39: 20416.81 | M39: 20804.53 | N39: 17697.4 | O39: 14960.82 | P39: 16793.61 | Q39: 29302.11 | R39: 17158.2 | S39: 17532.86 | T39: 5332.9 | U39: =S39-T39 -> 12199.96
B40: AdvancedMD | C40: 310.67 | D40: 7171.4 | E40: 6399.9 | F40: 9071.33 | G40: 9087.09 | H40: 9063.53 | I40: 9078.5 | J40: 21415.87 | K40: 9163.02 | L40: 17541.85 | M40: 13980.76 | N40: 13265.71 | O40: 9421.8 | P40: 13419.37 | Q40: 18963.63 | R40: 7046.68 | S40: 7046.68 | T40: 106.6 | U40: =S40-T40 -> 6940.08
B41: Availity | C41: 31.64 | D41: 26.65 | E41: 26.65 | F41: 26.65 | H41: 26.65 | I41: 26.65 | J41: 26.65 | K41: 28.09 | L41: 41.05 | M41: 70.69 | N41: 2734.34 | O41: 2215.06 | P41: 62.63 | Q41: 2196.77 | R41: 1398.06 | S41: 1066 | T41: 1066 | U41: =S41-T41 -> 0
B42: Claim.MD | C42: 105.8 | D42: 106.6 | E42: 106.6 | F42: 106.6 | G42: 111.33 | H42: 106.6 | I42: 107.67 | J42: 106.6 | K42: 106.6 | L42: 127.92 | M42: 128.56 | N42: 127.92 | O42: 127.92 | P42: 127.92 | Q42: 127.92 | R42: 127.92 | U42: =S42-T42 -> 0
B43: Cloudways LTD | C43: 103.84 | D43: 115.73 | E43: 151.38 | N43: 286.15 | R43: 333.94 | S43: 334.53 | T43: 335.12 | U43: =S43-T43 -> -0.59
B44: Contabo.com | C44: 16.89 | D44: 16.89 | E44: 19.9 | F44: 19.9 | G44: 19.9 | H44: 19.9 | J44: 19.9 | K44: 19.9 | L44: 19.9 | M44: 19.9 | N44: 19.9 | Q44: 22.45 | R44: 22.45 | U44: =S44-T44 -> 0
B45: Foxyproxy | L45: 161.78 | O45: 89.88 | U45: =S45-T45 -> 0
B46: Moet Advisors LLC | J46: 3856.63 | U46: =S46-T46 -> 0
B47: MongoDB | C47: 438.72 | D47: 487.3 | E47: 491.73 | F47: 650.59 | H47: 895.13 | I47: 899.65 | J47: 938.52 | K47: 905.42 | L47: 882.67 | M47: 930.85 | N47: 913.62 | O47: 937.77 | P47: 1015.3 | Q47: 656.99 | R47: 549.36 | S47: 570.63 | T47: 589.38 | U47: =S47-T47 -> -18.75
B48: Obo Health Inc | D48: 5000 | E48: 7000 | F48: 5000 | G48: 8000 | H48: 3500 | I48: 5000 | J48: 8000 | K48: 3500 | M48: 3500 | U48: =S48-T48 -> 0
B49: Office Ally | D49: 144.72 | E49: 143.76 | F49: 48.9 | G49: 48.4 | H49: 48.4 | I49: 48.4 | S49: 134.85 | T49: 89.9 | U49: =S49-T49 -> 44.95
B50: Trizetto Prov | F50: 373.92 | H50: 108.33 | I50: 2920.07 | J50: 2920.07 | U50: =S50-T50 -> 0
B51: RFPMart LLC | J51: 28 | U51: =S51-T51 -> 0
B52: SaaSMonk | K52: 1599 | L52: 1599 | U52: =S52-T52 -> 0
B53: Replit | L53: 42.64 | M53: 5.38 | U53: =S53-T53 -> 0
B54: Atlantic.net | M54: 2168.39 | N54: 349.76 | O54: 2168.39 | P54: 2168.39 | Q54: 2296.85 | R54: 2358.02 | S54: 2358.02 | T54: 2358.02 | U54: =S54-T54 -> 0
B55: Cair Health Inc. | Q55: 5000 | R55: 5000 | S55: 5000 | U55: =S55-T55 -> 5000
B56: Stedi, Inc. | Q56: 37.5 | R56: 321.77 | S56: 1022.15 | T56: 787.88 | U56: =S56-T56 -> 234.27
B57: Manpower | C57: 234.95 | D57: 899 | E57: 8095 | F57: 600 | G57: 2252.55 | H57: 115.43 | I57: 7678.65 | K57: 3445 | L57: 3500 | M57: 1250 | N57: 3750 | O57: 6383.42 | P57: 163.77 | Q57: 75 | U57: =S57-T57 -> 0
B58: Consultancy Fees | C58: 234.95 | D58: 899 | E58: 8095 | F58: 600 | G58: 2252.55 | H58: 115.43 | I58: 7678.65 | K58: 3445 | L58: 3500 | M58: 1250 | N58: 3750 | O58: 6383.42 | P58: 163.77 | Q58: 75 | U58: =S58-T58 -> 0
B59: Chugh LLP | E59: 8095 | F59: 600 | H59: 115.43 | U59: =S59-T59 -> 0
B60: HEALTHCARE BUSINESS | D60: 899 | I60: 2750 | U60: =S60-T60 -> 0
B61: Vfs Services | C61: 234.95 | U61: =S61-T61 -> 0
B62: iQuantified Management Services | G62: 2252.55 | I62: 661.65 | O62: 1688.42 | U62: =S62-T62 -> 0
B63: Lynx Realty | I63: 2000 | U63: =S63-T63 -> 0
B64: Gerald Mannikarote | I64: 2267 | U64: =S64-T64 -> 0
B65: Inc. Media | K65: 895 | O65: 2195 | U65: =S65-T65 -> 0
B66: Georgia Association | K66: 2550 | U66: =S66-T66 -> 0
B67: Maheshkumar Nagarajan | L67: 500 | U67: =S67-T67 -> 0
B68: HJC Consulting Group | L68: 3000 | U68: =S68-T68 -> 0
B69: MEDSOURCE AI LLC | M69: 1250 | N69: 3750 | O69: 2500 | U69: =S69-T69 -> 0
B70: MedTrade | P70: 163.77 | U70: =S70-T70 -> 0
B71: Harvard Business Services | Q71: 75 | U71: =S71-T71 -> 0
B72: SG&A | C72: 32725.65 | D72: 51292.53 | E72: 58047.99 | F72: 37674.75 | G72: 51041.81 | H72: 72849.56 | I72: 61825.75 | J72: 70957.79 | K72: 85172.25 | L72: 91962.23 | M72: 86109.18 | N72: 90520.92 | O72: 68881.78 | P72: 54279.27 | Q72: 46623.35 | R72: 38282.42 | S72: 31772.45 | T72: 36564.68 | U72: =S72-T72 -> -4792.23
B73: Management Salaries | C73: 29384.96 | D73: 37861.26 | E73: 30292.26 | F73: 30243.66 | G73: 30243.66 | H73: 54717.49 | I73: 44891.08 | J73: 49084.66 | K73: 48930.97 | L73: 68580.96 | M73: 51084.81 | N73: 59175.58 | O73: 48991.58 | P73: 35488.45 | Q73: 21186.16 | R73: 26840.43 | S73: 21805.57 | T73: 21563.65 | U73: =S73-T73 -> 241.92
B74: Payroll Taxes | C74: 8472.87 | D74: 7948.53 | E74: 7879.53 | F74: 7830.93 | G74: 7830.93 | H74: 11746.4 | I74: 10227.62 | J74: 11271.33 | K74: 11100.49 | L74: 11395.19 | M74: 11129.15 | N74: 17255.34 | O74: 11722.56 | P74: 7356.56 | Q74: 3764.4 | R74: 3675.33 | S74: 5513 | T74: 3675.34 | U74: =S74-T74 -> 1837.66
B75: ADP | C75: 8472.87 | D75: 7948.53 | E75: 7879.53 | F75: 7830.93 | G75: 7830.93 | H75: 11746.4 | I75: 10227.62 | J75: 11271.33 | K75: 11100.49 | L75: 11395.19 | M75: 11129.15 | N75: 17255.34 | O75: 11722.56 | P75: 7356.56 | Q75: 3764.4 | R75: 3675.33 | S75: 5513 | T75: 3675.34 | U75: =S75-T75 -> 1837.66
B76: Management salaries | C76: 20912.09 | D76: 29912.73 | E76: 22412.73 | F76: 22412.73 | G76: 22412.73 | H76: 42971.09 | I76: 34663.46 | J76: 37813.33 | K76: 37830.48 | L76: 57185.77 | M76: 39955.66 | N76: 41920.24 | O76: 37269.02 | P76: 28131.89 | Q76: 17421.76 | R76: 23165.1 | S76: 16292.57 | T76: 17888.31 | U76: =S76-T76 -> -1595.74
B77: ADP | C77: 20912.09 | D77: 29912.73 | E77: 22412.73 | F77: 22412.73 | G77: 22412.73 | H77: 42971.09 | I77: 34663.46 | J77: 37813.33 | K77: 37830.48 | L77: 57185.77 | M77: 39955.66 | N77: 41920.24 | O77: 37269.02 | P77: 28131.89 | Q77: 17421.76 | R77: 23165.1 | S77: 16292.57 | T77: 17888.31 | U77: =S77-T77 -> -1595.74
B78: G&A Cost | C78: 3081.17 | D78: 2739.06 | E78: 13631.97 | F78: 2879.35 | G78: 17739.28 | H78: 15256.63 | I78: 12498.98 | J78: 18151.03 | K78: 30611.88 | L78: 18714 | M78: 18187.01 | N78: 29676.12 | O78: 17157.32 | P78: 15266.51 | Q78: 17606.54 | R78: 9901.58 | S78: 8937.91 | T78: 13893.06 | U78: =S78-T78 -> -4955.15
B79: Fuel/Mileage Expenses | C79: 36.61 | D79: 66.57 | E79: 274.09 | F79: 163.81 | G79: 21.71 | I79: 53.98 | J79: 179.88 | K79: 226.48 | L79: 149.44 | M79: 199.15 | N79: 35.41 | O79: 132.06 | P79: 125.17 | Q79: 147.71 | R79: 212.1 | U79: =S79-T79 -> 0
B80: Buc-EES | F80: 115.27 | U80: =S80-T80 -> 0
B81: Chevron | E81: 18.36 | J81: 40 | O81: 37.46 | U81: =S81-T81 -> 0
B82: H-E-B | D82: 28.87 | E82: 64.77 | J82: 90.18 | L82: 149.44 | N82: 35.41 | O82: 94.6 | Q82: 147.71 | R82: 185.83 | U82: =S82-T82 -> 0
B83: Shell | C83: 36.61 | D83: 37.7 | E83: 111.05 | F83: 48.54 | G83: 21.71 | I83: 53.98 | K83: 183.21 | M83: 199.15 | P83: 49.41 | R83: 26.27 | U83: =S83-T83 -> 0
B84: Walmart | E84: 10.12 | U84: =S84-T84 -> 0
B85: Costco | E85: 40.82 | P85: 75.76 | U85: =S85-T85 -> 0
B86: BP | E86: 28.97 | U86: =S86-T86 -> 0
B87: Katy Fwy | K87: 43.27 | U87: =S87-T87 -> 0
B88: X Christiana Rd | J88: 49.7 | U88: =S88-T88 -> 0
B89: Insurance Expense | C89: 1811.88 | D89: 1322.48 | E89: 8253.68 | F89: 1322.48 | G89: 6785.72 | H89: 3980.16 | I89: 3768.26 | J89: 5843.53 | K89: 6509.57 | L89: 6814.58 | M89: 6487.08 | N89: 6487.08 | O89: 6727.8 | P89: 3582.42 | Q89: 9653.09 | R89: 3024.96 | S89: 5449.75 | T89: 5414.75 | U89: =S89-T89 -> 35
B90: United Health Care | C90: 454.4 | U90: =S90-T90 -> 0
B91: Manhattanlife | C91: 804.01 | D91: 804.01 | E91: 804.01 | F91: 804.01 | G91: 804.01 | H91: 804.01 | I91: 804.01 | U91: =S91-T91 -> 0
B92: NGIC | C92: 553.47 | D92: 518.47 | E92: 518.47 | F92: 518.47 | G92: 518.47 | H92: 518.47 | I92: 518.47 | J92: -234.15 | U92: =S92-T92 -> 0
B93: First Insurance | E93: 6931.2 | G93: 5463.24 | H93: 2657.68 | I93: 2445.78 | J93: 2445.78 | K93: 3102.67 | L93: 2657.68 | M93: 2657.68 | N93: 2657.68 | O93: 2657.68 | Q93: 6628.13 | S93: 2089.79 | T93: 2089.79 | U93: =S93-T93 -> 0
B94: ICHRA | J94: 600 | U94: =S94-T94 -> 0
B95: Base | K95: 375 | L95: 1125 | M95: 797.5 | N95: 797.5 | O95: 797.5 | P95: 717.5 | Q95: 717.5 | R95: 717.5 | S95: 1052.5 | T95: 1017.5 | U95: =S95-T95 -> 35
B96: iMagnum Healthcare Solutions Pvt Ltd | J96: 3031.9 | K96: 3031.9 | L96: 3031.9 | M96: 3031.9 | N96: 3031.9 | O96: 3272.62 | P96: 2864.92 | Q96: 2307.46 | R96: 2307.46 | S96: 2307.46 | T96: 2307.46 | U96: =S96-T96 -> 0
B97: Meals and Entertainment | C97: 145.84 | D97: 1109.45 | E97: 3461.15 | F97: 362.92 | G97: 520.75 | I97: 114.49 | J97: 1373.65 | K97: 548.37 | L97: 311.05 | M97: 687.38 | N97: 354.63 | O97: 579.89 | P97: 716.83 | Q97: 150.08 | R97: 565.97 | S97: 49 | U97: =S97-T97 -> 49
B98: Courtyard By MarriotLewisville | O98: 143.37 | U98: =S98-T98 -> 0
B99: Hilton Garden | D99: 456.61 | E99: 593.85 | G99: 520.75 | P99: 221.32 | U99: =S99-T99 -> 0
B100: Olive Garden | J100: 96.47 | U100: =S100-T100 -> 0
B101: Sangam Indian Cuisine | J101: 37.79 | N101: 169.44 | U101: =S101-T101 -> 0
...

Sheet Subs Detailed Exp Summary
A1: IMAGNUM HEALTHCARE SOLUTION PRIVATE LIMITED
B4: Sum of Amount | E4: Month
B5: Cost Category | C5: Ledger Name | D5: Supplier Name | E5: 45688 | F5: 45716 | G5: 45747 | H5: 45777 | I5: 45808 | J5: 45838 | K5: 45869 | L5: 45900 | M5: 45930 | N5: 45961 | O5: 45991 | P5: 46022 | Q5: 46053 | R5: 46081 | S5: 46112 | T5: 46142 | U5: 46173 | V5: 46203 | W5: Jun Vs May | X5: in $
B6: 1.Manpower | C6: Operation Salaries | D6: Operation Salaries | E6: 3762414 | F6: 4457855 | G6: 4579463 | H6: 4473906 | I6: 4728640 | J6: 5065520 | K6: 5158862 | L6: 5788065 | M6: 5991910 | N6: 6270781 | O6: 6229342 | P6: 6323574 | Q6: 6062679 | R6: 6115267 | S6: 6041252 | T6: 5768982 | U6: 5470829 | V6: 5698725 | W6: =U6-V6 -> -227896 | X6: =W6/94 -> -2424.4255
C7: Ops Support Salaries | D7: Ops Support Salaries | E7: 1911823 | F7: 2198354 | G7: 2043456 | H7: 2108487 | I7: 2151697 | J7: 2220435 | K7: 2498763 | L7: 2762127 | M7: 2796629 | N7: 3187170 | O7: 3255082 | P7: 3428387 | Q7: 3422489 | R7: 3333406 | S7: 3516012 | T7: 3503973 | U7: 3335558 | V7: 3198901 | W7: =U7-V7 -> 136657 | X7: =W7/94 -> 1453.7979
C8: Bonus and Incentives | D8: HDFC Bank | E8: 758750 | Q8: 15000 | W8: =U8-V8 -> 0 | X8: =W8/94 -> 0
C9: Contract Employee Salaries | D9: Contract Employee Salaries | E9: 47000 | F9: 47000 | G9: 47000 | H9: 47000 | I9: 28667 | J9: 12000 | K9: 12000 | L9: 12000 | M9: 12000 | N9: 12000 | O9: 12000 | P9: 12000 | R9: 20000 | S9: 20000 | U9: 20000 | V9: 20000 | W9: =U9-V9 -> 0 | X9: =W9/94 -> 0
B10: 1.Manpower Total | E10: 6479987 | F10: 6703209 | G10: 6669919 | H10: 6629393 | I10: 6909004 | J10: 7297955 | K10: 7669625 | L10: 8562192 | M10: 8800539 | N10: 9469951 | O10: 9496424 | P10: 9763961 | Q10: 9500168 | R10: 9468673 | S10: 9577264 | T10: 9272955 | U10: 8826387 | V10: 8917626 | W10: =U10-V10 -> -91239 | X10: =W10/94 -> -970.62766
B11: 2.Facility cost | C11: Janani Property Rental Charges | D11: JANANI PROPERTY & ESTATES PVT LTD | E11: 376923 | F11: 376923 | G11: 376923 | H11: 376923 | I11: 376923 | J11: 376923 | K11: 376923 | L11: 376923 | M11: 376923 | N11: 395769 | O11: 395769 | P11: 395769 | Q11: 395769 | R11: 395769 | S11: 395769 | T11: 395769 | U11: 395769 | V11: 395769 | W11: =U11-V11 -> 0 | X11: =W11/94 -> 0
C12: Max Office rental charges | D12: Max Office | K12: 400000 | L12: 400000 | M12: 400000 | N12: 400000 | O12: 400000 | P12: 400000 | Q12: 400000 | R12: 400000 | S12: 400000 | T12: 400000 | U12: 400000 | V12: 400000 | W12: =U12-V12 -> 0 | X12: =W12/94 -> 0
C13: Electricity Expense | D13: HDFC Bank | R13: 373 | W13: =U13-V13 -> 0 | X13: =W13/94 -> 0
D14: TAMILNADU GENERATION AND DISTRIBUTION CORPORATION LIMITED | E14: 180904.38 | F14: 217106.48 | G14: 182837.26 | H14: 237374.54 | I14: 205380.36 | J14: 275963.02 | K14: 222710.11 | L14: 282109.83 | M14: 219561 | N14: 278072 | O14: 200679 | P14: 246415 | Q14: 180086 | R14: 212225 | S14: 213905.73 | T14: 224144 | U14: 205772 | V14: 271740 | W14: =U14-V14 -> -65968 | X14: =W14/94 -> -701.78723
D15: Max Office | L15: 15396 | M15: 33468 | O15: 47724 | P15: 19848 | R15: 69324 | S15: 32304 | T15: 50052 | U15: 42360 | V15: 54060 | W15: =U15-V15 -> -11700 | X15: =W15/94 -> -124.46809
D16: Amutha Trichy Rental House | Q16: 974 | U16: 4907 | W16: =U16-V16 -> 4907 | X16: =W16/94 -> 52.202128
C17: Laptop Rental Charges | D17: M.R. INFOTECH | E17: 119245 | F17: 119485 | G17: 119470 | H17: 120435 | I17: 136370 | J17: 140575 | K17: 151460 | L17: 150740 | M17: 152855.09 | N17: 159250.09 | O17: 168956.09 | P17: 181117.09 | Q17: 189327.1 | R17: 190241.09 | S17: 175436.09 | T17: 180696.09 | U17: 182988.09 | V17: 192532.09 | W17: =U17-V17 -> -9544 | X17: =W17/94 -> -101.53191
C18: Janani Property Maintenance Charges | D18: JANANI PROPERTY & ESTATES PVT LTD | E18: 65105 | F18: 65105 | G18: 65105 | H18: 65105 | I18: 65105 | J18: 65105 | K18: 65105 | L18: 65105 | M18: 65105 | N18: 68360 | O18: 68360 | P18: 68360 | Q18: 68360 | R18: 68360 | S18: 68360 | T18: 68360 | U18: 68360 | V18: 68360 | W18: =U18-V18 -> 0 | X18: =W18/94 -> 0
C19: Thiruttani rental charges | D19: Balaji Towers | E19: 25000 | F19: 25000 | G19: 25000 | H19: 25000 | I19: 26250 | J19: 26250 | K19: 26250 | L19: 26250 | M19: 26250 | N19: 26250 | O19: 26250 | P19: 26250 | Q19: 26250 | R19: 26250 | S19: 26250 | T19: 26250 | U19: 27562 | V19: 27563 | W19: =U19-V19 -> -1 | X19: =W19/94 -> -0.010638298
C20: Trichy rental charges | D20: Amutha Trichy Rental House | O20: 25000 | P20: 25000 | Q20: 25000 | R20: 25000 | S20: 25000 | T20: 25000 | U20: 25000 | V20: 25000 | W20: =U20-V20 -> 0 | X20: =W20/94 -> 0
C21: Computer maintenance | D21: Xtreme Infotech | J21: 7000 | W21: =U21-V21 -> 0 | X21: =W21/94 -> 0
B22: 2.Facility cost Total | E22: 767177.38 | F22: 803619.48 | G22: 769335.26 | H22: 824837.54 | I22: 810028.36 | J22: 891816.02 | K22: 1242448.1 | L22: 1316523.8 | M22: 1274162.1 | N22: 1327701.1 | O22: 1332738.1 | P22: 1362759.1 | Q22: 1285766.1 | R22: 1387542.1 | S22: 1337024.8 | T22: 1370271.1 | U22: 1352718.1 | V22: 1435024.1 | W22: =U22-V22 -> -82306 | X22: =W22/94 -> -875.59574
B23: 3.Telecom Data & others | C23: License/Subscription/Certification Charges | D23: Adobe Systems Software Ireland Ltd | E23: 5160.06 | F23: 5160.06 | G23: 6659.06 | H23: 6659.06 | I23: 6659.06 | J23: 6659.06 | K23: 6659.06 | L23: 10243.06 | M23: 10041.06 | N23: 10041.06 | O23: 10041.06 | P23: 10041.06 | Q23: 10041.06 | R23: 10041.06 | S23: 11256.06 | T23: 11256.06 | U23: 2367 | V23: 2367 | W23: =U23-V23 -> 0 | X23: =W23/94 -> 0
D24: E2E Networks Limited | E24: 45000 | F24: 50000 | G24: 50000 | H24: 50000 | I24: 49999 | J24: 50000 | K24: 50000 | L24: 50000 | M24: 56153 | O24: 50000 | P24: 50000 | Q24: 32000 | R24: 7950 | W24: =U24-V24 -> 0 | X24: =W24/94 -> 0
D25: Esoftsol Infocom Pvt Ltd | E25: 147510 | F25: 18378 | W25: =U25-V25 -> 0 | X25: =W25/94 -> 0
D26: HDFC credit card (Kasi) | O26: 5990 | W26: =U26-V26 -> 0 | X26: =W26/94 -> 0
D27: LinkedIn | E27: 6299.14 | F27: 6299.14 | G27: 9446.74 | H27: 6299.14 | I27: 6299.14 | J27: 6299.14 | K27: 6299.14 | L27: 6299.14 | M27: 6299.14 | N27: 6299.14 | O27: 6299.14 | P27: 6299.14 | Q27: 6299.14 | S27: 21899.87 | T27: 9536.2 | W27: =U27-V27 -> 0 | X27: =W27/94 -> 0
D28: Udemy India LLP | F28: 1068 | W28: =U28-V28 -> 0 | X28: =W28/94 -> 0
D29: License/Subscription/Certification Charges | E29: 18468 | F29: 18468 | G29: 18468 | H29: 18468 | I29: 18468 | J29: 21097 | K29: 24486 | L29: 28554 | M29: 37971 | N29: 38106 | O29: 41354 | P29: 41354 | Q29: 42647 | R29: 42870 | S29: 43953 | T29: 48603 | U29: 48603 | V29: 74276 | W29: =U29-V29 -> -25673 | X29: =W29/94 -> -273.11702
D30: AAPC | O30: 19820.54 | W30: =U30-V30 -> 0 | X30: =W30/94 -> 0
D31: ClaudeAI | U31: 1916.04 | V31: 26433.59 | W31: =U31-V31 -> -24517.55 | X31: =W31/94 -> -260.825
C32: IT and Internet Expenses | D32: IT and Internet Expenses | E32: 20000 | F32: 27416 | G32: 27416 | H32: 33750 | I32: 33750 | J32: 33750 | K32: 33750 | L32: 42917 | M32: 42917 | N32: 52084 | O32: 42917 | P32: 42917 | Q32: 42917 | R32: 42917 | S32: 42917 | T32: 42917 | U32: 42917 | V32: 42916 | W32: =U32-V32 -> 1 | X32: =W32/94 -> 0.010638298
D33: SYSVEL TECHNOLOGY | I33: 3000 | W33: =U33-V33 -> 0 | X33: =W33/94 -> 0
D34: TATA TELESERVICES LIMITED | L34: 5000 | W34: =U34-V34 -> 0 | X34: =W34/94 -> 0
D35: Slack | S35: 1673.76 | T35: 1179 | U35: 1149.52 | V35: 1616.37 | W35: =U35-V35 -> -466.85 | X35: =W35/94 -> -4.9664894
D36: Reliance Jio Infocomm Limited | U36: 20750 | W36: =U36-V36 -> 20750 | X36: =W36/94 -> 220.74468
C37: Software development and Hosting charges | D37: Futurecalls Technology | L37: 1936 | M37: 15000 | N37: 15000 | O37: 15000 | P37: 23241.77 | Q37: 32542.65 | R37: 33095.87 | S37: 64203.88 | T37: 15000 | U37: 39529.52 | V37: 74866 | W37: =U37-V37 -> -35336.48 | X37: =W37/94 -> -375.92
D38: HDFC Bank | N38: 20997 | W38: =U38-V38 -> 0 | X38: =W38/94 -> 0
D39: Info Edge (India) Ltd | G39: 55800 | S39: 55800 | W39: =U39-V39 -> 0 | X39: =W39/94 -> 0
D40: Claritus Management Consulting Pvt. Ltd. | Q40: 967.34 | W40: =U40-V40 -> 0 | X40: =W40/94 -> 0
D41: Software development and Hosting charges | E41: 1000 | F41: 1000 | G41: 1000 | H41: 1000 | I41: 1000 | J41: 1000 | K41: 1000 | L41: 1000 | M41: 1000 | N41: 1000 | O41: 1000 | P41: 1000 | W41: =U41-V41 -> 0 | X41: =W41/94 -> 0
D42: GAMMA.APP | N42: 22787.23 | W42: =U42-V42 -> 0 | X42: =W42/94 -> 0
D43: Amazon | U43: 847.46 | W43: =U43-V43 -> 847.46 | X43: =W43/94 -> 9.0155319
C44: Telephone Rental Charges | D44: UNIFIED VOICE COMMUNICATION PRIVATE LIMITED | E44: 15900 | F44: 15100 | G44: 15100 | H44: 15100 | I44: 15100 | J44: 15100 | K44: 15100 | L44: 16300 | M44: 15900 | N44: 15900 | O44: 18100 | P44: 17400 | Q44: 17400 | R44: 17400 | S44: 17400 | T44: 19560 | U44: 19886 | V44: 19500 | W44: =U44-V44 -> 386 | X44: =W44/94 -> 4.106383
C45: Cyber Security Insurance | D45: Cyber Security Insurance | E45: 37500 | F45: 37500 | G45: 37500 | H45: 37500 | I45: 37500 | W45: =U45-V45 -> 0 | X45: =W45/94 -> 0
C46: Telecom Charges | D46: BHARTI AIRTEL LIMITED | E46: 2044.82 | F46: 2044.82 | G46: 2044.82 | H46: 2044.82 | I46: 6762.82 | J46: 2044.82 | K46: 2044.82 | L46: 2044.82 | M46: 2339.82 | N46: 2221.82 | O46: 3493 | P46: 2221.82 | Q46: 2221.82 | R46: 3021.36 | S46: 3156.71 | T46: 2679.9 | U46: 2679.9 | V46: 2679.9 | W46: =U46-V46 -> 0 | X46: =W46/94 -> 0
D47: HDFC Bank | E47: 3455 | R47: 10443 | W47: =U47-V47 -> 0 | X47: =W47/94 -> 0
B48: 3.Telecom Data & others Total | E48: 302337.02 | F48: 182434.02 | G48: 223434.62 | H48: 170821.02 | I48: 178538.02 | J48: 135950.02 | K48: 139339.02 | L48: 164294.02 | M48: 187621.02 | N48: 184436.25 | O48: 214014.74 | P48: 194474.79 | Q48: 187036.01 | R48: 167738.29 | S48: 262260.28 | T48: 150731.16 | U48: 180645.44 | V48: 244654.86 | W48: =U48-V48 -> -64009.42 | X48: =W48/94 -> -680.95128
B49: 4.Transport Cost | C49: Staff Transportation Charges | D49: HDFC Bank | M49: 4 | W49: =U49-V49 -> 0 | X49: =W49/94 -> 0
D50: VKS Travels | E50: 256800 | F50: 267200 | G50: 248000 | H50: 252400 | I50: 237080 | J50: 189600 | K50: 228800 | L50: 250200 | M50: 262000 | N50: 302876 | O50: 303800 | P50: 278000 | Q50: 297200 | R50: 299400 | S50: 318700 | T50: 286700 | U50: 325500 | V50: 410600 | W50: =U50-V50 -> -85100 | X50: =W50/94 -> -905.31915
D51: Select Cabs | L51: 54600 | M51: 39000 | N51: 90350 | O51: 92300 | P51: 111150 | Q51: 102700 | R51: 89700 | S51: 83850 | T51: 89050 | U51: 78650 | V51: 120596 | W51: =U51-V51 -> -41946 | X51: =W51/94 -> -446.23404
D52: TRTS Travels | V52: 8500 | W52: =U52-V52 -> -8500 | X52: =W52/94 -> -90.425532
B53: 4.Transport Cost Total | E53: 256800 | F53: 267200 | G53: 248000 | H53: 252400 | I53: 237080 | J53: 189600 | K53: 228800 | L53: 304800 | M53: 301004 | N53: 393226 | O53: 396100 | P53: 389150 | Q53: 399900 | R53: 389100 | S53: 402550 | T53: 375750 | U53: 404150 | V53: 539696 | W53: =U53-V53 -> -135546 | X53: =W53/94 -> -1441.9787
B54: 5.Other COGS | C54: Staff Welfare Expenses | D54: HDFC Bank | E54: 4200 | G54: 39096.45 | H54: 42861.25 | I54: 44593 | J54: 13596 | K54: 100 | L54: 90000 | M54: 3750 | N54: 208593 | O54: 22062 | P54: 32011 | Q54: 29246 | R54: 45039 | S54: 45037 | T54: 10135 | U54: 31508.66 | V54: 92619.5 | W54: =U54-V54 -> -61110.84 | X54: =W54/94 -> -650.11532
D55: HDFC credit card (Imagnum) | E55: 2432.6 | G55: 1579.91 | H55: 9110 | N55: 1899.11 | P55: 6871.29 | Q55: 9267.48 | R55: 8571.8 | T55: 14947.89 | U55: 1083.72 | V55: 12402.33 | W55: =U55-V55 -> -11318.61 | X55: =W55/94 -> -120.41074
D56: HDFC credit card (Kasi) | G56: 675 | J56: 1150 | O56: 1177.34 | U56: 3622 | W56: =U56-V56 -> 3622 | X56: =W56/94 -> 38.531915
D57: SRI LAKSHMI NARASIMHAR PHOTOFRAME CENTER | F57: 112960 | G57: 37160 | I57: 2760 | K57: 3160 | L57: 5750 | M57: 1325 | S57: 2570 | V57: 155353 | W57: =U57-V57 -> -155353 | X57: =W57/94 -> -1652.6915
D58: SRI LAKSHMI RESIDENCY | E58: 8750 | G58: 3750 | H58: 2589.29 | N58: 1143 | W58: =U58-V58 -> 0 | X58: =W58/94 -> 0
D59: Staff Welfare Expenses | E59: 27922 | F59: 34975 | G59: 33338 | H59: 144422 | I59: 23000 | J59: 13000 | K59: 31833 | L59: 47348 | M59: 74731 | N59: 73750 | O59: 197389.2 | P59: 11017 | R59: 269358.45 | S59: 285358.45 | T59: 122969.25 | U59: 120969.25 | V59: 150171.25 | W59: =U59-V59 -> -29202 | X59: =W59/94 -> -310.65957
D60: KHIVRAJ MOTORS PRIVATE LIMITED | F60: 29023.29 | W60: =U60-V60 -> 0 | X60: =W60/94 -> 0
D61: JENNYS HOTEL PVT. LTD. | F61: 10950 | W61: =U61-V61 -> 0 | X61: =W61/94 -> 0
D62: Aditya Birla Fashion | G62: 15594 | W62: =U62-V62 -> 0 | X62: =W62/94 -> 0
D63: VASANTH & CO | I63: 28125 | K63: 10932.28 | W63: =U63-V63 -> 0 | X63: =W63/94 -> 0
D64: Medway Hospitals | L64: 8514.75 | M64: 7019 | O64: 650 | R64: 1727.18 | W64: =U64-V64 -> 0 | X64: =W64/94 -> 0
D65: Health & Safety Hub | L65: 15000 | W65: =U65-V65 -> 0 | X65: =W65/94 -> 0
D66: Spelman Printers | M66: 400 | N66: 800 | W66: =U66-V66 -> 0 | X66: =W66/94 -> 0
D67: HDFC credit card (Ashok Kumar) | N67: 160 | V67: 1300 | W67: =U67-V67 -> -1300 | X67: =W67/94 -> -13.829787
D68: Tharikha Medicals | P68: 1091 | W68: =U68-V68 -> 0 | X68: =W68/94 -> 0
D69: CATAWING CYBERNETICS PVT. LTD. | R69: 3600 | S69: 2800 | T69: 4800 | U69: 1200 | W69: =U69-V69 -> 1200 | X69: =W69/94 -> 12.765957
D70: Pure Palate | S70: 22339 | T70: 24040 | U70: 22340 | W70: =U70-V70 -> 22340 | X70: =W70/94 -> 237.65957
C71: Insurance | D71: Insurance | E71: 47089 | F71: 47089 | G71: 47612 | H71: 49045 | I71: 50235 | J71: 50235 | K71: 60835 | L71: 60835 | M71: 60135 | N71: 63932 | O71: 63932 | P71: 69537 | Q71: 69537 | R71: 69537 | S71: 69537 | T71: 69537 | U71: 69537 | V71: 69537 | W71: =U71-V71 -> 0 | X71: =W71/94 -> 0
D72: HDFC OD Account | F72: 39839 | W72: =U72-V72 -> 0 | X72: =W72/94 -> 0
D73: BAJAJ ALLIANZ GENERAL INSURANCE COMPANY LIMITED | L73: 9326 | M73: 8273.5 | W73: =U73-V73 -> 0 | X73: =W73/94 -> 0
C74: Rewards and Recognition | D74: HDFC Bank | G74: 95500 | V74: 97000 | W74: =U74-V74 -> -97000 | X74: =W74/94 -> -1031.9149
D75: Razorpay Wallet | V75: 25000 | W75: =U75-V75 -> -25000 | X75: =W75/94 -> -265.95745
C76: Employee Engagement | D76: HDFC Bank | P76: 5000 | W76: =U76-V76 -> 0 | X76: =W76/94 -> 0
B77: 5.Other COGS Total | E77: 90393.6 | F77: 274836.29 | G77: 274305.36 | H77: 248027.54 | I77: 148713 | J77: 77981 | K77: 106860.28 | L77: 236773.75 | M77: 155633.5 | N77: 350277.11 | O77: 285210.54 | P77: 125527.29 | Q77: 108050.48 | R77: 397833.43 | S77: 427641.45 | T77: 246429.14 | U77: 250260.63 | V77: 603383.08 | W77: =U77-V77 -> -353122.45 | X77: =W77/94 -> -3756.6218
B78: 9.Exchange Gain or Loss | C78: Exchange Gain or Loss | D78: IMAGNUM US | E78: -167235.57 | F78: -138326.94 | G78: -28714.17 | H78: 219266.34 | I78: 83110.83 | J78: -55995.8 | K78: -95145.17 | M78: -256064.23 | N78: -595788.35 | O78: -362545.16 | P78: -476463.83 | Q78: -574648.6 | R78: -427104.2 | S78: -780353.77 | T78: -384237 | U78: -674963.8 | V78: -427214.65 | W78: =U78-V78 -> -247749.15 | X78: =W78/94 -> -2635.6293
B79: 9.Exchange Gain or Loss Total | E79: -167235.57 | F79: -138326.94 | G79: -28714.17 | H79: 219266.34 | I79: 83110.83 | J79: -55995.8 | K79: -95145.17 | M79: -256064.23 | N79: -595788.35 | O79: -362545.16 | P79: -476463.83 | Q79: -574648.6 | R79: -427104.2 | S79: -780353.77 | T79: -384237 | U79: -674963.8 | V79: -427214.65 | W79: =U79-V79 -> -247749.15 | X79: =W79/94 -> -2635.6293
B80: 6.G&A salaries | C80: Management Salaries | D80: Management Salaries | E80: 838403 | F80: 817569 | G80: 796736 | H80: 1055712 | I80: 884317 | J80: 1209843 | K80: 895074 | L80: 895074 | M80: 895074 | N80: 895074 | O80: 895074 | P80: 160000 | Q80: 895074 | R80: 895074 | S80: 895074 | T80: 886938 | U80: 886938 | V80: 886939 | W80: =U80-V80 -> -1 | X80: =W80/94 -> -0.010638298
C81: Admin Salaries | D81: Admin Salaries | E81: 54601 | F81: 77859 | G81: 74488 | H81: 74488 | I81: 74488 | J81: 74488 | K81: 74488 | L81: 89843 | M81: 92772 | N81: 91488 | O81: 91488 | P81: 91440 | Q81: 91470 | R81: 80185 | S81: 71674 | T81: 71219 | U81: 66261 | V81: 66650 | W81: =U81-V81 -> -389 | X81: =W81/94 -> -4.1382979
C82: IT Salaries | D82: IT Salaries | E82: 52473 | F82: 71393 | G82: 65718 | H82: 63878 | I82: 71081 | J82: 63878 | K82: 63878 | L82: 63878 | M82: 66558 | N82: 63878 | O82: 76816 | P82: 78606 | Q82: 78584 | R82: 61960 | S82: 81042 | T82: 76922 | U82: 73941 | V82: 66943 | W82: =U82-V82 -> 6998 | X82: =W82/94 -> 74.446809
C83: HR Salaries | D83: HR Salaries | E83: 43600 | F83: 43600 | G83: 42181 | H83: 43600 | I83: 36812 | J83: 28800 | K83: 44729 | L83: 48600 | M83: 49705 | N83: 48600 | O83: 56960 | P83: 69728 | Q83: 69706 | R83: 68994 | S83: 77295 | T83: 58100 | U83: 53341 | V83: 53343 | W83: =U83-V83 -> -2 | X83: =W83/94 -> -0.021276596
B84: 6.G&A salaries Total | E84: 989077 | F84: 1010421 | G84: 979123 | H84: 1237678 | I84: 1066698 | J84: 1377009 | K84: 1078169 | L84: 1097395 | M84: 1104109 | N84: 1099040 | O84: 1120338 | P84: 399774 | Q84: 1134834 | R84: 1106213 | S84: 1125085 | T84: 1093179 | U84: 1080481 | V84: 1073875 | W84: =U84-V84 -> 6606 | X84: =W84/94 -> 70.276596
B85: 7.Legal & Professional Fees | C85: FPO Charges - SRF | D85: Spice Route Finance | E85: 125000 | F85: 125000 | G85: 125000 | H85: 125000 | I85: 125000 | J85: 125000 | K85: 125000 | L85: 125000 | M85: 125000 | N85: 125000 | O85: 125000 | P85: 125000 | Q85: 125000 | R85: 125000 | S85: 185000 | T85: 125000 | U85: 125000 | V85: 125000 | W85: =U85-V85 -> 0 | X85: =W85/94 -> 0
C86: Coding charges | D86: Cure Claims Healthcare Services | F86: 12420 | G86: 53658 | W86: =U86-V86 -> 0 | X86: =W86/94 -> 0
D87: HDFC Bank | S87: 11172 | W87: =U87-V87 -> 0 | X87: =W87/94 -> 0
D88: Coding charges | E88: 210148 | F88: 414284 | G88: 1019968 | J88: 51954 | W88: =U88-V88 -> 0 | X88: =W88/94 -> 0
C89: Professional services | D89: AATRALAI TECH SOLUTIONS PVT. LTD. | F89: 100000 | W89: =U89-V89 -> 0 | X89: =W89/94 -> 0
D90: DQS India | I90: 60450 | W90: =U90-V90 -> 0 | X90: =W90/94 -> 0
D91: N V Balaji and Co. | J91: 131000 | W91: =U91-V91 -> 0 | X91: =W91/94 -> 0
C92: FPO Charges-SMCS GLOBAL | D92: SMCS Global | J92: 165000 | K92: 30000 | P92: 6000 | Q92: 5000 | W92: =U92-V92 -> 0 | X92: =W92/94 -> 0
C93: MCA Filing Fee | D93: Spice Route Finance | K93: 300 | W93: =U93-V93 -> 0 | X93: =W93/94 -> 0
B94: 7.Legal & Professional Fees Total | E94: 335148 | F94: 651704 | G94: 1198626 | H94: 125000 | I94: 185450 | J94: 472954 | K94: 155300 | L94: 125000 | M94: 125000 | N94: 125000 | O94: 125000 | P94: 131000 | Q94: 130000 | R94: 125000 | S94: 196172 | T94: 125000 | U94: 125000 | V94: 125000 | W94: =U94-V94 -> 0 | X94: =W94/94 -> 0
B95: 8.Sales & Marketing | C95: S&M Salaries | D95: S&M Salaries | E95: 106743 | F95: 143864 | G95: 123335 | H95: 135405 | I95: 131899 | J95: 19867 | K95: 19867 | L95: 125076 | M95: 112295 | N95: 130598 | O95: 118522 | P95: 106479 | Q95: 106145 | R95: 93372 | S95: 116553 | T95: 114721 | U95: 104048 | V95: 102491 | W95: =U95-V95 -> 1557 | X95: =W95/94 -> 16.56383
C96: Advertising And Marketing | D96: Amazon.in | O96: 10 | W96: =U96-V96 -> 0 | X96: =W96/94 -> 0
B97: 8.Sales & Marketing Total | E97: 106743 | F97: 143864 | G97: 123335 | H97: 135405 | I97: 131899 | J97: 19867 | K97: 19867 | L97: 125076 | M97: 112295 | N97: 130598 | O97: 118532 | P97: 106479 | Q97: 106145 | R97: 93372 | S97: 116553 | T97: 114721 | U97: 104048 | V97: 102491 | W97: =U97-V97 -> 1557 | X97: =W97/94 -> 16.56383
B98: 9.General & Administration | C98: Employee PF | D98: Employee PF | E98: 296342 | F98: 305791 | G98: 317357 | H98: 314981 | I98: 338119 | J98: 338763 | K98: 356938 | L98: 390653 | M98: 418465 | N98: 430132 | O98: 435979 | P98: 479345 | Q98: 467242 | R98: 426537 | S98: 458363 | T98: 458087 | U98: 450986.5 | V98: 462074 | W98: =U98-V98 -> -11087.5 | X98: =W98/94 -> -117.95213
C99: Employer PF | D99: Employer PF | E99: 296342 | F99: 305791 | G99: 317357 | H99: 314981 | I99: 338119 | J99: 338763 | K99: 356938 | L99: 390653 | M99: 418465 | N99: 430132 | O99: 435979 | P99: 479345 | Q99: 467242 | R99: 426537 | S99: 458363 | T99: 458087 | U99: 450986.5 | V99: 462074 | W99: =U99-V99 -> -11087.5 | X99: =W99/94 -> -117.95213
C100: Food Coupon-Happay Wallet | D100: Food Coupon-Happay Wallet | E100: 200794 | F100: 200730 | G100: 210292 | H100: 216462 | I100: 228978 | J100: 229828 | K100: 297205 | L100: 273626 | M100: 277256 | N100: 289438 | O100: 264362 | P100: 293709 | Q100: 296255 | R100: 267000 | S100: 282458 | T100: 271457 | U100: 268211 | V100: 281311 | W100: =U100-V100 -> -13100 | X100: =W100/94 -> -139.3617
C101: Meals and Entertainment | D101: HDFC Bank | E101: 8856 | H101: 3826 | I101: 10216 | J101: 7035 | P101: 35700 | R101: 3020 | S101: 710 | T101: 160 | U101: 730 | W101: =U101-V101 -> 730 | X101: =W101/94 -> 7.7659574
D102: HDFC credit card (Imagnum) | E102: 390 | F102: 3130 | H102: 820 | J102: 55256 | K102: 4673 | Q102: 230 | S102: 2150 | U102: 7080 | W102: =U102-V102 -> 7080 | X102: =W102/94 -> 75.319149
...

Sheet Budgeted
B5: Budgeted 2026
B7: >>>>

Sheet Proforma-May
A1: I-Magnum Healthcare Solution Inc.
A2: CONSOLIDATED P&L in $'s
B3: Actuals | C3: Forecast
A4: Particulars | B4: 46082 | C4: 46143 | D4: Remarks | E4: Detailed comments
A5: Service Income
A6: Other Information Technology Services | B6: 221215 | C6: 210021
A7: New Business | B7: 0 | C7: =10250-7000 -> 3250
A9: Total Revenue | B9: =SUM(B$6:B$7) -> 221215 | C9: 215820.9
A11: Operational Expenses
A13: India Salaries | B13: 120509 | C13: 94311
A14: Emp Statutory Expenses | B14: 11400 | C14: 10622.174
A15: Manpower | B15: =SUM(B13:B14) -> 131909 | C15: =SUM(C13:C14) -> 104933.17
A16: Electricity Expense | B16: 2676 | C16: 2800
A17: Computer maintenance | B17: 0 | C17: 0
A18: Janani Property Maintenance Charges | B18: 743 | C18: 743
A19: Janani Property Rental Charges | B19: 4302 | C19: =B19 -> 4302
A20: Laptop Rental Charges | B20: 1907 | C20: =B20 -> 1907
A21: Trichy Rental Charges | B21: 0 | C21: 0
A22: Thiruttani rental charges | B22: 285 | C22: =B22 -> 285
A23: Max Office rental charges | B23: 4348 | C23: =B23 -> 4348
A24: Rent Expense | B24: 1272 | C24: =B24 -> 1272
A25: Facility Cost | B25: =SUM(B16:B24) -> 15533 | C25: =SUM(C16:C24) -> 15657
A26: Telephone Expense | B26: 295 | C26: 300
A27: Dues and Subscriptions | B27: 459 | C27: =B27 -> 459
A28: Software Expenses | B28: 24152 | C28: =1379+1220+8175 -> 10774
A29: License/Subscription/Certification Charges | B29: 838 | C29: 586
A30: IT and Internet Expenses | B30: 985 | C30: =B30 -> 985
A31: Telecom Charges | B31: 34 | C31: =B31 -> 34
A32: Telephone Rental Charges | B32: 189 | C32: =B32 -> 189
A33: Telcom/Data & others | B33: =SUM(B26:B32) -> 26952 | C33: =SUM(C26:C32) -> 13327 | D33: 2000
A34: Transport | B34: 5351 | C34: 4084 | D34: 4254
A35: Software development and Hosting charges | B35: 1304 | C35: 3584 | E35: ask - MBMS (IT Software dev)
A36: Other Cogs- MD | C36: =B36 -> 0
A37: Employee Engagement | C37: =B37 -> 0
A38: Staff Welfare Expenses | B38: 3892 | C38: 850
A39: Interest on OD | B39: 1417 | C39: =B39 -> 1417 | E39: .
A40: Fuel expenses | C40: =B40
A41: Obo Health Inc | C41: =B41
A42: Food Coupon-Happay Wallet | B42: 3070 | C42: 3393
A43: Other COGS | B43: =SUM(B35:B42) -> 9683 | C43: =SUM(C35:C42) -> 9244 | D43: 17600
A45: Total Operational Expenses | B45: =B43+B34+B33+B25+B15 -> 189428 | C45: =C43+C34+C33+C25+C15 -> 147245.17 | D45: 137690 | E45: =C45-D45 -> 9555.1744
A47: Gross Profit | B47: =B9-B45 -> 31787 | C47: =C9-C45 -> 68575.723 | D47: 64300
A48: Gross Margin | B48: =IFERROR(B47/B$9,0) -> 0.14369279 | C48: =IFERROR(C47/C$9,0) -> 0.31774366 | D48: 0.31
A50: Indirect Incomes | B50: 0 | C50: 0
A52: Sales and Marketing Expenses
A53: Travel Expense | B53: 0 | C53: 1000 | D53: 1093
A54: Hubspot | B54: 0 | C54: 955
A55: Meals and Entertainment | B55: =62+90 -> 152
A56: Sales and marketing | B56: =SUM(B53:B55) -> 152 | C56: =SUM(C53:C55) -> 1955 | G56: us salaries 16293
A57: S&M Salaries | B57: 1476 | C57: 1620 | D57: india salaries
A58: S&M US | B58: 1211 | C58: 2240 | D58: us exps
A59: Selling Expenses | B59: =B58+B56+B57 -> 2839 | C59: =C58+C56+C57 -> 5815 | D59: 1400
A61: Total S&M Expenses | B61: =SUM(B59:B59) -> 2839 | C61: =SUM(C59:C59) -> 5815
A63: G&A Expenses
A64: Management Salaries (India) | B64: 9729 | C64: =B64 -> 9729 | D64: 9326
A65: Management Salaries (US) | B65: 17422 | C65: 21710 | D65: 16293
A66: Salaries-Management & Others | B66: =SUM(B64:B65) -> 27151 | C66: =SUM(C64:C65) -> 31439
A67: FPO Charges - SRF | B67: 2011 | C67: 1437
A68: Legal & Professional Fees | B68: 3976 | C68: =1000+1095+1074 -> 3169 | D68: 2300 | F68: aatralai take it off
A69: Payroll taxes(ADP) | B69: 3764 | C69: 3484
A70: HR Salaries | B70: 951 | C70: 2110
A71: Admin Salaries | B71: 860 | C71: 500
A72: IT Salaries | B72: 958 | C72: 900
A73: G&A salaries | B73: =SUM(B69:B72) -> 6533 | C73: =SUM(C69:C72) -> 6994 | D73: 7541 | E73: 2028-india | F73: 5513-us
A74: Fuel/Mileage Expenses | B74: 97 | C74: 57
A75: ADP | B75: 608 | C75: 500
A76: Parking | B76: 0 | C76: =B76 -> 0
A77: Toll Fee | B77: 0 | C77: =B77 -> 0
A78: Travelling Expenses | B78: 2571 | C78: 0
A79: Insurance Expense | B79: 10409 | C79: 9848 | D79: 5000-us
A80: Postage | B80: 15 | C80: 17
A81: Accommodation Charges | B81: 0 | C81: =B81 -> 0
A82: Blocked Credit | B82: 313 | C82: =B82 -> 313
A83: Housekeeping Charges | B83: 500 | C83: =B83 -> 500
A84: Other Expenses | B84: 295 | C84: =B84 -> 295
A85: Registration charges | B85: 272 | C85: =B85 -> 272
A86: Office Supplies | B86: 857 | C86: 848
A87: Referral bonus | B87: 54
A88: Gen & Admin. Expenses | B88: =SUM(B74:B87) -> 15991 | C88: =SUM(C74:C87) -> 12650
D89: consultancy - 1877 | E89: from june 2000 indtead of 2500
A90: Total SG&A Expenses | B90: =B88+B73+B68+B67+B66+B61 -> 58501 | C90: =C88+C73+C68+C67+C66+C61 -> 61504
A92: EBITDA | B92: =B47+B50-B90 -> -26714 | C92: =C47+C50-C90 -> 7071.7227
A93: EBITDA Margin | B93: =IFERROR(B92/B$9,0) -> -0.12076035 | C93: =IFERROR(C92/C$9,0) -> 0.032766626
A95: Total Burn | B95: =B9-B92 -> 247929 | C95: =C9-C92 -> 208749.17

Sheet Proforma-June
A1: I-Magnum Healthcare Solution Inc.
A2: CONSOLIDATED P&L in $'s
B3: Actuals | C3: Forecast | D3: Actuals | E3: Variance
A4: Particulars | B4: 46113 | C4: 46174 | F4: Remarks | G4: Detailed comments
A5: Service Income
A6: Other Information Technology Services | B6: 195207 | C6: 230589.09
A7: New Business | B7: 0
A9: Total Revenue | B9: =SUM(B$6:B$7) -> 195207 | C9: =SUM(C6:C7) -> 230589.09
A11: Operational Expenses
A13: India Salaries | B13: 100793 | C13: 98811
A14: Emp Statutory Expenses | B14: 11371 | C14: 10622.174
A15: Manpower | B15: =SUM(B13:B14) -> 112164 | C15: =SUM(C13:C14) -> 109433.17
A16: Electricity Expense | B16: 2980 | C16: 2980
A17: Computer maintenance | B17: 0 | C17: 0
A18: Janani Property Maintenance Charges | B18: 743 | C18: 786
A19: Janani Property Rental Charges | B19: 4302 | C19: 4549.069
A20: Laptop Rental Charges | B20: 1964 | C20: =B20+88 -> 2052
A21: Trichy Rental Charges | B21: 0 | C21: 0
A22: Thiruttani rental charges | B22: 285 | C22: =B22 -> 285
A23: Max Office rental charges | B23: 4348 | C23: 4597.7011
A24: Rent Expense | B24: 272 | C24: 301.72414
A25: Facility Cost | B25: =SUM(B16:B24) -> 14894 | C25: =SUM(C16:C24) -> 15551.494
A26: Telephone Expense | B26: 285 | C26: 300
A27: Dues and Subscriptions | B27: 220 | C27: 590
A28: Software Expenses | B28: 16686 | C28: =8675+3400 -> 12075 | E28: Move to other cogs
A29: License/Subscription/Certification Charges | B29: 754 | C29: 586
A30: IT and Internet Expenses | B30: 479 | C30: 600
A31: Telecom Charges | B31: 29 | C31: =B31 -> 29
A32: Telephone Rental Charges | B32: 213 | C32: 230
A33: Telcom/Data & others | B33: =SUM(B26:B32) -> 18666 | C33: =SUM(C26:C32) -> 14410
A34: Transport | B34: 4084 | C34: 4084 | D34: 5760
A35: Software development and Hosting charges | B35: 163 | C35: 446
A36: Other Cogs- MD | C36: =B36 -> 0
A37: Employee Engagement | C37: =283+2121 -> 2404
A38: Staff Welfare Expenses | B38: 1727 | C38: 850
A39: Interest on OD | B39: 0 | C39: =B39 -> 0
A40: Fuel expenses | C40: =B40
A41: Obo Health Inc | C41: =B41
A42: Food Coupon-Happay Wallet | B42: 2951 | C42: 3393
A43: Other COGS | B43: =SUM(B35:B42) -> 4841 | C43: =SUM(C35:C42) -> 7093
A45: Total Operational Expenses | B45: =B43+B34+B33+B25+B15 -> 154649 | C45: =C43+C34+C33+C25+C15 -> 150571.67
A47: Gross Profit | B47: =B9-B45 -> 40558 | C47: =C9-C45 -> 80017.421
A48: Gross Margin | B48: =IFERROR(B47/B$9,0) -> 0.20776919 | C48: =IFERROR(C47/C$9,0) -> 0.34701304
A50: Indirect Incomes | B50: 0 | C50: 0
A52: Sales and Marketing Expenses | B52: 128
A53: Travel Expense | B53: 0 | C53: 1000
A54: Hubspot | B54: 0 | C54: 955
A55: Meals and Entertainment | B55: 734 | C55: 320
A56: Sales and marketing | B56: =SUM(B52:B55) -> 862 | C56: =SUM(C53:C55) -> 2275
A57: S&M Salaries | B57: 1247 | C57: 1620
A58: S&M US | B58: 0 | C58: 2240
A59: Selling Expenses | B59: =B58+B56+B57 -> 2109 | C59: =C58+C56+C57 -> 6135
A61: Total S&M Expenses | B61: =SUM(B59:B59) -> 2109 | C61: =SUM(C59:C59) -> 6135
A63: G&A Expenses
A64: Management Salaries (India) | B64: 9641 | C64: =B64 -> 9641
A65: Management Salaries (US) | B65: 23165 | C65: 21710 | D65: 4000 | F65: Prakash, Mihir and Randy
A66: Salaries-Management & Others | B66: =SUM(B64:B65) -> 32806 | C66: =SUM(C64:C65) -> 31351
A67: FPO Charges - SRF | B67: 1359 | C67: 1437
A68: Legal & Professional Fees | B68: 2326 | C68: 2012 | D68: ?
A69: Payroll taxes(ADP) | B69: 3675 | C69: 3484
A70: HR Salaries | B70: 632 | C70: 2110 | D70: 1450
A71: Admin Salaries | B71: 774 | C71: 500
A72: IT Salaries | B72: 836 | C72: 900
A73: G&A salaries | B73: =SUM(B69:B72) -> 5917 | C73: =SUM(C69:C72) -> 6994
A74: Fuel/Mileage Expenses | B74: 89 | C74: 57
A75: ADP | B75: 523 | C75: 500
A76: Parking | B76: 0 | C76: =B76 -> 0
A77: Toll Fee | B77: 25 | C77: =B77 -> 25
A78: Travelling Expenses | B78: 447 | C78: 450
A79: Insurance Expense | B79: 3781 | C79: 4848 | D79: Include india 69000
A80: Postage | B80: 0 | C80: 17
A81: Accommodation Charges | B81: 0 | C81: =B81 -> 0
A82: Blocked Credit | B82: 236 | C82: =B82 -> 236
A83: Housekeeping Charges | B83: 495 | C83: 460
A84: Other Expenses | B84: 294 | C84: =B84 -> 294
A85: Registration charges | B85: 0 | C85: =B85 -> 0
A86: Office Supplies | B86: 742 | C86: 848
A87: Interest on PT | B87: 44
A88: Consultancy Fees - G&A | B88: 2500 | C88: 2500
A89: Referral bonus | B89: 0
A90: Gen & Admin. Expenses | B90: =SUM(B74:B89) -> 9176 | C90: =SUM(C74:C89) -> 10235
A92: Total SG&A Expenses | B92: =B90+B73+B68+B67+B66+B61 -> 53693 | C92: =C90+C73+C68+C67+C66+C61 -> 58164
A94: EBITDA | B94: =B47+B50-B92 -> -13135 | C94: =C47+C50-C92 -> 21853.421
A95: EBITDA Margin | B95: =IFERROR(B94/B$9,0) -> -0.067287546 | C95: =IFERROR(C94/C$9,0) -> 0.094772139
A97: Total Burn | B97: =B9-B94 -> 208342 | C97: =C9-C94 -> 208735.67

Sheet Proforma- July
A1: I-Magnum Healthcare Solution Inc.
A2: CONSOLIDATED P&L in $'s
B3: Forecast
A4: Particulars | B4: 46204 | C4: Remarks | D4: Detailed comments
A5: Service Income
A6: Other Information Technology Services | B6: 234361.04
A7: New Business
A9: Total Revenue | B9: =SUM(B6:B7) -> 234361.04
A11: Operational Expenses
A13: India Salaries | B13: 112624.56
A14: Emp Statutory Expenses | B14: 0
A15: Manpower | B15: =SUM(B13:B14) -> 112624.56
A16: Electricity Expense | B16: 3196.2299
A17: Computer maintenance | B17: 0
A18: Janani Property Maintenance Charges | B18: 0
A19: Janani Property Rental Charges | B19: 0
A20: Chennai New Facility Cost | B20: 9195.4023
A21: Chennai New Facility Cost - Maint | B21: 800
A22: Laptop Rental Charges | B22: 1830.4608
A23: Trichy Rental Charges | B23: 290 | C23: CHECK THE ACTUALS WITH CHARMISHA
A24: Thiruttani rental charges | B24: 302
A25: Trichy Max Office rental charges | B25: 4597.7011
A26: Rent Expense | B26: 2000
A27: Facility Cost | B27: =SUM(B16:B26) -> 22211.794
A28: Telephone Expense | B28: 285
A29: Dues and Subscriptions | B29: 212
A30: Software Expenses | B30: =8570+1036+1000 -> 10606
A31: License/Subscription/Certification Charges | B31: 392
A32: IT and Internet Expenses | B32: =541+582+17 -> 1140
A33: Telecom Charges | B33: 28.735632
A34: Telephone Rental Charges | B34: 229.88506
A35: Telcom/Data & others | B35: =SUM(B28:B34) -> 12893.621
A36: Transport | B36: 4254
A37: Software development and Hosting charges | B37: 3584
A38: Other Cogs- MD | B38: 0
A39: Employee Engagement | B39: 0
A40: Staff Welfare Expenses | B40: 849
A41: Interest on OD
A42: Fuel expenses | B42: 0
A43: Obo Health Inc | B43: 0
A44: Food Coupon-Happay Wallet | B44: 3393
A45: Other COGS | B45: =SUM(B37:B44) -> 7826
A47: Total Operational Expenses | B47: =B45+B36+B35+B27+B15 -> 159809.97
A49: Gross Profit | B49: =B9-B47 -> 74551.069
A50: Gross Margin | B50: =IFERROR(B49/B$9,0) -> 0.3181035
A52: Indirect Incomes | B52: 0
A54: Sales and Marketing Expenses
A55: Travel Expense | B55: 1000
A56: Hubspot | B56: 955
A57: Meals and Entertainment | B57: 320
A58: Sales and marketing | B58: =SUM(B55:B57) -> 2275
A59: S&M Salaries | B59: 1620
A60: S&M US | B60: 2240
A61: Selling Expenses | B61: =B60+B58+B59 -> 6135
A63: Total S&M Expenses | B63: =SUM(B61:B61) -> 6135
A65: G&A Expenses
A66: Management Salaries (India) | B66: 9945
A67: Management Salaries (US) | B67: 17154.84
A68: Salaries-Management & Others | B68: =SUM(B66:B67) -> 27099.84
A69: FPO Charges - SRF | B69: 1437
A70: Legal & Professional Fees | B70: 455
A71: Payroll taxes(ADP) | B71: 5513
A72: HR Salaries | B72: 660
A73: Admin Salaries | B73: 500
A74: IT Salaries | B74: 900
A75: G&A salaries | B75: =SUM(B71:B74) -> 7573
A76: Fuel/Mileage Expenses
A77: ADP
A78: Parking
A79: Toll Fee
A80: Travelling Expenses
A81: Insurance Expense | B81: =4848+800 -> 5648
A82: Postage
A83: Accommodation Charges
A84: Blocked Credit
A85: Housekeeping Charges | B85: 747
A86: Other Expenses
A87: Registration charges
A88: Office Supplies | B88: 575
A89: Interest on PT
A90: Consultancy Fees - G&A | B90: 2000
A91: Referral bonus
A92: Gen & Admin. Expenses | B92: =SUM(B76:B91) -> 8970
A94: Total SG&A Expenses | B94: =B92+B75+B70+B69+B68+B63 -> 51669.84
A96: EBITDA | B96: =B49+B52-B94 -> 22881.229
A97: EBITDA Margin | B97: =IFERROR(B96/B$9,0) -> 0.097632392
A99: Total Burn | B99: =B9-B96 -> 211479.81

Sheet P&L - Bud.
A1: Imagnum Health
A2: Consolidated Income Statement
A3: USD/INR | B3: 87 | C3: 87 | D3: 87 | E3: 87 | F3: 87 | G3: 87 | H3: 87 | I3: 87 | J3: 87 | K3: 87 | L3: 87 | M3: 87
A4: Particulars | B4: 46023 | C4: 46054 | D4: 46082 | E4: 46113 | F4: 46143 | G4: 46174 | H4: 46204 | I4: 46235 | J4: 46266 | K4: 46296 | L4: 46327 | M4: 46357 | N4: Total | Q4: 2024 Actuals | R4: % | S4: 2024 Budget | T4: % | U4: Bud Variance | V4: Actual Variance
A5: Current
A6: Revenue | B6: 225414.12 | C6: 238765.5 | D6: 239597.86 | E6: 203603.86 | F6: 212815.5 | G6: 215403.86 | H6: 215753.86 | I6: 246487.7 | J6: 250487.7 | K6: 252153.86 | L6: 253119.5 | M6: 256153.86 | N6: =SUM(B6:M6) -> 2809757.2 | O6: =N6/140000 -> 20.069694 | Q6: 2116756.6 | S6: 1186417.5
A7: Salaries | B7: 107468.67 | C7: 107468.67 | D7: 97886.472 | E7: 97886.472 | F7: 102053.98 | G7: 102053.98 | H7: 102053.98 | I7: 102053.98 | J7: 102053.98 | K7: 112770.44 | L7: 112770.44 | M7: 112770.44 | N7: =SUM(B7:M7) -> 1259291.5 | Q7: 836770.98 | R7: 0.39530808 | S7: 524458.73
A8: Facilities | B8: 15550.932 | C8: 15550.932 | D8: 15550.932 | E8: 15550.932 | F8: 15550.932 | G8: 15550.932 | H8: 16016.116 | I8: 16016.116 | J8: 16016.116 | K8: 16016.116 | L8: 16016.116 | M8: 16016.116 | N8: =SUM(B8:M8) -> 189402.29 | Q8: 109080.05 | R8: 0.051531694 | S8: 101610.99
A9: Telecom/Data & others | B9: 2306.9503 | C9: 2306.9503 | D9: 1416.3065 | E9: 1416.3065 | F9: 1416.3065 | G9: 1773.7778 | H9: 1773.7778 | I9: 1773.7778 | J9: 1773.7778 | K9: 1773.7778 | L9: 1773.7778 | M9: 1773.7778 | N9: =SUM(B9:M9) -> 21279.265 | Q9: 38074.979 | R9: 0.017987415 | S9: 23641.274
A10: Transport | B10: 3034.4828 | C10: 3034.4828 | D10: 3034.4828 | E10: 3034.4828 | F10: 3944.8276 | G10: 3944.8276 | H10: 3944.8276 | I10: 4691.954 | J10: 4691.954 | K10: 4691.954 | L10: 4691.954 | M10: 4691.954 | N10: =SUM(B10:M10) -> 47432.184 | Q10: 29439.337 | R10: 0.013907758 | S10: 30109.94
A11: Other Cogs | B11: 7044.2229 | C11: 7044.2229 | D11: 7044.2229 | E11: 7044.2229 | F11: 7044.2229 | G11: 7044.2229 | H11: 7044.2229 | I11: 7044.2229 | J11: 7044.2229 | K11: 7044.2229 | L11: 7044.2229 | M11: 7044.2229 | N11: =SUM(B11:M11) -> 84530.674 | Q11: 193079.67 | R11: 0.091214869 | S11: 1749.2242
A12: Total Cogs | B12: =SUM(B7:B11) -> 135405.26 | C12: =SUM(C7:C11) -> 135405.26 | D12: =SUM(D7:D11) -> 124932.42 | E12: =SUM(E7:E11) -> 124932.42 | F12: =SUM(F7:F11) -> 130010.27 | G12: =SUM(G7:G11) -> 130367.74 | H12: =SUM(H7:H11) -> 130832.93 | I12: =SUM(I7:I11) -> 131580.05 | ... N12: =SUM(N7:N11) -> 1601935.9 | Q12: 1206445 | S12: 681570.15
A13: GM | B13: =B6-B12 -> 90008.864 | C13: =C6-C12 -> 103360.24 | D13: =D6-D12 -> 114665.44 | E13: =E6-E12 -> 78671.444 | F13: =F6-F12 -> 82805.228 | G13: =G6-G12 -> 85036.117 | H13: =H6-H12 -> 84920.933 | I13: =I6-I12 -> 114907.65 | ... N13: =N6-N12 -> 1207821.3 | Q13: 910311.56 | S13: 504847.37
A14: GM% | B14: =B13/B6 -> 0.39930446 | C14: =C13/C6 -> 0.43289438 | D14: =D13/D6 -> 0.47857458 | E14: =E13/E6 -> 0.38639466 | F14: =F13/F6 -> 0.38909397 | G14: =G13/G6 -> 0.39477527 | H14: =H13/H6 -> 0.39360099 | I14: =I13/I6 -> 0.46618004 | ... N14: =N13/N6 -> 0.42986677 | Q14: 0.43005018 | S14: 0.42552252
A16: Incremental P&L
A17: Revenue | B17: 0 | C17: 0 | D17: 0 | E17: 0 | F17: 13800 | G17: 16800 | H17: 17150 | I17: 49550 | J17: 53550 | K17: 53550 | L17: 57550 | M17: 57550 | N17: =SUM(B17:M17) -> 319500 | S17: 3816468.6
A18: Salaries | S18: 1233644.8
A19: Facilities | S19: 24883.119
A20: Telcom/Data & others | S20: 13156.29
A21: Transport | S21: 71009.275
A22: Other Cogs | O22: Includes mBMS insurance as well | S22: 4125.2538
A23: Total Cogs | B23: =SUM(B18:B22) -> 0 | C23: =SUM(C18:C22) -> 0 | D23: =SUM(D18:D22) -> 0 | E23: =SUM(E18:E22) -> 0 | F23: =SUM(F18:F22) -> 0 | G23: =SUM(G18:G22) -> 0 | H23: =SUM(H18:H22) -> 0 | I23: =SUM(I18:I22) -> 0 | ... N23: =SUM(N18:N22) -> 0 | S23: 1346818.8
A24: GM | B24: =B17-B23 -> 0 | C24: =C17-C23 -> 0 | D24: =D17-D23 -> 0 | E24: =E17-E23 -> 0 | F24: =F17-F23 -> 13800 | G24: =G17-G23 -> 16800 | H24: =H17-H23 -> 17150 | I24: =I17-I23 -> 49550 | ... M24: =M17-M23 -> 57550 | N24: =SUM(B24:M24) -> 319500 | S24: 2469649.8
A25: GM% | B25: =IFERROR(B24/B17,0) -> 0 | C25: =IFERROR(C24/C17,0) -> 0 | D25: =IFERROR(D24/D17,0) -> 0 | E25: =IFERROR(E24/E17,0) -> 0 | F25: =IFERROR(F24/F17,0) -> 1 | G25: =IFERROR(G24/G17,0) -> 1 | H25: =IFERROR(H24/H17,0) -> 1 | I25: =IFERROR(I24/I17,0) -> 1 | ... N25: =IFERROR(N24/N17,0) -> 1 | S25: 0.6471034
A27: US
A28: Revenue | N28: =SUM(B28:M28) -> 0
A29: Salaries | N29: =SUM(B29:M29) -> 0
A30: Facilities | B30: 1000 | C30: 1000 | D30: 1000 | E30: 1000 | F30: 1000 | G30: 1000 | H30: 1000 | I30: 1000 | J30: 1000 | K30: 1000 | L30: 1000 | M30: 1000 | N30: =SUM(B30:M30) -> 12000
A31: Telecom | B31: 0 | C31: 0 | D31: 0 | E31: 0 | F31: 0 | G31: 0 | H31: 0 | I31: 0 | J31: 0 | K31: 0 | L31: 0 | M31: 0 | N31: =SUM(B31:M31) -> 0
A32: Transport | N32: =SUM(B32:M32) -> 0
A33: Other Cogs | B33: 21845.43 | C33: 21845.43 | D33: 9845.43 | E33: 9845.43 | F33: 9845.43 | G33: 9845.43 | H33: 7734.43 | I33: 8756.43 | J33: 8756.43 | K33: 8756.43 | L33: 8756.43 | M33: 8756.43 | N33: =SUM(B33:M33) -> 134589.16
A34: Total Cogs | B34: =SUM(B29:B33) -> 22845.43 | C34: =SUM(C29:C33) -> 22845.43 | D34: =SUM(D29:D33) -> 10845.43 | E34: =SUM(E29:E33) -> 10845.43 | F34: =SUM(F29:F33) -> 10845.43 | G34: =SUM(G29:G33) -> 10845.43 | H34: =SUM(H29:H33) -> 8734.43 | I34: =SUM(I29:I33) -> 9756.43 | ... N34: =SUM(N29:N33) -> 146589.16
A35: GM | B35: =B28-B34 -> -22845.43 | C35: =C28-C34 -> -22845.43 | D35: =D28-D34 -> -10845.43 | E35: =E28-E34 -> -10845.43 | F35: =F28-F34 -> -10845.43 | G35: =G28-G34 -> -10845.43 | H35: =H28-H34 -> -8734.43 | I35: =I28-I34 -> -9756.43 | ... M35: =M28-M34 -> -9756.43 | N35: =SUM(B35:M35) -> -146589.16
A36: GM% | B36: =IFERROR(B35/B28,0) -> 0 | C36: =IFERROR(C35/C28,0) -> 0 | D36: =IFERROR(D35/D28,0) -> 0 | E36: =IFERROR(E35/E28,0) -> 0 | F36: =IFERROR(F35/F28,0) -> 0 | G36: =IFERROR(G35/G28,0) -> 0 | H36: =IFERROR(H35/H28,0) -> 0 | I36: =IFERROR(I35/I28,0) -> 0 | ... N36: =IFERROR(N35/N28,0) -> 0
A38: Revenue | B38: =B17+B6 -> 225414.12 | C38: =C17+C6 -> 238765.5 | D38: =D17+D6 -> 239597.86 | E38: =E17+E6 -> 203603.86 | F38: =F17+F6 -> 226615.5 | G38: =G17+G6 -> 232203.86 | H38: =H17+H6 -> 232903.86 | I38: =I17+I6 -> 296037.7 | ... M38: =M17+M6 -> 313703.86 | N38: =SUM(B38:M38) -> 3129257.2 | Q38: 2116756.6 | S38: 5002886.1
A39: Salaries | B39: =B18+B7+B29 -> 107468.67 | C39: =C18+C7+C29 -> 107468.67 | D39: =D18+D7+D29 -> 97886.472 | E39: =E18+E7+E29 -> 97886.472 | F39: =F18+F7+F29 -> 102053.98 | G39: =G18+G7+G29 -> 102053.98 | H39: =H18+H7+H29 -> 102053.98 | I39: =I18+I7+I29 -> 102053.98 | ... M39: =M18+M7+M29 -> 112770.44 | N39: =SUM(B39:M39) -> 1259291.5 | O39: =N39/$N$38 -> 0.40242506 | Q39: 836770.98 | R39: =Q39/$Q$38 -> 0.39530808 | S39: 1758103.6 | T39: =S39/$S$38 -> 0.35141787
A40: Facilities | B40: =B19+B8+B30 -> 16550.932 | C40: =C19+C8+C30 -> 16550.932 | D40: =D19+D8+D30 -> 16550.932 | E40: =E19+E8+E30 -> 16550.932 | F40: =F19+F8+F30 -> 16550.932 | G40: =G19+G8+G30 -> 16550.932 | H40: =H19+H8+H30 -> 17016.116 | I40: =I19+I8+I30 -> 17016.116 | ... M40: =M19+M8+M30 -> 17016.116 | N40: =SUM(B40:M40) -> 201402.29 | O40: =N40/$N$38 -> 0.064361053 | Q40: 109080.05 | R40: =Q40/$Q$38 -> 0.051531694 | S40: 126494.1 | T40: =S40/$S$38 -> 0.025284226 | Z40: Headcount buildup comparison by dept level
A41: Telcom/Data & others | B41: =B20+B9+B31 -> 2306.9503 | C41: =C20+C9+C31 -> 2306.9503 | D41: =D20+D9+D31 -> 1416.3065 | E41: =E20+E9+E31 -> 1416.3065 | F41: =F20+F9+F31 -> 1416.3065 | G41: =G20+G9+G31 -> 1773.7778 | H41: =H20+H9+H31 -> 1773.7778 | I41: =I20+I9+I31 -> 1773.7778 | ... M41: =M20+M9+M31 -> 1773.7778 | N41: =SUM(B41:M41) -> 21279.265 | O41: =N41/$N$38 -> 0.0068001009 | Q41: 38074.979 | R41: =Q41/$Q$38 -> 0.017987415 | S41: 36797.564 | T41: =S41/$S$38 -> 0.0073552672
A42: Transport | B42: =B21+B10+B32 -> 3034.4828 | C42: =C21+C10+C32 -> 3034.4828 | D42: =D21+D10+D32 -> 3034.4828 | E42: =E21+E10+E32 -> 3034.4828 | F42: =F21+F10+F32 -> 3944.8276 | G42: =G21+G10+G32 -> 3944.8276 | H42: =H21+H10+H32 -> 3944.8276 | I42: =I21+I10+I32 -> 4691.954 | ... M42: =M21+M10+M32 -> 4691.954 | N42: =SUM(B42:M42) -> 47432.184 | O42: =N42/$N$38 -> 0.01515765 | Q42: 29439.337 | R42: =Q42/$Q$38 -> 0.013907758 | S42: 101119.21 | T42: =S42/$S$38 -> 0.020212176
A43: Other Cogs | B43: =B22+B11+B33 -> 28889.653 | C43: =C22+C11+C33 -> 28889.653 | D43: =D22+D11+D33 -> 16889.653 | E43: =E22+E11+E33 -> 16889.653 | F43: =F22+F11+F33 -> 16889.653 | G43: =G22+G11+G33 -> 16889.653 | H43: =H22+H11+H33 -> 14778.653 | I43: =I22+I11+I33 -> 15800.653 | ... M43: =M22+M11+M33 -> 15800.653 | N43: =SUM(B43:M43) -> 219119.83 | O43: =N43/$N$38 -> 0.070022955 | Q43: 193079.67 | R43: =Q43/$Q$38 -> 0.091214869 | S43: 5874.4781 | T43: =S43/$S$38 -> 0.0011742178
A44: Total Cogs | B44: =SUM(B39:B43) -> 158250.69 | C44: =SUM(C39:C43) -> 158250.69 | D44: =SUM(D39:D43) -> 135777.85 | E44: =SUM(E39:E43) -> 135777.85 | F44: =SUM(F39:F43) -> 140855.7 | G44: =SUM(G39:G43) -> 141213.17 | H44: =SUM(H39:H43) -> 139567.36 | I44: =SUM(I39:I43) -> 141336.48 | ... N44: =SUM(N39:N43) -> 1748525.1 | Q44: 1206445 | S44: 2028388.9
A45: GM | B45: =B38-B44 -> 67163.434 | C45: =C38-C44 -> 80514.814 | D45: =D38-D44 -> 103820.01 | E45: =E38-E44 -> 67826.014 | F45: =F38-F44 -> 85759.798 | G45: =G38-G44 -> 90990.687 | H45: =H38-H44 -> 93336.503 | I45: =I38-I44 -> 154701.22 | ... M45: =M38-M44 -> 161650.92 | N45: =SUM(B45:M45) -> 1380732.1 | Q45: 910311.56 | S45: 2974497.2
A46: GM% | B46: =B45/B38 -> 0.29795575 | C46: =C45/C38 -> 0.33721293 | D46: =D45/D38 -> 0.43330944 | E46: =E45/E38 -> 0.33312735 | F46: =F45/F38 -> 0.37843748 | G46: =G45/G38 -> 0.39185691 | H46: =H45/H38 -> 0.40075121 | I46: =I45/I38 -> 0.52257269 | ... N46: =N45/N38 -> 0.44123318 | Q46: 0.43005018 | S46: 0.59455624
A48: SG&A
A49: Selling Expenses
A50: India
A51: Salaries | B51: 3980 | C51: 2980 | D51: 1980 | E51: 1980 | F51: 1980 | G51: 1980 | H51: 1980 | I51: 1980 | J51: 1980 | K51: 1980 | L51: 1980 | M51: 1980 | N51: =SUM(B51:M51) -> 26760 | O51: =N51/$N$38 -> 0.0085515502 | Q51: 20525.325 | R51: =Q51/$Q$38 -> 0.0096965922 | S51: 47832.795 | T51: =S51/$S$38 -> 0.0095610402
A52: Sales & Marketing expenses | B52: 0 | C52: 0 | D52: 0 | E52: 0 | F52: 1000 | G52: 0 | H52: 0 | I52: 0 | J52: 0 | K52: 0 | L52: 0 | M52: 0 | N52: =SUM(B52:M52) -> 1000 | O52: =N52/$N$38 -> 0.00031956466 | Q52: 2971.2048 | R52: =Q52/$Q$38 -> 0.0014036592 | S52: 31421.221 | T52: =S52/$S$38 -> 0.0062806189
A53: Total | B53: =SUM(B51:B52) -> 3980 | C53: =SUM(C51:C52) -> 2980 | D53: =SUM(D51:D52) -> 1980 | E53: =SUM(E51:E52) -> 1980 | F53: =SUM(F51:F52) -> 2980 | G53: =SUM(G51:G52) -> 1980 | H53: =SUM(H51:H52) -> 1980 | I53: =SUM(I51:I52) -> 1980 | ... N53: =SUM(N51:N52) -> 27760 | Q53: 23496.53 | R53: =Q53/$Q$38 -> 0.011100251 | S53: 79254.016
A55: US | D55: 2240 | E55: 2240 | F55: 2240 | G55: 2240 | H55: 2240 | I55: 2240 | J55: 2240 | K55: 2240 | L55: 2240 | M55: 2240 | N55: =SUM(B55:M55) -> 22400
A56: Salaries | B56: 14760 | C56: 0 | D56: 0 | E56: 0 | F56: 0 | G56: 0 | H56: 0 | I56: 0 | J56: 0 | K56: 0 | L56: 0 | M56: 0 | N56: =SUM(B56:M56) -> 14760 | O56: =N56/$N$38 -> 0.0047167743 | Q56: 0 | R56: =Q56/$Q$38 -> 0 | S56: 0 | T56: =S56/$S$38 -> 0
A57: Sales & Marketing expenses | B57: 3628.52 | C57: 3628.52 | D57: 1455 | E57: 1955 | F57: 1955 | G57: 1955 | H57: 1955 | I57: 1955 | J57: 1955 | K57: 4455 | L57: 1955 | M57: 1955 | N57: =SUM(B57:M57) -> 28807.04 | O57: =N57/$N$38 -> 0.0092057119 | Q57: #REF! | R57: =Q57/$Q$38 -> #REF! | S57: 57400 | T57: =S57/$S$38 -> 0.011473377
A58: Total | B58: =SUM(B55:B57) -> 18388.52 | C58: =SUM(C55:C57) -> 3628.52 | D58: =SUM(D55:D57) -> 3695 | E58: =SUM(E55:E57) -> 4195 | F58: =SUM(F55:F57) -> 4195 | G58: =SUM(G55:G57) -> 4195 | H58: =SUM(H55:H57) -> 4195 | I58: =SUM(I55:I57) -> 4195 | ... M58: =SUM(M55:M57) -> 4195 | N58: =SUM(N56:N57) -> 43567.04 | Q58: #REF! | R58: =Q58/$Q$38 -> #REF! | S58: 57400
A60: Overall S&M expenses
A61: Salaries | B61: =B56+B51+B55 -> 18740 | C61: =C56+C51+C55 -> 2980 | D61: =D56+D51+D55 -> 4220 | E61: =E56+E51+E55 -> 4220 | F61: =F56+F51+F55 -> 4220 | G61: =G56+G51+G55 -> 4220 | H61: =H56+H51+H55 -> 4220 | I61: =I56+I51+I55 -> 4220 | ... M61: =M56+M51+M55 -> 4220 | N61: =SUM(B61:M61) -> 63920 | O61: =N61/$N$38 -> 0.020426573 | Q61: 20525.325 | R61: =Q61/$Q$38 -> 0.0096965922 | S61: 47832.795 | T61: =S61/$S$38 -> 0.0095610402
A62: Sales & Marketing expenses | B62: =B57+B52 -> 3628.52 | C62: =C57+C52 -> 3628.52 | D62: =D57+D52 -> 1455 | E62: =E57+E52 -> 1955 | F62: =F57+F52 -> 2955 | G62: =G57+G52 -> 1955 | H62: =H57+H52 -> 1955 | I62: =I57+I52 -> 1955 | ... M62: =M57+M52 -> 1955 | N62: =SUM(B62:M62) -> 29807.04 | O62: =N62/$N$38 -> 0.0095252765 | Q62: #REF! | R62: =Q62/$Q$38 -> #REF! | S62: 88821.221 | T62: =S62/$S$38 -> 0.017753996
A63: Total | B63: =SUM(B61:B62) -> 22368.52 | C63: =SUM(C61:C62) -> 6608.52 | D63: =SUM(D61:D62) -> 5675 | E63: =SUM(E61:E62) -> 6175 | F63: =SUM(F61:F62) -> 7175 | G63: =SUM(G61:G62) -> 6175 | H63: =SUM(H61:H62) -> 6175 | I63: =SUM(I61:I62) -> 6175 | ... N63: =SUM(N61:N62) -> 93727.04 | Q63: #REF! | R63: =Q63/$Q$38 -> #REF! | S63: 136654.02
A64: Selling & Marketing | B64: =B63/B38 -> 0.099233003 | C64: =C63/C38 -> 0.027677868 | D64: =D63/D38 -> 0.02368552 | E64: =E63/E38 -> 0.030328502 | F64: =F63/F38 -> 0.031661559 | G64: =G63/G38 -> 0.026593012 | H64: =H63/H38 -> 0.026513086 | I64: =I63/I38 -> 0.02085883 | ... N64: =N63/N38 -> 0.029951849 | S64: 0.027315036
A66: G&A Expenses
A67: India
A68: Management Salaries | B68: 9945 | C68: 9945 | D68: 9945 | E68: 9945 | F68: 9945 | G68: 9945 | H68: 9945 | I68: 9945 | J68: 9945 | K68: 9945 | L68: 9945 | M68: 9945 | N68: =SUM(B68:M68) -> 119340 | O68: =N68/$N$38 -> 0.038136846 | Q68: 145303.12 | R68: =Q68/$Q$38 -> 0.068644228 | S68: 128499.29 | T68: =S68/$S$38 -> 0.025685032
A69: Salaries | B69: 4480 | C69: 3930 | D69: 3380 | E69: 3380 | F69: 4830 | G69: 4830 | H69: 4830 | I69: 4830 | J69: 4830 | K69: 4830 | L69: 4830 | M69: 4830 | N69: =SUM(B69:M69) -> 53810 | O69: =N69/$N$38 -> 0.017195774 | Q69: 12785.627 | R69: =Q69/$Q$38 -> 0.0060401969 | S69: 33257.523 | T69: =S69/$S$38 -> 0.0066476674
A70: Legal & Professional Expenses | B70: 534.48276 | C70: 3224.1379 | D70: 63.218391 | E70: 63.218391 | F70: 63.218391 | G70: 63.218391 | H70: 63.218391 | I70: 63.218391 | J70: 63.218391 | K70: 63.218391 | L70: 63.218391 | M70: 63.218391 | N70: =SUM(B70:M70) -> 4390.8046 | O70: =N70/$N$38 -> 0.001403146 | Q70: 32492.627 | R70: =Q70/$Q$38 -> 0.015350195 | S70: 5060.241 | T70: =S70/$S$38 -> 0.0010114644
A71: Gen & Admin. Expenses | B71: 1379.3103 | C71: 4629.3103 | D71: 1379.3103 | E71: 7126.4368 | F71: 4629.3103 | G71: 1379.3103 | H71: 7379.3103 | I71: 1379.3103 | J71: 1379.3103 | K71: 1379.3103 | L71: 1379.3103 | M71: 1379.3103 | N71: =SUM(B71:M71) -> 34798.851 | O71: =N71/$N$38 -> 0.011120483 | Q71: 12785.627 | R71: =Q71/$Q$38 -> 0.0060401969 | S71: 11514.217 | T71: =S71/$S$38 -> 0.0023015149
A72: Total | B72: =SUM(B68:B71) -> 16338.793 | C72: =SUM(C68:C71) -> 21728.448 | D72: =SUM(D68:D71) -> 14767.529 | E72: =SUM(E68:E71) -> 20514.655 | F72: =SUM(F68:F71) -> 19467.529 | G72: =SUM(G68:G71) -> 16217.529 | H72: =SUM(H68:H71) -> 22217.529 | I72: =SUM(I68:I71) -> 16217.529 | ... N72: =SUM(N68:N71) -> 212339.66 | O72: =N72/$N$38 -> 0.067856249 | Q72: 203367 | R72: =Q72/$Q$38 -> 0.096074817 | S72: 178331.27 | T72: =S72/$S$38 -> 0.035645679
A74: US
A75: Management Salaries | B75: 27300 | C75: 17154.84 | D75: 17154.84 | E75: 17154.84 | F75: 21709.73 | G75: 17154.84 | H75: 17154.84 | I75: 17154.84 | J75: 17154.84 | K75: 21709.73 | L75: 17154.84 | M75: 17154.84 | N75: =SUM(B75:M75) -> 225113.02 | O75: =N75/$N$38 -> 0.071938165 | Q75: 377612.41 | R75: =Q75/$Q$38 -> 0.17839199 | S75: 339452.52 | T75: =S75/$S$38 -> 0.067851339
A76: Legal and Professional Fees | Q76: 38682.5 | R76: =Q76/$Q$38 -> 0.018274421
A77: Other G&A Expenses | B77: 0 | C77: 0 | D77: 0 | E77: 0 | F77: 0 | G77: 0 | H77: 0 | I77: 0 | J77: 0 | K77: 0 | L77: 0 | M77: 0 | N77: =SUM(B77:M77) -> 0 | O77: =N77/$N$38 -> 0 | Q77: 44083.28 | R77: =Q77/$Q$38 -> 0.020825862 | S77: 132480 | T77: =S77/$S$38 -> 0.026480715
A78: Total | B78: =SUM(B75:B77) -> 27300 | C78: =SUM(C75:C77) -> 17154.84 | D78: =SUM(D75:D77) -> 17154.84 | E78: =SUM(E75:E77) -> 17154.84 | F78: =SUM(F75:F77) -> 21709.73 | G78: =SUM(G75:G77) -> 17154.84 | H78: =SUM(H75:H77) -> 17154.84 | I78: =SUM(I75:I77) -> 17154.84 | ... N78: =SUM(N75:N77) -> 225113.02 | O78: =N78/$N$38 -> 0.071938165 | Q78: 460378.19 | R78: =Q78/$Q$38 -> 0.21749227 | S78: 471932.52 | T78: =S78/$S$38 -> 0.094332054
A80: Overall G&A expenses
A81: Management Salaries | B81: =B75+B68 -> 37245 | C81: =C75+C68 -> 27099.84 | D81: =D75+D68 -> 27099.84 | E81: =E75+E68 -> 27099.84 | F81: =F75+F68 -> 31654.73 | G81: =G75+G68 -> 27099.84 | H81: =H75+H68 -> 27099.84 | I81: =I75+I68 -> 27099.84 | ... M81: =M75+M68 -> 27099.84 | N81: =SUM(B81:M81) -> 344453.02 | O81: =N81/$N$38 -> 0.11007501 | Q81: 522915.53 | R81: =Q81/$Q$38 -> 0.24703621 | S81: 467951.81 | T81: =S81/$S$38 -> 0.093536371
A82: Salaries | B82: =B69 -> 4480 | C82: =C69 -> 3930 | D82: =D69 -> 3380 | E82: =E69 -> 3380 | F82: =F69 -> 4830 | G82: =G69 -> 4830 | H82: =H69 -> 4830 | I82: =I69 -> 4830 | ... M82: =M69 -> 4830 | N82: =SUM(B82:M82) -> 53810 | O82: =N82/$N$38 -> 0.017195774 | Q82: 12785.627 | R82: =Q82/$Q$38 -> 0.0060401969 | S82: 33257.523 | T82: =S82/$S$38 -> 0.0066476674
A83: Legal & Professinal Expenses | B83: =B70 -> 534.48276 | C83: =C70 -> 3224.1379 | D83: =D70 -> 63.218391 | E83: =E70 -> 63.218391 | F83: =F70 -> 63.218391 | G83: =G70 -> 63.218391 | H83: =H70 -> 63.218391 | I83: =I70 -> 63.218391 | ... M83: =M70 -> 63.218391 | N83: =SUM(B83:M83) -> 4390.8046 | O83: =N83/$N$38 -> 0.001403146 | Q83: 71175.127 | R83: =Q83/$Q$38 -> 0.033624616 | S83: 5060.241 | T83: =S83/$S$38 -> 0.0010114644
A84: Gen & Admin. Expenses | B84: =B77+B71 -> 1379.3103 | C84: =C77+C71 -> 4629.3103 | D84: =D77+D71 -> 1379.3103 | E84: =E77+E71 -> 7126.4368 | F84: =F77+F71 -> 4629.3103 | G84: =G77+G71 -> 1379.3103 | H84: =H77+H71 -> 7379.3103 | I84: =I77+I71 -> 1379.3103 | ... M84: =M77+M71 -> 1379.3103 | N84: =SUM(B84:M84) -> 34798.851 | O84: =N84/$N$38 -> 0.011120483 | Q84: 56868.907 | R84: =Q84/$Q$38 -> 0.026866059 | S84: 143994.22 | T84: =S84/$S$38 -> 0.02878223
A85: Total | B85: =SUM(B81:B84) -> 43638.793 | C85: =SUM(C81:C84) -> 38883.288 | D85: =SUM(D81:D84) -> 31922.369 | E85: =SUM(E81:E84) -> 37669.495 | F85: =SUM(F81:F84) -> 41177.259 | G85: =SUM(G81:G84) -> 33372.369 | H85: =SUM(H81:H84) -> 39372.369 | I85: =SUM(I81:I84) -> 33372.369 | ... N85: =SUM(N81:N84) -> 437452.68 | O85: =N85/$N$38 -> 0.13979441 | Q85: 663745.19 | R85: =Q85/$Q$38 -> 0.31356708 | S85: 650263.79 | T85: =S85/$S$38 -> 0.12997773
A86: Total G&A | B86: =B85/B38 -> 0.19359388 | C86: =C85/C38 -> 0.16285137 | D86: =D85/D38 -> 0.13323311 | E86: =E85/E38 -> 0.18501366 | F86: =F85/F38 -> 0.18170539 | G86: =G85/G38 -> 0.14372013 | H86: =H85/H38 -> 0.16904988 | I86: =I85/I38 -> 0.11273013 | ... N86: =N85/N38 -> 0.13979441 | Q86: 0.31356708 | S86: 0.12997773
A88: Overall SG&A | B88: =B85+B63 -> 66007.313 | C88: =C85+C63 -> 45491.808 | D88: =D85+D63 -> 37597.369 | E88: =E85+E63 -> 43844.495 | F88: =F85+F63 -> 48352.259 | G88: =G85+G63 -> 39547.369 | H88: =H85+H63 -> 45547.369 | I88: =I85+I63 -> 39547.369 | ... N88: =N85+N63 -> 531179.72 | O88: =N88/$N$38 -> 0.16974626 | Q88: #REF! | R88: =Q88/$Q$38 -> #REF! | S88: 786917.81 | T88: =S88/$S$38 -> 0.15729277
A89: Ebidta | B89: =B45-B88 -> 1156.1211 | C89: =C45-C88 -> 35023.006 | D89: =D45-D88 -> 66222.646 | E89: =E45-E88 -> 23981.519 | F89: =F45-F88 -> 37407.54 | G89: =G45-G88 -> 51443.318 | H89: =H45-H88 -> 47789.134 | I89: =I45-I88 -> 115153.85 | ... N89: =N45-N88 -> 849552.38 | Q89: #REF! | S89: 2187579.4
A90: Ebidta % | B90: =B89/B38 -> 0.0051288761 | C90: =C89/C38 -> 0.1466837 | D90: =D89/D38 -> 0.27639081 | E90: =E89/E38 -> 0.11778519 | F90: =F89/F38 -> 0.16507052 | G90: =G89/G38 -> 0.22154377 | H90: =H89/H38 -> 0.20518825 | I90: =I89/I38 -> 0.38898373 | ... N90: =N89/N38 -> 0.27148692 | P90: 0.11 | Q90: #REF! | S90: 0.43726348
A92: Interest/Finance Charges | B92: 171 | C92: 171 | D92: 171 | E92: 171 | F92: 171 | G92: 171 | H92: 171 | I92: 171 | J92: 171 | K92: 171 | L92: 171 | M92: 171 | N92: =SUM(B92:M92) -> 2052
A94: PBT | B94: =B89-B92 -> 985.12108 | C94: =C89-C92 -> 34852.006 | D94: =D89-D92 -> 66051.646 | E94: =E89-E92 -> 23810.519 | F94: =F89-F92 -> 37236.54 | G94: =G89-G92 -> 51272.318 | H94: =H89-H92 -> 47618.134 | I94: =I89-I92 -> 114982.85 | ... M94: =M89-M92 -> 121932.55 | N94: =SUM(B94:M94) -> 847500.38 | P94: 0.1
P95: =N94/P94 -> 8475003.8
A97: 2024
A98: Rev/ FTE | B98: 1234.9184 | C98: 1076.4965 | D98: 1270.8863 | E98: 1505.7856 | F98: 2040.1772 | G98: 1756.733 | H98: 1613.0393 | I98: 1459.9285 | J98: 1455.1137 | K98: 1323.7734 | L98: 1276.1176 | M98: 1235.5695 | N98: 1431.8413 | O98: Revenue/Operational Directs
A99: Cost/ FTE | B99: 631.97104 | C99: 895.66403 | D99: 625.68447 | E99: 649.86273 | F99: 759.83977 | G99: 647.27924 | H99: 649.94131 | I99: 624.64381 | J99: 612.83617 | K99: 633.45284 | L99: 652.77958 | M99: 652.77958 | N99: 661.27865 | O99: Indian costs/Operational Directs
A101: 2025
A102: Rev/ FTE | B102: 1287.7541 | C102: 1547.1734 | D102: 1265.2515 | E102: 1295.9267 | F102: 1422.1353 | G102: 1478.763 | H102: 1438.7982 | I102: 1195.4881 | J102: 1206.7187 | K102: 1153.4732 | L102: 1105.7537 | M102: 1105.7537 | N102: 1280.9981 | O102: Revenue/Operational Directs
A103: Cost/ FTE | B103: 739.17474 | C103: 682.37081 | D103: 810 | E103: 719 | F103: 744 | G103: 746 | H103: 777 | I103: 860 | J103: 793 | K103: 840 | L103: 842 | M103: 842 | N103: =AVERAGE(B103:M103) -> 782.8788 | O103: Indian costs/Operational Directs
A105: 2026
A106: Rev/ FTE | B106: 1218.4547 | C106: 1290.6243 | D106: 1361.3515 | E106: 1296.8399 | F106: 1297.6555 | G106: 1313.4382 | H106: 1315.5723 | I106: 1502.9738 | J106: 1527.364 | K106: 1385.4608 | L106: 1390.7665 | M106: 1407.4388 | N106: 1203.6042 | O106: Revenue/Operational Directs
A107: Cost/ FTE | B107: 731.9203 | C107: 731.9203 | D107: 709.84327 | E107: 795.74787 | F107: 792.74556 | G107: 794.92526 | H107: 797.76175 | I107: 802.3174 | J107: 802.3174 | K107: 781.84896 | L107: 781.84896 | M107: 781.84896 | N107: 774.25613 | O107: Indian costs/Operational Directs
B109: =B72+B53+B12 -> 155724.05 | C109: =C72+C53+C12 -> 160113.7 | D109: =D72+D53+D12 -> 141679.94 | E109: =E72+E53+E12 -> 147427.07 | F109: =F72+F53+F12 -> 152457.8 | G109: =G72+G53+G12 -> 148565.27 | H109: =H72+H53+H12 -> 155030.46 | I109: =I72+I53+I12 -> 149777.58 | ... M109: =M72+M53+M12 -> 160494.04
B111: =B78+B58+B34 -> 68533.95 | C111: =C78+C58+C34 -> 43628.79 | D111: =D78+D58+D34 -> 31695.27 | E111: =E78+E58+E34 -> 32195.27 | F111: =F78+F58+F34 -> 36750.16 | G111: =G78+G58+G34 -> 32195.27 | H111: =H78+H58+H34 -> 30084.27 | I111: =I78+I58+I34 -> 31106.27 | ... M111: =M78+M58+M34 -> 31106.27

Sheet US Bud-Exp
B1: 1
B3: Operational Cost | C3: Price | D3: 46023 | E3: 46054 | F3: 46082 | G3: 46113 | H3: 46143 | I3: 46174 | J3: 46204 | K3: 46235 | L3: 46266 | M3: 46296 | N3: 46327 | O3: 46357 | P3: Total
B4: Operational Cost | P4: =SUM(D4:O4) -> 0
B5: India Cost | P5: =SUM(D5:O5) -> 0
B6: Contractors | D6: 155475.81 | E6: 159865.46 | F6: 143932.76 | G6: 145533.34 | H6: 151827.62 | I6: 150424.02 | J6: 154400.27 | K6: 149440.34 | L6: 152357.02 | M6: 170283.36 | N6: 160664.53 | O6: 160673.16 | P6: =SUM(D6:O6) -> 1854877.7
B7: Facility Cost | P7: =SUM(D7:O7) -> 0
B8: Lynx Realty | C8: 1000 | D8: =$C8 -> 1000 | E8: =$C8 -> 1000 | F8: =$C8 -> 1000 | G8: =$C8 -> 1000 | H8: =$C8 -> 1000 | I8: =$C8 -> 1000 | J8: =$C8 -> 1000 | K8: =$C8 -> 1000 | ... O8: =$C8 -> 1000 | P8: =SUM(D8:O8) -> 12000
B9: Telecom Data & Others | P9: =SUM(D9:O9) -> 0
B10: Dues and Subscriptions | P10: =SUM(D10:O10) -> 0
B11: Amex - Cloudways | C11: 500 | D11: =$C11 -> 500 | E11: =$C11 -> 500 | F11: =$C11 -> 500 | G11: =$C11 -> 500 | H11: =$C11 -> 500 | I11: =$C11 -> 500 | J11: =$C11 -> 500 | K11: =$C11 -> 500 | ... O11: =$C11 -> 500 | P11: =SUM(D11:O11) -> 6000
A12: Check with Kasi | B12: A2Webhost | L12: 212.26 | P12: =SUM(D12:O12) -> 212.26
B13: Adobe Systems | C13: 13.8 | D13: =$C13 -> 13.8 | E13: =$C13 -> 13.8 | F13: =$C13 -> 13.8 | G13: =$C13 -> 13.8 | H13: =$C13 -> 13.8 | I13: =$C13 -> 13.8 | J13: =$C13 -> 13.8 | K13: =$C13 -> 13.8 | ... O13: =$C13 -> 13.8 | P13: =SUM(D13:O13) -> 165.6
B14: Calendly | C14: 25.54 | D14: =$C14 -> 25.54 | E14: =$C14 -> 25.54 | F14: =$C14 -> 25.54 | G14: =$C14 -> 25.54 | H14: =$C14 -> 25.54 | I14: =$C14 -> 25.54 | J14: =$C14 -> 25.54 | K14: =$C14 -> 25.54 | ... O14: =$C14 -> 25.54 | P14: =SUM(D14:O14) -> 306.48
B15: Chatgpt | C15: 178 | D15: =$C15 -> 178 | E15: =$C15 -> 178 | F15: =$C15 -> 178 | G15: =$C15 -> 178 | H15: =$C15 -> 178 | I15: =$C15 -> 178 | J15: =$C15 -> 178 | K15: =$C15 -> 178 | ... O15: =$C15 -> 178 | P15: =SUM(D15:O15) -> 2136
B16: DROPBOX | C16: 12.78 | D16: =$C16 -> 12.78 | E16: =$C16 -> 12.78 | F16: =$C16 -> 12.78 | G16: =$C16 -> 12.78 | H16: =$C16 -> 12.78 | I16: =$C16 -> 12.78 | J16: =$C16 -> 12.78 | K16: =$C16 -> 12.78 | ... O16: =$C16 -> 12.78 | P16: =SUM(D16:O16) -> 153.36
B17: READ - MEETING | C17: 21.01 | D17: =$C17 -> 21.01 | E17: =$C17 -> 21.01 | F17: =$C17 -> 21.01 | G17: =$C17 -> 21.01 | H17: =$C17 -> 21.01 | I17: =$C17 -> 21.01 | J17: =$C17 -> 21.01 | K17: =$C17 -> 21.01 | ... O17: =$C17 -> 21.01 | P17: =SUM(D17:O17) -> 252.12
B18: QuickBooks Payments | C18: 138.58 | D18: =$C18 -> 138.58 | E18: =$C18 -> 138.58 | F18: =$C18 -> 138.58 | G18: =$C18 -> 138.58 | H18: =$C18 -> 138.58 | I18: =$C18 -> 138.58 | J18: =$C18 -> 138.58 | K18: =$C18 -> 138.58 | ... O18: =$C18 -> 138.58 | P18: =SUM(D18:O18) -> 1662.96
B19: IT and Internet Expenses | D19: =$C19 -> 0 | E19: =$C19 -> 0 | F19: =$C19 -> 0 | G19: =$C19 -> 0 | H19: =$C19 -> 0 | I19: =$C19 -> 0 | J19: =$C19 -> 0 | K19: =$C19 -> 0 | ... O19: =$C19 -> 0 | P19: =SUM(D19:O19) -> 0
B20: Figma | C20: 85.12 | D20: =$C20 -> 85.12 | E20: =$C20 -> 85.12 | F20: =$C20 -> 85.12 | G20: =$C20 -> 85.12 | H20: =$C20 -> 85.12 | I20: =$C20 -> 85.12 | J20: =$C20 -> 85.12 | K20: =$C20 -> 85.12 | ... O20: =$C20 -> 85.12 | P20: =SUM(D20:O20) -> 1021.44
B21: Semrush | C21: 176 | D21: =$C21 -> 176 | E21: =$C21 -> 176 | F21: =$C21 -> 176 | G21: =$C21 -> 176 | H21: =$C21 -> 176 | I21: =$C21 -> 176 | J21: =$C21 -> 176 | K21: =$C21 -> 176 | ... O21: =$C21 -> 176 | P21: =SUM(D21:O21) -> 2112
B22: Telephone Expense
B23: Verizon | C23: 322 | D23: =$C23 -> 322 | E23: =$C23 -> 322 | F23: 228 | G23: 228 | H23: 180 | I23: 180 | J23: 180 | K23: 180 | L23: 180 | M23: 180 | N23: 180 | O23: 180 | P23: =SUM(D23:O23) -> 2540
B24: Telecom Data & Others | D24: =SUM(D11:D23) -> 1472.83 | E24: =SUM(E11:E23) -> 1472.83 | F24: =SUM(F11:F23) -> 1378.83 | G24: =SUM(G11:G23) -> 1378.83 | H24: =SUM(H11:H23) -> 1330.83 | I24: =SUM(I11:I23) -> 1330.83 | J24: =SUM(J11:J23) -> 1330.83 | K24: =SUM(K11:K23) -> 1330.83 | ... O24: =SUM(O11:O23) -> 1330.83 | P24: =SUM(D24:O24) -> 16562.22
B26: Other COGS | D26: =$C26 -> 0 | E26: =$C26 -> 0 | F26: =$C26 -> 0 | G26: =$C26 -> 0 | H26: =$C26 -> 0 | I26: =$C26 -> 0 | J26: =$C26 -> 0 | K26: =$C26 -> 0 | ... O26: =$C26 -> 0 | P26: =SUM(D26:O26) -> 0
B28: Software Expenses | D28: =$C28 -> 0 | E28: =$C28 -> 0 | F28: =$C28 -> 0 | G28: =$C28 -> 0 | H28: =$C28 -> 0 | I28: =$C28 -> 0 | J28: =$C28 -> 0 | K28: =$C28 -> 0 | ... O28: =$C28 -> 0 | P28: =SUM(D28:O28) -> 0
A29: standard 17.5K for 2026 - Removed the expense as we lost YDI | B29: AdvancedMD | C29: 12000 | D29: =$C29 -> 12000 | E29: =$C29 -> 12000 | P29: =SUM(D29:O29) -> 24000
B30: Availity | C30: 30 | D30: =$C30 -> 30 | E30: =$C30 -> 30 | F30: =$C30 -> 30 | G30: =$C30 -> 30 | H30: =$C30 -> 30 | I30: =$C30 -> 30 | J30: =$C30 -> 30 | K30: =$C30 -> 30 | ... O30: =$C30 -> 30 | P30: =SUM(D30:O30) -> 360
B31: MBMS Cloud - Atlantic | C31: 2169 | D31: =$C31 -> 2169 | E31: =$C31 -> 2169 | F31: =$C31 -> 2169 | G31: =$C31 -> 2169 | H31: =$C31 -> 2169 | I31: =$C31 -> 2169 | J31: =$C31 -> 2169 | K31: =$C31 -> 2169 | ... O31: =$C31 -> 2169 | P31: =SUM(D31:O31) -> 26028
B32: Foxyproxy | C32: 170 | D32: =$C32 -> 170 | E32: =$C32 -> 170 | F32: =$C32 -> 170 | G32: =$C32 -> 170 | H32: =$C32 -> 170 | I32: =$C32 -> 170 | J32: =$C32 -> 170 | K32: =$C32 -> 170 | ... O32: =$C32 -> 170 | P32: =SUM(D32:O32) -> 2040
B33: Moet Advisors LLC | D33: =$C33 -> 0 | E33: =$C33 -> 0 | F33: =$C33 -> 0 | G33: =$C33 -> 0 | H33: =$C33 -> 0 | I33: =$C33 -> 0 | J33: =$C33 -> 0 | K33: =$C33 -> 0 | ... O33: =$C33 -> 0 | P33: =SUM(D33:O33) -> 0
B34: Cair Health Software | C34: 5000 | D34: 5000 | E34: 5000 | F34: 5000 | G34: 5000 | H34: 5000 | I34: 5000 | J34: 3000 | K34: 3000 | L34: 3000 | M34: 3000 | N34: 3000 | O34: 3000 | P34: =SUM(D34:O34) -> 48000
B35: AHREFS* AHREFS | C35: 105.53 | D35: =$C35 -> 105.53 | E35: =$C35 -> 105.53 | F35: =$C35 -> 105.53 | G35: =$C35 -> 105.53 | H35: =$C35 -> 105.53 | I35: =$C35 -> 105.53 | J35: =$C35 -> 105.53 | K35: =$C35 -> 105.53 | ... O35: =$C35 -> 105.53 | P35: =SUM(D35:O35) -> 1266.36
B36: Claim.MD | C36: 111 | D36: =$C36 -> 111 | E36: =$C36 -> 111 | F36: =$C36 -> 111 | G36: =$C36 -> 111 | H36: =$C36 -> 111 | I36: =$C36 -> 111 | P36: =SUM(D36:O36) -> 666
B37: Contabo.com | C37: 19.9 | D37: =$C37 -> 19.9 | E37: =$C37 -> 19.9 | F37: =$C37 -> 19.9 | G37: =$C37 -> 19.9 | H37: =$C37 -> 19.9 | I37: =$C37 -> 19.9 | J37: =$C37 -> 19.9 | K37: =$C37 -> 19.9 | ... O37: =$C37 -> 19.9 | P37: =SUM(D37:O37) -> 238.8
A38: reduced from 889 to 570 | B38: MongoDB | C38: 570 | D38: =$C38 -> 570 | E38: =$C38 -> 570 | F38: =$C38 -> 570 | G38: =$C38 -> 570 | H38: =$C38 -> 570 | I38: =$C38 -> 570 | J38: =$C38 -> 570 | K38: =$C38 -> 570 | ... O38: =$C38 -> 570 | P38: =SUM(D38:O38) -> 6840
B39: 6.Other COGS | D39: =SUM(D28:D38) -> 20175.43 | E39: =SUM(E28:E38) -> 20175.43 | F39: =SUM(F28:F38) -> 8175.43 | G39: =SUM(G28:G38) -> 8175.43 | H39: =SUM(H28:H38) -> 8175.43 | I39: =SUM(I28:I38) -> 8175.43 | J39: =SUM(J28:J38) -> 6064.43 | K39: =SUM(K28:K38) -> 6064.43 | ... O39: =SUM(O28:O38) -> 6064.43 | P39: =SUM(D39:O39) -> 109439.16
B41: US Salaries
A42: 14 | B42: Backops Team - Medrina | C42: =80*14 -> 1120 | D42: =$C42*2 -> 2240 | E42: =$C42*2 -> 2240 | F42: =$C42*2 -> 2240 | G42: =$C42*2 -> 2240 | H42: =$C42*2 -> 2240 | I42: =$C42*2 -> 2240 | J42: =$C42*2 -> 2240 | K42: =$C42*2 -> 2240 | ... O42: =$C42*2 -> 2240 | P42: =SUM(D42:O42) -> 26880
B43: S&M Salaries | D43: =17000-D42 -> 14760 | E43: =$C43*2 -> 0 | F43: =$C43*2 -> 0 | G43: =$C43*2 -> 0 | H43: =$C43*3 -> 0 | I43: =$C43*2 -> 0 | J43: =$C43*2 -> 0 | K43: =$C43*2 -> 0 | L43: =$C43*2 -> 0 | M43: =$C43*3 -> 0 | N43: =$C43*2 -> 0 | O43: =$C43*2 -> 0 | P43: =SUM(D43:O43) -> 14760
B45: Total US Salaries | D45: =SUM(D42:D43) -> 17000 | E45: =SUM(E42:E43) -> 2240 | F45: =SUM(F42:F43) -> 2240 | G45: =SUM(G42:G43) -> 2240 | H45: =SUM(H42:H43) -> 2240 | I45: =SUM(I42:I43) -> 2240 | J45: =SUM(J42:J43) -> 2240 | K45: =SUM(K42:K43) -> 2240 | ... O45: =SUM(O42:O43) -> 2240 | P45: =SUM(D45:O45) -> 41640
B47: Travel Expense | P47: =SUM(D47:O47) -> 0
B48: Travel/Hotel Charges | E48: 2500 | F48: 500 | G48: 1000 | H48: 1000 | I48: 1000 | J48: 1000 | K48: 1000 | L48: 1000 | M48: 1000 | N48: 1000 | O48: 1000 | P48: =SUM(D48:O48) -> 12000
B49: Hubspot | C49: 955 | D49: 1128.52 | E49: 1128.52 | F49: =$C49 -> 955 | G49: =$C49 -> 955 | H49: =$C49 -> 955 | I49: =$C49 -> 955 | J49: =$C49 -> 955 | K49: =$C49 -> 955 | L49: =$C49 -> 955 | M49: =$C49 -> 955 | ... O49: =$C49 -> 955 | P49: =SUM(D49:O49) -> 11807.04
B50: Medsource AI LLP( Von Marie Gastello) | C50: 1250 | D50: =$C50*2 -> 2500 | P50: =SUM(D50:O50) -> 2500
B51: Conference & Events | C51: 2500 | G51: 0 | M51: 2500 | P51: =SUM(D51:O51) -> 2500
B52: Total S&M | D52: =SUM(D48:D51) -> 3628.52 | E52: =SUM(E48:E51) -> 3628.52 | F52: =SUM(F48:F51) -> 1455 | G52: =SUM(G48:G51) -> 1955 | H52: =SUM(H48:H51) -> 1955 | I52: =SUM(I48:I51) -> 1955 | J52: =SUM(J48:J51) -> 1955 | K52: =SUM(K48:K51) -> 1955 | ... O52: =SUM(O48:O51) -> 1955 | P52: =SUM(D52:O52) -> 28807.04
B54: Management Salaries | P54: =SUM(D54:O54) -> 0
P55: =SUM(D55:O55) -> 0
B56: Payroll Taxes - ADP | C56: 8045.06 | D56: 11300 | E56: =$C56 -> 8045.06 | F56: =$C56 -> 8045.06 | G56: =$C56 -> 8045.06 | H56: =$C56 -> 8045.06 | I56: =$C56 -> 8045.06 | J56: =$C56 -> 8045.06 | K56: =$C56 -> 8045.06 | L56: =$C56 -> 8045.06 | ... O56: =$C56 -> 8045.06 | P56: =SUM(D56:O56) -> 99795.66
B57: Management salaries - ADP | C57: 4554.89 | D57: 16000 | E57: =$C57*2 -> 9109.78 | F57: =$C57*2 -> 9109.78 | G57: =$C57*2 -> 9109.78 | H57: =$C57*3 -> 13664.67 | I57: =$C57*2 -> 9109.78 | J57: =$C57*2 -> 9109.78 | K57: =$C57*2 -> 9109.78 | L57: =$C57*2 -> 9109.78 | M57: =$C57*3 -> 13664.67 | N57: =$C57*2 -> 9109.78 | O57: =$C57*2 -> 9109.78 | P57: =SUM(D57:O57) -> 125317.36
B58: Total Management Salaries | D58: =SUM(D56:D57) -> 27300 | E58: =SUM(E56:E57) -> 17154.84 | F58: =SUM(F56:F57) -> 17154.84 | G58: =SUM(G56:G57) -> 17154.84 | H58: =SUM(H56:H57) -> 21709.73 | I58: =SUM(I56:I57) -> 17154.84 | J58: =SUM(J56:J57) -> 17154.84 | K58: =SUM(K56:K57) -> 17154.84 | ... O58: =SUM(O56:O57) -> 17154.84 | P58: =SUM(D58:O58) -> 225113.02
B60: G&A Cost | P60: =SUM(D60:O60) -> 0
B61: Consultancy Fees | P61: =SUM(D61:O61) -> 0
B62: CLEARME.COM | F62: 209 | I62: 209 | L62: 209 | O62: 209 | P62: =SUM(D62:O62) -> 836
B63: Emergent (Dottie) | C63: 2500 | D63: =$C63 -> 2500 | E63: =$C63 -> 2500 | F63: =$C63 -> 2500 | G63: =$C63-500 -> 2000 | H63: =$C63-500 -> 2000 | I63: =$C63-500 -> 2000 | J63: =$C63-500 -> 2000 | K63: =$C63-500 -> 2000 | L63: =$C63-500 -> 2000 | M63: =$C63-500 -> 2000 | N63: =$C63-500 -> 2000 | O63: =$C63-500 -> 2000 | P63: =SUM(D63:O63) -> 25500
B64: Fuel/Mileage Expenses | P64: =SUM(D64:O64) -> 0
B65: Fuel Charges | C65: 57 | D65: =$C65 -> 57 | E65: =$C65 -> 57 | F65: =$C65 -> 57 | G65: =$C65 -> 57 | H65: =$C65 -> 57 | I65: =$C65 -> 57 | J65: =$C65 -> 57 | K65: =$C65 -> 57 | ... O65: =$C65 -> 57 | P65: =SUM(D65:O65) -> 684
B66: Insurance Expense | P66: =SUM(D66:O66) -> 0
B67: Chase Credit card | C67: 5000 | D67: =$C$67 -> 5000 | E67: =$C$67 -> 5000 | F67: =$C$67 -> 5000 | G67: =$C$67 -> 5000 | H67: =$C$67 -> 5000 | I67: =$C$67 -> 5000 | J67: =$C$67 -> 5000 | K67: =$C$67 -> 5000 | ... O67: =$C$67 -> 5000 | P67: =SUM(D67:O67) -> 60000
A68: Do we also have a separate first insurance for Cyber security? | B68: At Bay - Cyber Security Insurance | C68: 2500 | D68: =$C68 -> 2500 | E68: =$C68 -> 2500 | F68: =$C68 -> 2500 | G68: =$C68 -> 2500 | H68: =$C68 -> 2500 | I68: =$C68 -> 2500 | J68: =$C68 -> 2500 | K68: =$C68 -> 2500 | ... O68: =$C68 -> 2500 | P68: =SUM(D68:O68) -> 30000
B69: Mihir | C69: 0 | D69: 1521 | E69: =$C69 -> 0 | F69: =$C69 -> 0 | G69: =$C69 -> 0 | H69: =$C69 -> 0 | I69: =$C69 -> 0 | J69: =$C69 -> 0 | K69: =$C69 -> 0 | L69: =$C69 -> 0 | ... O69: =$C69 -> 0 | P69: =SUM(D69:O69) -> 1521
B70: Prakash | C70: 2300 | D70: =$C70 -> 2300 | E70: =$C70 -> 2300 | F70: =$C70 -> 2300 | G70: =$C70 -> 2300 | H70: =$C70 -> 2300 | I70: =$C70 -> 2300 | J70: =$C70 -> 2300 | K70: =$C70 -> 2300 | ... O70: =$C70 -> 2300 | P70: =SUM(D70:O70) -> 27600
B71: ICHRA | C71: 30 | D71: =$C71 -> 30 | E71: =$C71 -> 30 | F71: =$C71 -> 30 | G71: =$C71 -> 30 | H71: =$C71 -> 30 | I71: =$C71 -> 30 | J71: =$C71 -> 30 | K71: =$C71 -> 30 | ... O71: =$C71 -> 30 | P71: =SUM(D71:O71) -> 360
B72: HSA | C72: 17.5 | D72: =$C72 -> 17.5 | E72: =$C72 -> 17.5 | F72: =$C72 -> 17.5 | G72: =$C72 -> 17.5 | H72: =$C72 -> 17.5 | I72: =$C72 -> 17.5 | J72: =$C72 -> 17.5 | K72: =$C72 -> 17.5 | ... O72: =$C72 -> 17.5 | P72: =SUM(D72:O72) -> 210
B73: Meals and Entertainment | D73: =$C73 -> 0 | E73: =$C73 -> 0 | F73: =$C73 -> 0 | G73: =$C73 -> 0 | H73: =$C73 -> 0 | I73: =$C73 -> 0 | J73: =$C73 -> 0 | K73: =$C73 -> 0 | ... O73: =$C73 -> 0 | P73: =SUM(D73:O73) -> 0
B74: Food Expenses | C74: 320 | D74: 0 | E74: 250 | F74: 100 | I74: =$C74 -> 320 | J74: =$C74 -> 320 | K74: =$C74 -> 320 | L74: =$C74 -> 320 | M74: =$C74 -> 320 | N74: =$C74 -> 320 | O74: =$C74 -> 320 | P74: =SUM(D74:O74) -> 2590
B75: Payroll Processing Fees | D75: =$C75 -> 0 | E75: =$C75 -> 0 | F75: =$C75 -> 0 | G75: =$C75 -> 0 | H75: =$C75 -> 0 | I75: =$C75 -> 0 | J75: =$C75 -> 0 | K75: =$C75 -> 0 | ... O75: =$C75 -> 0 | P75: =SUM(D75:O75) -> 0
B76: ADP | C76: 3484 | D76: =$C76 -> 3484 | E76: =$C76 -> 3484 | F76: =$C76 -> 3484 | G76: =$C76 -> 3484 | H76: =$C76 -> 3484 | I76: =$C76 -> 3484 | J76: =$C76 -> 3484 | K76: =$C76 -> 3484 | ... O76: =$C76 -> 3484 | P76: =SUM(D76:O76) -> 41808
B77: Postage | D77: =$C77 -> 0 | E77: =$C77 -> 0 | F77: =$C77 -> 0 | G77: =$C77 -> 0 | H77: =$C77 -> 0 | I77: =$C77 -> 0 | J77: =$C77 -> 0 | K77: =$C77 -> 0 | ... O77: =$C77 -> 0 | P77: =SUM(D77:O77) -> 0
B78: Ipostal | C78: 17 | D78: =$C78 -> 17 | E78: =$C78 -> 17 | F78: =$C78 -> 17 | G78: =$C78 -> 17 | H78: =$C78 -> 17 | I78: =$C78 -> 17 | J78: =$C78 -> 17 | K78: =$C78 -> 17 | ... O78: =$C78 -> 17 | P78: =SUM(D78:O78) -> 204
B79: Rates & Taxes | P79: =SUM(D79:O79) -> 0
A80: Federal tax processing fee - One Time | B80: BOA 7456 | C80: 225 | D80: =$C80 -> 225 | P80: =SUM(D80:O80) -> 225
B81: Toll Fee | P81: =SUM(D81:O81) -> 0
B82: Bancpass | C82: 25 | D82: =$C82 -> 25 | E82: =$C82 -> 25 | F82: =$C82 -> 25 | G82: =$C82 -> 25 | H82: =$C82 -> 25 | I82: =$C82 -> 25 | J82: =$C82 -> 25 | K82: =$C82 -> 25 | ... O82: =$C82 -> 25 | P82: =SUM(D82:O82) -> 300
B83: Legal & Professional Services | P83: =SUM(D83:O83) -> 0
B84: AATRALAI TECH SOLUTIONS PVT. LTD. | D84: =700000/87 -> 8045.977 | E84: =350000/87 -> 4022.9885 | P84: =SUM(D84:O84) -> 12068.966
B85: Ekam Legal | C85: 455 | D85: =$C85 -> 455 | E85: =$C85 -> 455 | F85: =$C85 -> 455 | G85: =$C85 -> 455 | H85: =$C85 -> 455 | I85: =$C85 -> 455 | J85: =$C85 -> 455 | K85: =$C85 -> 455 | ... O85: =$C85 -> 455 | P85: =SUM(D85:O85) -> 5460
B86: Office Supplies | P86: =SUM(D86:O86) -> 0
B87: Office supplies | D87: =$C87 -> 0 | E87: =$C87 -> 0 | F87: =$C87 -> 0 | G87: =$C87 -> 0 | H87: =$C87 -> 0 | I87: =$C87 -> 0 | J87: =$C87 -> 0 | K87: =$C87 -> 0 | ... O87: =$C87 -> 0 | P87: =SUM(D87:O87) -> 0
B88: Parking | P88: =SUM(D88:O88) -> 0
B89: Parking | D89: =$C89 -> 0 | E89: =$C89 -> 0 | F89: =$C89 -> 0 | G89: =$C89 -> 0 | H89: =$C89 -> 0 | I89: =$C89 -> 0 | J89: =$C89 -> 0 | K89: =$C89 -> 0 | ... O89: =$C89 -> 0 | P89: =SUM(D89:O89) -> 0
B90: Total G&A | D90: =SUM(D62:D89) -> 26177.477 | E90: =SUM(E62:E89) -> 20658.489 | F90: =SUM(F62:F89) -> 16694.5 | G90: =SUM(G62:G89) -> 15885.5 | H90: =SUM(H62:H89) -> 15885.5 | I90: =SUM(I62:I89) -> 16414.5 | J90: =SUM(J62:J89) -> 16205.5 | K90: =SUM(K62:K89) -> 16205.5 | ... O90: =SUM(O62:O89) -> 16414.5 | P90: =SUM(D90:O90) -> 209366.97
B92: Finance Cost | P92: =SUM(D92:O92) -> 0
B93: Bank Fees and Charges | P93: =SUM(D93:O93) -> 0
B94: BOA 7456 | C94: 21 | D94: =$C94 -> 21 | E94: =$C94 -> 21 | F94: =$C94 -> 21 | G94: =$C94 -> 21 | H94: =$C94 -> 21 | I94: =$C94 -> 21 | J94: =$C94 -> 21 | K94: =$C94 -> 21 | ... O94: =$C94 -> 21 | P94: =SUM(D94:O94) -> 252
B95: Interest on Car loan | P95: =SUM(D95:O95) -> 0
B96: BOA 7456 | C96: 171 | D96: =$C96 -> 171 | E96: =$C96 -> 171 | F96: =$C96 -> 171 | G96: =$C96 -> 171 | H96: =$C96 -> 171 | I96: =$C96 -> 171 | J96: =$C96 -> 171 | K96: =$C96 -> 171 | ... O96: =$C96 -> 171 | P96: =SUM(D96:O96) -> 2052
B97: Interest Paid | P97: =SUM(D97:O97) -> 0
A98: Interest for ECL Loan | B98: BOA 7456 (Loan) | C98: 2360.4 | D98: =$C98 -> 2360.4 | E98: =$C98 -> 2360.4 | F98: =$C98 -> 2360.4 | G98: =$C98 -> 2360.4 | H98: =$C98 -> 2360.4 | I98: =$C98 -> 2360.4 | J98: =$C98 -> 2360.4 | K98: =$C98 -> 2360.4 | P98: =SUM(D98:O98) -> 18883.2
B99: Total Finance costs | D99: =SUM(D93:D98) -> 2552.4 | E99: =SUM(E93:E98) -> 2552.4 | F99: =SUM(F93:F98) -> 2552.4 | G99: =SUM(G93:G98) -> 2552.4 | H99: =SUM(H93:H98) -> 2552.4 | I99: =SUM(I93:I98) -> 2552.4 | J99: =SUM(J93:J98) -> 2552.4 | K99: =SUM(K93:K98) -> 2552.4 | ... O99: =SUM(O93:O98) -> 192 | P99: =SUM(D99:O99) -> 21187.2
B101: Grand Total | D101: =D90+D52+D39+D24+D6+D58+D8+D45 -> 252230.07 | E101: =E90+E52+E39+E24+E6+E58+E8+E45 -> 226195.57 | F101: =F90+F52+F39+F24+F6+F58+F8+F45 -> 192031.36 | G101: =G90+G52+G39+G24+G6+G58+G8+G45 -> 193322.94 | H101: =H90+H52+H39+H24+H6+H58+H8+H45 -> 204124.11 | I101: =I90+I52+I39+I24+I6+I58+I8+I45 -> 198694.62 | J101: =J90+J52+J39+J24+J6+J58+J8+J45 -> 200350.87 | K101: =K90+K52+K39+K24+K6+K58+K8+K45 -> 195390.94 | ... O101: =O90+O52+O39+O24+O6+O58+O8+O45 -> 206832.76 | P101: =SUM(D101:O101) -> 2497806.1
D103: =D90+D58+D52+D45+D39+D24+D8 -> 96754.257 | E103: =E90+E58+E52+E45+E39+E24+E8 -> 66330.109 | F103: =F90+F58+F52+F45+F39+F24+F8 -> 48098.6 | G103: =G90+G58+G52+G45+G39+G24+G8 -> 47789.6 | H103: =H90+H58+H52+H45+H39+H24+H8 -> 52296.49 | I103: =I90+I58+I52+I45+I39+I24+I8 -> 48270.6 | J103: =J90+J58+J52+J45+J39+J24+J8 -> 45950.6 | K103: =K90+K58+K52+K45+K39+K24+K8 -> 45950.6 | ... O103: =O90+O58+O52+O45+O39+O24+O8 -> 46159.6

Sheet Ind Bud-Exp
A1: Imagnum India | R1: 87 | S1: With | XEW1: With
XEW2: Without
A3: Existing Headcount as on Dec-25 | E3: =300-13 -> 287 | F3: =300-13 -> 287 | G3: =300-41 -> 259 | H3: =300-41 -> 259 | I3: =300-41 -> 259 | J3: =300-41 -> 259 | K3: =300-41 -> 259 | L3: =300-41 -> 259 | M3: =300-41 -> 259 | N3: =300-41 -> 259 | ... P3: =300-41 -> 259
