Workbook
Name \: #REF!
Name \: #REF!
Name \: #REF!
Name \: #REF!
Name \: #REF!
Name \: #REF!
Name \0: #REF!
Name \0: #REF!
Name \0: #REF!
Name \0: #REF!
Name \0: #REF!
Name \0: #REF!
Name \A: #REF!
Name \A: #REF!
Name \A: #REF!
Name \A: #REF!
Name \A: #REF!
Name \A: #REF!
Name \B: #REF!
Name \B: #REF!
Name \B: #REF!
Name \B: #REF!
Name \B: #REF!
Name \B: #REF!
Name \E: #REF!
Name \E: #REF!
Name \E: #REF!
Name \E: #REF!
Name \E: #REF!
Name \E: #REF!
Name \G: #REF!
Name \G: #REF!
Name \G: #REF!
Name \G: #REF!
Name \G: #REF!
Name \G: #REF!
Name \L: #REF!
Name \L: #REF!
Name \L: #REF!
Name \L: #REF!
Name \L: #REF!
Name \L: #REF!
Name \q: #REF!
Name \q: #REF!
Name \q: #REF!
Name \q: #REF!
Name \q: #REF!
Name \q: #REF!
Name \S: #REF!
Name \S: #REF!
Name \S: #REF!
Name \S: #REF!
Name \S: #REF!
Name \S: #REF!
Name \T: #REF!
Name \T: #REF!
Name \T: #REF!
Name \T: #REF!
Name \T: #REF!
Name \T: #REF!

Sheet Sheet1
A1: Consolidated P&L — Jan to May 2026
A2: (USD in Whole Numbers)
A4: Particulars | B4: Jan-26 | C4: Feb-26 | D4: Mar-26 | E4: Apr-26 | F4: May-26
A5: Service Income
A6: Sales | B6: 226527 | C6: 227771 | D6: 221215 | E6: 195207 | F6: 209918
A7: Sales | B7: 226814 | C7: 227770 | D7: 221215 | E7: 194902 | F7: 209920
A8: Other Charges | B8: 0 | C8: 1 | D8: 0 | E8: 0 | F8: 0
A9: Buyout | B9: 0
A10: General Income | B10: 287 | C10: 0 | D10: 0 | E10: 16 | F10: 0
A11: Interest Income | B11: 0 | E11: 289 | F11: -2
A12: Total Revenue | B12: 226814 | C12: 227771 | D12: 221215 | E12: 195207 | F12: 209918
A13: Overall Operational cost
A14: Manpower | B14: 114851 | C14: 108834 | D14: 120509 | E14: 100793 | F14: 92483
A15: India Cost
A16: Consultancy fee | B16: 0 | C16: 5914 | D16: 7575 | E16: 0 | F16: 0
A17: Operation salaries | B17: 65899 | C17: 66470 | D17: 71381 | E17: 62706 | F17: 57391
A18: Ops Support Salaries | B18: 37201 | C18: 36233 | D18: 41215 | E18: 38087 | F18: 35040
A19: Contract employee salaries | B19: 0 | C19: 217 | D19: 217 | E19: 0 | F19: 53
A20: Coding charges | B20: 0 | D20: 121 | E20: 0 | F20: -1
A21: Employee statutory expenses | C21: 10714 | D21: 11400 | E21: 11371 | F21: 10965
A22: Employee ESI | B22: 83
A23: EPF Admin Charges | B23: 407 | C23: 370 | D23: 392 | E23: 411 | F23: 381
A24: Employee PF | B24: 5079 | C24: 9273 | D24: 9964 | E24: 9958 | F24: 9488
A25: Employer ESI | B25: 357 | C25: 428 | D25: 404 | E25: 391 | F25: 365
A26: Employer PF | B26: 5079
A27: Professional tax | B27: 748 | C27: 644 | D27: 639 | E27: 610 | F27: 597
A28: Interest on TDS | B28: 0 | F28: 8
A29: Interest on employee statutory dues | B29: 0
A30: Interest on Advance Tax | F30: 127
A31: Facility Cost | B31: 15976 | C31: 15082 | D31: 15533 | E31: 14894 | F31: 17229
A32: Electricity | B32: 0
A33: Electricity Expense | B33: 1968 | C33: 3064 | D33: 2676 | E33: 2980 | F33: 2663
A34: Computer maintenance | B34: 0
A35: Janani Property Maintenance Charges | B35: 743 | C35: 743 | D35: 743 | E35: 743 | F35: 719
A36: Janani Property Rental Charges | B36: 4302 | C36: 4302 | D36: 4302 | E36: 4302 | F36: 4162
A37: Laptop Rental Charges | B37: 2058 | C37: 2068 | D37: 1907 | E37: 1964 | F37: 1924
A38: Thiruttani rental charges | B38: 285 | C38: 285 | D38: 285 | E38: 285 | F38: 290
A39: Max Office rental charges | B39: 4348 | C39: 4348 | D39: 4348 | E39: 4348 | F39: 4207
A40: Rent Expense | B40: 2000 | C40: 272 | D40: 1272 | E40: 272 | F40: 3263
A41: Trichy rental charges | B41: 272
A42: Telcom/Data & others | B42: 4939 | C42: 19569 | D42: 26953 | E42: 1981 | F42: 1969
A43: Telephone Expense | B43: 2336 | C43: 541 | D43: 295 | E43: 285 | F43: 285
A44: Dues and Subscriptions | B44: 435 | C44: 393 | D44: 459 | E44: 220 | F44: 220
A45: IT and Internet Expenses | B45: 966 | C45: 973 | D45: 985 | E45: 479 | F45: 688
A46: Telecom Charges | C46: 146 | D46: 34 | E46: 29 | F46: 27
A47: Telephone Rental Charges | B47: 189 | C47: 189 | D47: 189 | E47: 213 | F47: 210
A48: License/Subscription Charges | B48: 989 | C48: 662 | D48: 838 | E48: 754 | F48: 539
A49: Transport | B49: 4439 | C49: 4371 | D49: 5351 | E49: 4084 | F49: 4254
A50: Staff Transportation Charges | B50: 4439 | C50: 4371 | D50: 5351 | E50: 4084 | F50: 4254
A51: Other COGS | B51: 20230 | C51: 7664 | D51: 9684 | E51: 21527 | F51: 17650
A52: General Insurance | B52: 0
A53: Insurance | B53: 756
A54: Donation | B54: 0
A55: Software development and Hosting charges | B55: 364 | C55: 360 | D55: 1304 | E55: 163 | F55: 427
A56: Other Cogs- MD | B56: 0
A57: Employee Engagement | B57: 0
A58: Staff Welfare Expenses | B58: 419 | C58: 3655 | D58: 3892 | E58: 1727 | F58: 1873
A59: Fuel expenses | B59: 0
A60: Obo Health Inc | B60: 0
A61: Food Coupon-Happay Wallet | B61: 3220 | C61: 2902 | D61: 3070 | E61: 2951 | F61: 2818
A62: Software Expenses | B62: 14832.9 | C62: 16666 | D62: 24152 | E62: 16686 | F62: 12533
A63: Total COGS | B63: 160435 | C63: 166233 | D63: 189430 | E63: 154650 | F63: 144550
A64: GM | B64: 66379 | C64: 61538 | D64: 31785 | E64: 40557 | F64: 65368
A65: GM% | C65: 0.27 | D65: 0.14 | E65: 0.21 | F65: 0.31
A66: SG&A
A67: Selling Expenses | B67: 5200 | C67: 3273 | D67: 2839 | E67: 2109 | F67: 1407
A68: Travel Expense | B68: 1499
A69: Cyber Security Insurance | B69: 0
A70: Rewards and recognition | B70: 0
A71: Meals and Entertainment | B71: 605 | C71: 1070 | D71: 152 | E71: 734 | F71: 318
A72: VISA charges | B72: 0
A73: Conference & Events | B73: 0
A74: Advertisement and marketing | B74: 0
A75: Sales and marketing | B75: 1362 | C75: 1188 | D75: 1211 | E75: 128 | F75: 0
A76: Business Promotion | B76: 0
A77: S&M Salaries | B77: 1154 | C77: 1015 | D77: 1476 | E77: 1247 | F77: 1093
A78: Gratuity | B78: 581 | C78: 0 | D78: 0 | E78: 0 | F78: -4
A79: G&A Expenses
A80: Salaries-Management & Others | B80: 47161 | C80: 37861 | D80: 27151 | E80: 32806 | F80: 25618
A81: Bonus and Incentives | B81: 163 | C81: 0 | D81: 0 | E81: 0 | F81: -1
A82: Management Salaries | B82: 46998 | C82: 37861 | D82: 27151 | E82: 32806 | F82: 25619
A83: Legal & Professional Fees | B83: 9353 | C83: 5878 | D83: 5987 | E83: 3685 | F83: 2340
A84: FPO Charges - SRF | B84: 1359 | C84: 1359 | D84: 2011 | E84: 1359 | F84: 1315
A85: Legal & Professional Services | B85: 7940 | C85: 4519 | D85: 3976 | E85: 2326 | F85: 1025
A86: FPO Charges-SMCS GLOBAL | B86: 54 | C86: 0 | D86: 0
A87: G&A salaries | B87: 14329 | C87: 9723 | D87: 6533 | E87: 5917 | F87: 7541
A88: Payroll taxes | B88: 11723 | C88: 7357 | D88: 3764 | E88: 3675 | F88: 5513
A89: HR Salaries | B89: 758 | C89: 750 | D89: 951 | E89: 632 | F89: 557
A90: Admin Salaries | B90: 994 | C90: 943 | D90: 860 | E90: 774 | F90: 693
A91: IT Salaries | B91: 854 | C91: 673 | D91: 958 | E91: 836 | F91: 777
A92: Coder | B92: 0
A93: Gen & Admin Expenses | B93: 16549 | C93: 9435 | D93: 15990 | E93: 9176 | F93: 10040
A94: Consultancy Fees | B94: 6383
A95: Comission Paid-Scinet Inc | B95: 0
A96: Leadership engagemnet | B96: 0
A97: Charitable Donations | B97: 0
A98: Fuel/Mileage Expenses | B98: 132 | C98: 125 | D98: 97 | E98: 89 | F98: 0
A99: Payroll Processing Fees | B99: 963 | C99: 468 | D99: 608 | E99: 523 | F99: 537
A100: Parking | B100: 0
A101: Toll Fee | B101: 25 | C101: 25 | D101: 0 | E101: 25 | F101: 0
...

Sheet Consolidated PnL-Jan
B1: IMAGNUM HEALTHCARE SOLUTION PRIVATE LIMITED
B2: =MID(CELL("filename",B1),FIND("]",CELL("filename",B1))+1,250) -> Consolidated PnL-Jan
B4: Particulars | C4: Jan-US | D4: Jan-India | E4: Jan Consolidation | F4: Budget Remarks
B5: Service Income
B6: Sales | C6: =C77 -> 226814 | D6: =D77 -> 0 | E6: =C6+D6 -> 226814
B7: Total Revenue | C7: =SUM(C6) -> 226814 | D7: =SUM(D6) -> 0 | E7: =C7+D7 -> 226814
B9: Overall Operational cost
B10: Manpower | C10: =C99 -> 0 | D10: =D99 -> 114851.43 | E10: =E99 -> 114851.43 | F10: Budgeted HC for operations & ops support is 208 whereas Actual HC is 270
B11: Facility Cost | C11: =C112 -> 2000 | D11: =D112 -> 13975.718 | E11: =C11+D11 -> 15975.718
B12: Telcom/Data & others | C12: =C123 -> 3270.23 | D12: =D123 -> 1668.7611 | E12: =C12+D12 -> 4938.9911
B13: Transport | C13: =C127 -> 0 | D13: =D127 -> 4438.587 | E13: =C13+D13 -> 4438.587 | F13: Transport cost budgeted in proportion with HC
B14: Other COGS | C14: =C142 -> 14832.9 | D14: =D142 -> 5397.5486 | E14: =C14+D14 -> 20230.449 | F14: Software Expense budgeted for $9,393 whereas actual it is $20,656
B15: Total COGS | C15: =SUM(C10:C14) -> 20103.13 | D15: =SUM(D10:D14) -> 140332.05 | E15: =SUM(E10:E14) -> 160435.18
B16: GP | C16: =C7-C15 -> 206710.87 | D16: =D7-D15 -> -140332.05 | E16: =E7-E15 -> 66378.82
B17: GM% | E17: =E16/E7 -> 0.29265751
B20: SG&A
B21: Selling Expenses | C21: =C159 -> 3440.69 | D21: =D159 -> 1759.788 | E21: =C21+D21 -> 5200.478
B22: G&A Expenses
B23: Salaries-Management & Others | C23: =C210 -> 37269.02 | D23: =D210 -> 9892.1087 | E23: =C23+D23 -> 47161.129
B24: Legal & Professional Fees | C24: =C205 -> 7940.38 | D24: =D205 -> 1413.0435 | E24: =C24+D24 -> 9353.4235
B25: G&A salaries | C25: =C198 -> 11722.56 | D25: =D198 -> 2606.087 | E25: =C25+D25 -> 14328.647
B26: Gen & Admin. Expenses | C26: =C190 -> 15020.47 | D26: =D190 -> 1528.303 | E26: =C26+D26 -> 16548.773 | F26: Insurance expense budgeted for $1,400 whereas actual it is $6,487 Consultancy fees not budgeted whereas actual it $3,750
B27: Total | C27: =SUM(C23:C26) -> 71952.43 | D27: =SUM(D23:D26) -> 15439.542 | E27: =C27+D27 -> 87391.972
B29: Overall SG&A | C29: =+C21+C27 -> 75393.12 | D29: =+D21+D27 -> 17199.33 | E29: =C29+D29 -> 92592.45
B31: EBITDA | C31: =C16-C29 -> 131317.75 | D31: =D16-D29 -> -157531.38 | E31: =E16-E29 -> -26213.63
B32: EBITDA% | E32: =E31/E7 -> -0.11557325
B34: Finance Cost | C34: =C219 -> 4889.52 | D34: =D219 -> -6231.8296 | E34: =C34+D34 -> -1342.3096
B35: Rates & Taxes | C35: =C221 -> 0 | D35: =D221 -> 0 | E35: =C35+D35 -> 0
B36: Depreciation | C36: =C222 -> 0 | D36: =D222 -> 0 | E36: =C36+D36 -> 0
B37: Total | C37: =SUM(C34:C36) -> 4889.52 | D37: =SUM(D34:D36) -> -6231.8296 | E37: =C37+D37 -> -1342.3096
B39: PBT | C39: =C31-C37 -> 126428.23 | D39: =D31-D37 -> -151299.55 | E39: =E31-E37 -> -24871.321
E40: =E39/E7 -> -0.10965514
B41: Check point
B42: Revenue | E42: =C72 -> 226527
B43: India cost | E43: ='[1]Subs MoM PnL'!T7-'[1]Subs MoM PnL'!T37 -> 151604.88
B44: US cost | E44: =C7-C39 -> 100385.77
B45: Profit | E45: =E42-E43-E44 -> -25463.647
E46: =E45-E39 -> -592.32609
B49: Total Revenue | E49: =E7 -> 226814
B50: Directs | E50: ='[1]Payroll Dashboard'!BA5 -> 197
B51: Overall HC | E51: ='[1]Payroll Dashboard'!BA12 -> 281
B54: Rev/FTE (Pricing) | E54: =E49/E50 -> 1151.3401
B55: Cost/FTE | E55: =E15/E50 -> 814.39178
B56: Gross Profit/FTE | E56: =E54-E55 -> 336.94833
E57: =E56/E54 -> 0.29265751
B60: Rev/Head | E60: =E49/E51 -> 807.16726
B61: Cost/Head | E61: =(E7-E39)/E51 -> 895.6773
B62: Margin/Head | E62: =E60-E61 -> -88.510038
E63: =E62/E60 -> -0.10965514
B68: Detailed Break up
C69: 27
B70: =B4 -> Particulars | C70: =C4 -> Jan-US | D70: =D4 -> Jan-India | E70: =E4 -> Jan Consolidation | F70: =F4 -> Budget Remarks
B71: Service Income
B72: Sales | C72: =IFERROR(VLOOKUP(B72,'[1]Holding Inc statement'!$B$45:$AB$119,'Consolidated PnL-Jan'!$C$69,0),) -> 226527 | E72: =C72+D72 -> 226527
B73: Other Charges | C73: =IFERROR(VLOOKUP(B73,'[1]Holding Inc statement'!$B$45:$AB$119,'Consolidated PnL-Jan'!$C$69,0),) -> 0 | E73: =C73+D73 -> 0
B74: Buyout | C74: =IFERROR(VLOOKUP(B74,'[1]Holding Inc statement'!$B$45:$AB$119,'Consolidated PnL-Jan'!$C$69,0),) -> 0 | D74: =IFERROR(VLOOKUP(B74,'[1]Subs Income statement'!$AF$48:$BF$178,'Consolidated PnL-Jan'!$C$69,0),) -> 0 | E74: =C74+D74 -> 0
B75: Interest Income | C75: =IFERROR(VLOOKUP(B75,'[1]Holding Inc statement'!$B$45:$AB$119,'Consolidated PnL-Jan'!$C$69,0),) -> 0 | D75: =IFERROR(VLOOKUP(B75,'[1]Subs Income statement'!$AF$48:$BF$178,'Consolidated PnL-Jan'!$C$69,0),) -> 0 | E75: =C75+D75 -> 0
B76: General Income | C76: =IFERROR(VLOOKUP(B76,'[1]Holding Inc statement'!$B$45:$AB$119,'Consolidated PnL-Jan'!$C$69,0),) -> 287 | E76: =C76+D76 -> 287
B77: Direct Incomes | C77: =SUM(C72:C76) -> 226814 | D77: =SUM(D72:D76) -> 0 | E77: =SUM(E72:E76) -> 226814
B79: Manpower
B80: India cost
B81: Consultancy fee | C81: =IFERROR(VLOOKUP(B81,'[1]Holding Inc statement'!$B$45:$AB$119,'Consolidated PnL-Jan'!$C$69,0),) -> 0 | D81: =IFERROR(VLOOKUP(B81,'[1]Subs Income statement'!$AF$48:$BF$178,'Consolidated PnL-Jan'!$C$69,0),) -> 0 | E81: =C81+D81 -> 0
B82: Operation salaries | C82: =IFERROR(VLOOKUP(B82,'[1]Holding Inc statement'!$B$45:$AB$119,'Consolidated PnL-Jan'!$C$69,0),) -> 0 | D82: =IFERROR(VLOOKUP(B82,'[1]Subs Income statement'!$AF$48:$BF$178,'Consolidated PnL-Jan'!$C$69,0),) -> 65898.685 | E82: =C82+D82 -> 65898.685
B83: Ops Support Salaries | C83: =IFERROR(VLOOKUP(B83,'[1]Holding Inc statement'!$B$45:$AB$119,'Consolidated PnL-Jan'!$C$69,0),) -> 0 | D83: =IFERROR(VLOOKUP(B83,'[1]Subs Income statement'!$AF$48:$BF$178,'Consolidated PnL-Jan'!$C$69,0),) -> 37200.967 | E83: =C83+D83 -> 37200.967
B84: Contract employee salaries | C84: =IFERROR(VLOOKUP(B84,'[1]Holding Inc statement'!$B$45:$AB$119,'Consolidated PnL-Jan'!$C$69,0),) -> 0 | D84: =IFERROR(VLOOKUP(B84,'[1]Subs Income statement'!$AF$48:$BF$178,'Consolidated PnL-Jan'!$C$69,0),) -> 0 | E84: =C84+D84 -> 0
B85: Coding charges | C85: =IFERROR(VLOOKUP(B85,'[1]Holding Inc statement'!$B$45:$AB$119,'Consolidated PnL-Jan'!$C$69,0),) -> 0 | D85: =IFERROR(VLOOKUP(B85,'[1]Subs Income statement'!$AF$48:$BF$178,'Consolidated PnL-Jan'!$C$69,0),) -> 0 | E85: =C85+D85 -> 0
B86: Total | C86: =SUM(C81:C85) -> 0 | D86: =SUM(D81:D85) -> 103099.65 | E86: =SUM(E81:E85) -> 103099.65
B88: Employee statutory expenses
B89: Employee ESI | C89: =IFERROR(VLOOKUP(B89,'[1]Holding Inc statement'!$B$45:$AB$119,'Consolidated PnL-Jan'!$C$69,0),) -> 0 | D89: =IFERROR(VLOOKUP(B89,'[1]Subs Income statement'!$AF$48:$BF$178,'Consolidated PnL-Jan'!$C$69,0),) -> 82.630435 | E89: =C89+D89 -> 82.630435
B90: EPF Admin Charges | C90: =IFERROR(VLOOKUP(B90,'[1]Holding Inc statement'!$B$45:$AB$119,'Consolidated PnL-Jan'!$C$69,0),) -> 0 | D90: =IFERROR(VLOOKUP(B90,'[1]Subs Income statement'!$AF$48:$BF$178,'Consolidated PnL-Jan'!$C$69,0),) -> 406.91304 | E90: =C90+D90 -> 406.91304
B91: Employee PF | C91: =IFERROR(VLOOKUP(B91,'[1]Holding Inc statement'!$B$45:$AB$119,'Consolidated PnL-Jan'!$C$69,0),) -> 0 | D91: =IFERROR(VLOOKUP(B91,'[1]Subs Income statement'!$AF$48:$BF$178,'Consolidated PnL-Jan'!$C$69,0),) -> 5078.7174 | E91: =C91+D91 -> 5078.7174
B92: Employer ESI | C92: =IFERROR(VLOOKUP(B92,'[1]Holding Inc statement'!$B$45:$AB$119,'Consolidated PnL-Jan'!$C$69,0),) -> 0 | D92: =IFERROR(VLOOKUP(B92,'[1]Subs Income statement'!$AF$48:$BF$178,'Consolidated PnL-Jan'!$C$69,0),) -> 356.8913 | E92: =C92+D92 -> 356.8913
B93: Employer PF | C93: =IFERROR(VLOOKUP(B93,'[1]Holding Inc statement'!$B$45:$AB$119,'Consolidated PnL-Jan'!$C$69,0),) -> 0 | D93: =IFERROR(VLOOKUP(B93,'[1]Subs Income statement'!$AF$48:$BF$178,'Consolidated PnL-Jan'!$C$69,0),) -> 5078.7174 | E93: =C93+D93 -> 5078.7174
B94: Professional tax | C94: =IFERROR(VLOOKUP(B94,'[1]Holding Inc statement'!$B$45:$AB$119,'Consolidated PnL-Jan'!$C$69,0),) -> 0 | D94: =IFERROR(VLOOKUP(B94,'[1]Subs Income statement'!$AF$48:$BF$178,'Consolidated PnL-Jan'!$C$69,0),) -> 747.91304 | E94: =C94+D94 -> 747.91304
B95: Interest on TDS | C95: =IFERROR(VLOOKUP(B95,'[1]Holding Inc statement'!$B$45:$AB$119,'Consolidated PnL-Jan'!$C$69,0),) -> 0 | D95: =IFERROR(VLOOKUP(B95,'[1]Subs Income statement'!$AF$48:$BF$178,'Consolidated PnL-Jan'!$C$69,0),) -> 0 | E95: =C95+D95 -> 0
B96: Interest on employee statutory dues | C96: =IFERROR(VLOOKUP(B96,'[1]Holding Inc statement'!$B$45:$AB$119,'Consolidated PnL-Jan'!$C$69,0),) -> 0 | D96: =IFERROR(VLOOKUP(B96,'[1]Subs Income statement'!$AF$48:$BF$178,'Consolidated PnL-Jan'!$C$69,0),) -> 0 | E96: =C96+D96 -> 0
B97: Total | C97: =SUM(C88:C96) -> 0 | D97: =SUM(D88:D96) -> 11751.783 | E97: =C97+D97 -> 11751.783
B99: Total Manpower | C99: =C86+C97 -> 0 | D99: =D86+D97 -> 114851.43 | E99: =E86+E97 -> 114851.43
B101: Facility Cost
B102: Electricity | C102: =IFERROR(VLOOKUP(B102,'[1]Holding Inc statement'!$B$45:$AB$119,'Consolidated PnL-Jan'!$C$69,0),) -> 0 | D102: =IFERROR(VLOOKUP(B102,'[1]Subs Income statement'!$AF$48:$BF$178,'Consolidated PnL-Jan'!$C$69,0),) -> 0 | E102: =C102+D102 -> 0
B103: Electricity Expense | C103: =IFERROR(VLOOKUP(B103,'[1]Holding Inc statement'!$B$45:$AB$119,'Consolidated PnL-Jan'!$C$69,0),) -> 0 | D103: =IFERROR(VLOOKUP(B103,'[1]Subs Income statement'!$AF$48:$BF$178,'Consolidated PnL-Jan'!$C$69,0),) -> 1968.0435 | E103: =C103+D103 -> 1968.0435
B104: Computer maintenance | C104: =IFERROR(VLOOKUP(B104,'[1]Holding Inc statement'!$B$45:$AB$119,'Consolidated PnL-Jan'!$C$69,0),) -> 0 | D104: =IFERROR(VLOOKUP(B104,'[1]Subs Income statement'!$AF$48:$BF$178,'Consolidated PnL-Jan'!$C$69,0),) -> 0 | E104: =C104+D104 -> 0
B105: Janani Property Maintenance Charges | C105: =IFERROR(VLOOKUP(B105,'[1]Holding Inc statement'!$B$45:$AB$119,'Consolidated PnL-Jan'!$C$69,0),) -> 0 | D105: =IFERROR(VLOOKUP(B105,'[1]Subs Income statement'!$AF$48:$BF$178,'Consolidated PnL-Jan'!$C$69,0),) -> 743.04348 | E105: =C105+D105 -> 743.04348
B106: Janani Property Rental Charges | C106: =IFERROR(VLOOKUP(B106,'[1]Holding Inc statement'!$B$45:$AB$119,'Consolidated PnL-Jan'!$C$69,0),) -> 0 | D106: =IFERROR(VLOOKUP(B106,'[1]Subs Income statement'!$AF$48:$BF$178,'Consolidated PnL-Jan'!$C$69,0),) -> 4301.837 | E106: =C106+D106 -> 4301.837
B107: Laptop Rental Charges | C107: =IFERROR(VLOOKUP(B107,'[1]Holding Inc statement'!$B$45:$AB$119,'Consolidated PnL-Jan'!$C$69,0),) -> 0 | D107: =IFERROR(VLOOKUP(B107,'[1]Subs Income statement'!$AF$48:$BF$178,'Consolidated PnL-Jan'!$C$69,0),) -> 2057.9033 | E107: =C107+D107 -> 2057.9033
B108: Trichy rental charges | C108: =IFERROR(VLOOKUP(B108,'[1]Holding Inc statement'!$B$45:$AB$119,'Consolidated PnL-Jan'!$C$69,0),) -> 0 | D108: =IFERROR(VLOOKUP(B108,'[1]Subs Income statement'!$AF$48:$BF$178,'Consolidated PnL-Jan'!$C$69,0),) -> 271.73913 | E108: =C108+D108 -> 271.73913
B109: Thiruttani rental charges | C109: =IFERROR(VLOOKUP(B109,'[1]Holding Inc statement'!$B$45:$AB$119,'Consolidated PnL-Jan'!$C$69,0),) -> 0 | D109: =IFERROR(VLOOKUP(B109,'[1]Subs Income statement'!$AF$48:$BF$178,'Consolidated PnL-Jan'!$C$69,0),) -> 285.32609 | E109: =C109+D109 -> 285.32609
B110: Max Office rental charges | C110: =IFERROR(VLOOKUP(B110,'[1]Holding Inc statement'!$B$45:$AB$119,'Consolidated PnL-Jan'!$C$69,0),) -> 0 | D110: =IFERROR(VLOOKUP(B110,'[1]Subs Income statement'!$AF$48:$BF$178,'Consolidated PnL-Jan'!$C$69,0),) -> 4347.8261 | E110: =C110+D110 -> 4347.8261
B111: Rent Expense | C111: =IFERROR(VLOOKUP(B111,'[1]Holding Inc statement'!$B$45:$AB$119,'Consolidated PnL-Jan'!$C$69,0),) -> 2000 | D111: =IFERROR(VLOOKUP(B111,'[1]Subs Income statement'!$AF$48:$BF$178,'Consolidated PnL-Jan'!$C$69,0),) -> 0 | E111: =C111+D111 -> 2000
B112: Total | C112: =SUM(C102:C111) -> 2000 | D112: =SUM(D102:D111) -> 13975.718 | E112: =C112+D112 -> 15975.718
B115: Telecom Charges
B116: Telephone Expense | C116: =IFERROR(VLOOKUP(B116,'[1]Holding Inc statement'!$B$45:$AB$119,'Consolidated PnL-Jan'!$C$69,0),) -> 2335.84 | D116: =IFERROR(VLOOKUP(B116,'[1]Subs Income statement'!$AF$48:$BF$178,'Consolidated PnL-Jan'!$C$69,0),) -> 0 | E116: =C116+D116 -> 2335.84
B117: Dues and Subscriptions | C117: =IFERROR(VLOOKUP(B117,'[1]Holding Inc statement'!$B$45:$AB$119,'Consolidated PnL-Jan'!$C$69,0),) -> 435.09 | D117: =IFERROR(VLOOKUP(B117,'[1]Subs Income statement'!$AF$48:$BF$178,'Consolidated PnL-Jan'!$C$69,0),) -> 0 | E117: =C117+D117 -> 435.09
B118: Software Expenses | C118: =IFERROR(VLOOKUP(B118,'[1]Holding Inc statement'!$B$45:$AB$119,'Consolidated PnL-Jan'!$C$69,0),) -> 0 | D118: =IFERROR(VLOOKUP(B118,'[1]Subs Income statement'!$AF$48:$BF$178,'Consolidated PnL-Jan'!$C$69,0),) -> 0 | E118: =C118+D118 -> 0
B119: License/Subscription/Certification Charges | C119: =IFERROR(VLOOKUP(B119,'[1]Holding Inc statement'!$B$45:$AB$119,'Consolidated PnL-Jan'!$C$69,0),) -> 0 | D119: =IFERROR(VLOOKUP(B119,'[1]Subs Income statement'!$AF$48:$BF$178,'Consolidated PnL-Jan'!$C$69,0),) -> 988.9913 | E119: =C119+D119 -> 988.9913
B120: IT and Internet Expenses | C120: =IFERROR(VLOOKUP(B120,'[1]Holding Inc statement'!$B$45:$AB$119,'Consolidated PnL-Jan'!$C$69,0),) -> 499.3 | D120: =IFERROR(VLOOKUP(B120,'[1]Subs Income statement'!$AF$48:$BF$178,'Consolidated PnL-Jan'!$C$69,0),) -> 466.48913 | E120: =C120+D120 -> 965.78913
B121: Telecom Charges | C121: =IFERROR(VLOOKUP(B121,'[1]Holding Inc statement'!$B$45:$AB$119,'Consolidated PnL-Jan'!$C$69,0),) -> 0 | D121: =IFERROR(VLOOKUP(B121,'[1]Subs Income statement'!$AF$48:$BF$178,'Consolidated PnL-Jan'!$C$69,0),) -> 24.150217 | E121: =C121+D121 -> 24.150217
B122: Telephone Rental Charges | C122: =IFERROR(VLOOKUP(B122,'[1]Holding Inc statement'!$B$45:$AB$119,'Consolidated PnL-Jan'!$C$69,0),) -> 0 | D122: =IFERROR(VLOOKUP(B122,'[1]Subs Income statement'!$AF$48:$BF$178,'Consolidated PnL-Jan'!$C$69,0),) -> 189.13043 | E122: =C122+D122 -> 189.13043
B123: Total | C123: =SUM(C116:C122) -> 3270.23 | D123: =SUM(D116:D122) -> 1668.7611 | E123: =C123+D123 -> 4938.9911
B125: Transportation Costs
...

Sheet Consolidated- Mar&Feb
B2: iMagnum US | C2: Period: March 2026 | G2: Period: February 2026
B3: FTM_CurrentYear_CV_SPL | F3: ( USD in Whole Number ) | J3: ( USD in Whole Number )
B6: particulars | C6: iMagnum India | D6: iMagnum US | E6: Total | F6: Elimination-iMagnum Segment | G6: iMagnum India | H6: iMagnum US | I6: Total | J6: Elimination-iMagnum Segment | K6: Variance
B7: Service Income
B8: Sales | C8: 123319 | D8: 221215 | E8: 221215 | F8: -123319 | G8: 184916 | H8: 227771 | I8: 227771 | J8: -184916 | K8: =E8-I8 -> -6556
B9: Sales | C9: 123319 | D9: 221215 | E9: 221215 | F9: -123319 | G9: 184916 | H9: 227770 | I9: 227770 | J9: -184916
B10: Other Charges | C10: 0 | D10: 0 | E10: 0 | G10: 0 | H10: 1 | I10: 1
B11: Buyout
B12: General Income | D12: 0 | E12: 0 | H12: 0 | I12: 0
B13: Interest Income
B14: Total Revenue | C14: 123319 | D14: 221215 | E14: 221215 | F14: -123319 | G14: 184916 | H14: 227771 | I14: 227771 | J14: -184916
B15: Overall Operational cost
B16: Manpower | C16: 112934 | D16: 130894 | E16: 120509 | F16: -123319 | G16: 102920 | H16: 190830 | I16: 108834 | J16: -184916 | K16: =I16-E16 -> -11675
B17: India Cost
B18: Consultancy fee | D18: 7575 | E18: 7575 | H18: 5914 | I18: 5914
B19: Operation salaries | C19: 71381 | E19: 71381 | G19: 66470 | I19: 66470
B20: Ops Support Salaries | C20: 41215 | E20: 41215 | G20: 36233 | I20: 36233
B21: Contract employee salaries | C21: 217 | D21: 123319 | E21: 217 | F21: -123319 | G21: 217 | H21: 184916 | I21: 217 | J21: -184916
B22: Coding charges | C22: 121 | E22: 121
B23: Employee statutory expenses | C23: 11400 | E23: 11400 | G23: 10714 | I23: 10714 | K23: =I23-E23 -> -686
B24: Employee ESI
B25: EPF Admin Charges | C25: 392 | E25: 392 | G25: 370 | I25: 370
B26: Employee PF | C26: 9964 | E26: 9964 | G26: 9273 | I26: 9273
B27: Employer ESI | C27: 404 | E27: 404 | G27: 428 | I27: 428
B28: Employer PF
B29: Professional tax | C29: 639 | E29: 639 | G29: 644 | I29: 644
B30: Interest on TDS
B31: Interest on employee statutory dues
B32: Facility Cost | C32: 14533 | D32: 1000 | E32: 15533 | G32: 15082 | H32: 0 | I32: 15082 | K32: =I32-E32 -> -451
B33: Electricity
B34: Electricity Expense | C34: 2676 | E34: 2676 | G34: 3064 | I34: 3064
B35: Computer maintenance
B36: Janani Property Maintenance Charges | C36: 743 | E36: 743 | G36: 743 | I36: 743
B37: Janani Property Rental Charges | C37: 4302 | E37: 4302 | G37: 4302 | I37: 4302
B38: Laptop Rental Charges | C38: 1907 | E38: 1907 | G38: 2068 | I38: 2068
B39: Thiruttani rental charges | C39: 285 | E39: 285 | G39: 285 | I39: 285
B40: Max Office rental charges | C40: 4348 | E40: 4348 | G40: 4348 | I40: 4348
B41: Rent Expense | C41: 272 | D41: 1000 | E41: 1272 | G41: 272 | H41: 0 | I41: 272
B42: Trichy rental charges
B43: Telcom/Data & others | C43: 1546 | D43: 25406 | E43: 26953 | G43: 1464 | H43: 18105 | I43: 19569 | K43: =I43-E43 -> -7384
B44: Telephone Expense | D44: 295 | E44: 295 | H44: 541 | I44: 541 | K44: =I44-E44 -> 246
B45: Dues and Subscriptions | D45: 459 | E45: 459 | H45: 393 | I45: 393 | K45: =I45-E45 -> -66
B46: Software Expenses | D46: 24152 | E46: 24152 | H46: 16666 | I46: 16666 | K46: =I46-E46 -> -7486
B47: IT and Internet Expenses | C47: 485 | D47: 501 | E47: 985 | G47: 466 | H47: 506 | I47: 973 | K47: =I47-E47 -> -12
B48: Telecom Charges | C48: 34 | E48: 34 | G48: 146 | I48: 146 | K48: =I48-E48 -> 112
B49: Telephone Rental Charges | C49: 189 | E49: 189 | G49: 189 | I49: 189 | K49: =I49-E49 -> 0
B50: License/Subscription Charges | C50: 838 | E50: 838 | G50: 662 | I50: 662 | K50: =I50-E50 -> -176
B51: Transport | C51: 5351 | E51: 5351 | G51: 4371 | I51: 4371 | K51: =I51-E51 -> -980
B52: Staff Transportation Charges | C52: 5351 | E52: 5351 | G52: 4371 | I52: 4371 | K52: =I52-E52 -> -980
B53: Other COGS | C53: 9684 | E53: 9684 | G53: 7664 | I53: 7664 | K53: =I53-E53 -> -2020
B54: General Insurance
B55: Insurance
B56: Donation
B57: Software development and Hosting charges | C57: 1304 | E57: 1304 | G57: 360 | I57: 360
B58: Other Cogs- MD
B59: Employee Engagement
B60: Staff Welfare Expenses | C60: 3892 | E60: 3892 | G60: 3655 | I60: 3655
B61: Interest on OD | C61: 1417 | E61: 1417 | G61: 746 | I61: 746
B62: Fuel expenses
B63: Obo Health Inc
B64: Food Coupon-Happay Wallet | C64: 3070 | E64: 3070 | G64: 2902 | I64: 2902
B65: Software expense
B66: Total COGS | C66: 155448 | D66: 157300 | E66: 189430 | F66: -123319 | G66: 142214 | H66: 208935 | I66: 166233 | J66: -184916 | K66: =I66-E66 -> -23197
B67: GM | C67: -32129 | D67: 63915 | E67: 31785 | F67: 0 | G67: 42702 | H67: 18836 | I67: 61538 | J67: 0
B68: GM% | C68: (26 %) | D68: 29 % | E68: 14 % | F68: 0 | G68: 23 % | H68: 8 % | I68: 27 % | J68: 0
B69: SG&A
B70: Selling Expenses | C70: 1538 | D70: 1301 | E70: 2839 | G70: 1368 | H70: 1905 | I70: 3273 | K70: =I70-E70 -> 434
B71: Travel Expense
B72: Cyber Security Insurance
B73: Rewards and recognition
B74: Meals and Entertainment | C74: 62 | D74: 90 | E74: 152 | G74: 353 | H74: 717 | I74: 1070
B75: VISA charges
B76: Conference & Events
B77: Advertisement and marketing
B78: Sales and marketing | D78: 1211 | E78: 1211 | H78: 1188 | I78: 1188
B79: Business Promotion
B80: S&M Salaries | C80: 1476 | E80: 1476 | G80: 1015 | I80: 1015
B81: Gratuity | C81: 0 | E81: 0 | G81: 0 | I81: 0
B82: New Tools and Accesses - Needed
B83: Customs Duty
B84: G&A Expenses
B85: Salaries-Management & Others | C85: 9729 | D85: 17422 | E85: 27151 | G85: 9729 | H85: 28132 | I85: 37861 | K85: =I85-E85 -> 10710
B86: Bonus and Incentives | C86: 0 | E86: 0 | G86: 0 | I86: 0 | K86: =I86-E86 -> 0
B87: Management Salaries | C87: 9729 | D87: 17422 | E87: 27151 | G87: 9729 | H87: 28132 | I87: 37861 | K87: =I87-E87 -> 10710
B88: Legal & Professional Fees | C88: 2011 | D88: 3976 | E88: 5987 | G88: 1359 | H88: 4519 | I88: 5878 | K88: =I88-E88 -> -109
B89: Professional fees | K89: =I89-E89 -> #VALUE!
B90: FPO Charges - SRF | C90: 2011 | E90: 2011 | G90: 1359 | I90: 1359 | K90: =I90-E90 -> -652
B91: Legal & Professional Services | D91: 3976 | E91: 3976 | H91: 4519 | I91: 4519 | K91: =I91-E91 -> 543
B92: FPO Charges-SMCS GLOBAL | C92: 0 | E92: 0 | G92: 0 | I92: 0 | K92: =I92-E92 -> 0
B93: G&A salaries | C93: 2768 | D93: 3764 | E93: 6533 | G93: 2366 | H93: 7357 | I93: 9723 | K93: =I93-E93 -> 3190
B94: Payroll taxes | D94: 3764 | E94: 3764 | H94: 7357 | I94: 7357 | K94: =I94-E94 -> 3593
B95: HR Salaries | C95: 951 | E95: 951 | G95: 750 | I95: 750 | K95: =I95-E95 -> -201
B96: Admin Salaries | C96: 860 | E96: 860 | G96: 943 | I96: 943 | K96: =I96-E96 -> 83
B97: IT Salaries | C97: 958 | E97: 958 | G97: 673 | I97: 673 | K97: =I97-E97 -> -285
B98: Coder | K98: =I98-E98 -> #VALUE!
B99: Gen & Admin Expenses | C99: 3126 | D99: 12864 | E99: 15990 | G99: 2690 | H99: 6744 | I99: 9435 | K99: =I99-E99 -> -6555
B100: Consultancy Fees | K100: =I100-E100 -> #VALUE!
B101: Comission Paid-Scinet Inc | K101: =I101-E101 -> #VALUE!
B102: Leadership engagemnet | K102: =I102-E102 -> #VALUE!
B103: Charitable Donations | K103: =I103-E103 -> #VALUE!
...

Sheet Consolidted PnL-April
B2: iMagnum US | C2: Period: April 2026 | G2: Period: March 2026
B3: FTM_CurrentYear_CV_SPL | E3: ( USD in Whole Number ) | I3: ( USD in Whole Number )
B6: particulars | C6: iMagnum India | D6: iMagnum US | E6: Elimination-iMagnum Segment | F6: Total | G6: iMagnum India | H6: iMagnum US | I6: Elimination-iMagnum Segment | J6: Total | K6: Variance
B7: Service Income
B8: Sales | C8: 176206 | D8: 194902 | E8: -175901 | F8: 195207 | G8: 75319 | H8: 237839 | I8: -75319 | J8: 237839 | K8: =F8-J8 -> -42632
B9: Sales | C9: 175901 | D9: 194902 | E9: -175901 | F9: 194902 | G9: 75319 | H9: 237839 | I9: -75319 | J9: 237839 | K9: =F9-J9 -> -42937
B10: Other Charges | C10: 0 | D10: 0 | F10: 0 | G10: 0 | H10: 0 | J10: 0 | K10: =F10-J10 -> 0
B11: Buyout
B12: General Income | C12: 16 | D12: 0 | F12: 16 | H12: 0 | J12: 0 | K12: =F12-J12 -> 16
B13: Interest Income | C13: 289 | F13: 289
B14: Total Revenue | C14: 176206 | D14: 194902 | E14: -175901 | F14: 195207 | G14: 75319 | H14: 237839 | I14: -75319 | J14: 237839 | K14: =F14-J14 -> -42632
B15: Overall Operational cost
B16: Manpower | C16: 100793 | D16: 175901 | E16: -175901 | F16: 100793 | G16: 104521 | H16: 75394 | I16: -75319 | J16: 104596 | K16: =F16-J16 -> -3803
B17: India Cost
B18: Consultancy fee | D18: 0 | F18: 0 | H18: 75 | J18: 75 | K18: =F18-J18 -> -75
B19: Operation salaries | C19: 62706 | F19: 62706 | G19: 65666 | J19: 65666 | K19: =F19-J19 -> -2960
B20: Ops Support Salaries | C20: 38087 | F20: 38087 | G20: 38517 | J20: 38517 | K20: =F20-J20 -> -430
B21: Contract employee salaries | C21: 0 | D21: 175901 | E21: -175901 | F21: 0 | G21: 217 | H21: 75319 | I21: -75319 | J21: 217 | K21: =F21-J21 -> -217
B22: Coding charges | C22: 0 | F22: 0 | G22: 121 | J22: 121 | K22: =F22-J22 -> -121
B23: Employee statutory expenses | C23: 11371 | F23: 11371 | G23: 10999 | J23: 10999 | K23: =F23-J23 -> 372
B24: Employee ESI
B25: EPF Admin Charges | C25: 411 | F25: 411 | G25: 383 | J25: 383 | K25: =F25-J25 -> 28
B26: Employee PF | C26: 9958 | F26: 9958 | G26: 9573 | J26: 9573 | K26: =F26-J26 -> 385
B27: Employer ESI | C27: 391 | F27: 391 | G27: 404 | J27: 404 | K27: =F27-J27 -> -13
B28: Employer PF
B29: Professional tax | C29: 610 | F29: 610 | G29: 639 | J29: 639 | K29: =F29-J29 -> -29
B30: Interest on TDS
B31: Interest on employee statutory dues
B32: Facility Cost | C32: 14894 | D32: 0 | F32: 14894 | G32: 14533 | H32: 1000 | J32: 15533 | K32: =F32-J32 -> -639
B33: Electricity
B34: Electricity Expense | C34: 2980 | F34: 2980 | G34: 2676 | J34: 2676 | K34: =F34-J34 -> 304
B35: Computer maintenance
B36: Janani Property Maintenance Charges | C36: 743 | F36: 743 | G36: 743 | J36: 743 | K36: =F36-J36 -> 0
B37: Janani Property Rental Charges | C37: 4302 | F37: 4302 | G37: 4302 | J37: 4302 | K37: =F37-J37 -> 0
B38: Laptop Rental Charges | C38: 1964 | F38: 1964 | G38: 1907 | J38: 1907 | K38: =F38-J38 -> 57
B39: Thiruttani rental charges | C39: 285 | F39: 285 | G39: 285 | J39: 285 | K39: =F39-J39 -> 0
B40: Max Office rental charges | C40: 4348 | F40: 4348 | G40: 4348 | J40: 4348 | K40: =F40-J40 -> 0
B41: Rent Expense | C41: 272 | D41: 0 | F41: 272 | G41: 272 | H41: 1000 | J41: 1272 | K41: =F41-J41 -> -1000
B42: Trichy rental charges
B43: Telcom/Data & others | C43: 1475 | D43: 506 | F43: 1981 | G43: 1603 | H43: 1255 | J43: 2858 | K43: =F43-J43 -> -877
B44: Telephone Expense | D44: 285 | F44: 285 | H44: 295 | J44: 295 | K44: =F44-J44 -> -10
B45: Dues and Subscriptions | D45: 220 | F45: 220 | H45: 459 | J45: 459 | K45: =F45-J45 -> -239
B46: IT and Internet Expenses | C46: 479 | D46: 0 | F46: 479 | G46: 485 | H46: 501 | J46: 985 | K46: =F46-J46 -> -506
B47: Telecom Charges | C47: 29 | F47: 29 | G47: 41 | J47: 41 | K47: =F47-J47 -> -12
B48: Telephone Rental Charges | C48: 213 | F48: 213 | G48: 189 | J48: 189 | K48: =F48-J48 -> 24
B49: License/Subscription Charges | C49: 754 | F49: 754 | G49: 889 | J49: 889 | K49: =F49-J49 -> -135
B50: Transport | C50: 4084 | F50: 4084 | G50: 4376 | J50: 4376 | K50: =F50-J50 -> -292
B51: Staff Transportation Charges | C51: 4084 | F51: 4084 | G51: 4376 | J51: 4376 | K51: =F51-J51 -> -292
B52: Other COGS | C52: 4841 | D52: 16686 | F52: 21527 | G52: 7740 | H52: 29152 | J52: 36892 | K52: =F52-J52 -> -15365
B53: General Insurance
B54: Insurance
B55: Donation
B56: Software development and Hosting charges | C56: 163 | F56: 163 | G56: 515 | J56: 515 | K56: =F56-J56 -> -352
B57: Other Cogs- MD
B58: Employee Engagement
B59: Staff Welfare Expenses | C59: 1727 | F59: 1727 | G59: 4155 | J59: 4155 | K59: =F59-J59 -> -2428
B60: Fuel expenses
B61: Obo Health Inc
B62: Food Coupon-Happay Wallet | C62: 2951 | F62: 2951 | G62: 3070 | J62: 3070 | K62: =F62-J62 -> -119
B63: Software Expenses | D63: 16686 | F63: 16686 | H63: 29152 | J63: 29152 | K63: =F63-J63 -> -12466
B64: Total COGS | C64: 137458 | D64: 193093 | E64: -175901 | F64: 154650 | G64: 143772 | H64: 106800 | I64: -75319 | J64: 175254 | K64: =F64-J64 -> -20604
B65: GM | C65: 38748 | D65: 1809 | E65: 0 | F65: 40557 | G65: -68453 | H65: 131039 | I65: 0 | J65: 62585 | K65: =F65-J65 -> -22028
B66: GM% | C66: 22 % | D66: 1 % | E66: 0 | F66: 21 % | G66: (91 %) | H66: 55 % | I66: 0 | J66: 26 % | K66: =F66-J66 -> -0.05
B67: SG&A
B68: Selling Expenses | C68: 1354 | D68: 755 | F68: 2109 | G68: 1427 | H68: 1361 | J68: 2788 | K68: =F68-J68 -> -679
B69: Travel Expense
B70: Cyber Security Insurance
B71: Rewards and recognition
B72: Meals and Entertainment | C72: 107 | D72: 627 | F72: 734 | G72: 160 | H72: 150 | J72: 310 | K72: =F72-J72 -> 424
B73: VISA charges
B74: Conference & Events
B75: Advertisement and marketing
B76: Sales and marketing | D76: 128 | F76: 128 | H76: 1211 | J76: 1211 | K76: =F76-J76 -> -1083
B77: Business Promotion
B78: S&M Salaries | C78: 1247 | F78: 1247 | G78: 1267 | J78: 1267 | K78: =F78-J78 -> -20
B79: Gratuity | C79: 0 | F79: 0 | G79: 0 | J79: 0 | K79: =F79-J79 -> 0
B80: New Tools and Accesses - Needed
B81: Customs Duty
B82: G&A Expenses
B83: Salaries-Management & Others | C83: 9641 | D83: 23165 | F83: 32806 | G83: 9729 | H83: 17422 | J83: 27151 | K83: =F83-J83 -> 5655
B84: Bonus and Incentives | C84: 0 | F84: 0 | G84: 0 | J84: 0 | K84: =F84-J84 -> 0
B85: Management Salaries | C85: 9641 | D85: 23165 | F85: 32806 | G85: 9729 | H85: 17422 | J85: 27151 | K85: =F85-J85 -> 5655
B86: Legal & Professional Fees | C86: 1359 | D86: 2326 | F86: 3685 | G86: 2011 | H86: 3976 | J86: 5987 | K86: =F86-J86 -> -2302
B87: Professional fees
B88: FPO Charges - SRF | C88: 1359 | F88: 1359 | G88: 2011 | J88: 2011 | K88: =F88-J88 -> -652
B89: Legal & Professional Services | D89: 2326 | F89: 2326 | H89: 3976 | J89: 3976 | K89: =F89-J89 -> -1650
B90: FPO Charges-SMCS GLOBAL
B91: G&A salaries | C91: 2242 | D91: 3675 | F91: 5917 | G91: 2500 | H91: 3764 | J91: 6265 | K91: =F91-J91 -> -348
B92: Payroll taxes | D92: 3675 | F92: 3675 | H92: 3764 | J92: 3764 | K92: =F92-J92 -> -89
B93: HR Salaries | C93: 632 | F93: 632 | G93: 840 | J93: 840 | K93: =F93-J93 -> -208
B94: Admin Salaries | C94: 774 | F94: 774 | G94: 779 | J94: 779 | K94: =F94-J94 -> -5
B95: IT Salaries | C95: 836 | F95: 836 | G95: 881 | J95: 881 | K95: =F95-J95 -> -45
B96: Coder
B97: Gen & Admin Expenses | C97: 2741 | D97: 6434 | F97: 9176 | G97: 4915 | H97: 19734 | J97: 24649 | K97: =F97-J97 -> -15473
B98: Consultancy Fees
B99: Comission Paid-Scinet Inc
B100: Leadership engagemnet
B101: Charitable Donations
B102: Fuel/Mileage Expenses | D102: 89 | F102: 89 | H102: 148 | J102: 148 | K102: =F102-J102 -> -59
B103: Payroll Processing Fees | D103: 523 | F103: 523 | H103: 608 | J103: 608 | K103: =F103-J103 -> -85
...

Sheet Consolidted PnL-May
B2: iMagnum US | C2: Period: May 2026 | G2: Period: April 2026
B3: FTM_CurrentYear_CV_SPL | E3: ( USD in Whole Number ) | I3: ( USD in Whole Number )
B6: particulars | C6: iMagnum India | D6: iMagnum US | E6: Elimination-iMagnum Segment | F6: Total | G6: iMagnum India | H6: iMagnum US | I6: Elimination-iMagnum Segment | J6: Total | K6: Variance
B7: Service Income
B8: Sales | C8: 158437 | D8: 209920 | E8: -158439 | F8: 209918 | G8: 176206 | H8: 194902 | I8: -175901 | J8: 195207 | K8: =F8-J8 -> 14711
B9: Sales | C9: 158439 | D9: 209920 | E9: -158439 | F9: 209920 | G9: 175901 | H9: 194902 | I9: -175901 | J9: 194902 | K9: =F9-J9 -> 15018
B10: Other Charges | C10: 0 | D10: 0 | F10: 0 | G10: 0 | H10: 0 | J10: 0 | K10: =F10-J10 -> 0
B11: Buyout
B12: General Income | C12: 0 | D12: 0 | F12: 0 | G12: 16 | H12: 0 | J12: 16 | K12: =F12-J12 -> -16
B13: Interest Income | C13: -2 | F13: -2 | G13: 289 | J13: 289 | K13: =F13-J13 -> -291
B14: Total Revenue | C14: 158437 | D14: 209920 | E14: -158439 | F14: 209918 | G14: 176206 | H14: 194902 | I14: -175901 | J14: 195207 | K14: =F14-J14 -> 14711
B15: Overall Operational cost
B16: Manpower | C16: 92642 | D16: 158280 | E16: -158439 | F16: 92483 | G16: 101010 | H16: 175901 | I16: -175901 | J16: 101010 | K16: =F16-J16 -> -8527
B17: India Cost
B18: Consultancy fee | D18: 0 | F18: 0 | H18: 0 | J18: 0 | K18: =F18-J18 -> 0
B19: Operation salaries | C19: 57391 | F19: 57391 | G19: 62706 | J19: 62706 | K19: =F19-J19 -> -5315
B20: Ops Support Salaries | C20: 35040 | F20: 35040 | G20: 38087 | J20: 38087 | K20: =F20-J20 -> -3047
B21: Contract employee salaries | C21: 212 | D21: 158280 | E21: -158439 | F21: 53 | G21: 217 | H21: 175901 | I21: -175901 | J21: 217 | K21: =F21-J21 -> -164
B22: Coding charges | C22: -1 | F22: -1 | G22: 0 | J22: 0 | K22: =F22-J22 -> -1
B23: Employee statutory expenses | C23: 10965 | F23: 10965 | G23: 11375 | J23: 11375 | K23: =F23-J23 -> -410
B24: Employee ESI
B25: EPF Admin Charges | C25: 381 | F25: 381 | G25: 415 | J25: 415 | K25: =F25-J25 -> -34
B26: Employee PF | C26: 9488 | F26: 9488 | G26: 9958 | J26: 9958 | K26: =F26-J26 -> -470
B27: Employer ESI | C27: 365 | F27: 365 | G27: 391 | J27: 391 | K27: =F27-J27 -> -26
B28: Employer PF
B29: Professional tax | C29: 597 | F29: 597 | G29: 610 | J29: 610 | K29: =F29-J29 -> -13
B30: Interest on TDS | C30: 8 | F30: 8
B31: Interest on employee statutory dues
B32: Interest on Advance Tax | C32: 127 | F32: 127
B33: Facility Cost | C33: 14229 | D33: 3000 | F33: 17229 | G33: 14894 | H33: 0 | J33: 14894 | K33: =F33-J33 -> 2335
B34: Electricity
B35: Electricity Expense | C35: 2663 | F35: 2663 | G35: 2980 | J35: 2980 | K35: =F35-J35 -> -317
B36: Computer maintenance
B37: Janani Property Maintenance Charges | C37: 719 | F37: 719 | G37: 743 | J37: 743 | K37: =F37-J37 -> -24
B38: Janani Property Rental Charges | C38: 4162 | F38: 4162 | G38: 4302 | J38: 4302 | K38: =F38-J38 -> -140
B39: Laptop Rental Charges | C39: 1924 | F39: 1924 | G39: 1964 | J39: 1964 | K39: =F39-J39 -> -40
B40: Thiruttani rental charges | C40: 290 | F40: 290 | G40: 285 | J40: 285 | K40: =F40-J40 -> 5
B41: Max Office rental charges | C41: 4207 | F41: 4207 | G41: 4348 | J41: 4348 | K41: =F41-J41 -> -141
B42: Rent Expense | C42: 263 | D42: 3000 | F42: 3263 | G42: 272 | H42: 0 | J42: 272 | K42: =F42-J42 -> 2991
B43: Trichy rental charges
B44: Telcom/Data & others | C44: 1464 | D44: 505 | F44: 1969 | G44: 1496 | H44: 638 | J44: 2134 | K44: =F44-J44 -> -165
B45: Telephone Expense | D45: 285 | F45: 285 | H45: 285 | J45: 285 | K45: =F45-J45 -> 0
B46: Dues and Subscriptions | D46: 220 | F46: 220 | H46: 352 | J46: 352 | K46: =F46-J46 -> -132
B47: IT and Internet Expenses | C47: 688 | D47: 0 | F47: 688 | G47: 479 | H47: 0 | J47: 479 | K47: =F47-J47 -> 209
B48: Telecom Charges | C48: 27 | F48: 27 | G48: 29 | J48: 29 | K48: =F48-J48 -> -2
B49: Telephone Rental Charges | C49: 210 | F49: 210 | G49: 213 | J49: 213 | K49: =F49-J49 -> -3
B50: License/Subscription Charges | C50: 539 | F50: 539 | G50: 775 | J50: 775 | K50: =F50-J50 -> -236
B51: Transport | C51: 4254 | F51: 4254 | G51: 4084 | J51: 4084 | K51: =F51-J51 -> 170
B52: Staff Transportation Charges | C52: 4254 | F52: 4254 | G52: 4084 | J52: 4084 | K52: =F52-J52 -> 170
B53: Other COGS | C53: 5117 | D53: 12533 | F53: 17650 | G53: 5091 | H53: 16922 | J53: 22012 | K53: =F53-J53 -> -4362
B54: General Insurance
B55: Insurance
B56: Donation
B57: Software development and Hosting charges | C57: 427 | F57: 427 | G57: 163 | J57: 163 | K57: =F57-J57 -> 264
B58: Other Cogs- MD
B59: Employee Engagement
B60: Staff Welfare Expenses | C60: 1873 | F60: 1873 | G60: 1977 | J60: 1977 | K60: =F60-J60 -> -104
B61: Fuel expenses
B62: Obo Health Inc
B63: Food Coupon-Happay Wallet | C63: 2818 | F63: 2818 | G63: 2951 | J63: 2951 | K63: =F63-J63 -> -133
B64: Software Expenses | D64: 12533 | F64: 12533 | H64: 16922 | J64: 16922 | K64: =F64-J64 -> -4389
B65: Total COGS | C65: 128671 | D65: 174318 | E65: -158439 | F65: =F53+F44+F33+F23+F16+F51 -> 144550 | G65: 137951 | H65: 193460 | I65: -175901 | J65: 155510 | K65: =F65-J65 -> -10960
B66: GM | C66: 29766 | D66: 35602 | F66: 65368 | G66: 38256 | H66: 1442 | I66: 0 | J66: 39697 | K66: =F66-J66 -> 25671
B67: GM% | C67: 19 % | D67: 17 % | E67: 0 | F67: 31 % | G67: 22 % | H67: 1 % | I67: 0 | J67: 20 % | K67: =F67-J67 -> 0.11
B68: SG&A
B69: Selling Expenses | C69: 1358 | D69: 49 | F69: 1407 | G69: 1354 | H69: 2076 | J69: 3430 | K69: =F69-J69 -> -2023
B70: Travel Expense
B71: Cyber Security Insurance
B72: Rewards and recognition
B73: Meals and Entertainment | C73: 269 | D73: 49 | F73: 318 | G73: 107 | H73: 888 | J73: 994 | K73: =F73-J73 -> -676
B74: VISA charges
B75: Conference & Events
B76: Advertisement and marketing
B77: Sales and marketing | D77: 0 | F77: 0 | H77: 1188 | J77: 1188 | K77: =F77-J77 -> -1188
B78: Business Promotion
B79: S&M Salaries | C79: 1093 | F79: 1093 | G79: 1247 | J79: 1247 | K79: =F79-J79 -> -154
B80: Gratuity | C80: -4 | F80: -4 | G80: 0 | J80: 0 | K80: =F80-J80 -> -4
B81: New Tools and Accesses - Needed
B82: Customs Duty
B83: G&A Expenses
B84: Salaries-Management & Others | C84: 9326 | D84: 16293 | F84: 25618 | G84: 9641 | H84: 23165 | J84: 32806 | K84: =F84-J84 -> -7188
B85: Bonus and Incentives | C85: -1 | F85: -1 | G85: 0 | J85: 0 | K85: =F85-J85 -> -1
B86: Management Salaries | C86: 9327 | D86: 16293 | F86: 25619 | G86: 9641 | H86: 23165 | J86: 32806 | K86: =F86-J86 -> -7187
B87: Legal & Professional Fees | C87: 1315 | D87: 1025 | F87: 2340 | G87: 1359 | H87: 2326 | J87: 3685 | K87: =F87-J87 -> -1345
B88: Professional fees
B89: FPO Charges - SRF | C89: 1315 | F89: 1315 | G89: 1359 | J89: 1359 | K89: =F89-J89 -> -44
B90: Legal & Professional Services | D90: 1025 | F90: 1025 | H90: 2326 | J90: 2326 | K90: =F90-J90 -> -1301
B91: FPO Charges-SMCS GLOBAL
B92: G&A salaries | C92: 2028 | D92: 5513 | F92: 7541 | G92: 2242 | H92: 3675 | J92: 5917 | K92: =F92-J92 -> 1624
B93: Payroll taxes | D93: 5513 | F93: 5513 | H93: 3675 | J93: 3675 | K93: =F93-J93 -> 1838
B94: HR Salaries | C94: 557 | F94: 557 | G94: 632 | J94: 632 | K94: =F94-J94 -> -75
B95: Admin Salaries | C95: 693 | F95: 693 | G95: 774 | J95: 774 | K95: =F95-J95 -> -81
B96: IT Salaries | C96: 777 | F96: 777 | G96: 836 | J96: 836 | K96: =F96-J96 -> -59
B97: Coder
B98: Gen & Admin Expenses | C98: 2255 | D98: 7785 | F98: 10040 | G98: 2776 | H98: 6780 | J98: 9556 | K98: =F98-J98 -> 484
B99: Consultancy Fees
B100: Comission Paid-Scinet Inc
B101: Leadership engagemnet
B102: Charitable Donations
B103: Fuel/Mileage Expenses | D103: 0 | F103: 0 | H103: 212 | J103: 212 | K103: =F103-J103 -> -212
...

Sheet Holding Detailed Exp summary
A2: IMAGNUM HEALTHCARE SOLUTION PRIVATE LIMITED
B3: Sum of Amount | C3: Column Labels
B4: Row Labels | C4: 45688 | D4: 45716 | E4: 45747 | F4: 45777 | G4: 45808 | H4: 45838 | I4: 45869 | J4: 45900 | K4: 45930 | L4: 45961 | M4: 45991 | N4: 46022 | O4: 46053 | P4: 46081 | Q4: 46112 | R4: 46142 | S4: 46173 | T4: May Vs Apr
B5: Operational Cost | C5: 140372.38 | D5: 156066.25 | E5: 163126.01 | F5: 182521.71 | G5: 172967.17 | H5: 217751.89 | I5: 187196.35 | J5: 211746.73 | K5: 209436.87 | L5: 208717.45 | M5: 216280.72 | N5: 209450.3 | O5: 211311.47 | P5: 203313.12 | Q5: 106950.86 | R5: 193588.31 | S5: 174317.96 | T5: =R5-S5 -> 19270.35
B6: India Cost | C6: 137139 | D6: 141484 | E6: 140018 | F6: 164649 | G6: 151760 | H6: 200674 | I6: 158956 | J6: 173054 | K6: 187101 | L6: 183412 | M6: 190966 | N6: 187035 | O6: 184697 | P6: 184916 | Q6: 75319 | R6: 175901 | S6: 158280 | T6: =R6-S6 -> 17621
B7: Contractors | C7: 137139 | D7: 141484 | E7: 140018 | F7: 164649 | G7: 151760 | H7: 200674 | I7: 158956 | J7: 173054 | K7: 187101 | L7: 183412 | M7: 190966 | N7: 187035 | O7: 184697 | P7: 184916 | Q7: 75319 | R7: 175901 | S7: 158280 | T7: =R7-S7 -> 17621
B8: iMagnum Healthcare Solutions Pvt Ltd | C8: 137139 | D8: 141484 | E8: 140018 | F8: 164649 | G8: 151760 | H8: 200674 | I8: 158956 | J8: 173054 | K8: 187101 | L8: 183412 | M8: 190966 | N8: 187035 | O8: 184697 | P8: 184916 | Q8: 75319 | R8: 175901 | S8: 158280 | T8: =R8-S8 -> 17621
B9: Facility Cost | F9: 1050 | H9: 2000 | K9: 2000 | M9: 2000 | O9: 2000 | Q9: 1000 | S9: 3000 | T9: =R9-S9 -> -3000
B10: Rent Expense | F10: 1050 | H10: 2000 | K10: 2000 | M10: 2000 | O10: 2000 | Q10: 1000 | S10: 3000 | T10: =R10-S10 -> -3000
B11: Lynx Realty | F11: 1050 | H11: 2000 | K11: 2000 | M11: 2000 | O11: 2000 | Q11: 1000 | S11: 3000 | T11: =R11-S11 -> -3000
B12: Telecom Data & Others | C12: 1990.87 | D12: 613.96 | E12: 673.09 | F12: 924.82 | G12: 1687.9 | H12: 1193.92 | I12: 2480.76 | J12: 1380.49 | K12: 1568.84 | L12: 1388.64 | M12: 1260.19 | N12: 967.9 | O12: 3270.23 | P12: 1439.74 | Q12: 1254.75 | R12: 637.73 | S12: 505.1 | T12: =R12-S12 -> 132.63
B13: Dues and Subscriptions | C13: 314.84 | D13: 321.81 | E13: 431.18 | F13: 309.74 | G13: 1155.59 | H13: 447.56 | I13: 375.97 | J13: 492.04 | K13: 610.89 | L13: 494.47 | M13: 426.89 | N13: 403.23 | O13: 435.09 | P13: 392.63 | Q13: 459.2 | R13: 352.46 | S13: 220.25 | T13: =R13-S13 -> 132.21
B14: A2Webhost | K14: 212.26 | T14: =R14-S14 -> 0
B15: Adobe Systems | C15: 13.8 | D15: 13.8 | E15: 13.8 | F15: 13.8 | G15: 13.8 | H15: 13.8 | I15: 13.8 | J15: 13.8 | K15: 13.8 | L15: 13.8 | M15: 13.8 | N15: 13.8 | O15: 45.66 | P15: 13.8 | Q15: 13.8 | R15: 13.8 | S15: 13.8 | T15: =R15-S15 -> 0
B16: Availity | G16: 26.65 | T16: =R16-S16 -> 0
B17: Calendly | C17: 25.3 | D17: 25.3 | E17: 25.3 | F17: 25.3 | G17: 25.3 | H17: 25.3 | I17: 25.3 | J17: 25.54 | K17: 25.54 | L17: 25.54 | M17: 25.54 | N17: 25.54 | O17: 25.54 | P17: 25.54 | Q17: 25.54 | R17: 25.54 | S17: 25.54 | T17: =R17-S17 -> 0
B18: Chatgpt | C18: 180.88 | D18: 180.88 | E18: 180.88 | F18: 180.88 | G18: 180.88 | H18: 180.88 | I18: 186.2 | J18: 159.6 | K18: 159.6 | L18: 203.77 | M18: 191.52 | N18: 191.52 | O18: 191.52 | P18: 159.6 | Q18: 159.6 | R18: 119.43 | T18: =R18-S18 -> 119.43
B19: DROPBOX | C19: 12.78 | E19: 25.56 | F19: 12.78 | G19: 12.78 | H19: 12.78 | I19: 12.78 | J19: 12.78 | K19: 12.78 | L19: 12.78 | M19: 12.78 | N19: 12.78 | O19: 12.78 | P19: 12.78 | Q19: 12.78 | R19: 12.78 | T19: =R19-S19 -> 12.78
B20: MICROSOFT | J20: 137.79 | T20: =R20-S20 -> 0
B21: MongoDB | G21: 814.4 | T21: =R21-S21 -> 0
B22: Zoho Corp | C22: 82.08 | D22: 82.08 | E22: 82.08 | P22: 21.32 | Q22: 21.32 | R22: 21.32 | S22: 21.32 | T22: =R22-S22 -> 0
B23: READ - MEETING | D23: 19.75 | E23: 21.01 | F23: 21.01 | G23: 21.01 | H23: 21.01 | I23: 21.01 | J23: 21.01 | K23: 21.01 | L23: 21.01 | M23: 21.01 | N23: 21.01 | O23: 21.01 | P23: 21.01 | Q23: 21.01 | R23: 21.01 | S23: 21.01 | T23: =R23-S23 -> 0
B24: Bluefin | E24: 56.57 | T24: =R24-S24 -> 0
B25: GoDaddy | E25: 25.98 | H25: 133.02 | K25: 44.38 | Q25: 66.57 | T25: =R25-S25 -> 0
B26: QuickBooks Payments | F26: 55.97 | G26: 60.77 | H26: 60.77 | I26: 116.88 | J26: 121.52 | K26: 121.52 | L26: 138.58 | M26: 138.58 | N26: 138.58 | O26: 138.58 | P26: 138.58 | Q26: 138.58 | R26: 138.58 | S26: 138.58 | T26: =R26-S26 -> 0
B27: McAfee | L27: 49.99 | T27: =R27-S27 -> 0
B28: Awaz | L28: 29 | T28: =R28-S28 -> 0
B29: Tailwind | M29: 23.66 | T29: =R29-S29 -> 0
B30: IT and Internet Expenses | C30: 31.92 | D30: 31.92 | F30: 227.68 | G30: 274.94 | H30: 509.84 | I30: 1726.01 | J30: 511.61 | K30: 586.55 | L30: 582.65 | M30: 540.68 | N30: 255.71 | O30: 499.3 | P30: 506.14 | Q30: 500.65 | T30: =R30-S30 -> 0
B31: Digital Ocean | F31: 227.68 | G31: 274.94 | H31: 275.53 | I31: 303.7 | J31: 277.3 | K31: 283.79 | L31: 284.38 | M31: 284.97 | O31: 286.15 | P31: 292.99 | Q31: 287.5 | T31: =R31-S31 -> 0
B32: Figma | C32: 31.92 | D32: 31.92 | H32: 85.12 | I32: 85.12 | J32: 85.12 | K32: 85.12 | L32: 85.12 | M32: 42.56 | N32: 42.56 | T32: =R32-S32 -> 0
B33: Scalela | I33: 1188 | T33: =R33-S33 -> 0
B34: Semrush | H34: 149.19 | I34: 149.19 | J34: 149.19 | K34: 217.64 | L34: 213.15 | M34: 213.15 | N34: 213.15 | O34: 213.15 | P34: 213.15 | Q34: 213.15 | T34: =R34-S34 -> 0
B35: Telephone Expense | C35: 1644.11 | D35: 260.23 | E35: 241.91 | F35: 387.4 | G35: 257.37 | H35: 236.52 | I35: 378.78 | J35: 376.84 | K35: 371.4 | L35: 311.52 | M35: 292.62 | N35: 308.96 | O35: 2335.84 | P35: 540.97 | Q35: 294.9 | R35: 285.27 | S35: 284.85 | T35: =R35-S35 -> 0.42
B36: RINGCENTRAL INC | C36: 1427.47 | N36: 32.25 | O36: 2036.8 | T36: =R36-S36 -> 0
B37: Verizon | C37: 216.64 | D37: 260.23 | E37: 241.91 | F37: 387.4 | G37: 257.37 | H37: 236.52 | I37: 378.78 | J37: 376.84 | K37: 371.4 | L37: 311.52 | M37: 292.62 | N37: 276.71 | O37: 299.04 | P37: 540.97 | Q37: 294.9 | R37: 285.27 | S37: 284.85 | T37: =R37-S37 -> 0.42
B38: Other COGS | C38: 1007.56 | D38: 13069.29 | E38: 14339.92 | F38: 15297.89 | G38: 17266.72 | H38: 13768.54 | I38: 18080.94 | J38: 37312.24 | K38: 15322.03 | L38: 20416.81 | M38: 20804.53 | N38: 17697.4 | O38: 14960.82 | P38: 16793.61 | Q38: 29302.11 | R38: 17049.58 | S38: 12532.86 | T38: =R38-S38 -> 4516.72
B39: Software Expenses | C39: 1007.56 | D39: 13069.29 | E39: 14339.92 | F39: 15297.89 | G39: 17266.72 | H39: 13768.54 | I39: 18080.94 | J39: 37312.24 | K39: 15322.03 | L39: 20416.81 | M39: 20804.53 | N39: 17697.4 | O39: 14960.82 | P39: 16793.61 | Q39: 29302.11 | R39: 17049.58 | S39: 12532.86 | T39: =R39-S39 -> 4516.72
B40: AdvancedMD | C40: 310.67 | D40: 7171.4 | E40: 6399.9 | F40: 9071.33 | G40: 9087.09 | H40: 9063.53 | I40: 9078.5 | J40: 21415.87 | K40: 9163.02 | L40: 17541.85 | M40: 13980.76 | N40: 13265.71 | O40: 9421.8 | P40: 13419.37 | Q40: 18963.63 | R40: 7046.68 | S40: 7046.68 | T40: =R40-S40 -> 0
B41: Availity | C41: 31.64 | D41: 26.65 | E41: 26.65 | F41: 26.65 | H41: 26.65 | I41: 26.65 | J41: 26.65 | K41: 28.09 | L41: 41.05 | M41: 70.69 | N41: 2734.34 | O41: 2215.06 | P41: 62.63 | Q41: 2196.77 | R41: 1398.06 | S41: 1066 | T41: =R41-S41 -> 332.06
B42: Claim.MD | C42: 105.8 | D42: 106.6 | E42: 106.6 | F42: 106.6 | G42: 111.33 | H42: 106.6 | I42: 107.67 | J42: 106.6 | K42: 106.6 | L42: 127.92 | M42: 128.56 | N42: 127.92 | O42: 127.92 | P42: 127.92 | Q42: 127.92 | R42: 127.92 | T42: =R42-S42 -> 127.92
B43: Cloudways LTD | C43: 103.84 | D43: 115.73 | E43: 151.38 | N43: 286.15 | R43: 333.94 | S43: 334.53 | T43: =R43-S43 -> -0.59
B44: Contabo.com | C44: 16.89 | D44: 16.89 | E44: 19.9 | F44: 19.9 | G44: 19.9 | H44: 19.9 | J44: 19.9 | K44: 19.9 | L44: 19.9 | M44: 19.9 | N44: 19.9 | Q44: 22.45 | R44: 22.45 | T44: =R44-S44 -> 22.45
B45: Foxyproxy | L45: 161.78 | O45: 89.88 | T45: =R45-S45 -> 0
B46: Moet Advisors LLC | J46: 3856.63 | T46: =R46-S46 -> 0
B47: MongoDB | C47: 438.72 | D47: 487.3 | E47: 491.73 | F47: 650.59 | H47: 895.13 | I47: 899.65 | J47: 938.52 | K47: 905.42 | L47: 882.67 | M47: 930.85 | N47: 913.62 | O47: 937.77 | P47: 1015.3 | Q47: 656.99 | R47: 549.36 | S47: 570.63 | T47: =R47-S47 -> -21.27
B48: Obo Health Inc | D48: 5000 | E48: 7000 | F48: 5000 | G48: 8000 | H48: 3500 | I48: 5000 | J48: 8000 | K48: 3500 | M48: 3500 | T48: =R48-S48 -> 0
B49: Office Ally | D49: 144.72 | E49: 143.76 | F49: 48.9 | G49: 48.4 | H49: 48.4 | I49: 48.4 | S49: 134.85 | T49: =R49-S49 -> -134.85
B50: Trizetto Prov | F50: 373.92 | H50: 108.33 | I50: 2920.07 | J50: 2920.07 | T50: =R50-S50 -> 0
B51: Semrush | R51: 213.15 | T51: =R51-S51 -> 213.15
B52: RFPMart LLC | J52: 28 | T52: =R52-S52 -> 0
B53: SaaSMonk | K53: 1599 | L53: 1599 | T53: =R53-S53 -> 0
B54: Replit | L54: 42.64 | M54: 5.38 | T54: =R54-S54 -> 0
B55: Atlantic.net | M55: 2168.39 | N55: 349.76 | O55: 2168.39 | P55: 2168.39 | Q55: 2296.85 | R55: 2358.02 | S55: 2358.02 | T55: =R55-S55 -> 0
B56: Cair Health Inc. | Q56: 5000 | R56: 5000 | T56: =R56-S56 -> 5000 | U56: ask
B57: Stedi, Inc. | Q57: 37.5 | T57: =R57-S57 -> 0
B58: Stedi | S58: 674.15 | T58: =R58-S58 -> -674.15
B59: S10.AI INC | S59: 348 | T59: =R59-S59 -> -348
B60: Manpower | C60: 234.95 | D60: 899 | E60: 8095 | F60: 600 | G60: 2252.55 | H60: 115.43 | I60: 7678.65 | K60: 3445 | L60: 3500 | M60: 1250 | N60: 3750 | O60: 6383.42 | P60: 163.77 | Q60: 75 | T60: =R60-S60 -> 0
B61: Consultancy Fees | C61: 234.95 | D61: 899 | E61: 8095 | F61: 600 | G61: 2252.55 | H61: 115.43 | I61: 7678.65 | K61: 3445 | L61: 3500 | M61: 1250 | N61: 3750 | O61: 6383.42 | P61: 163.77 | Q61: 75 | T61: =R61-S61 -> 0
B62: Chugh LLP | E62: 8095 | F62: 600 | H62: 115.43 | T62: =R62-S62 -> 0
B63: HEALTHCARE BUSINESS | D63: 899 | I63: 2750 | T63: =R63-S63 -> 0
B64: Vfs Services | C64: 234.95 | T64: =R64-S64 -> 0
B65: iQuantified Management Services | G65: 2252.55 | I65: 661.65 | O65: 1688.42 | T65: =R65-S65 -> 0
B66: Lynx Realty | I66: 2000 | T66: =R66-S66 -> 0
B67: Gerald Mannikarote | I67: 2267 | T67: =R67-S67 -> 0
B68: Inc. Media | K68: 895 | O68: 2195 | T68: =R68-S68 -> 0
B69: Georgia Association | K69: 2550 | T69: =R69-S69 -> 0
B70: Maheshkumar Nagarajan | L70: 500 | T70: =R70-S70 -> 0
B71: HJC Consulting Group | L71: 3000 | T71: =R71-S71 -> 0
B72: MEDSOURCE AI LLC | M72: 1250 | N72: 3750 | O72: 2500 | T72: =R72-S72 -> 0
B73: MedTrade | P73: 163.77 | T73: =R73-S73 -> 0
B74: Harvard Business Services | Q74: 75 | T74: =R74-S74 -> 0
B75: SG&A | C75: 32725.65 | D75: 51292.53 | E75: 58047.99 | F75: 37674.75 | G75: 51041.81 | H75: 72849.56 | I75: 61825.75 | J75: 70957.79 | K75: 85172.25 | L75: 91962.23 | M75: 86109.18 | N75: 90520.92 | O75: 68881.78 | P75: 54279.27 | Q75: 46623.35 | R75: 38604.19 | S75: 30664.48 | T75: =R75-S75 -> 7939.71
B76: Management Salaries | C76: 29384.96 | D76: 37861.26 | E76: 30292.26 | F76: 30243.66 | G76: 30243.66 | H76: 54717.49 | I76: 44891.08 | J76: 49084.66 | K76: 48930.97 | L76: 68580.96 | M76: 51084.81 | N76: 59175.58 | O76: 48991.58 | P76: 35488.45 | Q76: 21186.16 | R76: 26840.43 | S76: 21805.57 | T76: =R76-S76 -> 5034.86
B77: Payroll Taxes | C77: 8472.87 | D77: 7948.53 | E77: 7879.53 | F77: 7830.93 | G77: 7830.93 | H77: 11746.4 | I77: 10227.62 | J77: 11271.33 | K77: 11100.49 | L77: 11395.19 | M77: 11129.15 | N77: 17255.34 | O77: 11722.56 | P77: 7356.56 | Q77: 3764.4 | R77: 3675.33 | S77: 5513 | T77: =R77-S77 -> -1837.67
B78: ADP | C78: 8472.87 | D78: 7948.53 | E78: 7879.53 | F78: 7830.93 | G78: 7830.93 | H78: 11746.4 | I78: 10227.62 | J78: 11271.33 | K78: 11100.49 | L78: 11395.19 | M78: 11129.15 | N78: 17255.34 | O78: 11722.56 | P78: 7356.56 | Q78: 3764.4 | R78: 3675.33 | S78: 5513 | T78: =R78-S78 -> -1837.67
B79: Management salaries | C79: 20912.09 | D79: 29912.73 | E79: 22412.73 | F79: 22412.73 | G79: 22412.73 | H79: 42971.09 | I79: 34663.46 | J79: 37813.33 | K79: 37830.48 | L79: 57185.77 | M79: 39955.66 | N79: 41920.24 | O79: 37269.02 | P79: 28131.89 | Q79: 17421.76 | R79: 23165.1 | S79: 16292.57 | T79: =R79-S79 -> 6872.53
B80: ADP | C80: 20912.09 | D80: 29912.73 | E80: 22412.73 | F80: 22412.73 | G80: 22412.73 | H80: 42971.09 | I80: 34663.46 | J80: 37813.33 | K80: 37830.48 | L80: 57185.77 | M80: 39955.66 | N80: 41920.24 | O80: 37269.02 | P80: 28131.89 | Q80: 17421.76 | R80: 23165.1 | S80: 16292.57 | T80: =R80-S80 -> 6872.53
B81: G&A Cost | C81: 3081.17 | D81: 2739.06 | E81: 13631.97 | F81: 2879.35 | G81: 17739.28 | H81: 15256.63 | I81: 12498.98 | J81: 18151.03 | K81: 30611.88 | L81: 18714 | M81: 18187.01 | N81: 29676.12 | O81: 17157.32 | P81: 15266.51 | Q81: 17606.54 | R81: 10223.35 | S81: 8937.91 | T81: =R81-S81 -> 1285.44
B82: Fuel/Mileage Expenses | C82: 36.61 | D82: 66.57 | E82: 274.09 | F82: 163.81 | G82: 21.71 | I82: 53.98 | J82: 179.88 | K82: 226.48 | L82: 149.44 | M82: 199.15 | N82: 35.41 | O82: 132.06 | P82: 125.17 | Q82: 147.71 | R82: 212.1 | T82: =R82-S82 -> 212.1
B83: Buc-EES | F83: 115.27 | T83: =R83-S83 -> 0
B84: Chevron | E84: 18.36 | J84: 40 | O84: 37.46 | T84: =R84-S84 -> 0
B85: H-E-B | D85: 28.87 | E85: 64.77 | J85: 90.18 | L85: 149.44 | N85: 35.41 | O85: 94.6 | Q85: 147.71 | R85: 185.83 | T85: =R85-S85 -> 185.83
B86: Shell | C86: 36.61 | D86: 37.7 | E86: 111.05 | F86: 48.54 | G86: 21.71 | I86: 53.98 | K86: 183.21 | M86: 199.15 | P86: 49.41 | R86: 26.27 | T86: =R86-S86 -> 26.27
B87: Walmart | E87: 10.12 | T87: =R87-S87 -> 0
B88: Costco | E88: 40.82 | P88: 75.76 | T88: =R88-S88 -> 0
B89: BP | E89: 28.97 | T89: =R89-S89 -> 0
B90: Katy Fwy | K90: 43.27 | T90: =R90-S90 -> 0
B91: X Christiana Rd | J91: 49.7 | T91: =R91-S91 -> 0
B92: Insurance Expense | C92: 1811.88 | D92: 1322.48 | E92: 8253.68 | F92: 1322.48 | G92: 6785.72 | H92: 3980.16 | I92: 3768.26 | J92: 5843.53 | K92: 6509.57 | L92: 6814.58 | M92: 6487.08 | N92: 6487.08 | O92: 6727.8 | P92: 3582.42 | Q92: 9653.09 | R92: 3024.96 | S92: 5449.75 | T92: =R92-S92 -> -2424.79
B93: United Health Care | C93: 454.4 | T93: =R93-S93 -> 0
B94: Manhattanlife | C94: 804.01 | D94: 804.01 | E94: 804.01 | F94: 804.01 | G94: 804.01 | H94: 804.01 | I94: 804.01 | T94: =R94-S94 -> 0
B95: NGIC | C95: 553.47 | D95: 518.47 | E95: 518.47 | F95: 518.47 | G95: 518.47 | H95: 518.47 | I95: 518.47 | J95: -234.15 | T95: =R95-S95 -> 0
B96: First Insurance | E96: 6931.2 | G96: 5463.24 | H96: 2657.68 | I96: 2445.78 | J96: 2445.78 | K96: 3102.67 | L96: 2657.68 | M96: 2657.68 | N96: 2657.68 | O96: 2657.68 | Q96: 6628.13 | S96: 2089.79 | T96: =R96-S96 -> -2089.79
B97: ICHRA | J97: 600 | T97: =R97-S97 -> 0
B98: Base | K98: 375 | L98: 1125 | M98: 797.5 | N98: 797.5 | O98: 797.5 | P98: 717.5 | Q98: 717.5 | R98: 717.5 | S98: 1052.5 | T98: =R98-S98 -> -335
B99: iMagnum Healthcare Solutions Pvt Ltd | J99: 3031.9 | K99: 3031.9 | L99: 3031.9 | M99: 3031.9 | N99: 3031.9 | O99: 3272.62 | P99: 2864.92 | Q99: 2307.46 | R99: 2307.46 | S99: 2307.46 | T99: =R99-S99 -> 0
B100: Meals and Entertainment | C100: 145.84 | D100: 1109.45 | E100: 3461.15 | F100: 362.92 | G100: 520.75 | I100: 114.49 | J100: 1373.65 | K100: 548.37 | L100: 311.05 | M100: 687.38 | N100: 354.63 | O100: 579.89 | P100: 716.83 | Q100: 150.08 | R100: 887.74 | S100: 49 | T100: =R100-S100 -> 838.74
B101: Courtyard By MarriotLewisville | O101: 143.37 | T101: =R101-S101 -> 0
...

Sheet Subs Detailed Exp Summary
A1: IMAGNUM HEALTHCARE SOLUTION PRIVATE LIMITED
B4: Sum of Amount | E4: Month
B5: Cost Category | C5: Ledger Name | D5: Supplier Name | E5: 45688 | F5: 45716 | G5: 45747 | H5: 45777 | I5: 45808 | J5: 45838 | K5: 45869 | L5: 45900 | M5: 45930 | N5: 45961 | O5: 45991 | P5: 46022 | Q5: 46053 | R5: 46081 | S5: 46112 | T5: 46142 | U5: 46173 | V5: May Vs Apr | W5: in $ | Y5: 95
B6: 1.Manpower | C6: Operation Salaries | D6: Operation Salaries | E6: 3762414 | F6: 4457855 | G6: 4579463 | H6: 4473906 | I6: 4728640 | J6: 5065520 | K6: 5158862 | L6: 5788065 | M6: 5991910 | N6: 6270781 | O6: 6229342 | P6: 6323574 | Q6: 6062679 | R6: 6115267 | S6: 6041252 | T6: 5768982 | U6: 5470829 | V6: =T6-U6 -> 298153 | W6: =V6/95 -> 3138.4526 | Y6: =U6/$Y$5 -> 57587.674
C7: Ops Support Salaries | D7: Ops Support Salaries | E7: 1911823 | F7: 2198354 | G7: 2043456 | H7: 2108487 | I7: 2151697 | J7: 2220435 | K7: 2498763 | L7: 2762127 | M7: 2796629 | N7: 3187170 | O7: 3255082 | P7: 3428387 | Q7: 3422489 | R7: 3333406 | S7: 3516012 | T7: 3503973 | U7: 3335558 | V7: =T7-U7 -> 168415 | W7: =V7/95 -> 1772.7895 | Y7: =U7/$Y$5 -> 35111.137
C8: Bonus and Incentives | D8: HDFC Bank | E8: 758750 | Q8: 15000 | V8: =T8-U8 -> 0 | W8: =V8/95 -> 0 | Y8: =U8/$Y$5 -> 0
C9: Contract Employee Salaries | D9: Contract Employee Salaries | E9: 47000 | F9: 47000 | G9: 47000 | H9: 47000 | I9: 28667 | J9: 12000 | K9: 12000 | L9: 12000 | M9: 12000 | N9: 12000 | O9: 12000 | P9: 12000 | R9: 20000 | S9: 20000 | U9: 20000 | V9: =T9-U9 -> -20000 | W9: =V9/95 -> -210.52632 | Y9: =U9/$Y$5 -> 210.52632
B10: 1.Manpower Total | E10: 6479987 | F10: 6703209 | G10: 6669919 | H10: 6629393 | I10: 6909004 | J10: 7297955 | K10: 7669625 | L10: 8562192 | M10: 8800539 | N10: 9469951 | O10: 9496424 | P10: 9763961 | Q10: 9500168 | R10: 9468673 | S10: 9577264 | T10: 9272955 | U10: 8826387 | V10: =T10-U10 -> 446568 | W10: =V10/95 -> 4700.7158 | Y10: =U10/$Y$5 -> 92909.337
B11: 2.Facility cost | C11: Janani Property Rental Charges | D11: JANANI PROPERTY & ESTATES PVT LTD | E11: 376923 | F11: 376923 | G11: 376923 | H11: 376923 | I11: 376923 | J11: 376923 | K11: 376923 | L11: 376923 | M11: 376923 | N11: 395769 | O11: 395769 | P11: 395769 | Q11: 395769 | R11: 395769 | S11: 395769 | T11: 395769 | U11: 395769 | V11: =T11-U11 -> 0 | W11: =V11/95 -> 0 | Y11: =U11/$Y$5 -> 4165.9895
C12: Max Office rental charges | D12: Max Office | K12: 400000 | L12: 400000 | M12: 400000 | N12: 400000 | O12: 400000 | P12: 400000 | Q12: 400000 | R12: 400000 | S12: 400000 | T12: 400000 | U12: 400000 | V12: =T12-U12 -> 0 | W12: =V12/95 -> 0 | Y12: =U12/$Y$5 -> 4210.5263
C13: Electricity Expense | D13: HDFC Bank | R13: 373 | V13: =T13-U13 -> 0 | W13: =V13/95 -> 0 | Y13: =U13/$Y$5 -> 0
D14: TAMILNADU GENERATION AND DISTRIBUTION CORPORATION LIMITED | E14: 180904.38 | F14: 217106.48 | G14: 182837.26 | H14: 237374.54 | I14: 205380.36 | J14: 275963.02 | K14: 222710.11 | L14: 282109.83 | M14: 219561 | N14: 278072 | O14: 200679 | P14: 246415 | Q14: 180086 | R14: 212225 | S14: 213905.73 | T14: 224144 | U14: 205772 | V14: =T14-U14 -> 18372 | W14: =V14/95 -> 193.38947 | Y14: =U14/$Y$5 -> 2166.0211
D15: Max Office | L15: 15396 | M15: 33468 | O15: 47724 | P15: 19848 | R15: 69324 | S15: 32304 | T15: 50052 | U15: 42360 | V15: =T15-U15 -> 7692 | W15: =V15/95 -> 80.968421 | Y15: =U15/$Y$5 -> 445.89474
D16: Amutha Trichy Rental House | Q16: 974 | U16: 4907 | V16: =T16-U16 -> -4907 | W16: =V16/95 -> -51.652632 | Y16: =U16/$Y$5 -> 51.652632
C17: Laptop Rental Charges | D17: M.R. INFOTECH | E17: 119245 | F17: 119485 | G17: 119470 | H17: 120435 | I17: 136370 | J17: 140575 | K17: 151460 | L17: 150740 | M17: 152855.09 | N17: 159250.09 | O17: 168956.09 | P17: 181117.09 | Q17: 189327.1 | R17: 190241.09 | S17: 175436.09 | T17: 180696.09 | U17: 182988.09 | V17: =T17-U17 -> -2292 | W17: =V17/95 -> -24.126316 | Y17: =U17/$Y$5 -> 1926.1904
C18: Janani Property Maintenance Charges | D18: JANANI PROPERTY & ESTATES PVT LTD | E18: 65105 | F18: 65105 | G18: 65105 | H18: 65105 | I18: 65105 | J18: 65105 | K18: 65105 | L18: 65105 | M18: 65105 | N18: 68360 | O18: 68360 | P18: 68360 | Q18: 68360 | R18: 68360 | S18: 68360 | T18: 68360 | U18: 68360 | V18: =T18-U18 -> 0 | W18: =V18/95 -> 0 | Y18: =U18/$Y$5 -> 719.57895
C19: Thiruttani rental charges | D19: Balaji Towers | E19: 25000 | F19: 25000 | G19: 25000 | H19: 25000 | I19: 26250 | J19: 26250 | K19: 26250 | L19: 26250 | M19: 26250 | N19: 26250 | O19: 26250 | P19: 26250 | Q19: 26250 | R19: 26250 | S19: 26250 | T19: 26250 | U19: 27562 | V19: =T19-U19 -> -1312 | W19: =V19/95 -> -13.810526 | Y19: =U19/$Y$5 -> 290.12632
C20: Trichy rental charges | D20: Amutha Trichy Rental House | O20: 25000 | P20: 25000 | Q20: 25000 | R20: 25000 | S20: 25000 | T20: 25000 | U20: 25000 | V20: =T20-U20 -> 0 | W20: =V20/95 -> 0 | Y20: =U20/$Y$5 -> 263.15789
C21: Computer maintenance | D21: Xtreme Infotech | J21: 7000 | V21: =T21-U21 -> 0 | W21: =V21/95 -> 0 | Y21: =U21/$Y$5 -> 0
B22: 2.Facility cost Total | E22: 767177.38 | F22: 803619.48 | G22: 769335.26 | H22: 824837.54 | I22: 810028.36 | J22: 891816.02 | K22: 1242448.1 | L22: 1316523.8 | M22: 1274162.1 | N22: 1327701.1 | O22: 1332738.1 | P22: 1362759.1 | Q22: 1285766.1 | R22: 1387542.1 | S22: 1337024.8 | T22: 1370271.1 | U22: 1352718.1 | V22: =T22-U22 -> 17553 | W22: =V22/95 -> 184.76842 | Y22: =U22/$Y$5 -> 14239.138
B23: 3.Telecom Data & others | C23: License/Subscription/Certification Charges | D23: Adobe Systems Software Ireland Ltd | E23: 5160.06 | F23: 5160.06 | G23: 6659.06 | H23: 6659.06 | I23: 6659.06 | J23: 6659.06 | K23: 6659.06 | L23: 10243.06 | M23: 10041.06 | N23: 10041.06 | O23: 10041.06 | P23: 10041.06 | Q23: 10041.06 | R23: 10041.06 | S23: 11256.06 | T23: 11256.06 | U23: 2367 | V23: =T23-U23 -> 8889.06 | W23: =V23/95 -> 93.569053 | Y23: =U23/$Y$5 -> 24.915789
D24: E2E Networks Limited | E24: 45000 | F24: 50000 | G24: 50000 | H24: 50000 | I24: 49999 | J24: 50000 | K24: 50000 | L24: 50000 | M24: 56153 | O24: 50000 | P24: 50000 | Q24: 32000 | R24: 7950 | V24: =T24-U24 -> 0 | W24: =V24/95 -> 0 | Y24: =U24/$Y$5 -> 0
D25: Esoftsol Infocom Pvt Ltd | E25: 147510 | F25: 18378 | V25: =T25-U25 -> 0 | W25: =V25/95 -> 0 | Y25: =U25/$Y$5 -> 0
D26: HDFC credit card (Kasi) | O26: 5990 | V26: =T26-U26 -> 0 | W26: =V26/95 -> 0 | Y26: =U26/$Y$5 -> 0
D27: LinkedIn | E27: 6299.14 | F27: 6299.14 | G27: 9446.74 | H27: 6299.14 | I27: 6299.14 | J27: 6299.14 | K27: 6299.14 | L27: 6299.14 | M27: 6299.14 | N27: 6299.14 | O27: 6299.14 | P27: 6299.14 | Q27: 6299.14 | S27: 21899.87 | T27: 9536.2 | V27: =T27-U27 -> 9536.2 | W27: =V27/95 -> 100.38105 | Y27: =U27/$Y$5 -> 0
D28: Udemy India LLP | F28: 1068 | V28: =T28-U28 -> 0 | W28: =V28/95 -> 0 | Y28: =U28/$Y$5 -> 0
D29: License/Subscription/Certification Charges | E29: 18468 | F29: 18468 | G29: 18468 | H29: 18468 | I29: 18468 | J29: 21097 | K29: 24486 | L29: 28554 | M29: 37971 | N29: 38106 | O29: 41354 | P29: 41354 | Q29: 42647 | R29: 42870 | S29: 43953 | T29: 48603 | U29: 48603 | V29: =T29-U29 -> 0 | W29: =V29/95 -> 0 | Y29: =U29/$Y$5 -> 511.61053
D30: AAPC | O30: 19820.54 | V30: =T30-U30 -> 0 | W30: =V30/95 -> 0 | Y30: =U30/$Y$5 -> 0
D31: ClaudeAI | U31: 1916.04 | V31: =T31-U31 -> -1916.04 | W31: =V31/95 -> -20.168842 | Y31: =U31/$Y$5 -> 20.168842
C32: IT and Internet Expenses | D32: IT and Internet Expenses | E32: 20000 | F32: 27416 | G32: 27416 | H32: 33750 | I32: 33750 | J32: 33750 | K32: 33750 | L32: 42917 | M32: 42917 | N32: 52084 | O32: 42917 | P32: 42917 | Q32: 42917 | R32: 42917 | S32: 42917 | T32: 42917 | U32: 42917 | V32: =T32-U32 -> 0 | W32: =V32/95 -> 0 | Y32: =U32/$Y$5 -> 451.75789
D33: SYSVEL TECHNOLOGY | I33: 3000 | V33: =T33-U33 -> 0 | W33: =V33/95 -> 0 | Y33: =U33/$Y$5 -> 0
D34: TATA TELESERVICES LIMITED | L34: 5000 | V34: =T34-U34 -> 0 | W34: =V34/95 -> 0 | Y34: =U34/$Y$5 -> 0
D35: Slack | S35: 1673.76 | T35: 1179 | U35: 1149.52 | V35: =T35-U35 -> 29.48 | W35: =V35/95 -> 0.31031579 | Y35: =U35/$Y$5 -> 12.100211
D36: Reliance Jio Infocomm Limited | U36: 20750 | V36: =T36-U36 -> -20750 | W36: =V36/95 -> -218.42105 | Y36: =U36/$Y$5 -> 218.42105
C37: Software development and Hosting charges | D37: Futurecalls Technology | L37: 1936 | M37: 15000 | N37: 15000 | O37: 15000 | P37: 23241.77 | Q37: 32542.65 | R37: 33095.87 | S37: 64203.88 | T37: 15000 | U37: 39529.52 | V37: =T37-U37 -> -24529.52 | W37: =V37/95 -> -258.20547 | Y37: =U37/$Y$5 -> 416.10021
D38: HDFC Bank | N38: 20997 | V38: =T38-U38 -> 0 | W38: =V38/95 -> 0 | Y38: =U38/$Y$5 -> 0
D39: Info Edge (India) Ltd | G39: 55800 | S39: 55800 | V39: =T39-U39 -> 0 | W39: =V39/95 -> 0 | Y39: =U39/$Y$5 -> 0
D40: Claritus Management Consulting Pvt. Ltd. | Q40: 967.34 | V40: =T40-U40 -> 0 | W40: =V40/95 -> 0 | Y40: =U40/$Y$5 -> 0
D41: Software development and Hosting charges | E41: 1000 | F41: 1000 | G41: 1000 | H41: 1000 | I41: 1000 | J41: 1000 | K41: 1000 | L41: 1000 | M41: 1000 | N41: 1000 | O41: 1000 | P41: 1000 | V41: =T41-U41 -> 0 | W41: =V41/95 -> 0 | Y41: =U41/$Y$5 -> 0
D42: GAMMA.APP | N42: 22787.23 | V42: =T42-U42 -> 0 | W42: =V42/95 -> 0 | Y42: =U42/$Y$5 -> 0
D43: Amazon | U43: 847.46 | V43: =T43-U43 -> -847.46 | W43: =V43/95 -> -8.9206316 | Y43: =U43/$Y$5 -> 8.9206316
C44: Telephone Rental Charges | D44: UNIFIED VOICE COMMUNICATION PRIVATE LIMITED | E44: 15900 | F44: 15100 | G44: 15100 | H44: 15100 | I44: 15100 | J44: 15100 | K44: 15100 | L44: 16300 | M44: 15900 | N44: 15900 | O44: 18100 | P44: 17400 | Q44: 17400 | R44: 17400 | S44: 17400 | T44: 19560 | U44: 19886 | V44: =T44-U44 -> -326 | W44: =V44/95 -> -3.4315789 | Y44: =U44/$Y$5 -> 209.32632
C45: Cyber Security Insurance | D45: Cyber Security Insurance | E45: 37500 | F45: 37500 | G45: 37500 | H45: 37500 | I45: 37500 | V45: =T45-U45 -> 0 | W45: =V45/95 -> 0 | Y45: =U45/$Y$5 -> 0
C46: Telecom Charges | D46: BHARTI AIRTEL LIMITED | E46: 2044.82 | F46: 2044.82 | G46: 2044.82 | H46: 2044.82 | I46: 6762.82 | J46: 2044.82 | K46: 2044.82 | L46: 2044.82 | M46: 2339.82 | N46: 2221.82 | O46: 3493 | P46: 2221.82 | Q46: 2221.82 | R46: 3021.36 | S46: 3156.71 | T46: 2679.9 | U46: 2679.9 | V46: =T46-U46 -> 0 | W46: =V46/95 -> 0 | Y46: =U46/$Y$5 -> 28.209474
D47: HDFC Bank | E47: 3455 | R47: 10443 | V47: =T47-U47 -> 0 | W47: =V47/95 -> 0 | Y47: =U47/$Y$5 -> 0
B48: 3.Telecom Data & others Total | E48: 302337.02 | F48: 182434.02 | G48: 223434.62 | H48: 170821.02 | I48: 178538.02 | J48: 135950.02 | K48: 139339.02 | L48: 164294.02 | M48: 187621.02 | N48: 184436.25 | O48: 214014.74 | P48: 194474.79 | Q48: 187036.01 | R48: 167738.29 | S48: 262260.28 | T48: 150731.16 | U48: 180645.44 | V48: =T48-U48 -> -29914.28 | W48: =V48/95 -> -314.88716 | Y48: =U48/$Y$5 -> 1901.5309
B49: 4.Transport Cost | C49: Staff Transportation Charges | D49: HDFC Bank | M49: 4 | V49: =T49-U49 -> 0 | W49: =V49/95 -> 0 | Y49: =U49/$Y$5 -> 0
D50: VKS Travels | E50: 256800 | F50: 267200 | G50: 248000 | H50: 252400 | I50: 237080 | J50: 189600 | K50: 228800 | L50: 250200 | M50: 262000 | N50: 302876 | O50: 303800 | P50: 278000 | Q50: 297200 | R50: 299400 | S50: 318700 | T50: 286700 | U50: 325500 | V50: =T50-U50 -> -38800 | W50: =V50/95 -> -408.42105 | Y50: =U50/$Y$5 -> 3426.3158
D51: Select Cabs | L51: 54600 | M51: 39000 | N51: 90350 | O51: 92300 | P51: 111150 | Q51: 102700 | R51: 89700 | S51: 83850 | T51: 89050 | U51: 78650 | V51: =T51-U51 -> 10400 | W51: =V51/95 -> 109.47368 | Y51: =U51/$Y$5 -> 827.89474
B52: 4.Transport Cost Total | E52: 256800 | F52: 267200 | G52: 248000 | H52: 252400 | I52: 237080 | J52: 189600 | K52: 228800 | L52: 304800 | M52: 301004 | N52: 393226 | O52: 396100 | P52: 389150 | Q52: 399900 | R52: 389100 | S52: 402550 | T52: 375750 | U52: 404150 | V52: =T52-U52 -> -28400 | W52: =V52/95 -> -298.94737 | Y52: =U52/$Y$5 -> 4254.2105
B53: 5.Other COGS | C53: Staff Welfare Expenses | D53: HDFC Bank | E53: 4200 | G53: 39096.45 | H53: 42861.25 | I53: 44593 | J53: 13596 | K53: 100 | L53: 90000 | M53: 3750 | N53: 208593 | O53: 22062 | P53: 32011 | Q53: 29246 | R53: 45039 | S53: 45037 | T53: 10135 | U53: 31508.66 | V53: =T53-U53 -> -21373.66 | W53: =V53/95 -> -224.98589 | Y53: =U53/$Y$5 -> 331.67011
D54: HDFC credit card (Imagnum) | E54: 2432.6 | G54: 1579.91 | H54: 9110 | N54: 1899.11 | P54: 6871.29 | Q54: 9267.48 | R54: 8571.8 | T54: 14947.89 | U54: 1083.72 | V54: =T54-U54 -> 13864.17 | W54: =V54/95 -> 145.93863 | Y54: =U54/$Y$5 -> 11.407579
D55: HDFC credit card (Kasi) | G55: 675 | J55: 1150 | O55: 1177.34 | U55: 3622 | V55: =T55-U55 -> -3622 | W55: =V55/95 -> -38.126316 | Y55: =U55/$Y$5 -> 38.126316
D56: SRI LAKSHMI NARASIMHAR PHOTOFRAME CENTER | F56: 112960 | G56: 37160 | I56: 2760 | K56: 3160 | L56: 5750 | M56: 1325 | S56: 2570 | V56: =T56-U56 -> 0 | W56: =V56/95 -> 0 | Y56: =U56/$Y$5 -> 0
D57: SRI LAKSHMI RESIDENCY | E57: 8750 | G57: 3750 | H57: 2589.29 | N57: 1143 | V57: =T57-U57 -> 0 | W57: =V57/95 -> 0 | Y57: =U57/$Y$5 -> 0
D58: Staff Welfare Expenses | E58: 27922 | F58: 34975 | G58: 33338 | H58: 144422 | I58: 23000 | J58: 13000 | K58: 31833 | L58: 47348 | M58: 74731 | N58: 73750 | O58: 197389.2 | P58: 11017 | R58: 269358.45 | S58: 285358.45 | T58: 122969.25 | U58: 120969.25 | V58: =T58-U58 -> 2000 | W58: =V58/95 -> 21.052632 | Y58: =U58/$Y$5 -> 1273.3605
D59: KHIVRAJ MOTORS PRIVATE LIMITED | F59: 29023.29 | V59: =T59-U59 -> 0 | W59: =V59/95 -> 0 | Y59: =U59/$Y$5 -> 0
D60: JENNYS HOTEL PVT. LTD. | F60: 10950 | V60: =T60-U60 -> 0 | W60: =V60/95 -> 0 | Y60: =U60/$Y$5 -> 0
D61: Aditya Birla Fashion | G61: 15594 | V61: =T61-U61 -> 0 | W61: =V61/95 -> 0 | Y61: =U61/$Y$5 -> 0
D62: VASANTH & CO | I62: 28125 | K62: 10932.28 | V62: =T62-U62 -> 0 | W62: =V62/95 -> 0 | Y62: =U62/$Y$5 -> 0
D63: Medway Hospitals | L63: 8514.75 | M63: 7019 | O63: 650 | R63: 1727.18 | V63: =T63-U63 -> 0 | W63: =V63/95 -> 0 | Y63: =U63/$Y$5 -> 0
D64: Health & Safety Hub | L64: 15000 | V64: =T64-U64 -> 0 | W64: =V64/95 -> 0 | Y64: =U64/$Y$5 -> 0
D65: Spelman Printers | M65: 400 | N65: 800 | V65: =T65-U65 -> 0 | W65: =V65/95 -> 0 | Y65: =U65/$Y$5 -> 0
D66: HDFC credit card (Ashok Kumar) | N66: 160 | V66: =T66-U66 -> 0 | W66: =V66/95 -> 0 | Y66: =U66/$Y$5 -> 0
D67: Tharikha Medicals | P67: 1091 | V67: =T67-U67 -> 0 | W67: =V67/95 -> 0 | Y67: =U67/$Y$5 -> 0
D68: CATAWING CYBERNETICS PVT. LTD. | R68: 3600 | S68: 2800 | T68: 4800 | U68: 1200 | V68: =T68-U68 -> 3600 | W68: =V68/95 -> 37.894737 | Y68: =U68/$Y$5 -> 12.631579
D69: Pure Palate | S69: 22339 | T69: 24040 | U69: 22340 | V69: =T69-U69 -> 1700 | W69: =V69/95 -> 17.894737 | Y69: =U69/$Y$5 -> 235.15789
C70: Insurance | D70: Insurance | E70: 47089 | F70: 47089 | G70: 47612 | H70: 49045 | I70: 50235 | J70: 50235 | K70: 60835 | L70: 60835 | M70: 60135 | N70: 63932 | O70: 63932 | P70: 69537 | Q70: 69537 | R70: 69537 | S70: 69537 | T70: 69537 | U70: 69537 | V70: =T70-U70 -> 0 | W70: =V70/95 -> 0 | Y70: =U70/$Y$5 -> 731.96842
D71: HDFC OD Account | F71: 39839 | V71: =T71-U71 -> 0 | W71: =V71/95 -> 0 | Y71: =U71/$Y$5 -> 0
D72: BAJAJ ALLIANZ GENERAL INSURANCE COMPANY LIMITED | L72: 9326 | M72: 8273.5 | V72: =T72-U72 -> 0 | W72: =V72/95 -> 0 | Y72: =U72/$Y$5 -> 0
C73: Rewards and Recognition | D73: HDFC Bank | G73: 95500 | V73: =T73-U73 -> 0 | W73: =V73/95 -> 0 | Y73: =U73/$Y$5 -> 0
C74: Employee Engagement | D74: HDFC Bank | P74: 5000 | V74: =T74-U74 -> 0 | W74: =V74/95 -> 0 | Y74: =U74/$Y$5 -> 0
B75: 5.Other COGS Total | E75: 90393.6 | F75: 274836.29 | G75: 274305.36 | H75: 248027.54 | I75: 148713 | J75: 77981 | K75: 106860.28 | L75: 236773.75 | M75: 155633.5 | N75: 350277.11 | O75: 285210.54 | P75: 125527.29 | Q75: 108050.48 | R75: 397833.43 | S75: 427641.45 | T75: 246429.14 | U75: 250260.63 | V75: =T75-U75 -> -3831.49 | W75: =V75/95 -> -40.331474 | Y75: =U75/$Y$5 -> 2634.3224
B76: 9.Exchange Gain or Loss | C76: Exchange Gain or Loss | D76: IMAGNUM US | E76: -167235.57 | F76: -138326.94 | G76: -28714.17 | H76: 219266.34 | I76: 83110.83 | J76: -55995.8 | K76: -95145.17 | M76: -256064.23 | N76: -595788.35 | O76: -362545.16 | P76: -476463.83 | Q76: -574648.6 | R76: -427104.2 | S76: -780353.77 | T76: -384237 | U76: -674963.8 | V76: =T76-U76 -> 290726.8 | W76: =V76/95 -> 3060.2821 | Y76: =U76/$Y$5 -> -7104.8821
B77: 9.Exchange Gain or Loss Total | E77: -167235.57 | F77: -138326.94 | G77: -28714.17 | H77: 219266.34 | I77: 83110.83 | J77: -55995.8 | K77: -95145.17 | M77: -256064.23 | N77: -595788.35 | O77: -362545.16 | P77: -476463.83 | Q77: -574648.6 | R77: -427104.2 | S77: -780353.77 | T77: -384237 | U77: -674963.8 | V77: =T77-U77 -> 290726.8 | W77: =V77/95 -> 3060.2821 | Y77: =U77/$Y$5 -> -7104.8821
B78: 6.G&A salaries | C78: Management Salaries | D78: Management Salaries | E78: 838403 | F78: 817569 | G78: 796736 | H78: 1055712 | I78: 884317 | J78: 1209843 | K78: 895074 | L78: 895074 | M78: 895074 | N78: 895074 | O78: 895074 | P78: 160000 | Q78: 895074 | R78: 895074 | S78: 895074 | T78: 886938 | U78: 886938 | V78: =T78-U78 -> 0 | W78: =V78/95 -> 0 | Y78: =U78/$Y$5 -> 9336.1895
C79: Admin Salaries | D79: Admin Salaries | E79: 54601 | F79: 77859 | G79: 74488 | H79: 74488 | I79: 74488 | J79: 74488 | K79: 74488 | L79: 89843 | M79: 92772 | N79: 91488 | O79: 91488 | P79: 91440 | Q79: 91470 | R79: 80185 | S79: 71674 | T79: 71219 | U79: 66261 | V79: =T79-U79 -> 4958 | W79: =V79/95 -> 52.189474 | Y79: =U79/$Y$5 -> 697.48421
C80: IT Salaries | D80: IT Salaries | E80: 52473 | F80: 71393 | G80: 65718 | H80: 63878 | I80: 71081 | J80: 63878 | K80: 63878 | L80: 63878 | M80: 66558 | N80: 63878 | O80: 76816 | P80: 78606 | Q80: 78584 | R80: 61960 | S80: 81042 | T80: 76922 | U80: 73941 | V80: =T80-U80 -> 2981 | W80: =V80/95 -> 31.378947 | Y80: =U80/$Y$5 -> 778.32632
C81: HR Salaries | D81: HR Salaries | E81: 43600 | F81: 43600 | G81: 42181 | H81: 43600 | I81: 36812 | J81: 28800 | K81: 44729 | L81: 48600 | M81: 49705 | N81: 48600 | O81: 56960 | P81: 69728 | Q81: 69706 | R81: 68994 | S81: 77295 | T81: 58100 | U81: 53341 | V81: =T81-U81 -> 4759 | W81: =V81/95 -> 50.094737 | Y81: =U81/$Y$5 -> 561.48421
B82: 6.G&A salaries Total | E82: 989077 | F82: 1010421 | G82: 979123 | H82: 1237678 | I82: 1066698 | J82: 1377009 | K82: 1078169 | L82: 1097395 | M82: 1104109 | N82: 1099040 | O82: 1120338 | P82: 399774 | Q82: 1134834 | R82: 1106213 | S82: 1125085 | T82: 1093179 | U82: 1080481 | V82: =T82-U82 -> 12698 | W82: =V82/95 -> 133.66316 | Y82: =U82/$Y$5 -> 11373.484
B83: 7.Legal & Professional Fees | C83: FPO Charges - SRF | D83: Spice Route Finance | E83: 125000 | F83: 125000 | G83: 125000 | H83: 125000 | I83: 125000 | J83: 125000 | K83: 125000 | L83: 125000 | M83: 125000 | N83: 125000 | O83: 125000 | P83: 125000 | Q83: 125000 | R83: 125000 | S83: 185000 | T83: 125000 | U83: 125000 | V83: =T83-U83 -> 0 | W83: =V83/95 -> 0 | Y83: =U83/$Y$5 -> 1315.7895
C84: Coding charges | D84: Cure Claims Healthcare Services | F84: 12420 | G84: 53658 | V84: =T84-U84 -> 0 | W84: =V84/95 -> 0 | Y84: =U84/$Y$5 -> 0
D85: HDFC Bank | S85: 11172 | V85: =T85-U85 -> 0 | W85: =V85/95 -> 0 | Y85: =U85/$Y$5 -> 0
D86: Coding charges | E86: 210148 | F86: 414284 | G86: 1019968 | J86: 51954 | V86: =T86-U86 -> 0 | W86: =V86/95 -> 0 | Y86: =U86/$Y$5 -> 0
C87: Professional services | D87: AATRALAI TECH SOLUTIONS PVT. LTD. | F87: 100000 | V87: =T87-U87 -> 0 | W87: =V87/95 -> 0 | Y87: =U87/$Y$5 -> 0
D88: DQS India | I88: 60450 | V88: =T88-U88 -> 0 | W88: =V88/95 -> 0 | Y88: =U88/$Y$5 -> 0
D89: N V Balaji and Co. | J89: 131000 | V89: =T89-U89 -> 0 | W89: =V89/95 -> 0 | Y89: =U89/$Y$5 -> 0
C90: FPO Charges-SMCS GLOBAL | D90: SMCS Global | J90: 165000 | K90: 30000 | P90: 6000 | Q90: 5000 | V90: =T90-U90 -> 0 | W90: =V90/95 -> 0 | Y90: =U90/$Y$5 -> 0
C91: MCA Filing Fee | D91: Spice Route Finance | K91: 300 | V91: =T91-U91 -> 0 | W91: =V91/95 -> 0 | Y91: =U91/$Y$5 -> 0
B92: 7.Legal & Professional Fees Total | E92: 335148 | F92: 651704 | G92: 1198626 | H92: 125000 | I92: 185450 | J92: 472954 | K92: 155300 | L92: 125000 | M92: 125000 | N92: 125000 | O92: 125000 | P92: 131000 | Q92: 130000 | R92: 125000 | S92: 196172 | T92: 125000 | U92: 125000 | V92: =T92-U92 -> 0 | W92: =V92/95 -> 0 | Y92: =U92/$Y$5 -> 1315.7895
B93: 8.Sales & Marketing | C93: S&M Salaries | D93: S&M Salaries | E93: 106743 | F93: 143864 | G93: 123335 | H93: 135405 | I93: 131899 | J93: 19867 | K93: 19867 | L93: 125076 | M93: 112295 | N93: 130598 | O93: 118522 | P93: 106479 | Q93: 106145 | R93: 93372 | S93: 116553 | T93: 114721 | U93: 104048 | V93: =T93-U93 -> 10673 | W93: =V93/95 -> 112.34737 | Y93: =U93/$Y$5 -> 1095.2421
C94: Advertising And Marketing | D94: Amazon.in | O94: 10 | V94: =T94-U94 -> 0 | W94: =V94/95 -> 0 | Y94: =U94/$Y$5 -> 0
B95: 8.Sales & Marketing Total | E95: 106743 | F95: 143864 | G95: 123335 | H95: 135405 | I95: 131899 | J95: 19867 | K95: 19867 | L95: 125076 | M95: 112295 | N95: 130598 | O95: 118532 | P95: 106479 | Q95: 106145 | R95: 93372 | S95: 116553 | T95: 114721 | U95: 104048 | V95: =T95-U95 -> 10673 | W95: =V95/95 -> 112.34737 | Y95: =U95/$Y$5 -> 1095.2421
B96: 9.General & Administration | C96: Employer PF | D96: Employer PF | E96: 296342 | F96: 305791 | G96: 317357 | H96: 314981 | I96: 338119 | J96: 338763 | K96: 356938 | L96: 390653 | M96: 418465 | N96: 430132 | O96: 435979 | P96: 479345 | Q96: 467242 | R96: 426537 | S96: 458363 | T96: 458087 | U96: 450986.5 | V96: =T96-U96 -> 7100.5 | W96: =V96/95 -> 74.742105 | Y96: =U96/$Y$5 -> 4747.2263
C97: Employee PF | D97: Employee PF | E97: 296342 | F97: 305791 | G97: 317357 | H97: 314981 | I97: 338119 | J97: 338763 | K97: 356938 | L97: 390653 | M97: 418465 | N97: 430132 | O97: 435979 | P97: 479345 | Q97: 467242 | R97: 426537 | S97: 458363 | T97: 458087 | U97: 450986.5 | V97: =T97-U97 -> 7100.5 | W97: =V97/95 -> 74.742105 | Y97: =U97/$Y$5 -> 4747.2263
C98: Food Coupon-Happay Wallet | D98: Food Coupon-Happay Wallet | E98: 200794 | F98: 200730 | G98: 210292 | H98: 216462 | I98: 228978 | J98: 229828 | K98: 297205 | L98: 273626 | M98: 277256 | N98: 289438 | O98: 264362 | P98: 293709 | Q98: 296255 | R98: 267000 | S98: 282458 | T98: 271457 | U98: 268211 | V98: =T98-U98 -> 3246 | W98: =V98/95 -> 34.168421 | Y98: =U98/$Y$5 -> 2823.2737 | Z98: =Y96+Y97+Y99 -> 10092.747
C99: Professional Tax | D99: Professional Tax | E99: 40200 | F99: 41600 | G99: 53330 | H99: 45400 | I99: 48785 | J99: 50500 | K99: 51405 | L99: 56800 | M99: 101380 | N99: 57910 | O99: 59440 | P99: 72328 | Q99: 68808 | R99: 59223 | S99: 58813 | T99: 56163 | U99: 56838 | V99: =T99-U99 -> -675 | W99: =V99/95 -> -7.1052632 | Y99: =U99/$Y$5 -> 598.29474
C100: Office Supplies | D100: DARLING DIGITAL WORLD PVT LTD | N100: 1186.44 | V100: =T100-U100 -> 0 | W100: =V100/95 -> 0 | Y100: =U100/$Y$5 -> 0
D101: DEVA PRINTERS | I101: 2000 | V101: =T101-U101 -> 0 | W101: =V101/95 -> 0 | Y101: =U101/$Y$5 -> 0
D102: HDFC Bank | E102: 10012 | K102: 20273 | N102: 3400 | O102: 1350 | P102: 4350 | Q102: 7168 | R102: 8011 | S102: 44118 | T102: 19516.5 | V102: =T102-U102 -> 19516.5 | W102: =V102/95 -> 205.43684 | Y102: =U102/$Y$5 -> 0
...
